Workbook

Sheet Model Flow
B1: ALUR MODEL (MODEL FLOW) - panduan praktis model keuangan FSL tanpa Sapphire, direvisi dari workbook v29 asli
B2: Semua angka di lembar ini adalah rumus yang membaca sel model (bukan ketikan). Klik teks biru bergaris bawah untuk melompat ke sel yang dimaksud. Nama lembar, nomor bagian dan alamat sel ditulis apa adanya (bahasa Inggris).
B3: Go to sheet: | C3: [Model Flow] | D3: Inputs | E3: FS Request | F3: Revenue | G3: Costs | H3: BUMN Synergy | I3: Capex | J3: Work. cap. | K3: Financing | L3: Funding | M3: Out: w/o BUMN | N3: Out: With BUMN | O3: Val: w/o BUMN | P3: Val: With BUMN | Q3: Proj. CF | R3: Proj. Summary | S3: Checks | T3: Source Data
B6: 1. MULAI DARI MANA - status model dan hasil utama (rumus hidup)
B7: Lembar Checks & Reconciliation bagian A menjawab tiga pertanyaan. Model ini adalah BASELINE REVISI: semua asumsi v29 dipertahankan kecuali perubahan yang diminta (tanggal valuasi, pinjaman LT, capex %, Badas, pendanaan). Karena itu sebagian baris sengaja berbeda dari v29; statusnya "Differs - requested change" dan setiap selisih dijelaskan (bagian D dan G).
B8: 1. Apakah model mereproduksi v29, selain perubahan yang diminta? | C8: ='Checks & Reconciliation'!$C$7 -> Differs - inputs / switches changed: 46 line(s) affected | H8: Checks & Reconciliation A
B9: Tingkat proyek: 16 blok bisnis v29 | C9: ='Checks & Reconciliation'!$C$8 -> YES - all 16 v29 business blocks reproduced (14 identical; 2 differ only through the LT loan interest in FY2026-27) | H9: Checks & Reconciliation A
B10: Jembatan v29 -> baseline revisi | C10: ='Checks & Reconciliation'!$C$9 -> Differs - inputs changed | H10: Checks & Reconciliation A
B11: 2. Apakah model lolos pemeriksaan integritas akuntansi dan keuangan? | C11: ='Checks & Reconciliation'!$C$12 -> YES - all 36 checks pass (balance sheet, cash, roll-forwards, funding sources = uses, tax, bridges, valuation, capex, Badas, summaries) | H11: Checks & Reconciliation A
B12: Peringatan tentang hasil | C12: ='Checks & Reconciliation'!$C$13 -> 1 warning(s) about the result - see section B | H12: Checks & Reconciliation A
B13: 3. Apakah ada masalah data sumber yang belum terselesaikan? | C13: ='Checks & Reconciliation'!$C$15 -> 13 v29 source issues documented; corrections ON: 0 of 13 - v29 treatment kept (incl. its 0.006 balance-sheet residual and negative fixed assets) | H13: Checks & Reconciliation A
B14: Item yang perlu dikonfirmasi | C14: ='Checks & Reconciliation'!$C$16 -> 33 item(s): provisional valuation / funding parameters, the LT loan terms, Badas FS data and open source questions | H14: Checks & Reconciliation A
B15: Perubahan yang aktif dan perubahan input Anda | C15: ='Checks & Reconciliation'!$C$18 -> Requested changes active: LT loan repaid FY2027 + equity = residual requirement | inputs changed vs the delivered baseline: 1 row(s) / switch(es) (Inputs column U) | Corrections ON: none | H15: Checks & Reconciliation A
B16: Kasus yang sedang berlaku | C16: ='Checks & Reconciliation'!$C$19 -> Scenario 1 | projects in the valuation: 15 of 19 | BUMN control: ON | valuation date 31-Dec-2026 | Badas IN the valuation (DUMMY) | H16: Checks & Reconciliation A
B18: Hasil utama (IDR miliar; tanggal valuasi 31-Des-2026). Nilai ekuitas = nilai; kebutuhan ekuitas = kas yang harus disetor pemegang saham. Keduanya BERBEDA.
B19: Hasil | C19: Dengan BUMN | D19: Tanpa BUMN | E19: Sel (Dengan BUMN) | F19: Sel (Tanpa BUMN)
B20: Nilai perusahaan (EV, 100%) | C20: ='Valuation — With BUMN'!$E$67 -> 4633.2655 | D20: ='Valuation — Without BUMN'!$E$67 -> 4121.4079 | E20: Valuation — With BUMN!E67 | F20: Valuation — Without BUMN!E67
B21: Nilai ekuitas untuk pemegang saham FSL | C21: ='Valuation — With BUMN'!$E$74 -> 3959.7433 | D21: ='Valuation — Without BUMN'!$E$74 -> 3536.8634 | E21: Valuation — With BUMN!E74 | F21: Valuation — Without BUMN!E74
B22: Nilai ekuitas (USD juta, kurs tahun valuasi) | C22: ='Valuation — With BUMN'!$E$75 -> 243.45178 | D22: ='Valuation — Without BUMN'!$E$75 -> 217.45241 | E22: Valuation — With BUMN!E75 | F22: Valuation — Without BUMN!E75
B23: Total kebutuhan ekuitas (kas yang harus disetor, semua tahun) | C23: ='Funding Requirement'!$E$21 -> 28.884163 | D23: ='Funding Requirement'!$F$21 -> 76.665204 | E23: Funding Requirement!E21 | F23: Funding Requirement!F21
B24: Tahun pertama ekuitas dibutuhkan | C24: ='Funding Requirement'!$E$23 -> 2027 | D24: ='Funding Requirement'!$F$23 -> 2027 | E24: Funding Requirement!E23 | F24: Funding Requirement!F23
B25: Kesenjangan pendanaan terbesar dalam satu tahun | C25: ='Funding Requirement'!$E$14 -> 28.884163 | D25: ='Funding Requirement'!$F$14 -> 76.665204 | E25: Funding Requirement!E14 | F25: Funding Requirement!F14
B26: Nilai skema BUMN yang menjadi hak FSL (EV Dengan - Tanpa BUMN) | C26: ='Valuation — With BUMN'!$E$116 -> 511.85758 | D26: IDR miliar | E26: Valuation — With BUMN!E116
B27: Badas (ilustratif, input DUMMY): NPV 100% pada tanggal valuasi | C27: ='Project Cash Flows'!$E$379 -> 14.116098 | D27: IDR miliar | E27: Project Cash Flows!E379
B28: Dua kasus dan jembatan di antara keduanya (FY2026, IDR miliar). Angka referensi: 494,571 (FSL tanpa BUMN) + 127,494 (kontribusi BUMN) = 622,065 (v29 Output_FSL!L44) - tidak berubah oleh revisi.
B29: Pendapatan FY2026 - kasus Tanpa BUMN | C29: ='FSL Output - Without BUMN'!J9 -> 494.57108 | D29: IDR miliar | E29: FSL Output - Without BUMN!J9
B30: Kontribusi BUMN FY2026 = pendapatan hak FSL dari skema operatorship P12-P14 | C30: ='BUMN Synergy Calculation'!J98 -> 127.49381 | D30: IDR miliar | E30: BUMN Synergy Calculation!J98
B31: Pendapatan FY2026 - kasus Dengan BUMN | C31: ='FSL Output - With BUMN'!J59 -> 622.06489 | D31: IDR miliar | E31: FSL Output - With BUMN!J59
B33: Urutan lembar dan fungsinya (nama lembar persis seperti di tab):
B34: Inputs | C34: Semua asumsi dan kontrol - satu-satunya lembar yang diedit. Kolom D = tipe (v29 / Derived / CHANGE / DUMMY / TO CONFIRM / Control / Placeholder); kolom U menandai nilai yang berbeda dari nilai yang diserahkan (Source Data, baris sama).
B35: FS Data Request | C35: Daftar data yang diminta dari studi kelayakan Badas (dan proyek funding-only / placeholder): definisi, satuan, status, sel Inputs tempat mengisi, baris perhitungan yang memakainya.
B36: Revenue Calculation | C36: Volume x tarif per bisnis dan proyek (E1-E4, P01-P11, P15-P19). A: tahun mulai dan bendera operasi. E: Badas (template).
B37: Cost Calculation | C37: Biaya pokok, beban usaha dan EBITDA per bisnis; D: Badas; E: ringkasan per kasus.
B38: BUMN Synergy Calculation | C38: Skema operatorship P12-P14: ekonomi per ton, hak FSL, bagian yang tetap di BUMN (informasi saja).
B39: Capex & Depreciation | C39: A: capex USD = total investasi x % belanja per tahun; A2: ringkasan sebelum / sesudah tanggal valuasi; B-C: kurs dan IDR; D-E: penyusutan; G: per bisnis (termasuk nilai buku); J: capex di luar laporan (funding request); K: tangkapan layar daftar proyek.
B40: Working Capital | C40: Piutang, persediaan, utang usaha per bisnis dan per kasus (metode v29).
B41: Financing | C41: Pinjaman lama (termasuk pinjaman LT 12 USD juta yang dilunasi 2027), fasilitas utang baru, utang proyek Badas, dividen (aturan v29), ekuitas, DSCR.
B42: Funding Requirement | C42: Arus kas (sumber dan penggunaan dana), kesenjangan pendanaan, utang, ekuitas residual, proyek capex-only, total kebutuhan ekuitas dan waktunya.
B43: FSL Output - Without BUMN | C43: Laba rugi, pajak, neraca, arus kas FSL tanpa skema BUMN; referensi FCFF / IRR v29.
B44: FSL Output - With BUMN | C44: Sama dengan skema BUMN P12-P14; bagian A: jembatan Tanpa BUMN + kontribusi BUMN = Dengan BUMN.
B45: Valuation — Without BUMN | C45: DCF kasus Tanpa BUMN pada 31-Des-2026 (FCFF FY2027+), jembatan EV -> nilai ekuitas, sensitivitas.
... B50: Source Data | C50: Nilai input yang diserahkan (cermin Inputs 1-16), neraca Des-23 (17), tolok ukur v29 kedua kasus (18), blok bisnis v29 (19), daftar masalah sumber (20). Jangan diedit.
B52: 2. PERUBAHAN TERHADAP v29 YANG DIMINTA (dan cara kembali ke v29)
B53: a) Tanggal valuasi 31-Des-2026. DCF hanya memakai FCFF FY2027 dan seterusnya; FY2024-26 berada sebelum tanggal valuasi. Konvensi akhir tahun: FCFF FY2027 didiskonto satu tahun penuh dari 31-Des-2026. Kas, utang dan penyesuaian lain di jembatan nilai ekuitas memakai saldo proyeksi 31-Des-2026 (belum ada aktual FY2024-26).
B54: Tanggal valuasi (Inputs 3) | C54: =Inputs!$E$93 -> 46387 | E54: Inputs!E93
B55: Periode diskonto FY2027 (Valuation - Dengan BUMN bagian C) | C55: ='Valuation — With BUMN'!K46 -> 1 | D55: tahun | E55: Valuation — With BUMN!K46
B56: Faktor diskonto FY2027 | C56: ='Valuation — With BUMN'!K47 -> 0.89392257 | E56: Valuation — With BUMN!K47
B57: b) Pinjaman LT 12 USD juta (195,18 IDR miliar) tidak dilunasi 2025 seperti di v29: saldo tetap sampai 31-Des-2026 dan dilunasi 2027 (tanggal sementara 30-Jun-2027, dapat diubah). Bunga dihitung sampai tanggal pelunasan dengan tarif tersirat v29 (7,83%), dibagi ke baris pajak v29 Cigading existing / Wharf 2. Pinjaman lain (29,3) tetap dilunasi FY2024.
B58: Saldo pinjaman LT 31-Des-2026 (Financing A) | C58: =Financing!J14 -> 195.18 | D58: IDR miliar | E58: Financing!J14
B59: Bunga pinjaman LT FY2026 | C59: =Financing!J16 -> 15.27345 | D59: IDR miliar | E59: Financing!J16
B60: Bunga pinjaman LT FY2027 (sampai tanggal pelunasan) | C60: =Financing!K16 -> 7.5739575 | D60: IDR miliar | E60: Financing!K16
B61: Pelunasan FY2027 | C61: =Financing!K13 -> 195.18 | D61: IDR miliar | E61: Financing!K13
B62: Tanggal pelunasan (Inputs 10; CHANGE, TO CONFIRM) | C62: =Inputs!$E$494 -> 46568 | E62: Inputs!E494
B63: c) Capex setiap proyek = total investasi (USD juta) x % belanja per periode (kolom pra-2024 = sudah dibelanjakan / sunk). Persentase awal = waktu v29, sehingga angka capex tidak berubah. Kontrol "tahun mulai" capex yang lama dihapus; tahun mulai operasi (pendapatan) tetap terpisah di Inputs 2.
B64: d) Badas (P19) ditambahkan sebagai template proyek lengkap dengan input DUMMY (warna emas, "DUMMY - REPLACE WITH FS DATA"). Hasilnya selalu terlihat (ilustratif) tetapi TIDAK masuk valuasi (saklar OFF); capex-nya masuk permintaan pendanaan (kontrol terpisah).
B65: e) Pendanaan: ekuitas baru = kebutuhan residual setelah kas internal, pendanaan yang sudah dikomitmenkan dan utang (Funding Requirement), bukan jadwal v29 (ekuitas = capex FY2026-27, 35,6 USD juta). Lima proyek funding-only (F01-F05) dapat diisi capex saja.
B66: Untuk mereproduksi v29 persis (semua baris "Matches v29"): Inputs 10 tanggal pelunasan pinjaman LT = 31-Des-2025 dan Inputs 1 basis ekuitas = 2. Tanggal valuasi dan struktur capex % tidak mengubah baris laporan (diuji).
B67: Lompat ke kontrol | E67: Inputs 10 - tanggal pelunasan | F67: Inputs 1 - basis ekuitas | G67: Checks G - jembatan
B69: 3. APA YANG BOLEH DIUBAH - hanya sel biru berlatar warna di lembar Inputs
B70: Warna tipe: abu-abu = nilai v29; hijau = turunan v29; biru muda = CHANGE (perubahan yang diminta; nilai v29 di kolom F); emas = DUMMY (ganti dengan data FS); oranye = TO CONFIRM (provisional); kuning = kontrol / saklar; ungu = placeholder (sengaja kosong). Teks hitam = rumus, jangan diedit; teks hijau = link dari lembar lain.
B71: Asumsi tahunan mempunyai satu sel per tahun (kolom H:T; G = pra-2024 / Des-23). Mengubah FY2028 hanya mengubah FY2028; baris pertumbuhan membawa efeknya ke tahun berikutnya. Kolom E = parameter yang memang bukan tahunan.
B72: Kontrol (Inputs) | C72: Nilai sekarang | D72: Diserahkan | E72: Sel
B73: Pemilih skenario: 1 = bisnis lama + proyek yang ON; 2 = bisnis lama saja | C73: =Inputs!$E$42 -> 1 | D73: 1 | E73: Inputs!E42
B74: Skema operatorship BUMN (P12-P14) masuk kasus Dengan BUMN: 1 = ya, 0 = tidak | C74: =Inputs!$E$43 -> 1 | D74: 1 | E74: Inputs!E43
B75: Basis ekuitas: 1 = kebutuhan residual (revisi), 2 = jadwal v29 | C75: =Inputs!$E$44 -> 1 | D75: 1 | E75: Inputs!E44
B76: Tuas volume / tarif / biaya / capex (% perubahan) | C76: =Inputs!$E$45 -> 0 | D76: 0 | E76: Inputs!E45
B77: Badas masuk valuasi (Inputs 2, saklar P19; OFF) | C77: =Inputs!$E$82 -> 1 | D77: 0 | E77: Inputs!E82
B78: Capex Badas masuk permintaan pendanaan saat di luar valuasi (Inputs 13) | C78: =Inputs!$E$568 -> 1 | D78: 1 | E78: Inputs!E568
B79: Tahun yang dijelaskan dengan kalimat di Checks & Reconciliation D | C79: =Inputs!$E$49 -> 2036 | D79: 2036 | E79: Inputs!E49
B80: Toleransi kecocokan dengan v29 (IDR miliar per baris dan tahun) | C80: =Inputs!$E$50 -> 0.001 | D80: 0.001 | E80: Inputs!E50
B81: ="Koreksi opsional yang ON (Inputs 16, teknis): "&Inputs!$E$753&" dari 13 | baris input / saklar yang berubah dari baseline yang diserahkan: "&'Checks & Reconciliation'!$E$21 -> Koreksi opsional yang ON (Inputs 16, teknis): 0 dari 13 | baris input / saklar yang berubah dari baseline yang diserahkan: 1
B82: Setelah mengubah input: Checks & Reconciliation A menunjukkan "Differs - inputs changed" dan bagian D menunjukkan baris dan tahun mana yang berubah. Untuk kembali: kembalikan sel yang ditandai di kolom U Inputs (nilai asli ada di Source Data, baris yang sama).
B84: 4. BAGAIMANA SETIAP PROYEK DIHITUNG - rantai perhitungan yang sama untuk semua bisnis
B85: Inputs | C85: Volume dasar, pertumbuhan, tarif, rasio biaya, total investasi dan % belanja per tahun, porsi bangunan / peralatan dan umur aset, saklar dan tahun mulai.
B86: Revenue Calculation | C86: A: bendera operasi (1 dari tahun mulai). Volume = dasar x indeks x tuas volume; tarif = input tahunan x tuas tarif; pendapatan = volume x tarif / 1e9 (IDR miliar).
B87: Cost Calculation | C87: Biaya pokok (per ton x volume, atau % pendapatan, plus asuransi % x total investasi x kurs), beban usaha, EBITDA per bisnis.
B88: Capex & Depreciation | C88: A: capex USD = total x % x tuas capex x saklar. B-C: kurs dan IDR. D: penyusutan metode v29 (capex x porsi / umur mulai tahun mulai). G: D&A, capex dan nilai buku per bisnis.
B89: Working Capital | C89: Piutang = pendapatan x hari piutang / hari; utang = biaya pokok x hari utang / hari; persediaan per v29.
B90: FSL Output - Without BUMN / FSL Output - With BUMN | C90: Laba rugi, pajak metode baris v29 (22% x MAX(0, laba) per blok bisnis), neraca, arus kas per kasus; nomor baris v29 Output_FSL di setiap label.
B91: Financing / Funding Requirement | C91: Kas sebelum dana baru -> kesenjangan terhadap kas minimum -> pendanaan komitmen, utang, ekuitas residual -> dividen (aturan v29) -> kas akhir.
B92: Valuation - Tanpa / Dengan BUMN | C92: FCFF = NOPAT + D&A - capex - kenaikan modal kerja; hanya FY2027+; nilai terminal; EV -> nilai ekuitas pada 31-Des-2026.
B93: Project Cash Flows / Project Summary | C93: Per bisnis: laba sendiri, arus kas tanpa leverage, NPV, IRR, payback, kebutuhan pendanaan; ringkasan satu bagian per proyek dengan jembatan ke total FSL.
B95: Daftar proyek: baris pendapatan, EBITDA, capex / D&A dan bagian ringkasan setiap bisnis (klik untuk melompat). Kolom C = masuk valuasi saat ini (1 = ya); kolom D = tahun mulai operasi.
B96: Bisnis / proyek | C96: Valuasi | D96: Mulai | E96: Pendapatan | F96: Biaya / EBITDA | G96: Capex / D&A | H96: Sumber v29
B97: E1 Teluk Lamong cargodoring & delivery (NPLOG) [Existing] | C97: =Inputs!$H$60 -> 1 | D97: lama | E97: Revenue row 41 | F97: Costs row 35 | G97: Capex row 231 (D&A) | H97: NPLOG - Teluk Lamong existing
B98: E2 Cigading existing terminal (SGT 2) [Existing] | C98: =Inputs!$H$61 -> 1 | D98: lama | E98: Revenue row 47 | F98: Costs row 66 | G98: Capex row 232 (D&A) | H98: Cigading Existing
B99: E3 Belawan existing (conveyor & warehouse) [Existing] | C99: =Inputs!$H$62 -> 1 | D99: lama | E99: Revenue row 53 | F99: Costs row 94 | G99: Capex row 233 (D&A) | H99: Belawan (existing part of the Belawan block)
B100: E4 WIN stevedoring (Cilegon, Makassar, Surabaya, Medan) [Existing] | C100: =Inputs!$H$63 -> 1 | D100: lama | E100: Revenue row 92 | F100: Costs row 131 | G100: Capex row 234 (D&A) | H100: Stevedoring WIN combine
B101: P01 Cigading Wharf 2 [Committed] | C101: =Inputs!$H$64 -> 1 | D101: ='Revenue Calculation'!$D$10 -> 2025 | E101: Revenue row 99 | F101: Costs row 137 | G101: Capex row 56 | H101: Cigading Expansion: Wharf 2
B102: P02 Cigading extended conveyor [Committed] | C102: =Inputs!$H$65 -> 1 | D102: ='Revenue Calculation'!$D$11 -> 2025 | E102: Revenue row 104 | F102: Costs row 141 | G102: Capex row 57 | H102: Cigading Expansion: Extended Conveyor
B103: P03 KBS warehouse revitalisation (FSL 49% revenue share) [Planned] | C103: =Inputs!$H$66 -> 1 | D103: ='Revenue Calculation'!$D$12 -> 2027 | E103: Revenue row 111 | F103: Costs row 145 | G103: Capex row 58 | H103: Cigading Expansion: KBS Warehouse Revitalization
B104: P04 Teluk Lamong silo [Planned] | C104: =Inputs!$H$67 -> 1 | D104: ='Revenue Calculation'!$D$13 -> 2027 | E104: Revenue row 115 | F104: Costs row 149 | G104: Capex row 59 | H104: Teluk Lamong - Silo (TTL Silo)
B105: P05 Dumai bagging & weighbridge [Planned] | C105: =Inputs!$H$68 -> 1 | D105: ='Revenue Calculation'!$D$14 -> 2026 | E105: Revenue row 122 | F105: Costs row 153 | G105: Capex row 60 | H105: Dumai (bagging and weighbridge)
B106: P06 Ciwandan expansion (FSL 52% tariff share) [Planned] | C106: =Inputs!$H$69 -> 1 | D106: ='Revenue Calculation'!$D$15 -> 2028 | E106: Revenue row 129 | F106: Costs row 157 | G106: Capex row 61 | H106: Ciwandan Expansion
B107: P07 Belawan expansion (additional volume) [Planned] | C107: =Inputs!$H$70 -> 1 | D107: ='Revenue Calculation'!$D$16 -> 2026 | E107: Revenue row 133 | F107: Costs row 161 | G107: Capex row 62 | H107: Belawan (incl. Belawan expansion)
B108: P08 DMS trucking fee - Teluk Lamong [Planned] | C108: =Inputs!$H$71 -> 1 | D108: ='Revenue Calculation'!$D$17 -> 2027 | E108: Revenue row 137 | F108: Costs row 165 | G108: Capex row 68 | H108: Trucking DMS Teluk Lamong
B109: P09 DMS trucking fee - Cigading [Planned] | C109: =Inputs!$H$72 -> 1 | D109: ='Revenue Calculation'!$D$18 -> 2027 | E109: Revenue row 140 | F109: Costs row 168 | G109: Capex row 69 | H109: Trucking DMS Cigading
B110: P10 DMS trucking fee - Ciwandan [Planned] | C110: =Inputs!$H$73 -> 1 | D110: ='Revenue Calculation'!$D$19 -> 2028 | E110: Revenue row 143 | F110: Costs row 171 | G110: Capex row 70 | H110: Trucking DMS Ciwandan
B111: P11 DMS trucking fee - Belawan [Planned] | C111: =Inputs!$H$74 -> 1 | D111: ='Revenue Calculation'!$D$20 -> 2027 | E111: Revenue row 146 | F111: Costs row 174 | G111: Capex row 71 | H111: Trucking DMS Belawan
B112: P12 BUMN synergy - Pelindo Teluk Lamong operatorship [BUMN synergy] | C112: =Inputs!$H$75 -> 1 | D112: ='Revenue Calculation'!$D$21 -> 2026 | E112: BUMN Synergy row 34 | F112: BUMN Synergy row 37 | G112: Capex row 77 | H112: Operatorship with BUMN - Pelindo Teluk Lamong
...

Sheet Inputs
B1: INPUTS - every assumption and control (edit only here)
B2: Blue text on a coloured fill = editable. Parameters: column E. Annual assumptions: one cell per year, columns H:T (G = pre-2024 / Dec-23). Type (column D): v29 / Derived / CHANGE (requested vs v29) / DUMMY / TO CONFIRM / Control. Column U flags cells that differ from the delivered value.
B3: Go to sheet: | C3: Model Flow | D3: [Inputs] | E3: FS Request | F3: Revenue | G3: Costs | H3: BUMN Synergy | I3: Capex | J3: Work. cap. | K3: Financing | L3: Funding | M3: Out: w/o BUMN | N3: Out: With BUMN | O3: Val: w/o BUMN | P3: Val: With BUMN | Q3: Proj. CF | R3: Proj. Summary | S3: Checks | T3: Source Data
B5: HOW TO USE THIS SHEET
B6: 1. Change only cells with blue text on a coloured fill. Black text = formula (do not edit); green text = link from another sheet. Column U flags a value that differs from the delivered value (kept on Source Data, same row).
B7: 2. As delivered the inputs are the REVISED BASELINE: every v29 assumption except the requested changes (type CHANGE): valuation date 31-Dec-2026, LT loan repaid in 2027, new equity = residual funding requirement. Capex = total investment x spending % (v29 timing).
B8: Checks & Reconciliation D compares every line with v29 and names the change behind each difference. To reproduce v29 exactly: LT loan repayment date 31-Dec-2025 (section 10) and equity basis 2 (section 1).
B9: 3. Annual assumptions have one cell per year (columns H:T; G = pre-2024 / 2023 base). Changing FY2028 changes only FY2028; growth rows carry the effect into later years. Type (column D): v29 / Derived / CHANGE / DUMMY / TO CONFIRM / Control / Placeholder.
B10: 4. Sections: 1 controls | 2 project register (valuation inclusion) | 5 projects (capex = total x %) | 10 financing incl. the LT loan | 12 valuation (WACC) | 13 Badas (DUMMY) | 14 pipeline placeholders | 15 funding-only projects | 16 optional v29 corrections (technical, all 0).
B11: 5. Badas FS data: the FS Data Request sheet lists every item with its cell here. Enter FS data only on this sheet - one authoritative cell per item; never paste over formulas.
B13: Colour key (column D = type)
C14: v29 | D14: Value taken from v29 (V29_Ruby_FM_Danantara.xlsm) or the value v29 applies (cell in column F)
C15: Derived | D15: Derived or interpreted from v29 data (derivation in column V)
C16: CHANGE | D16: User-requested change vs v29 (v29 value / cell in column F; reconciled on Checks & Reconciliation D)
C17: DUMMY | D17: DUMMY - REPLACE WITH FS DATA (Badas; listed on the FS Data Request sheet)
C18: TO CONFIRM | D18: Provisional assumption - not in v29 (register on Checks & Reconciliation section C)
C19: Control | D19: Switch or lever (delivered setting)
C20: Placeholder | D20: Future-project or funding-only input intentionally left blank
C21: formula | D21: Calculated cell (black); link from another sheet (green) - do not edit
B23: SECTIONS (click to jump)
B24: 1. CONTROLS - business cases, funding basis and sensitivity levers (project switches: section 2; Badas: 2 and 13; optional v29 corrections: 16)
B25: 2. PROJECT REGISTER - every business and project, its source, inclusion switch, timing and where it is modelled
B26: 3. GENERAL ASSUMPTIONS - dates, currency, units
B27: 4. EXISTING OPERATIONS (E1-E4) - volumes, tariffs, growth and existing-asset depreciation schedules
B28: 5. PROJECTS (P01-P11, P15) - operating assumptions, capex (total investment x annual spending %) and asset lives, project by project
B29: 6. OPERATING COSTS OF EXISTING BUSINESSES - FY2023 base x v29 uplift, then each year's growth; cost ratios
B30: 7. BUMN SYNERGIES (P12-P14) - SOE-level tariffs and unit costs by year, FSL margins, investment and working-capital requirements
B31: 8. SUSTAINING CAPEX AND CANCELLATION (all asset-owning businesses) - nil in v29
B32: 9. WORKING CAPITAL
B33: 10. FINANCING - existing loans (incl. the 12 USD mn LT loan, now repaid in 2027), new debt, committed funding, equity basis, dividends
B34: 11. TAX AND OWNERSHIP
... B40: 1. CONTROLS - business cases, funding basis and sensitivity levers (project switches: section 2; Badas: 2 and 13; optional v29 corrections: 16)
B41: Control | C41: Unit | D41: Type | E41: Parameter | F41: v29 source | U41: Diff | V41: Source and explanation
B42: Scenario selector | C42: code | D42: Control | E42: 1 | F42: Delivered setting (v29 Output_FSL!F27 = 1) | U42: =IF(E42='Source Data'!E42,"","changed") | V42: 1 = existing businesses + every project switched ON in section 2 (v29 saved case). 2 = existing businesses only (every project excluded).
B43: BUMN operatorship schemes (P12-P14) included in the With BUMN case | C43: 0 / 1 | D43: Control | E43: 1 | F43: Delivered setting (v29 Output_FSL!G35 = 1) | U43: =IF(E43='Source Data'!E43,"","changed") | V43: 1 = the With BUMN sheets include the FSL entitlement under the operatorship schemes (v29 saved case). 0 = both cases exclude them. The Without BUMN sheets always exclude them.
B44: Equity injection basis: 1 = equity required by the cash roll-forward, 2 = v29 schedule (100% of FY2026-27 project capex) | C44: code | D44: CHANGE | E44: 1 | F44: v29: 2 (Call Rights scenario 4, Calculation_FSL!L1498:M1498) | U44: =IF(E44='Source Data'!E44,"","changed") | V44: USER-REQUESTED CHANGE: v29 issues new shares equal to the FY2026-27 project capex whether or not cash is short. Revised: new equity = the funding gap left after internal cash, committed funding and debt (Funding Requirement). Set 2 to reproduce v29.
B45: Volume lever (% change applied to every volume in every year) | C45: % | D45: Control | E45: 0 | F45: Delivered setting | U45: =IF(E45='Source Data'!E45,"","changed") | V45: Sensitivity lever; 0% = inputs as entered.
B46: Tariff lever (% change applied to every FSL tariff and fee) | C46: % | D46: Control | E46: 0 | F46: Delivered setting | U46: =IF(E46='Source Data'!E46,"","changed") | V46: Sensitivity lever; 0% = inputs as entered.
B47: Operating cost lever (% change applied to cost of sales and operating expenses) | C47: % | D47: Control | E47: 0 | F47: Delivered setting | U47: =IF(E47='Source Data'!E47,"","changed") | V47: Sensitivity lever; 0% = inputs as entered.
B48: Project capex lever (% change applied to post-2023 project capex) | C48: % | D48: Control | E48: 0 | F48: Delivered setting | U48: =IF(E48='Source Data'!E48,"","changed") | V48: Sensitivity lever; 0% = inputs as entered.
B49: Year explained in words on Checks & Reconciliation | C49: year | D49: Control | E49: 2036 | F49: Delivered setting | U49: =IF(E49='Source Data'!E49,"","changed") | V49: Choose 2024-2036; each reconciled line explains its difference for this year in a sentence.
B50: Tolerance for agreement with v29 (absolute, per line and year) | C50: IDR bn | D50: Control | E50: 0.001 | F50: Delivered setting | U50: =IF(E50='Source Data'!E50,"","changed") | V50: Differences within this amount count as agreement (IDR 1 million; v29 Output_FSL displays one decimal and rounds its own balance check to two). At the delivered settings the differences are floating-point only (below 1e-6).
B51: Multipliers used by the calculations (formulas)
B52: Volume multiplier = 1 + volume lever | C52: x | E52: =1+$E$45 -> 1
B53: Tariff multiplier = 1 + tariff lever | C53: x | E53: =1+$E$46 -> 1
B54: Cost multiplier = 1 + cost lever | C54: x | E54: =1+$E$47 -> 1
B55: Capex multiplier = 1 + capex lever | C55: x | E55: =1+$E$48 -> 1 | F55: ='Valuation — Without BUMN'!E75 -> 217.45241
B56: Scenario in force | E56: =$E$42 -> 1
B58: 2. PROJECT REGISTER - every business and project, its source, inclusion switch, timing and where it is modelled
B59: ID Business / project (model name) | C59: Category | D59: Entity | E59: Switch (edit; 1 = ON) | F59: v29 flag / start | G59: Commencement year (edit) | H59: Included (live) | I59: Status (live) | L59: v29 source name | O59: Project-list screenshot name | R59: Go to: revenue | V59: Notes
B60: E1 Teluk Lamong cargodoring & delivery (NPLOG) | C60: Existing | D60: NPLOG | E60: always | F60: in v29 | G60: operating | H60: 1 | I60: Included - existing business | L60: NPLOG - Teluk Lamong existing | O60: - (existing business, no capex line) | R60: Revenue | S60: Costs | T60: D&A | V60: NPLOG entity: FSL 65% economic interest (35% minority) - TO CONFIRM legal shareholding. Not the screenshot line "Teluk Lamong (Surabaya, NP Log)", which is the silo project P04.
B61: E2 Cigading existing terminal (SGT 2) | C61: Existing | D61: SGT2 | E61: always | F61: in v29 | G61: operating | H61: 1 | I61: Included - existing business | L61: Cigading Existing | O61: - (existing business, no capex line) | R61: Revenue | S61: Costs | T61: D&A | V61: Existing business - not in the capex screenshot.
B62: E3 Belawan existing (conveyor & warehouse) | C62: Existing | D62: BLW | E62: always | F62: in v29 | G62: operating | H62: 1 | I62: Included - existing business | L62: Belawan (existing part of the Belawan block) | O62: - (existing business, no capex line) | R62: Revenue | S62: Costs | T62: D&A | V62: Shares the v29 Belawan block with P07; the screenshot line "Belawan/Medan (SGT3)" is the expansion (P07).
B63: E4 WIN stevedoring (Cilegon, Makassar, Surabaya, Medan) | C63: Existing | D63: WIN | E63: always | F63: in v29 | G63: operating | H63: 1 | I63: Included - existing business | L63: Stevedoring WIN combine | O63: - (existing business, no capex line) | R63: Revenue | S63: Costs | T63: D&A | V63: WIN Medan stevedoring is a different business from the Belawan / Medan expansion (P07).
B64: P01 Cigading Wharf 2 | C64: Committed | D64: SGT2 | E64: 1 | F64: ON, 2025 | G64: 2025 | H64: =IF($E$56=1,$E$64,0) -> 1 | I64: =IF(H64=1,"Included - both cases",IF($E$56=2,"Excluded - scenario 2 (existing only)","Switched OFF")) -> Included - both cases | L64: Cigading Expansion: Wharf 2 | O64: Cigading Wharf 2 | R64: Revenue | S64: Costs | T64: Capex / D&A | V64: 10.0 USD mn spent before FY2024 is sunk (Dec-23 assets under construction).
B65: P02 Cigading extended conveyor | C65: Committed | D65: SGT2 | E65: 1 | F65: ON, 2025 | G65: 2025 | H65: =IF($E$56=1,$E$65,0) -> 1 | I65: =IF(H65=1,"Included - both cases",IF($E$56=2,"Excluded - scenario 2 (existing only)","Switched OFF")) -> Included - both cases | L65: Cigading Expansion: Extended Conveyor | O65: Cigading Ext. Conveyor | R65: Revenue | S65: Costs | T65: Capex / D&A | V65: 2.2 USD mn spent before FY2024 is sunk.
B66: P03 KBS warehouse revitalisation (FSL 49% revenue share) | C66: Planned | D66: SGT2 | E66: 1 | F66: ON, 2027 | G66: 2027 | H66: =IF($E$56=1,$E$66,0) -> 1 | I66: =IF(H66=1,"Included - both cases",IF($E$56=2,"Excluded - scenario 2 (existing only)","Switched OFF")) -> Included - both cases | L66: Cigading Expansion: KBS Warehouse Revitalization | O66: Ciwadan Expansion (part - inferred, TO CONFIRM) | R66: Revenue | S66: Costs | T66: Capex / D&A | V66: Not named in the screenshot: only Ciwandan 5.025 + KBS warehouse 6.025 reproduces the 11.0 "Ciwadan Expansion" line - TO CONFIRM the grouping. v29 spends 6.02 USD mn but depreciates nothing (C02).
B67: P04 Teluk Lamong silo | C67: Planned | D67: NPLOG | E67: 1 | F67: ON, 2027 | G67: 2027 | H67: =IF($E$56=1,$E$67,0) -> 1 | I67: =IF(H67=1,"Included - both cases",IF($E$56=2,"Excluded - scenario 2 (existing only)","Switched OFF")) -> Included - both cases | L67: Teluk Lamong - Silo (TTL Silo) | O67: Teluk Lamong (Surabaya, NP Log) | R67: Revenue | S67: Costs | T67: Capex / D&A | V67: Silo project in the NPLOG entity (3.762 USD mn); not the existing Teluk Lamong business.
B68: P05 Dumai bagging & weighbridge | C68: Planned | D68: DUMAI | E68: 1 | F68: ON, 2026 | G68: 2026 | H68: =IF($E$56=1,$E$68,0) -> 1 | I68: =IF(H68=1,"Included - both cases",IF($E$56=2,"Excluded - scenario 2 (existing only)","Switched OFF")) -> Included - both cases | L68: Dumai (bagging and weighbridge) | O68: Dumai | R68: Revenue | S68: Costs | T68: Capex / D&A | V68: v29 6.81 USD mn; the board Stage 2 scope of 20.0 is not in v29.
B69: P06 Ciwandan expansion (FSL 52% tariff share) | C69: Planned | D69: CWD | E69: 1 | F69: ON, 2028 | G69: 2028 | H69: =IF($E$56=1,$E$69,0) -> 1 | I69: =IF(H69=1,"Included - both cases",IF($E$56=2,"Excluded - scenario 2 (existing only)","Switched OFF")) -> Included - both cases | L69: Ciwandan Expansion | O69: Ciwadan Expansion (part - inferred, TO CONFIRM) | R69: Revenue | S69: Costs | T69: Capex / D&A | V69: Spelling differs (Ciwadan / Ciwandan). FSL receives 52% of the total Ciwandan tariff (contract share, not equity).
B70: P07 Belawan expansion (additional volume) | C70: Planned | D70: BLW | E70: 1 | F70: ON, 2026 | G70: 2026 | H70: =IF($E$56=1,$E$70,0) -> 1 | I70: =IF(H70=1,"Included - both cases",IF($E$56=2,"Excluded - scenario 2 (existing only)","Switched OFF")) -> Included - both cases | L70: Belawan (incl. Belawan expansion) | O70: Belawan/Medan (SGT3) | R70: Revenue | S70: Costs | T70: Capex / D&A | V70: Capex 14.025 USD mn. The v29 Belawan block also holds E3; P14 uses the Belawan volume without adding capex (no double count).
B71: P08 DMS trucking fee - Teluk Lamong | C71: Planned | D71: NPLOG | E71: 1 | F71: ON, 2027 | G71: 2027 | H71: =IF($E$56=1,$E$71,0) -> 1 | I71: =IF(H71=1,"Included - both cases",IF($E$56=2,"Excluded - scenario 2 (existing only)","Switched OFF")) -> Included - both cases | L71: Trucking DMS Teluk Lamong | O71: - (fee business, no capex line) | R71: Revenue | S71: Costs | T71: Capex / D&A | V71: Fee business; v29 depreciates 0.04 USD mn of equipment it never buys (C08 adds the capex).
B72: P09 DMS trucking fee - Cigading | C72: Planned | D72: SGT2 | E72: 1 | F72: ON, 2027 | G72: 2027 | H72: =IF($E$56=1,$E$72,0) -> 1 | I72: =IF(H72=1,"Included - both cases",IF($E$56=2,"Excluded - scenario 2 (existing only)","Switched OFF")) -> Included - both cases | L72: Trucking DMS Cigading | O72: - (fee business) | R72: Revenue | S72: Costs | T72: Capex / D&A | V72: Fee business; equipment 0.04 USD mn depreciated, not bought (C08).
B73: P10 DMS trucking fee - Ciwandan | C73: Planned | D73: CWD | E73: 1 | F73: ON, 2028 | G73: 2028 | H73: =IF($E$56=1,$E$73,0) -> 1 | I73: =IF(H73=1,"Included - both cases",IF($E$56=2,"Excluded - scenario 2 (existing only)","Switched OFF")) -> Included - both cases | L73: Trucking DMS Ciwandan | O73: - (fee business) | R73: Revenue | S73: Costs | T73: Capex / D&A | V73: Fee business; equipment 0.03 USD mn (C08).
B74: P11 DMS trucking fee - Belawan | C74: Planned | D74: BLW | E74: 1 | F74: ON, 2027 | G74: 2027 | H74: =IF($E$56=1,$E$74,0) -> 1 | I74: =IF(H74=1,"Included - both cases",IF($E$56=2,"Excluded - scenario 2 (existing only)","Switched OFF")) -> Included - both cases | L74: Trucking DMS Belawan | O74: - (fee business) | R74: Revenue | S74: Costs | T74: Capex / D&A | V74: Fee business; equipment 0.04 USD mn (C08).
B75: P12 BUMN synergy - Pelindo Teluk Lamong operatorship | C75: BUMN synergy | D75: NPLOG | E75: 1 | F75: ON, 2026 | G75: 2026 | H75: =IF($E$56=1,$E$75*$E$43,0) -> 1 | I75: =IF(H75=1,"Included - With BUMN case only",IF($E$56=2,"Excluded - scenario 2 (existing only)",IF($E$43=0,"Excluded - BUMN control OFF (section 1)","Switched OFF"))) -> Included - With BUMN case only | L75: Operatorship with BUMN - Pelindo Teluk Lamong | O75: - (SOE scheme, no capex line) | R75: Revenue | S75: Costs | T75: Capex / D&A | V75: FSL entitlement only (BUMN synergy case); the SOE-retained benefit is shown on BUMN Synergy Calculation and never added to FSL value.
B76: P13 BUMN synergy - KBS Cigading operatorship | C76: BUMN synergy | D76: SGT2 | E76: 1 | F76: ON, 2026 | G76: 2026 | H76: =IF($E$56=1,$E$76*$E$43,0) -> 1 | I76: =IF(H76=1,"Included - With BUMN case only",IF($E$56=2,"Excluded - scenario 2 (existing only)",IF($E$43=0,"Excluded - BUMN control OFF (section 1)","Switched OFF"))) -> Included - With BUMN case only | L76: Operatorship with BUMN - KBS Cigading | O76: - (SOE scheme) | R76: Revenue | S76: Costs | T76: Capex / D&A | V76: FSL entitlement only (BUMN synergy case).
B77: P14 BUMN synergy - Pelindo Belawan operatorship | C77: BUMN synergy | D77: BLW | E77: 1 | F77: ON, 2026 | G77: 2026 | H77: =IF($E$56=1,$E$77*$E$43,0) -> 1 | I77: =IF(H77=1,"Included - With BUMN case only",IF($E$56=2,"Excluded - scenario 2 (existing only)",IF($E$43=0,"Excluded - BUMN control OFF (section 1)","Switched OFF"))) -> Included - With BUMN case only | L77: Operatorship with BUMN - Pelindo Belawan | O77: - (SOE scheme) | R77: Revenue | S77: Costs | T77: Capex / D&A | V77: FSL entitlement on existing and expansion Belawan volume (BUMN synergy case).
B78: P15 TBM (land lease, warehousing, cargo handling) | C78: Pipeline | D78: TBM | E78: 0 | F78: OFF, 2029 | G78: 2029 | H78: =IF($E$56=1,$E$78,0) -> 0 | I78: =IF(H78=1,"Included - both cases",IF($E$56=2,"Excluded - scenario 2 (existing only)","Switched OFF")) -> Switched OFF | L78: TBM (business flag Output_FSL!G40 = 0) | O78: TBM (potential pipeline) | R78: Revenue | S78: Costs | T78: Capex / D&A | V78: In v29 but switched off (Output_FSL!G40 = 0). v29 capex 40.0 USD mn (108 - 68, unexplained) vs 108 in the board deck; land-lease tariff blank in v29 - TO CONFIRM.
B79: ="P16 "&$E$605 -> P16 Lampung | C79: Placeholder | D79: LPG | E79: 0 | F79: not in v29 | G79: =IF(ISNUMBER($E$607),YEAR($E$607),"not set") -> not set | H79: =IF($E$56=1,$E$79,0)*$E$634 -> 0 | I79: =IF(H79=1,"Included",IF($E$79=1,IF($E$634=0,"WARNING: switched ON but EXCLUDED until ready - missing inputs: "&$G$633,"Excluded - scenario 2 (existing only)"),IF($E$634=1,"Ready - switched OFF","Placeholder - inputs not yet populated (OFF)"))) -> Placeholder - inputs not yet populated (OFF) | L79: not in v29 | O79: - (future project) | R79: Revenue | S79: Costs | T79: Capex / D&A | V79: Placeholder: inputs blank and OFF (section 14); fully wired. "Lampung" is not in v29 (it appears only as a region label in the unrelated hidden Sheet2).
B80: ="P17 "&$E$639 -> P17 Pipeline Project 2 | C80: Placeholder | D80: PP2 | E80: 0 | F80: not in v29 | G80: =IF(ISNUMBER($E$641),YEAR($E$641),"not set") -> not set | H80: =IF($E$56=1,$E$80,0)*$E$668 -> 0 | I80: =IF(H80=1,"Included",IF($E$80=1,IF($E$668=0,"WARNING: switched ON but EXCLUDED until ready - missing inputs: "&$G$667,"Excluded - scenario 2 (existing only)"),IF($E$668=1,"Ready - switched OFF","Placeholder - inputs not yet populated (OFF)"))) -> Placeholder - inputs not yet populated (OFF) | L80: not in v29 | O80: - (future project) | R80: Revenue | S80: Costs | T80: Capex / D&A | V80: Placeholder: inputs blank and OFF (section 14); can hold Vietnam or long-term storage once inputs exist.
B81: ="P18 "&$E$673 -> P18 Pipeline Project 3 | C81: Placeholder | D81: PP3 | E81: 0 | F81: not in v29 | G81: =IF(ISNUMBER($E$675),YEAR($E$675),"not set") -> not set | H81: =IF($E$56=1,$E$81,0)*$E$702 -> 0 | I81: =IF(H81=1,"Included",IF($E$81=1,IF($E$702=0,"WARNING: switched ON but EXCLUDED until ready - missing inputs: "&$G$701,"Excluded - scenario 2 (existing only)"),IF($E$702=1,"Ready - switched OFF","Placeholder - inputs not yet populated (OFF)"))) -> Placeholder - inputs not yet populated (OFF) | L81: not in v29 | O81: - (future project) | R81: Revenue | S81: Costs | T81: Capex / D&A | V81: Placeholder: inputs blank and OFF (section 14).
B82: P19 Badas (project template - DUMMY FS data) | C82: Pipeline - FS pending | D82: BADAS | E82: 1 | F82: not in v29 | G82: =YEAR($E$571) -> 2029 | H82: =IF($E$56=1,$E$82,0) -> 1 | I82: =IF(H82=1,"Included in the valuation - DUMMY inputs (FS Data Request)",IF($E$56=2,"Excluded - scenario 2 (existing only)",IF($E$568=1,"Not in the valuation (OFF) - capex in the funding request (DUMMY)","Not in the valuation or the funding request"))) -> Included in the valuation - DUMMY inputs (FS Data Request) | L82: not in v29 (board deck Stage 2) | O82: Badas | R82: Revenue | S82: Costs | T82: Capex / D&A | V82: Badas project template (section 13): every operating input is DUMMY until the FS is received (FS Data Request). Switch = include in company valuation (OFF by default); funding inclusion is set in section 13.
B83: ="F01 "&IF(LEN($E$711&"")=0,"Funding-only project 1 (blank)",$E$711) -> F01 Funding-only project 1 (blank) | C83: Funding only | D83: - | E83: section 15 | F83: not in v29 | G83: - | H83: 0 | I83: =IF(N($E$712)=0,"Blank - contributes nothing",IF($E$714=1,"Funding request only (never valued)","Excluded from the funding request")) -> Blank - contributes nothing | L83: not in v29 (capex-only project without an FS) | O83: - (enter in section 15) | V83: Capex and funding request only; never in the valuation or the financial statements; operating results "FS not available".
B84: ="F02 "&IF(LEN($E$716&"")=0,"Funding-only project 2 (blank)",$E$716) -> F02 Funding-only project 2 (blank) | C84: Funding only | D84: - | E84: section 15 | F84: not in v29 | G84: - | H84: 0 | I84: =IF(N($E$717)=0,"Blank - contributes nothing",IF($E$719=1,"Funding request only (never valued)","Excluded from the funding request")) -> Blank - contributes nothing | L84: not in v29 (capex-only project without an FS) | O84: - (enter in section 15) | V84: Capex and funding request only; never in the valuation or the financial statements; operating results "FS not available".
B85: ="F03 "&IF(LEN($E$721&"")=0,"Funding-only project 3 (blank)",$E$721) -> F03 Funding-only project 3 (blank) | C85: Funding only | D85: - | E85: section 15 | F85: not in v29 | G85: - | H85: 0 | I85: =IF(N($E$722)=0,"Blank - contributes nothing",IF($E$724=1,"Funding request only (never valued)","Excluded from the funding request")) -> Blank - contributes nothing | L85: not in v29 (capex-only project without an FS) | O85: - (enter in section 15) | V85: Capex and funding request only; never in the valuation or the financial statements; operating results "FS not available".
B86: ="F04 "&IF(LEN($E$726&"")=0,"Funding-only project 4 (blank)",$E$726) -> F04 Funding-only project 4 (blank) | C86: Funding only | D86: - | E86: section 15 | F86: not in v29 | G86: - | H86: 0 | I86: =IF(N($E$727)=0,"Blank - contributes nothing",IF($E$729=1,"Funding request only (never valued)","Excluded from the funding request")) -> Blank - contributes nothing | L86: not in v29 (capex-only project without an FS) | O86: - (enter in section 15) | V86: Capex and funding request only; never in the valuation or the financial statements; operating results "FS not available".
B87: ="F05 "&IF(LEN($E$731&"")=0,"Funding-only project 5 (blank)",$E$731) -> F05 Funding-only project 5 (blank) | C87: Funding only | D87: - | E87: section 15 | F87: not in v29 | G87: - | H87: 0 | I87: =IF(N($E$732)=0,"Blank - contributes nothing",IF($E$734=1,"Funding request only (never valued)","Excluded from the funding request")) -> Blank - contributes nothing | L87: not in v29 (capex-only project without an FS) | O87: - (enter in section 15) | V87: Capex and funding request only; never in the valuation or the financial statements; operating results "FS not available".
B88: Switches / commencement years changed vs delivered (cells) | E88: =SUMPRODUCT(--(E64:E82<>'Source Data'!E64:E82))+SUMPRODUCT(--(G64:G78<>'Source Data'!G64:G78)) -> 1 | G88: Projects in valuation (live, P01-P19) | H88: =SUM(H64:H82) -> 15 | I88: =SUM(H75:H77) -> 3 | J88: <- of which BUMN schemes P12-P14
B89: Included = switch x scenario x readiness (placeholders need complete inputs); P12-P14 also need the BUMN control (section 1). With BUMN = E1-E4 + P01-P11 + P12-P14; Without BUMN = the same without P12-P14. Commencement year = first operating year (revenue); capex timing is set separately by the spending % rows.
B91: 3. GENERAL ASSUMPTIONS - dates, currency, units
B92: Assumption | C92: Unit | D92: Type | E92: Parameter | F92: v29 source | G92: Pre-2024 | H92: 2024 | I92: 2025 | J92: 2026 | K92: 2027 | L92: 2028 | M92: 2029 | N92: 2030 | O92: 2031 | P92: 2032 | Q92: 2033 | R92: 2034 | S92: 2035 | T92: 2036 | U92: Diff | V92: Source and explanation
B93: Valuation date (31 December of a model year) | C93: date | D93: CHANGE | E93: 46387 | F93: not in v29 (previous delivery: 31-Dec-2025) | U93: =IF(E93='Source Data'!E93,"","changed") | V93: USER-REQUESTED CHANGE: Requested: 31-Dec-2026. The DCF values FCFF from FY2027; cash, debt and other bridge items are the projected balances at this date (no FY2024-26 actuals supplied).
B94: Discounting convention (1 = mid-year, 2 = year-end) | C94: code | D94: TO CONFIRM | E94: 2 | F94: not in v29 | U94: =IF(E94='Source Data'!E94,"","changed") | V94: TO CONFIRM - PROVISIONAL ASSUMPTION: Not in v29. Basis: year-end - FY2027 cash flow is discounted one full year from 31-Dec-2026 (mid-year would use 0.5 years). Affects: all present values and IRR dates.
B95: Exchange rate (IDR per USD) - converts USD capex, depreciation bases and equity injections of each year; pre-2024 column for sunk spend | C95: IDR per USD | D95: v29 | F95: Calculation_FSL!F17 (named range USD_IDR, one rate for all years) | G95: 16265 | H95: 16265 | I95: 16265 | J95: 16265 | K95: 16265 | L95: 16265 | M95: 16265 | N95: 16265 | O95: 16265 | P95: 16265 | Q95: 16265 | R95: 16265 | S95: 16265 | T95: 16265 | U95: =IF(SUMPRODUCT(--(G95:T95<>'Source Data'!G95:T95))=0,"",SUMPRODUCT(--(G95:T95<>'Source Data'!G95:T95))&" yr") | V95: v29 constant repeated in every year - edit any year on its own. v29 uses one rate for every year; here each year can be edited. USD presentation of the valuation uses the rate of the valuation year.
B96: Model periods: 31-Dec-2023 opening balance sheet (v29 Output_FSL column I); FY2024-FY2036 forecasts (FY2024-26 are v29 forecasts - actuals not supplied, so balances at the valuation date are projections). Financial years end 31 December.
B97: Units: IDR billion unless stated; volumes in tons; tariffs in IDR per ton; project capex inputs in USD million converted at the exchange rate of the spending year.
B99: 4. EXISTING OPERATIONS (E1-E4) - volumes, tariffs, growth and existing-asset depreciation schedules
B100: Base-year volumes are parameters (the starting point); the annual growth rows then drive every later year. Changing the growth of one year moves that year and the years after it.
B101: E1 Teluk Lamong - NPLOG cargodoring & delivery
B102: E1 assumption | C102: Unit | D102: Type | E102: Parameter | F102: v29 source | G102: 2023 | H102: 2024 | I102: 2025 | J102: 2026 | K102: 2027 | L102: 2028 | M102: 2029 | N102: 2030 | O102: 2031 | P102: 2032 | Q102: 2033 | R102: 2034 | S102: 2035 | T102: 2036 | U102: Diff | V102: Source and explanation
B103: Meals throughput FY2023 (actual base) | C103: tons | D103: v29 | E103: 2292945.6 | F103: Input!K41 (=2292945.63*90%) | U103: =IF(E103='Source Data'!E103,"","changed")
B104: FY2024 meals volume as % of FY2023 (one-off reset) | C104: % | D104: v29 | E104: 0.9 | F104: Input!K41 | U104: =IF(E104='Source Data'!E104,"","changed")
B105: Grains throughput FY2023 (actual base) | C105: tons | D105: v29 | E105: 1686920.2 | F105: Input!K55 (=1686920.22*95%) | U105: =IF(E105='Source Data'!E105,"","changed")
B106: FY2024 grains volume as % of FY2023 (one-off reset) | C106: % | D106: v29 | E106: 0.95 | F106: Input!K55 | U106: =IF(E106='Source Data'!E106,"","changed")
B107: Total throughput FY2023 (denominator for per-ton costs) | C107: tons | D107: v29 | E107: 3579865.9 | F107: Calculation_FSL!E52 | U107: =IF(E107='Source Data'!E107,"","changed")
B108: Meals volume growth | C108: % | D108: v29 | F108: Input!K36:W36 | H108: 0 | I108: 0.03 | J108: 0.03 | K108: 0.03 | L108: 0.03 | M108: 0.03 | N108: 0.03 | O108: 0.03 | P108: 0.03 | Q108: 0.03 | R108: 0.03 | S108: 0.03 | T108: 0.03 | U108: =IF(SUMPRODUCT(--(H108:T108<>'Source Data'!H108:T108))=0,"",SUMPRODUCT(--(H108:T108<>'Source Data'!H108:T108))&" yr") | V108: v29 value for each year.
B109: Grains volume growth | C109: % | D109: v29 | F109: Input!K51:W51 (v29 active case 1) | H109: 0 | I109: 0.03 | J109: 0.03 | K109: 0.03 | L109: 0.03 | M109: 0.03 | N109: 0.03 | O109: 0.03 | P109: 0.03 | Q109: 0.03 | R109: 0.03 | S109: 0.03 | T109: 0.03 | U109: =IF(SUMPRODUCT(--(H109:T109<>'Source Data'!H109:T109))=0,"",SUMPRODUCT(--(H109:T109<>'Source Data'!H109:T109))&" yr") | V109: v29 value for each year. v29 alternative case: Input row 52 (3-5%).
B110: Meals tariff | C110: IDR/t | D110: v29 | F110: Input!K43:W43 | H110: 42880 | I110: 42880 | J110: 42880 | K110: 42880 | L110: 42880 | M110: 44166.4 | N110: 44166.4 | O110: 44166.4 | P110: 45491.392 | Q110: 45491.392 | R110: 45491.392 | S110: 45491.392 | T110: 45491.392 | U110: =IF(SUMPRODUCT(--(H110:T110<>'Source Data'!H110:T110))=0,"",SUMPRODUCT(--(H110:T110<>'Source Data'!H110:T110))&" yr") | V110: v29 value for each year.
B111: Grains tariff | C111: IDR/t | D111: v29 | F111: Input!K57:W57 | H111: 42400 | I111: 42400 | J111: 42400 | K111: 42400 | L111: 42400 | M111: 43672 | N111: 43672 | O111: 43672 | P111: 44982.16 | Q111: 44982.16 | R111: 44982.16 | S111: 44982.16 | T111: 44982.16 | U111: =IF(SUMPRODUCT(--(H111:T111<>'Source Data'!H111:T111))=0,"",SUMPRODUCT(--(H111:T111<>'Source Data'!H111:T111))&" yr") | V111: v29 value for each year.
...

Sheet FS Data Request
B1: FS DATA REQUEST - data needed from the Badas feasibility study (and for funding-only projects and pipeline placeholders)
B2: Each item is entered in ONE place only: the Inputs cell in column I (click to go there). This sheet only reads - never paste over it. Status turns to "Updated" once the Inputs value differs from the delivered DUMMY value.
B3: Go to sheet: | C3: Model Flow | D3: Inputs | E3: [FS Request] | F3: Revenue | G3: Costs | H3: BUMN Synergy | I3: Capex | J3: Work. cap. | K3: Financing | L3: Funding | M3: Out: w/o BUMN | N3: Out: With BUMN | O3: Val: w/o BUMN | P3: Val: With BUMN | Q3: Proj. CF | R3: Proj. Summary | S3: Checks | T3: Source Data
C5: Badas items still DUMMY / provisional (count) | E5: =COUNTIF(H9:H38,"DUMMY*")+COUNTIF(H9:H38,"PROVISIONAL*") -> 30 | F5: ="of 30 items" -> of 30 items
B7: A. BADAS (P19) - FEASIBILITY STUDY DATA (every item is DUMMY until replaced; total investment provisional from the board deck)
B8: # | C8: Data item | D8: Definition (what the FS should provide) | E8: Unit | F8: Period | G8: Current assumption (FY2029 for annual items; phasing = total) | H8: Status | I8: Enter in (Inputs) | J8: Used in (calculation rows)
B9: B01 | C9: Commercial operation date | D9: First day of commercial operations after construction and commissioning (date). | E9: date | F9: Date | G9: =Inputs!$E$571 -> 47119 | H9: =IF(Inputs!$E$571<>'Source Data'!$E$571,"Updated - FS data entered","DUMMY - awaiting FS") -> DUMMY - awaiting FS | I9: Inputs E571 | J9: Revenue row 28
B10: B02 | C10: Design capacity | D10: Maximum annual throughput of the terminal at 100% utilisation (tons per year). | E10: tons p.a. | F10: Parameter | G10: =Inputs!$E$572 -> 1000000 | H10: =IF(Inputs!$E$572<>'Source Data'!$E$572,"Updated - FS data entered","DUMMY - awaiting FS") -> DUMMY - awaiting FS | I10: Inputs E572 | J10: Revenue row 175
B11: B03 | C11: Utilisation by year | D11: Expected throughput / design capacity for each operating year (ramp-up to steady state). | E11: % capacity | F11: Annual FY2024-36 | G11: =Inputs!M587 -> 0.55 | H11: =IF(SUMPRODUCT(--(Inputs!$H$587:$T$587<>'Source Data'!$H$587:$T$587))>0,"Updated - FS data entered","DUMMY - awaiting FS") -> DUMMY - awaiting FS | I11: Inputs H587 | J11: Revenue row 175
B12: B04 | C12: Handling tariff | D12: Tariff per ton for cargo handling (100%, before any revenue sharing), by year. | E12: IDR/t | F12: Annual FY2024-36 | G12: =Inputs!M588 -> 45000 | H12: =IF(SUMPRODUCT(--(Inputs!$H$588:$T$588<>'Source Data'!$H$588:$T$588))>0,"Updated - FS data entered","DUMMY - awaiting FS") -> DUMMY - awaiting FS | I12: Inputs H588 | J12: Revenue row 178 (+1)
B13: B05 | C13: Share of throughput stored | D13: Share of annual throughput that is stored in the terminal. | E13: % | F13: Parameter | G13: =Inputs!$E$573 -> 0.5 | H13: =IF(Inputs!$E$573<>'Source Data'!$E$573,"Updated - FS data entered","DUMMY - awaiting FS") -> DUMMY - awaiting FS | I13: Inputs E573 | J13: Revenue row 176
B14: B06 | C14: Average storage period | D14: Average months each stored ton stays in storage (drives storage revenue). | E14: months | F14: Parameter | G14: =Inputs!$E$574 -> 1.5 | H14: =IF(Inputs!$E$574<>'Source Data'!$E$574,"Updated - FS data entered","DUMMY - awaiting FS") -> DUMMY - awaiting FS | I14: Inputs E574 | J14: Revenue row 182
B15: B07 | C15: Storage tariff | D15: Tariff per ton per month of storage, by year. | E15: IDR/t/month | F15: Annual FY2024-36 | G15: =Inputs!M589 -> 12000 | H15: =IF(SUMPRODUCT(--(Inputs!$H$589:$T$589<>'Source Data'!$H$589:$T$589))>0,"Updated - FS data entered","DUMMY - awaiting FS") -> DUMMY - awaiting FS | I15: Inputs H589 | J15: Revenue row 179 (+1)
B16: B08 | C16: Share of throughput using ancillary services | D16: Share of throughput bagged / weighed (ancillary services). | E16: % | F16: Parameter | G16: =Inputs!$E$575 -> 0.3 | H16: =IF(Inputs!$E$575<>'Source Data'!$E$575,"Updated - FS data entered","DUMMY - awaiting FS") -> DUMMY - awaiting FS | I16: Inputs E575 | J16: Revenue row 177
B17: B09 | C17: Ancillary services tariff | D17: Tariff per ton for bagging / weighing, by year. | E17: IDR/t | F17: Annual FY2024-36 | G17: =Inputs!M590 -> 9000 | H17: =IF(SUMPRODUCT(--(Inputs!$H$590:$T$590<>'Source Data'!$H$590:$T$590))>0,"Updated - FS data entered","DUMMY - awaiting FS") -> DUMMY - awaiting FS | I17: Inputs H590 | J17: Revenue row 180 (+1)
B18: B10 | C18: FSL revenue share | D18: Share of gross Badas revenue received by FSL under the port / concession arrangement. | E18: % | F18: Parameter | G18: =Inputs!$E$570 -> 1 | H18: =IF(Inputs!$E$570<>'Source Data'!$E$570,"Updated - FS data entered","DUMMY - awaiting FS") -> DUMMY - awaiting FS | I18: Inputs E570 | J18: Revenue row 185
B19: B11 | C19: Concession / port fee | D19: Fee paid to the port owner or concession grantor as % of revenue, by year. | E19: % revenue | F19: Annual FY2024-36 | G19: =Inputs!M597 -> 0.05 | H19: =IF(SUMPRODUCT(--(Inputs!$H$597:$T$597<>'Source Data'!$H$597:$T$597))>0,"Updated - FS data entered","DUMMY - awaiting FS") -> DUMMY - awaiting FS | I19: Inputs H597 | J19: Costs row 205
B20: B12 | C20: Variable operating cost | D20: Cost per ton handled: fuel, power, casual labour, consumables, by year. | E20: IDR/t | F20: Annual FY2024-36 | G20: =Inputs!M591 -> 8500 | H20: =IF(SUMPRODUCT(--(Inputs!$H$591:$T$591<>'Source Data'!$H$591:$T$591))>0,"Updated - FS data entered","DUMMY - awaiting FS") -> DUMMY - awaiting FS | I20: Inputs H591 | J20: Costs row 201
B21: B13 | C21: Permanent headcount | D21: Number of permanent staff by year (staffing plan). | E21: persons | F21: Annual FY2024-36 | G21: =Inputs!M592 -> 40 | H21: =IF(SUMPRODUCT(--(Inputs!$H$592:$T$592<>'Source Data'!$H$592:$T$592))>0,"Updated - FS data entered","DUMMY - awaiting FS") -> DUMMY - awaiting FS | I21: Inputs H592 | J21: Costs row 202
B22: B14 | C22: Staff cost per head | D22: Average annual salary and benefits per permanent employee (IDR mn), by year. | E22: IDR mn p.a. | F22: Annual FY2024-36 | G22: =Inputs!M593 -> 150 | H22: =IF(SUMPRODUCT(--(Inputs!$H$593:$T$593<>'Source Data'!$H$593:$T$593))>0,"Updated - FS data entered","DUMMY - awaiting FS") -> DUMMY - awaiting FS | I22: Inputs H593 | J22: Costs row 202
B23: B15 | C23: Other fixed operating costs | D23: G&A, security, utilities and other fixed costs per year (IDR bn). | E23: IDR bn p.a. | F23: Annual FY2024-36 | G23: =Inputs!M594 -> 2.5 | H23: =IF(SUMPRODUCT(--(Inputs!$H$594:$T$594<>'Source Data'!$H$594:$T$594))>0,"Updated - FS data entered","DUMMY - awaiting FS") -> DUMMY - awaiting FS | I23: Inputs H594 | J23: Costs row 207
B24: B16 | C24: Maintenance cost | D24: Annual maintenance as % of total investment, by year. | E24: % of capex p.a. | F24: Annual FY2024-36 | G24: =Inputs!M595 -> 0.015 | H24: =IF(SUMPRODUCT(--(Inputs!$H$595:$T$595<>'Source Data'!$H$595:$T$595))>0,"Updated - FS data entered","DUMMY - awaiting FS") -> DUMMY - awaiting FS | I24: Inputs H595 | J24: Costs row 203
B25: B17 | C25: Insurance cost | D25: Annual insurance premium as % of total investment, by year. | E25: % of capex p.a. | F25: Annual FY2024-36 | G25: =Inputs!M596 -> 0.005 | H25: =IF(SUMPRODUCT(--(Inputs!$H$596:$T$596<>'Source Data'!$H$596:$T$596))>0,"Updated - FS data entered","DUMMY - awaiting FS") -> DUMMY - awaiting FS | I25: Inputs H596 | J25: Costs row 204
B26: B18 | C26: Pre-operating costs | D26: Recruitment, training and commissioning costs expensed before operations start (IDR bn). | E26: IDR bn | F26: Parameter | G26: =Inputs!$E$576 -> 1.5 | H26: =IF(Inputs!$E$576<>'Source Data'!$E$576,"Updated - FS data entered","DUMMY - awaiting FS") -> DUMMY - awaiting FS | I26: Inputs E576 | J26: Costs row 208
B27: B19 | C27: Total project investment | D27: Total capex budget incl. contingency (USD mn); provisional 10.0 from the board deck Stage 2. | E27: USD mn | F27: Parameter | G27: =Inputs!$E$577 -> 10 | H27: =IF(Inputs!$E$577<>'Source Data'!$E$577,"Updated - FS data entered","PROVISIONAL (board deck)") -> PROVISIONAL (board deck) | I27: Inputs E577 | J27: Capex row 27 (+1)
B28: B20 | C28: Capex phasing | D28: Share of the total investment spent in each year of construction (must add to 100%). | E28: % of total | F28: Annual FY2024-36 | G28: =SUM(Inputs!$H$578:$T$578) -> 1 | H28: =IF(SUMPRODUCT(--(Inputs!$H$578:$T$578<>'Source Data'!$H$578:$T$578))>0,"Updated - FS data entered","DUMMY - awaiting FS") -> DUMMY - awaiting FS | I28: Inputs H578 | J28: Capex row 27
B29: B21 | C29: Building / civil works share | D29: Share of capex in buildings and civil works (balance = equipment), for depreciation. | E29: % | F29: Parameter | G29: =Inputs!$E$579 -> 0.6 | H29: =IF(Inputs!$E$579<>'Source Data'!$E$579,"Updated - FS data entered","DUMMY - awaiting FS") -> DUMMY - awaiting FS | I29: Inputs E579 | J29: Capex row 170
B30: B22 | C30: Useful life - buildings / civil works | D30: Depreciation life of buildings and civil works (years). | E30: years | F30: Parameter | G30: =Inputs!$E$580 -> 20 | H30: =IF(Inputs!$E$580<>'Source Data'!$E$580,"Updated - FS data entered","DUMMY - awaiting FS") -> DUMMY - awaiting FS | I30: Inputs E580 | J30: Capex row 170
B31: B23 | C31: Useful life - equipment | D31: Depreciation life of equipment (years). | E31: years | F31: Parameter | G31: =Inputs!$E$581 -> 10 | H31: =IF(Inputs!$E$581<>'Source Data'!$E$581,"Updated - FS data entered","DUMMY - awaiting FS") -> DUMMY - awaiting FS | I31: Inputs E581 | J31: Capex row 170
B32: B24 | C32: Receivable days | D32: Average collection period on revenue (days). | E32: days | F32: Parameter | G32: =Inputs!$E$582 -> 45 | H32: =IF(Inputs!$E$582<>'Source Data'!$E$582,"Updated - FS data entered","DUMMY - awaiting FS") -> DUMMY - awaiting FS | I32: Inputs E582 | J32: Work. cap. row 106
B33: B25 | C33: Payable days | D33: Average payment period on cost of sales (days). | E33: days | F33: Parameter | G33: =Inputs!$E$583 -> 30 | H33: =IF(Inputs!$E$583<>'Source Data'!$E$583,"Updated - FS data entered","DUMMY - awaiting FS") -> DUMMY - awaiting FS | I33: Inputs E583 | J33: Work. cap. row 107
B34: B26 | C34: Project debt share | D34: Share of capex financed by Badas project debt (financing plan). | E34: % | F34: Parameter | G34: =Inputs!$E$584 -> 0.5 | H34: =IF(Inputs!$E$584<>'Source Data'!$E$584,"Updated - FS data entered","DUMMY - awaiting FS") -> DUMMY - awaiting FS | I34: Inputs E584 | J34: Financing row 48
B35: B27 | C35: Project debt interest rate | D35: All-in interest rate on the project debt, by year. | E35: % p.a. | F35: Annual FY2024-36 | G35: =Inputs!M598 -> 0.105 | H35: =IF(SUMPRODUCT(--(Inputs!$H$598:$T$598<>'Source Data'!$H$598:$T$598))>0,"Updated - FS data entered","DUMMY - awaiting FS") -> DUMMY - awaiting FS | I35: Inputs H598 | J35: Financing row 51
B36: B28 | C36: Project debt tenor | D36: Tenor of each drawdown incl. grace (years). | E36: years | F36: Parameter | G36: =Inputs!$E$585 -> 7 | H36: =IF(Inputs!$E$585<>'Source Data'!$E$585,"Updated - FS data entered","DUMMY - awaiting FS") -> DUMMY - awaiting FS | I36: Inputs E585 | J36: Financing row 49
B37: B29 | C37: Project debt grace period | D37: Years before principal repayments start. | E37: years | F37: Parameter | G37: =Inputs!$E$586 -> 2 | H37: =IF(Inputs!$E$586<>'Source Data'!$E$586,"Updated - FS data entered","DUMMY - awaiting FS") -> DUMMY - awaiting FS | I37: Inputs E586 | J37: Financing row 49
B38: B30 | C38: FSL ownership of the Badas entity | D38: FSL economic interest in the project company (below 100% creates a minority interest). | E38: % | F38: Parameter | G38: =Inputs!$E$569 -> 1 | H38: =IF(Inputs!$E$569<>'Source Data'!$E$569,"Updated - FS data entered","DUMMY - awaiting FS") -> DUMMY - awaiting FS | I38: Inputs E569 | J38: Out: With BUMN row 235
C40: Controls (not FS data): valuation inclusion = Inputs section 2 (register switch P19, OFF as delivered); funding inclusion = Inputs section 13 (bd.fund, ON). Corporate tax rate, FX, WACC and levers are shared with the other projects.
B42: B. FUNDING-ONLY PROJECTS (F01-F05) - capex and phasing only (no FS; never valued)
B43: # | C43: Project | D43: Data needed | E43: Unit | F43: Period | G43: Current | H43: Status | I43: Enter in (Inputs) | J43: Used in
B44: F01 | C44: ="F01 "&IF(LEN(Inputs!$E$711&"")=0,"(blank)",Inputs!$E$711) -> F01 (blank) | D44: Name | E44: text | F44: Parameter | G44: =IF(LEN(Inputs!$E$711&"")=0,"(blank)",Inputs!$E$711) -> (blank) | H44: =IF(LEN(Inputs!$E$711&"")=0,"Blank - optional","Entered") -> Blank - optional | I44: Inputs E711 | J44: Capex row 341
B45: F01 | C45: ="F01 "&IF(LEN(Inputs!$E$711&"")=0,"(blank)",Inputs!$E$711) -> F01 (blank) | D45: Total capex | E45: USD mn | F45: Parameter | G45: =IF(LEN(Inputs!$E$712&"")=0,"(blank)",Inputs!$E$712) -> (blank) | H45: =IF(LEN(Inputs!$E$712&"")=0,"Blank - optional","Entered") -> Blank - optional | I45: Inputs E712 | J45: Capex row 341
B46: F01 | C46: ="F01 "&IF(LEN(Inputs!$E$711&"")=0,"(blank)",Inputs!$E$711) -> F01 (blank) | D46: Spending % by year (must add to 100%) | E46: % of total | F46: Annual FY2024-36 | G46: =SUM(Inputs!$H$713:$T$713) -> 0 | H46: =IF(COUNT(Inputs!$H$713:$T$713)=0,"Blank - optional",IF(ABS(SUM(Inputs!$H$713:$T$713)-1)<0.0001,"Entered - adds to 100%","WARNING - does not add to 100%")) -> Blank - optional | I46: Inputs H713:T713 | J46: Capex row 341
B47: F02 | C47: ="F02 "&IF(LEN(Inputs!$E$716&"")=0,"(blank)",Inputs!$E$716) -> F02 (blank) | D47: Name | E47: text | F47: Parameter | G47: =IF(LEN(Inputs!$E$716&"")=0,"(blank)",Inputs!$E$716) -> (blank) | H47: =IF(LEN(Inputs!$E$716&"")=0,"Blank - optional","Entered") -> Blank - optional | I47: Inputs E716 | J47: Capex row 342
B48: F02 | C48: ="F02 "&IF(LEN(Inputs!$E$716&"")=0,"(blank)",Inputs!$E$716) -> F02 (blank) | D48: Total capex | E48: USD mn | F48: Parameter | G48: =IF(LEN(Inputs!$E$717&"")=0,"(blank)",Inputs!$E$717) -> (blank) | H48: =IF(LEN(Inputs!$E$717&"")=0,"Blank - optional","Entered") -> Blank - optional | I48: Inputs E717 | J48: Capex row 342
B49: F02 | C49: ="F02 "&IF(LEN(Inputs!$E$716&"")=0,"(blank)",Inputs!$E$716) -> F02 (blank) | D49: Spending % by year (must add to 100%) | E49: % of total | F49: Annual FY2024-36 | G49: =SUM(Inputs!$H$718:$T$718) -> 0 | H49: =IF(COUNT(Inputs!$H$718:$T$718)=0,"Blank - optional",IF(ABS(SUM(Inputs!$H$718:$T$718)-1)<0.0001,"Entered - adds to 100%","WARNING - does not add to 100%")) -> Blank - optional | I49: Inputs H718:T718 | J49: Capex row 342
B50: F03 | C50: ="F03 "&IF(LEN(Inputs!$E$721&"")=0,"(blank)",Inputs!$E$721) -> F03 (blank) | D50: Name | E50: text | F50: Parameter | G50: =IF(LEN(Inputs!$E$721&"")=0,"(blank)",Inputs!$E$721) -> (blank) | H50: =IF(LEN(Inputs!$E$721&"")=0,"Blank - optional","Entered") -> Blank - optional | I50: Inputs E721 | J50: Capex row 343
B51: F03 | C51: ="F03 "&IF(LEN(Inputs!$E$721&"")=0,"(blank)",Inputs!$E$721) -> F03 (blank) | D51: Total capex | E51: USD mn | F51: Parameter | G51: =IF(LEN(Inputs!$E$722&"")=0,"(blank)",Inputs!$E$722) -> (blank) | H51: =IF(LEN(Inputs!$E$722&"")=0,"Blank - optional","Entered") -> Blank - optional | I51: Inputs E722 | J51: Capex row 343
B52: F03 | C52: ="F03 "&IF(LEN(Inputs!$E$721&"")=0,"(blank)",Inputs!$E$721) -> F03 (blank) | D52: Spending % by year (must add to 100%) | E52: % of total | F52: Annual FY2024-36 | G52: =SUM(Inputs!$H$723:$T$723) -> 0 | H52: =IF(COUNT(Inputs!$H$723:$T$723)=0,"Blank - optional",IF(ABS(SUM(Inputs!$H$723:$T$723)-1)<0.0001,"Entered - adds to 100%","WARNING - does not add to 100%")) -> Blank - optional | I52: Inputs H723:T723 | J52: Capex row 343
B53: F04 | C53: ="F04 "&IF(LEN(Inputs!$E$726&"")=0,"(blank)",Inputs!$E$726) -> F04 (blank) | D53: Name | E53: text | F53: Parameter | G53: =IF(LEN(Inputs!$E$726&"")=0,"(blank)",Inputs!$E$726) -> (blank) | H53: =IF(LEN(Inputs!$E$726&"")=0,"Blank - optional","Entered") -> Blank - optional | I53: Inputs E726 | J53: Capex row 344
B54: F04 | C54: ="F04 "&IF(LEN(Inputs!$E$726&"")=0,"(blank)",Inputs!$E$726) -> F04 (blank) | D54: Total capex | E54: USD mn | F54: Parameter | G54: =IF(LEN(Inputs!$E$727&"")=0,"(blank)",Inputs!$E$727) -> (blank) | H54: =IF(LEN(Inputs!$E$727&"")=0,"Blank - optional","Entered") -> Blank - optional | I54: Inputs E727 | J54: Capex row 344
B55: F04 | C55: ="F04 "&IF(LEN(Inputs!$E$726&"")=0,"(blank)",Inputs!$E$726) -> F04 (blank) | D55: Spending % by year (must add to 100%) | E55: % of total | F55: Annual FY2024-36 | G55: =SUM(Inputs!$H$728:$T$728) -> 0 | H55: =IF(COUNT(Inputs!$H$728:$T$728)=0,"Blank - optional",IF(ABS(SUM(Inputs!$H$728:$T$728)-1)<0.0001,"Entered - adds to 100%","WARNING - does not add to 100%")) -> Blank - optional | I55: Inputs H728:T728 | J55: Capex row 344
B56: F05 | C56: ="F05 "&IF(LEN(Inputs!$E$731&"")=0,"(blank)",Inputs!$E$731) -> F05 (blank) | D56: Name | E56: text | F56: Parameter | G56: =IF(LEN(Inputs!$E$731&"")=0,"(blank)",Inputs!$E$731) -> (blank) | H56: =IF(LEN(Inputs!$E$731&"")=0,"Blank - optional","Entered") -> Blank - optional | I56: Inputs E731 | J56: Capex row 345
B57: F05 | C57: ="F05 "&IF(LEN(Inputs!$E$731&"")=0,"(blank)",Inputs!$E$731) -> F05 (blank) | D57: Total capex | E57: USD mn | F57: Parameter | G57: =IF(LEN(Inputs!$E$732&"")=0,"(blank)",Inputs!$E$732) -> (blank) | H57: =IF(LEN(Inputs!$E$732&"")=0,"Blank - optional","Entered") -> Blank - optional | I57: Inputs E732 | J57: Capex row 345
B58: F05 | C58: ="F05 "&IF(LEN(Inputs!$E$731&"")=0,"(blank)",Inputs!$E$731) -> F05 (blank) | D58: Spending % by year (must add to 100%) | E58: % of total | F58: Annual FY2024-36 | G58: =SUM(Inputs!$H$733:$T$733) -> 0 | H58: =IF(COUNT(Inputs!$H$733:$T$733)=0,"Blank - optional",IF(ABS(SUM(Inputs!$H$733:$T$733)-1)<0.0001,"Entered - adds to 100%","WARNING - does not add to 100%")) -> Blank - optional | I58: Inputs H733:T733 | J58: Capex row 345
B60: C. PIPELINE PLACEHOLDERS (P16-P18, e.g. Lampung) - required inputs before a placeholder can be switched into the valuation
B61: # | C61: Placeholder | D61: Readiness (missing inputs listed on Inputs) | E61: Ready | F61: Switch | H61: Status | I61: Enter in (Inputs)
B62: P16 | C62: ="P16 "&Inputs!$E$605 -> P16 Lampung | D62: =IF(Inputs!$E$634=1,"All required inputs complete","Missing: "&Inputs!$G$633) -> Missing: ownership (0-100%); commencement date (2026-2036); capacity; utilisation for every operating year; tariff for every operating year; variable cost for every operating year; fixed cost for every operating year; capex total; capex phasing adding to 100%; building share and useful lives; | E62: =Inputs!$E$634 -> 0 | F62: =Inputs!$E$79 -> 0 | H62: =Inputs!$I$79 -> Placeholder - inputs not yet populated (OFF) | I62: Inputs row 605
B63: P17 | C63: ="P17 "&Inputs!$E$639 -> P17 Pipeline Project 2 | D63: =IF(Inputs!$E$668=1,"All required inputs complete","Missing: "&Inputs!$G$667) -> Missing: ownership (0-100%); commencement date (2026-2036); capacity; utilisation for every operating year; tariff for every operating year; variable cost for every operating year; fixed cost for every operating year; capex total; capex phasing adding to 100%; building share and useful lives; | E63: =Inputs!$E$668 -> 0 | F63: =Inputs!$E$80 -> 0 | H63: =Inputs!$I$80 -> Placeholder - inputs not yet populated (OFF) | I63: Inputs row 639
B64: P18 | C64: ="P18 "&Inputs!$E$673 -> P18 Pipeline Project 3 | D64: =IF(Inputs!$E$702=1,"All required inputs complete","Missing: "&Inputs!$G$701) -> Missing: ownership (0-100%); commencement date (2026-2036); capacity; utilisation for every operating year; tariff for every operating year; variable cost for every operating year; fixed cost for every operating year; capex total; capex phasing adding to 100%; building share and useful lives; | E64: =Inputs!$E$702 -> 0 | F64: =Inputs!$E$81 -> 0 | H64: =Inputs!$I$81 -> Placeholder - inputs not yet populated (OFF) | I64: Inputs row 673

Sheet Revenue Calculation
B1: REVENUE CALCULATION - volume x tariff for every business and project (operational drivers visible; v29 methods)
B2: Volume drivers -> volume -> tariff (x tariff lever) -> revenue, each year from its own annual input. P12-P14 are calculated on BUMN Synergy Calculation and summarised here. Badas (P19): section E, DUMMY inputs. Model Flow explains the chain.
B3: Go to sheet: | C3: Model Flow | D3: Inputs | E3: FS Request | F3: [Revenue] | G3: Costs | H3: BUMN Synergy | I3: Capex | J3: Work. cap. | K3: Financing | L3: Funding | M3: Out: w/o BUMN | N3: Out: With BUMN | O3: Val: w/o BUMN | P3: Val: With BUMN | Q3: Proj. CF | R3: Proj. Summary | S3: Checks | T3: Source Data
G4: Dec-23 | H4: FY | I4: FY | J4: FY | K4: FY | L4: FY | M4: FY | N4: FY | O4: FY | P4: FY | Q4: FY | R4: FY | S4: FY | T4: FY
B5: IDR bn unless stated | C5: Unit | D5: Basis | E5: Parameter | G5: 2023 | H5: 2024 | I5: 2025 | J5: 2026 | K5: 2027 | L5: 2028 | M5: 2029 | N5: 2030 | O5: 2031 | P5: 2032 | Q5: 2033 | R5: 2034 | S5: 2035 | T5: 2036 | U5: Note
B6: A. TIMELINE AND PROJECT TIMING (1 = operating in the year; commencement year = Inputs section 2; capex timing is separate - Capex & Depreciation A)
B7: Financial year (31 December year-end) | C7: year | G7: 2023 | H7: 2024 | I7: 2025 | J7: 2026 | K7: 2027 | L7: 2028 | M7: 2029 | N7: 2030 | O7: 2031 | P7: 2032 | Q7: 2033 | R7: 2034 | S7: 2035 | T7: 2036
B8: Days in year | C8: days | G8: =DATE(G7,12,31)-DATE(G7,1,1)+1 -> 365 | H8: =DATE(H7,12,31)-DATE(H7,1,1)+1 -> 366 | I8: =DATE(I7,12,31)-DATE(I7,1,1)+1 -> 365 | J8: =DATE(J7,12,31)-DATE(J7,1,1)+1 -> 365 | K8: =DATE(K7,12,31)-DATE(K7,1,1)+1 -> 365 | L8: =DATE(L7,12,31)-DATE(L7,1,1)+1 -> 366 | M8: =DATE(M7,12,31)-DATE(M7,1,1)+1 -> 365 | N8: =DATE(N7,12,31)-DATE(N7,1,1)+1 -> 365 | ... T8: =DATE(T7,12,31)-DATE(T7,1,1)+1 -> 366
D9: Start year | E9: Included | F9: Shift vs v29 (yrs)
B10: P01 Cigading Wharf 2 | C10: flag | D10: =Inputs!$G$64 -> 2025 | E10: =Inputs!$H$64 -> 1 | F10: =D10-'Source Data'!$G$64 -> 0 | G10: 0 | H10: =IF(H7>=$D$10,1,0)*Inputs!$H$64 -> 0 | I10: =IF(I7>=$D$10,1,0)*Inputs!$H$64 -> 1 | J10: =IF(J7>=$D$10,1,0)*Inputs!$H$64 -> 1 | K10: =IF(K7>=$D$10,1,0)*Inputs!$H$64 -> 1 | L10: =IF(L7>=$D$10,1,0)*Inputs!$H$64 -> 1 | M10: =IF(M7>=$D$10,1,0)*Inputs!$H$64 -> 1 | N10: =IF(N7>=$D$10,1,0)*Inputs!$H$64 -> 1 | O10: =IF(O7>=$D$10,1,0)*Inputs!$H$64 -> 1 | ... T10: =IF(T7>=$D$10,1,0)*Inputs!$H$64 -> 1
B11: P02 Cigading extended conveyor | C11: flag | D11: =Inputs!$G$65 -> 2025 | E11: =Inputs!$H$65 -> 1 | F11: =D11-'Source Data'!$G$65 -> 0 | G11: 0 | H11: =IF(H7>=$D$11,1,0)*Inputs!$H$65 -> 0 | I11: =IF(I7>=$D$11,1,0)*Inputs!$H$65 -> 1 | J11: =IF(J7>=$D$11,1,0)*Inputs!$H$65 -> 1 | K11: =IF(K7>=$D$11,1,0)*Inputs!$H$65 -> 1 | L11: =IF(L7>=$D$11,1,0)*Inputs!$H$65 -> 1 | M11: =IF(M7>=$D$11,1,0)*Inputs!$H$65 -> 1 | N11: =IF(N7>=$D$11,1,0)*Inputs!$H$65 -> 1 | O11: =IF(O7>=$D$11,1,0)*Inputs!$H$65 -> 1 | ... T11: =IF(T7>=$D$11,1,0)*Inputs!$H$65 -> 1
B12: P03 KBS warehouse revitalisation (FSL 49% revenue share) | C12: flag | D12: =Inputs!$G$66 -> 2027 | E12: =Inputs!$H$66 -> 1 | F12: =D12-'Source Data'!$G$66 -> 0 | G12: 0 | H12: =IF(H7>=$D$12,1,0)*Inputs!$H$66 -> 0 | I12: =IF(I7>=$D$12,1,0)*Inputs!$H$66 -> 0 | J12: =IF(J7>=$D$12,1,0)*Inputs!$H$66 -> 0 | K12: =IF(K7>=$D$12,1,0)*Inputs!$H$66 -> 1 | L12: =IF(L7>=$D$12,1,0)*Inputs!$H$66 -> 1 | M12: =IF(M7>=$D$12,1,0)*Inputs!$H$66 -> 1 | N12: =IF(N7>=$D$12,1,0)*Inputs!$H$66 -> 1 | O12: =IF(O7>=$D$12,1,0)*Inputs!$H$66 -> 1 | ... T12: =IF(T7>=$D$12,1,0)*Inputs!$H$66 -> 1
B13: P04 Teluk Lamong silo | C13: flag | D13: =Inputs!$G$67 -> 2027 | E13: =Inputs!$H$67 -> 1 | F13: =D13-'Source Data'!$G$67 -> 0 | G13: 0 | H13: =IF(H7>=$D$13,1,0)*Inputs!$H$67 -> 0 | I13: =IF(I7>=$D$13,1,0)*Inputs!$H$67 -> 0 | J13: =IF(J7>=$D$13,1,0)*Inputs!$H$67 -> 0 | K13: =IF(K7>=$D$13,1,0)*Inputs!$H$67 -> 1 | L13: =IF(L7>=$D$13,1,0)*Inputs!$H$67 -> 1 | M13: =IF(M7>=$D$13,1,0)*Inputs!$H$67 -> 1 | N13: =IF(N7>=$D$13,1,0)*Inputs!$H$67 -> 1 | O13: =IF(O7>=$D$13,1,0)*Inputs!$H$67 -> 1 | ... T13: =IF(T7>=$D$13,1,0)*Inputs!$H$67 -> 1
B14: P05 Dumai bagging & weighbridge | C14: flag | D14: =Inputs!$G$68 -> 2026 | E14: =Inputs!$H$68 -> 1 | F14: =D14-'Source Data'!$G$68 -> 0 | G14: 0 | H14: =IF(H7>=$D$14,1,0)*Inputs!$H$68 -> 0 | I14: =IF(I7>=$D$14,1,0)*Inputs!$H$68 -> 0 | J14: =IF(J7>=$D$14,1,0)*Inputs!$H$68 -> 1 | K14: =IF(K7>=$D$14,1,0)*Inputs!$H$68 -> 1 | L14: =IF(L7>=$D$14,1,0)*Inputs!$H$68 -> 1 | M14: =IF(M7>=$D$14,1,0)*Inputs!$H$68 -> 1 | N14: =IF(N7>=$D$14,1,0)*Inputs!$H$68 -> 1 | O14: =IF(O7>=$D$14,1,0)*Inputs!$H$68 -> 1 | ... T14: =IF(T7>=$D$14,1,0)*Inputs!$H$68 -> 1
B15: P06 Ciwandan expansion (FSL 52% tariff share) | C15: flag | D15: =Inputs!$G$69 -> 2028 | E15: =Inputs!$H$69 -> 1 | F15: =D15-'Source Data'!$G$69 -> 0 | G15: 0 | H15: =IF(H7>=$D$15,1,0)*Inputs!$H$69 -> 0 | I15: =IF(I7>=$D$15,1,0)*Inputs!$H$69 -> 0 | J15: =IF(J7>=$D$15,1,0)*Inputs!$H$69 -> 0 | K15: =IF(K7>=$D$15,1,0)*Inputs!$H$69 -> 0 | L15: =IF(L7>=$D$15,1,0)*Inputs!$H$69 -> 1 | M15: =IF(M7>=$D$15,1,0)*Inputs!$H$69 -> 1 | N15: =IF(N7>=$D$15,1,0)*Inputs!$H$69 -> 1 | O15: =IF(O7>=$D$15,1,0)*Inputs!$H$69 -> 1 | ... T15: =IF(T7>=$D$15,1,0)*Inputs!$H$69 -> 1
B16: P07 Belawan expansion (additional volume) | C16: flag | D16: =Inputs!$G$70 -> 2026 | E16: =Inputs!$H$70 -> 1 | F16: =D16-'Source Data'!$G$70 -> 0 | G16: 0 | H16: =IF(H7>=$D$16,1,0)*Inputs!$H$70 -> 0 | I16: =IF(I7>=$D$16,1,0)*Inputs!$H$70 -> 0 | J16: =IF(J7>=$D$16,1,0)*Inputs!$H$70 -> 1 | K16: =IF(K7>=$D$16,1,0)*Inputs!$H$70 -> 1 | L16: =IF(L7>=$D$16,1,0)*Inputs!$H$70 -> 1 | M16: =IF(M7>=$D$16,1,0)*Inputs!$H$70 -> 1 | N16: =IF(N7>=$D$16,1,0)*Inputs!$H$70 -> 1 | O16: =IF(O7>=$D$16,1,0)*Inputs!$H$70 -> 1 | ... T16: =IF(T7>=$D$16,1,0)*Inputs!$H$70 -> 1
B17: P08 DMS trucking fee - Teluk Lamong | C17: flag | D17: =Inputs!$G$71 -> 2027 | E17: =Inputs!$H$71 -> 1 | F17: =D17-'Source Data'!$G$71 -> 0 | G17: 0 | H17: =IF(H7>=$D$17,1,0)*Inputs!$H$71 -> 0 | I17: =IF(I7>=$D$17,1,0)*Inputs!$H$71 -> 0 | J17: =IF(J7>=$D$17,1,0)*Inputs!$H$71 -> 0 | K17: =IF(K7>=$D$17,1,0)*Inputs!$H$71 -> 1 | L17: =IF(L7>=$D$17,1,0)*Inputs!$H$71 -> 1 | M17: =IF(M7>=$D$17,1,0)*Inputs!$H$71 -> 1 | N17: =IF(N7>=$D$17,1,0)*Inputs!$H$71 -> 1 | O17: =IF(O7>=$D$17,1,0)*Inputs!$H$71 -> 1 | ... T17: =IF(T7>=$D$17,1,0)*Inputs!$H$71 -> 1
B18: P09 DMS trucking fee - Cigading | C18: flag | D18: =Inputs!$G$72 -> 2027 | E18: =Inputs!$H$72 -> 1 | F18: =D18-'Source Data'!$G$72 -> 0 | G18: 0 | H18: =IF(H7>=$D$18,1,0)*Inputs!$H$72 -> 0 | I18: =IF(I7>=$D$18,1,0)*Inputs!$H$72 -> 0 | J18: =IF(J7>=$D$18,1,0)*Inputs!$H$72 -> 0 | K18: =IF(K7>=$D$18,1,0)*Inputs!$H$72 -> 1 | L18: =IF(L7>=$D$18,1,0)*Inputs!$H$72 -> 1 | M18: =IF(M7>=$D$18,1,0)*Inputs!$H$72 -> 1 | N18: =IF(N7>=$D$18,1,0)*Inputs!$H$72 -> 1 | O18: =IF(O7>=$D$18,1,0)*Inputs!$H$72 -> 1 | ... T18: =IF(T7>=$D$18,1,0)*Inputs!$H$72 -> 1
B19: P10 DMS trucking fee - Ciwandan | C19: flag | D19: =Inputs!$G$73 -> 2028 | E19: =Inputs!$H$73 -> 1 | F19: =D19-'Source Data'!$G$73 -> 0 | G19: 0 | H19: =IF(H7>=$D$19,1,0)*Inputs!$H$73 -> 0 | I19: =IF(I7>=$D$19,1,0)*Inputs!$H$73 -> 0 | J19: =IF(J7>=$D$19,1,0)*Inputs!$H$73 -> 0 | K19: =IF(K7>=$D$19,1,0)*Inputs!$H$73 -> 0 | L19: =IF(L7>=$D$19,1,0)*Inputs!$H$73 -> 1 | M19: =IF(M7>=$D$19,1,0)*Inputs!$H$73 -> 1 | N19: =IF(N7>=$D$19,1,0)*Inputs!$H$73 -> 1 | O19: =IF(O7>=$D$19,1,0)*Inputs!$H$73 -> 1 | ... T19: =IF(T7>=$D$19,1,0)*Inputs!$H$73 -> 1
B20: P11 DMS trucking fee - Belawan | C20: flag | D20: =Inputs!$G$74 -> 2027 | E20: =Inputs!$H$74 -> 1 | F20: =D20-'Source Data'!$G$74 -> 0 | G20: 0 | H20: =IF(H7>=$D$20,1,0)*Inputs!$H$74 -> 0 | I20: =IF(I7>=$D$20,1,0)*Inputs!$H$74 -> 0 | J20: =IF(J7>=$D$20,1,0)*Inputs!$H$74 -> 0 | K20: =IF(K7>=$D$20,1,0)*Inputs!$H$74 -> 1 | L20: =IF(L7>=$D$20,1,0)*Inputs!$H$74 -> 1 | M20: =IF(M7>=$D$20,1,0)*Inputs!$H$74 -> 1 | N20: =IF(N7>=$D$20,1,0)*Inputs!$H$74 -> 1 | O20: =IF(O7>=$D$20,1,0)*Inputs!$H$74 -> 1 | ... T20: =IF(T7>=$D$20,1,0)*Inputs!$H$74 -> 1
B21: P12 BUMN synergy - Pelindo Teluk Lamong operatorship | C21: flag | D21: =Inputs!$G$75 -> 2026 | E21: =Inputs!$H$75 -> 1 | F21: =D21-'Source Data'!$G$75 -> 0 | G21: 0 | H21: =IF(H7>=$D$21,1,0)*Inputs!$H$75 -> 0 | I21: =IF(I7>=$D$21,1,0)*Inputs!$H$75 -> 0 | J21: =IF(J7>=$D$21,1,0)*Inputs!$H$75 -> 1 | K21: =IF(K7>=$D$21,1,0)*Inputs!$H$75 -> 1 | L21: =IF(L7>=$D$21,1,0)*Inputs!$H$75 -> 1 | M21: =IF(M7>=$D$21,1,0)*Inputs!$H$75 -> 1 | N21: =IF(N7>=$D$21,1,0)*Inputs!$H$75 -> 1 | O21: =IF(O7>=$D$21,1,0)*Inputs!$H$75 -> 1 | ... T21: =IF(T7>=$D$21,1,0)*Inputs!$H$75 -> 1
B22: P13 BUMN synergy - KBS Cigading operatorship | C22: flag | D22: =Inputs!$G$76 -> 2026 | E22: =Inputs!$H$76 -> 1 | F22: =D22-'Source Data'!$G$76 -> 0 | G22: 0 | H22: =IF(H7>=$D$22,1,0)*Inputs!$H$76 -> 0 | I22: =IF(I7>=$D$22,1,0)*Inputs!$H$76 -> 0 | J22: =IF(J7>=$D$22,1,0)*Inputs!$H$76 -> 1 | K22: =IF(K7>=$D$22,1,0)*Inputs!$H$76 -> 1 | L22: =IF(L7>=$D$22,1,0)*Inputs!$H$76 -> 1 | M22: =IF(M7>=$D$22,1,0)*Inputs!$H$76 -> 1 | N22: =IF(N7>=$D$22,1,0)*Inputs!$H$76 -> 1 | O22: =IF(O7>=$D$22,1,0)*Inputs!$H$76 -> 1 | ... T22: =IF(T7>=$D$22,1,0)*Inputs!$H$76 -> 1
B23: P14 BUMN synergy - Pelindo Belawan operatorship | C23: flag | D23: =Inputs!$G$77 -> 2026 | E23: =Inputs!$H$77 -> 1 | F23: =D23-'Source Data'!$G$77 -> 0 | G23: 0 | H23: =IF(H7>=$D$23,1,0)*Inputs!$H$77 -> 0 | I23: =IF(I7>=$D$23,1,0)*Inputs!$H$77 -> 0 | J23: =IF(J7>=$D$23,1,0)*Inputs!$H$77 -> 1 | K23: =IF(K7>=$D$23,1,0)*Inputs!$H$77 -> 1 | L23: =IF(L7>=$D$23,1,0)*Inputs!$H$77 -> 1 | M23: =IF(M7>=$D$23,1,0)*Inputs!$H$77 -> 1 | N23: =IF(N7>=$D$23,1,0)*Inputs!$H$77 -> 1 | O23: =IF(O7>=$D$23,1,0)*Inputs!$H$77 -> 1 | ... T23: =IF(T7>=$D$23,1,0)*Inputs!$H$77 -> 1
B24: P15 TBM (land lease, warehousing, cargo handling) | C24: flag | D24: =Inputs!$G$78 -> 2029 | E24: =Inputs!$H$78 -> 0 | F24: =D24-'Source Data'!$G$78 -> 0 | G24: 0 | H24: =IF(H7>=$D$24,1,0)*Inputs!$H$78 -> 0 | I24: =IF(I7>=$D$24,1,0)*Inputs!$H$78 -> 0 | J24: =IF(J7>=$D$24,1,0)*Inputs!$H$78 -> 0 | K24: =IF(K7>=$D$24,1,0)*Inputs!$H$78 -> 0 | L24: =IF(L7>=$D$24,1,0)*Inputs!$H$78 -> 0 | M24: =IF(M7>=$D$24,1,0)*Inputs!$H$78 -> 0 | N24: =IF(N7>=$D$24,1,0)*Inputs!$H$78 -> 0 | O24: =IF(O7>=$D$24,1,0)*Inputs!$H$78 -> 0 | ... T24: =IF(T7>=$D$24,1,0)*Inputs!$H$78 -> 0
B25: ="P16 "&Inputs!$E$605&" - operating fraction of the year (part year from the commencement date)" -> P16 Lampung - operating fraction of the year (part year from the commencement date) | C25: share | E25: =Inputs!$H$79 -> 0 | G25: 0 | H25: =IF(Inputs!$H$79=1,MAX(0,MIN(1,(DATE(H7,12,31)-MAX(DATE(H7,1,1),N(Inputs!$E$607))+1)/H8)),0) -> 0 | I25: =IF(Inputs!$H$79=1,MAX(0,MIN(1,(DATE(I7,12,31)-MAX(DATE(I7,1,1),N(Inputs!$E$607))+1)/I8)),0) -> 0 | J25: =IF(Inputs!$H$79=1,MAX(0,MIN(1,(DATE(J7,12,31)-MAX(DATE(J7,1,1),N(Inputs!$E$607))+1)/J8)),0) -> 0 | K25: =IF(Inputs!$H$79=1,MAX(0,MIN(1,(DATE(K7,12,31)-MAX(DATE(K7,1,1),N(Inputs!$E$607))+1)/K8)),0) -> 0 | L25: =IF(Inputs!$H$79=1,MAX(0,MIN(1,(DATE(L7,12,31)-MAX(DATE(L7,1,1),N(Inputs!$E$607))+1)/L8)),0) -> 0 | M25: =IF(Inputs!$H$79=1,MAX(0,MIN(1,(DATE(M7,12,31)-MAX(DATE(M7,1,1),N(Inputs!$E$607))+1)/M8)),0) -> 0 | N25: =IF(Inputs!$H$79=1,MAX(0,MIN(1,(DATE(N7,12,31)-MAX(DATE(N7,1,1),N(Inputs!$E$607))+1)/N8)),0) -> 0 | O25: =IF(Inputs!$H$79=1,MAX(0,MIN(1,(DATE(O7,12,31)-MAX(DATE(O7,1,1),N(Inputs!$E$607))+1)/O8)),0) -> 0 | ... T25: =IF(Inputs!$H$79=1,MAX(0,MIN(1,(DATE(T7,12,31)-MAX(DATE(T7,1,1),N(Inputs!$E$607))+1)/T8)),0) -> 0
B26: ="P17 "&Inputs!$E$639&" - operating fraction of the year (part year from the commencement date)" -> P17 Pipeline Project 2 - operating fraction of the year (part year from the commencement date) | C26: share | E26: =Inputs!$H$80 -> 0 | G26: 0 | H26: =IF(Inputs!$H$80=1,MAX(0,MIN(1,(DATE(H7,12,31)-MAX(DATE(H7,1,1),N(Inputs!$E$641))+1)/H8)),0) -> 0 | I26: =IF(Inputs!$H$80=1,MAX(0,MIN(1,(DATE(I7,12,31)-MAX(DATE(I7,1,1),N(Inputs!$E$641))+1)/I8)),0) -> 0 | J26: =IF(Inputs!$H$80=1,MAX(0,MIN(1,(DATE(J7,12,31)-MAX(DATE(J7,1,1),N(Inputs!$E$641))+1)/J8)),0) -> 0 | K26: =IF(Inputs!$H$80=1,MAX(0,MIN(1,(DATE(K7,12,31)-MAX(DATE(K7,1,1),N(Inputs!$E$641))+1)/K8)),0) -> 0 | L26: =IF(Inputs!$H$80=1,MAX(0,MIN(1,(DATE(L7,12,31)-MAX(DATE(L7,1,1),N(Inputs!$E$641))+1)/L8)),0) -> 0 | M26: =IF(Inputs!$H$80=1,MAX(0,MIN(1,(DATE(M7,12,31)-MAX(DATE(M7,1,1),N(Inputs!$E$641))+1)/M8)),0) -> 0 | N26: =IF(Inputs!$H$80=1,MAX(0,MIN(1,(DATE(N7,12,31)-MAX(DATE(N7,1,1),N(Inputs!$E$641))+1)/N8)),0) -> 0 | O26: =IF(Inputs!$H$80=1,MAX(0,MIN(1,(DATE(O7,12,31)-MAX(DATE(O7,1,1),N(Inputs!$E$641))+1)/O8)),0) -> 0 | ... T26: =IF(Inputs!$H$80=1,MAX(0,MIN(1,(DATE(T7,12,31)-MAX(DATE(T7,1,1),N(Inputs!$E$641))+1)/T8)),0) -> 0
B27: ="P18 "&Inputs!$E$673&" - operating fraction of the year (part year from the commencement date)" -> P18 Pipeline Project 3 - operating fraction of the year (part year from the commencement date) | C27: share | E27: =Inputs!$H$81 -> 0 | G27: 0 | H27: =IF(Inputs!$H$81=1,MAX(0,MIN(1,(DATE(H7,12,31)-MAX(DATE(H7,1,1),N(Inputs!$E$675))+1)/H8)),0) -> 0 | I27: =IF(Inputs!$H$81=1,MAX(0,MIN(1,(DATE(I7,12,31)-MAX(DATE(I7,1,1),N(Inputs!$E$675))+1)/I8)),0) -> 0 | J27: =IF(Inputs!$H$81=1,MAX(0,MIN(1,(DATE(J7,12,31)-MAX(DATE(J7,1,1),N(Inputs!$E$675))+1)/J8)),0) -> 0 | K27: =IF(Inputs!$H$81=1,MAX(0,MIN(1,(DATE(K7,12,31)-MAX(DATE(K7,1,1),N(Inputs!$E$675))+1)/K8)),0) -> 0 | L27: =IF(Inputs!$H$81=1,MAX(0,MIN(1,(DATE(L7,12,31)-MAX(DATE(L7,1,1),N(Inputs!$E$675))+1)/L8)),0) -> 0 | M27: =IF(Inputs!$H$81=1,MAX(0,MIN(1,(DATE(M7,12,31)-MAX(DATE(M7,1,1),N(Inputs!$E$675))+1)/M8)),0) -> 0 | N27: =IF(Inputs!$H$81=1,MAX(0,MIN(1,(DATE(N7,12,31)-MAX(DATE(N7,1,1),N(Inputs!$E$675))+1)/N8)),0) -> 0 | O27: =IF(Inputs!$H$81=1,MAX(0,MIN(1,(DATE(O7,12,31)-MAX(DATE(O7,1,1),N(Inputs!$E$675))+1)/O8)),0) -> 0 | ... T27: =IF(Inputs!$H$81=1,MAX(0,MIN(1,(DATE(T7,12,31)-MAX(DATE(T7,1,1),N(Inputs!$E$675))+1)/T8)),0) -> 0
B28: P19 Badas - operating fraction of the year from the commercial operation date (illustrative, always calculated) | C28: share | D28: =YEAR(Inputs!$E$571) -> 2029 | G28: 0 | H28: =MAX(0,MIN(1,(DATE(H7,12,31)-MAX(DATE(H7,1,1),Inputs!$E$571)+1)/H8)) -> 0 | I28: =MAX(0,MIN(1,(DATE(I7,12,31)-MAX(DATE(I7,1,1),Inputs!$E$571)+1)/I8)) -> 0 | J28: =MAX(0,MIN(1,(DATE(J7,12,31)-MAX(DATE(J7,1,1),Inputs!$E$571)+1)/J8)) -> 0 | K28: =MAX(0,MIN(1,(DATE(K7,12,31)-MAX(DATE(K7,1,1),Inputs!$E$571)+1)/K8)) -> 0 | L28: =MAX(0,MIN(1,(DATE(L7,12,31)-MAX(DATE(L7,1,1),Inputs!$E$571)+1)/L8)) -> 0 | M28: =MAX(0,MIN(1,(DATE(M7,12,31)-MAX(DATE(M7,1,1),Inputs!$E$571)+1)/M8)) -> 1 | N28: =MAX(0,MIN(1,(DATE(N7,12,31)-MAX(DATE(N7,1,1),Inputs!$E$571)+1)/N8)) -> 1 | O28: =MAX(0,MIN(1,(DATE(O7,12,31)-MAX(DATE(O7,1,1),Inputs!$E$571)+1)/O8)) -> 1 | ... T28: =MAX(0,MIN(1,(DATE(T7,12,31)-MAX(DATE(T7,1,1),Inputs!$E$571)+1)/T8)) -> 1
B29: P19 Badas - operating fraction in the FSL statements = illustrative x valuation inclusion | C29: share | E29: =Inputs!$H$82 -> 1 | G29: 0 | H29: =H28*Inputs!$H$82 -> 0 | I29: =I28*Inputs!$H$82 -> 0 | J29: =J28*Inputs!$H$82 -> 0 | K29: =K28*Inputs!$H$82 -> 0 | L29: =L28*Inputs!$H$82 -> 0 | M29: =M28*Inputs!$H$82 -> 1 | N29: =N28*Inputs!$H$82 -> 1 | O29: =O28*Inputs!$H$82 -> 1 | ... T29: =T28*Inputs!$H$82 -> 1
B30: P01-P02 commence in FY2025 under v29 (construction since before FY2024). Changing a commencement year (Inputs section 2) moves the operating flags and the v29 calendar schedules of that project (column F); it does not move capex, which follows the spending % rows.
B32: B. EXISTING BUSINESSES (E1-E4)
B33: E1 Teluk Lamong - NPLOG cargodoring & delivery
B34: Meals volume index (FY2023 = 1; x (1 + growth of the year)) | C34: index | D34: Inputs 4 growth | G34: 1 | H34: =G34*(1+Inputs!H108) -> 1 | I34: =H34*(1+Inputs!I108) -> 1.03 | J34: =I34*(1+Inputs!J108) -> 1.0609 | K34: =J34*(1+Inputs!K108) -> 1.092727 | L34: =K34*(1+Inputs!L108) -> 1.1255088 | M34: =L34*(1+Inputs!M108) -> 1.1592741 | N34: =M34*(1+Inputs!N108) -> 1.1940523 | O34: =N34*(1+Inputs!O108) -> 1.2298739 | ... T34: =S34*(1+Inputs!T108) -> 1.4257609
B35: Grains volume index (FY2023 = 1) | C35: index | D35: Inputs 4 growth | G35: 1 | H35: =G35*(1+Inputs!H109) -> 1 | I35: =H35*(1+Inputs!I109) -> 1.03 | J35: =I35*(1+Inputs!J109) -> 1.0609 | K35: =J35*(1+Inputs!K109) -> 1.092727 | L35: =K35*(1+Inputs!L109) -> 1.1255088 | M35: =L35*(1+Inputs!M109) -> 1.1592741 | N35: =M35*(1+Inputs!N109) -> 1.1940523 | O35: =N35*(1+Inputs!O109) -> 1.2298739 | ... T35: =S35*(1+Inputs!T109) -> 1.4257609
B36: Meals throughput = FY2023 base x FY2024 reset x index x volume lever | C36: tons | H36: =Inputs!$E$103*Inputs!$E$104*H34*Inputs!$E$52 -> 2063651.1 | I36: =Inputs!$E$103*Inputs!$E$104*I34*Inputs!$E$52 -> 2125560.6 | J36: =Inputs!$E$103*Inputs!$E$104*J34*Inputs!$E$52 -> 2189327.4 | K36: =Inputs!$E$103*Inputs!$E$104*K34*Inputs!$E$52 -> 2255007.2 | L36: =Inputs!$E$103*Inputs!$E$104*L34*Inputs!$E$52 -> 2322657.5 | M36: =Inputs!$E$103*Inputs!$E$104*M34*Inputs!$E$52 -> 2392337.2 | N36: =Inputs!$E$103*Inputs!$E$104*N34*Inputs!$E$52 -> 2464107.3 | O36: =Inputs!$E$103*Inputs!$E$104*O34*Inputs!$E$52 -> 2538030.5 | ... T36: =Inputs!$E$103*Inputs!$E$104*T34*Inputs!$E$52 -> 2942273
B37: Grains throughput = FY2023 base x FY2024 reset x index x volume lever | C37: tons | H37: =Inputs!$E$105*Inputs!$E$106*H35*Inputs!$E$52 -> 1602574.2 | I37: =Inputs!$E$105*Inputs!$E$106*I35*Inputs!$E$52 -> 1650651.4 | J37: =Inputs!$E$105*Inputs!$E$106*J35*Inputs!$E$52 -> 1700171 | K37: =Inputs!$E$105*Inputs!$E$106*K35*Inputs!$E$52 -> 1751176.1 | L37: =Inputs!$E$105*Inputs!$E$106*L35*Inputs!$E$52 -> 1803711.4 | M37: =Inputs!$E$105*Inputs!$E$106*M35*Inputs!$E$52 -> 1857822.7 | N37: =Inputs!$E$105*Inputs!$E$106*N35*Inputs!$E$52 -> 1913557.4 | O37: =Inputs!$E$105*Inputs!$E$106*O35*Inputs!$E$52 -> 1970964.1 | ... T37: =Inputs!$E$105*Inputs!$E$106*T35*Inputs!$E$52 -> 2284887.6
B38: Total throughput | C38: tons | H38: =H36+H37 -> 3666225.3 | I38: =I36+I37 -> 3776212 | J38: =J36+J37 -> 3889498.4 | K38: =K36+K37 -> 4006183.3 | L38: =L36+L37 -> 4126368.8 | M38: =M36+M37 -> 4250159.9 | N38: =N36+N37 -> 4377664.7 | O38: =O36+O37 -> 4508994.7 | ... T38: =T36+T37 -> 5227160.6
B39: Meals tariff (annual input x tariff lever) | C39: IDR/t | H39: =Inputs!H110*Inputs!$E$53 -> 42880 | I39: =Inputs!I110*Inputs!$E$53 -> 42880 | J39: =Inputs!J110*Inputs!$E$53 -> 42880 | K39: =Inputs!K110*Inputs!$E$53 -> 42880 | L39: =Inputs!L110*Inputs!$E$53 -> 42880 | M39: =Inputs!M110*Inputs!$E$53 -> 44166.4 | N39: =Inputs!N110*Inputs!$E$53 -> 44166.4 | O39: =Inputs!O110*Inputs!$E$53 -> 44166.4 | ... T39: =Inputs!T110*Inputs!$E$53 -> 45491.392
B40: Grains tariff (annual input x tariff lever) | C40: IDR/t | H40: =Inputs!H111*Inputs!$E$53 -> 42400 | I40: =Inputs!I111*Inputs!$E$53 -> 42400 | J40: =Inputs!J111*Inputs!$E$53 -> 42400 | K40: =Inputs!K111*Inputs!$E$53 -> 42400 | L40: =Inputs!L111*Inputs!$E$53 -> 42400 | M40: =Inputs!M111*Inputs!$E$53 -> 43672 | N40: =Inputs!N111*Inputs!$E$53 -> 43672 | O40: =Inputs!O111*Inputs!$E$53 -> 43672 | ... T40: =Inputs!T111*Inputs!$E$53 -> 44982.16
B41: E1 Revenue = (meals volume x meals tariff + grains volume x grains tariff) / 1e9 | C41: IDR bn | H41: =(H36*H39+H37*H40)/1000000000 -> 156.4385 | I41: =(I36*I39+I37*I40)/1000000000 -> 161.13166 | J41: =(J36*J39+J37*J40)/1000000000 -> 165.96561 | K41: =(K36*K39+K37*K40)/1000000000 -> 170.94458 | L41: =(L36*L39+L37*L40)/1000000000 -> 176.07291 | M41: =(M36*M39+M37*M40)/1000000000 -> 186.79576 | N41: =(N36*N39+N37*N40)/1000000000 -> 192.39963 | O41: =(O36*O39+O37*O40)/1000000000 -> 198.17162 | ... T41: =(T36*T39+T37*T40)/1000000000 -> 236.62727
B43: E2 Cigading existing terminal (SGT 2)
B44: Volume index (FY2024 = 1; x (1 + growth of the year)) | C44: index | G44: 1 | H44: =G44*(1+Inputs!H117) -> 1 | I44: =H44*(1+Inputs!I117) -> 1.03 | J44: =I44*(1+Inputs!J117) -> 1.0609 | K44: =J44*(1+Inputs!K117) -> 1.092727 | L44: =K44*(1+Inputs!L117) -> 1.1255088 | M44: =L44*(1+Inputs!M117) -> 1.1592741 | N44: =M44*(1+Inputs!N117) -> 1.1940523 | O44: =N44*(1+Inputs!O117) -> 1.2298739 | ... T44: =S44*(1+Inputs!T117) -> 1.4257609
B45: Throughput = FY2024 base x index x volume lever | C45: tons | H45: =Inputs!$E$115*H44*Inputs!$E$52 -> 1100000 | I45: =Inputs!$E$115*I44*Inputs!$E$52 -> 1133000 | J45: =Inputs!$E$115*J44*Inputs!$E$52 -> 1166990 | K45: =Inputs!$E$115*K44*Inputs!$E$52 -> 1201999.7 | L45: =Inputs!$E$115*L44*Inputs!$E$52 -> 1238059.7 | M45: =Inputs!$E$115*M44*Inputs!$E$52 -> 1275201.5 | N45: =Inputs!$E$115*N44*Inputs!$E$52 -> 1313457.5 | O45: =Inputs!$E$115*O44*Inputs!$E$52 -> 1352861.3 | ... T45: =Inputs!$E$115*T44*Inputs!$E$52 -> 1568337
B46: Tariff (annual input x tariff lever) | C46: IDR/t | H46: =Inputs!H118*Inputs!$E$53 -> 35143.6 | I46: =Inputs!I118*Inputs!$E$53 -> 40944 | J46: =Inputs!J118*Inputs!$E$53 -> 40944 | K46: =Inputs!K118*Inputs!$E$53 -> 49132.8 | L46: =Inputs!L118*Inputs!$E$53 -> 49132.8 | M46: =Inputs!M118*Inputs!$E$53 -> 54046.08 | N46: =Inputs!N118*Inputs!$E$53 -> 54046.08 | O46: =Inputs!O118*Inputs!$E$53 -> 57288.845 | ... T46: =Inputs!T118*Inputs!$E$53 -> 60726.175
B47: E2 Revenue = throughput x tariff / 1e9 | C47: IDR bn | H47: =H45*H46/1000000000 -> 38.65796 | I47: =I45*I46/1000000000 -> 46.389552 | J47: =J45*J46/1000000000 -> 47.781239 | K47: =K45*K46/1000000000 -> 59.057611 | L47: =L45*L46/1000000000 -> 60.829339 | M47: =M45*M46/1000000000 -> 68.919641 | N47: =N45*N46/1000000000 -> 70.987231 | O47: =O45*O46/1000000000 -> 77.503858 | ... T47: =T45*T46/1000000000 -> 95.239106
B49: E3 Belawan existing (conveyor & warehouse)
B50: Volume index (FY2024 = 1) | C50: index | G50: 1 | H50: =G50*(1+Inputs!H124) -> 1 | I50: =H50*(1+Inputs!I124) -> 1.03 | J50: =I50*(1+Inputs!J124) -> 1.0609 | K50: =J50*(1+Inputs!K124) -> 1.092727 | L50: =K50*(1+Inputs!L124) -> 1.1255088 | M50: =L50*(1+Inputs!M124) -> 1.1592741 | N50: =M50*(1+Inputs!N124) -> 1.1940523 | O50: =N50*(1+Inputs!O124) -> 1.2298739 | ... T50: =S50*(1+Inputs!T124) -> 1.4257609
B51: Throughput - existing = FY2024 base x index x volume lever | C51: tons | H51: =Inputs!$E$122*H50*Inputs!$E$52 -> 750000 | I51: =Inputs!$E$122*I50*Inputs!$E$52 -> 772500 | J51: =Inputs!$E$122*J50*Inputs!$E$52 -> 795675 | K51: =Inputs!$E$122*K50*Inputs!$E$52 -> 819545.25 | L51: =Inputs!$E$122*L50*Inputs!$E$52 -> 844131.61 | M51: =Inputs!$E$122*M50*Inputs!$E$52 -> 869455.56 | N51: =Inputs!$E$122*N50*Inputs!$E$52 -> 895539.22 | O51: =Inputs!$E$122*O50*Inputs!$E$52 -> 922405.4 | ... T51: =Inputs!$E$122*T50*Inputs!$E$52 -> 1069320.7
B52: Tariff (existing and expansion volume; annual input x tariff lever) | C52: IDR/t | H52: =Inputs!H125*Inputs!$E$53 -> 29658 | I52: =Inputs!I125*Inputs!$E$53 -> 29658 | J52: =Inputs!J125*Inputs!$E$53 -> 43947.5 | K52: =Inputs!K125*Inputs!$E$53 -> 43947.5 | L52: =Inputs!L125*Inputs!$E$53 -> 45265.925 | M52: =Inputs!M125*Inputs!$E$53 -> 46623.903 | N52: =Inputs!N125*Inputs!$E$53 -> 48022.62 | O52: =Inputs!O125*Inputs!$E$53 -> 49463.298 | ... T52: =Inputs!T125*Inputs!$E$53 -> 57341.519
B53: E3 Revenue = existing throughput x tariff / 1e9 | C53: IDR bn | H53: =H51*H52/1000000000 -> 22.2435 | I53: =I51*I52/1000000000 -> 22.910805 | J53: =J51*J52/1000000000 -> 34.967927 | K53: =K51*K52/1000000000 -> 36.016965 | L53: =L51*L52/1000000000 -> 38.210398 | M53: =M51*M52/1000000000 -> 40.537411 | N53: =N51*N52/1000000000 -> 43.00614 | O53: =O51*O52/1000000000 -> 45.625214 | ... T53: =T51*T52/1000000000 -> 61.316472
B55: E4 WIN stevedoring (Cilegon, Makassar, Surabaya, Medan) - volume index, revenue by branch and commodity
B56: Cilegon Corn - volume index (1 in the first year, then x (1 + growth)) | C56: index | G56: =IF(2023<Inputs!$E$131,0,1) -> 1 | H56: =IF(H7<Inputs!$E$131,0,IF(H7=Inputs!$E$131,1,G56*(1+Inputs!H156))) -> 1.05 | I56: =IF(I7<Inputs!$E$131,0,IF(I7=Inputs!$E$131,1,H56*(1+Inputs!I156))) -> 1.1025 | J56: =IF(J7<Inputs!$E$131,0,IF(J7=Inputs!$E$131,1,I56*(1+Inputs!J156))) -> 1.157625 | K56: =IF(K7<Inputs!$E$131,0,IF(K7=Inputs!$E$131,1,J56*(1+Inputs!K156))) -> 1.2155063 | L56: =IF(L7<Inputs!$E$131,0,IF(L7=Inputs!$E$131,1,K56*(1+Inputs!L156))) -> 1.2762816 | M56: =IF(M7<Inputs!$E$131,0,IF(M7=Inputs!$E$131,1,L56*(1+Inputs!M156))) -> 1.3400956 | N56: =IF(N7<Inputs!$E$131,0,IF(N7=Inputs!$E$131,1,M56*(1+Inputs!N156))) -> 1.4071004 | O56: =IF(O7<Inputs!$E$131,0,IF(O7=Inputs!$E$131,1,N56*(1+Inputs!O156))) -> 1.4774554 | ... T56: =IF(T7<Inputs!$E$131,0,IF(T7=Inputs!$E$131,1,S56*(1+Inputs!T156))) -> 1.8856491
B57: Cilegon SBM - volume index (1 in the first year, then x (1 + growth)) | C57: index | G57: =IF(2023<Inputs!$E$133,0,1) -> 1 | H57: =IF(H7<Inputs!$E$133,0,IF(H7=Inputs!$E$133,1,G57*(1+Inputs!H158))) -> 1.05 | I57: =IF(I7<Inputs!$E$133,0,IF(I7=Inputs!$E$133,1,H57*(1+Inputs!I158))) -> 1.1025 | J57: =IF(J7<Inputs!$E$133,0,IF(J7=Inputs!$E$133,1,I57*(1+Inputs!J158))) -> 1.157625 | K57: =IF(K7<Inputs!$E$133,0,IF(K7=Inputs!$E$133,1,J57*(1+Inputs!K158))) -> 1.2155063 | L57: =IF(L7<Inputs!$E$133,0,IF(L7=Inputs!$E$133,1,K57*(1+Inputs!L158))) -> 1.2762816 | M57: =IF(M7<Inputs!$E$133,0,IF(M7=Inputs!$E$133,1,L57*(1+Inputs!M158))) -> 1.3400956 | N57: =IF(N7<Inputs!$E$133,0,IF(N7=Inputs!$E$133,1,M57*(1+Inputs!N158))) -> 1.4071004 | O57: =IF(O7<Inputs!$E$133,0,IF(O7=Inputs!$E$133,1,N57*(1+Inputs!O158))) -> 1.4774554 | ... T57: =IF(T7<Inputs!$E$133,0,IF(T7=Inputs!$E$133,1,S57*(1+Inputs!T158))) -> 1.8856491
B58: Cilegon Soybean - volume index (1 in the first year, then x (1 + growth)) | C58: index | G58: =IF(2023<Inputs!$E$135,0,1) -> 1 | H58: =IF(H7<Inputs!$E$135,0,IF(H7=Inputs!$E$135,1,G58*(1+Inputs!H160))) -> 1.05 | I58: =IF(I7<Inputs!$E$135,0,IF(I7=Inputs!$E$135,1,H58*(1+Inputs!I160))) -> 1.1025 | J58: =IF(J7<Inputs!$E$135,0,IF(J7=Inputs!$E$135,1,I58*(1+Inputs!J160))) -> 1.157625 | K58: =IF(K7<Inputs!$E$135,0,IF(K7=Inputs!$E$135,1,J58*(1+Inputs!K160))) -> 1.2155063 | L58: =IF(L7<Inputs!$E$135,0,IF(L7=Inputs!$E$135,1,K58*(1+Inputs!L160))) -> 1.2762816 | M58: =IF(M7<Inputs!$E$135,0,IF(M7=Inputs!$E$135,1,L58*(1+Inputs!M160))) -> 1.3400956 | N58: =IF(N7<Inputs!$E$135,0,IF(N7=Inputs!$E$135,1,M58*(1+Inputs!N160))) -> 1.4071004 | O58: =IF(O7<Inputs!$E$135,0,IF(O7=Inputs!$E$135,1,N58*(1+Inputs!O160))) -> 1.4774554 | ... T58: =IF(T7<Inputs!$E$135,0,IF(T7=Inputs!$E$135,1,S58*(1+Inputs!T160))) -> 1.8856491
B59: Cilegon Sugar - volume index (1 in the first year, then x (1 + growth)) | C59: index | G59: =IF(2023<Inputs!$E$137,0,1) -> 1 | H59: =IF(H7<Inputs!$E$137,0,IF(H7=Inputs!$E$137,1,G59*(1+Inputs!H162))) -> 1.05 | I59: =IF(I7<Inputs!$E$137,0,IF(I7=Inputs!$E$137,1,H59*(1+Inputs!I162))) -> 1.1025 | J59: =IF(J7<Inputs!$E$137,0,IF(J7=Inputs!$E$137,1,I59*(1+Inputs!J162))) -> 1.157625 | K59: =IF(K7<Inputs!$E$137,0,IF(K7=Inputs!$E$137,1,J59*(1+Inputs!K162))) -> 1.2155063 | L59: =IF(L7<Inputs!$E$137,0,IF(L7=Inputs!$E$137,1,K59*(1+Inputs!L162))) -> 1.2762816 | M59: =IF(M7<Inputs!$E$137,0,IF(M7=Inputs!$E$137,1,L59*(1+Inputs!M162))) -> 1.3400956 | N59: =IF(N7<Inputs!$E$137,0,IF(N7=Inputs!$E$137,1,M59*(1+Inputs!N162))) -> 1.4071004 | O59: =IF(O7<Inputs!$E$137,0,IF(O7=Inputs!$E$137,1,N59*(1+Inputs!O162))) -> 1.4774554 | ... T59: =IF(T7<Inputs!$E$137,0,IF(T7=Inputs!$E$137,1,S59*(1+Inputs!T162))) -> 1.8856491
B60: Cilegon Wheat - volume index (1 in the first year, then x (1 + growth)) | C60: index | G60: =IF(2023<Inputs!$E$139,0,1) -> 1 | H60: =IF(H7<Inputs!$E$139,0,IF(H7=Inputs!$E$139,1,G60*(1+Inputs!H164))) -> 1.05 | I60: =IF(I7<Inputs!$E$139,0,IF(I7=Inputs!$E$139,1,H60*(1+Inputs!I164))) -> 1.1025 | J60: =IF(J7<Inputs!$E$139,0,IF(J7=Inputs!$E$139,1,I60*(1+Inputs!J164))) -> 1.157625 | K60: =IF(K7<Inputs!$E$139,0,IF(K7=Inputs!$E$139,1,J60*(1+Inputs!K164))) -> 1.2155063 | L60: =IF(L7<Inputs!$E$139,0,IF(L7=Inputs!$E$139,1,K60*(1+Inputs!L164))) -> 1.2762816 | M60: =IF(M7<Inputs!$E$139,0,IF(M7=Inputs!$E$139,1,L60*(1+Inputs!M164))) -> 1.3400956 | N60: =IF(N7<Inputs!$E$139,0,IF(N7=Inputs!$E$139,1,M60*(1+Inputs!N164))) -> 1.4071004 | O60: =IF(O7<Inputs!$E$139,0,IF(O7=Inputs!$E$139,1,N60*(1+Inputs!O164))) -> 1.4774554 | ... T60: =IF(T7<Inputs!$E$139,0,IF(T7=Inputs!$E$139,1,S60*(1+Inputs!T164))) -> 1.8856491
B61: Makassar Sugar - volume index (1 in the first year, then x (1 + growth)) | C61: index | G61: =IF(2023<Inputs!$E$141,0,1) -> 1 | H61: =IF(H7<Inputs!$E$141,0,IF(H7=Inputs!$E$141,1,G61*(1+Inputs!H166))) -> 1 | I61: =IF(I7<Inputs!$E$141,0,IF(I7=Inputs!$E$141,1,H61*(1+Inputs!I166))) -> 1.04 | J61: =IF(J7<Inputs!$E$141,0,IF(J7=Inputs!$E$141,1,I61*(1+Inputs!J166))) -> 1.0816 | K61: =IF(K7<Inputs!$E$141,0,IF(K7=Inputs!$E$141,1,J61*(1+Inputs!K166))) -> 1.124864 | L61: =IF(L7<Inputs!$E$141,0,IF(L7=Inputs!$E$141,1,K61*(1+Inputs!L166))) -> 1.1698586 | M61: =IF(M7<Inputs!$E$141,0,IF(M7=Inputs!$E$141,1,L61*(1+Inputs!M166))) -> 1.2166529 | N61: =IF(N7<Inputs!$E$141,0,IF(N7=Inputs!$E$141,1,M61*(1+Inputs!N166))) -> 1.265319 | O61: =IF(O7<Inputs!$E$141,0,IF(O7=Inputs!$E$141,1,N61*(1+Inputs!O166))) -> 1.3159318 | ... T61: =IF(T7<Inputs!$E$141,0,IF(T7=Inputs!$E$141,1,S61*(1+Inputs!T166))) -> 1.6010322
B62: Makassar Wheat - volume index (1 in the first year, then x (1 + growth)) | C62: index | G62: =IF(2023<Inputs!$E$143,0,1) -> 1 | H62: =IF(H7<Inputs!$E$143,0,IF(H7=Inputs!$E$143,1,G62*(1+Inputs!H168))) -> 1 | I62: =IF(I7<Inputs!$E$143,0,IF(I7=Inputs!$E$143,1,H62*(1+Inputs!I168))) -> 1.04 | J62: =IF(J7<Inputs!$E$143,0,IF(J7=Inputs!$E$143,1,I62*(1+Inputs!J168))) -> 1.0816 | K62: =IF(K7<Inputs!$E$143,0,IF(K7=Inputs!$E$143,1,J62*(1+Inputs!K168))) -> 1.124864 | L62: =IF(L7<Inputs!$E$143,0,IF(L7=Inputs!$E$143,1,K62*(1+Inputs!L168))) -> 1.1698586 | M62: =IF(M7<Inputs!$E$143,0,IF(M7=Inputs!$E$143,1,L62*(1+Inputs!M168))) -> 1.2166529 | N62: =IF(N7<Inputs!$E$143,0,IF(N7=Inputs!$E$143,1,M62*(1+Inputs!N168))) -> 1.265319 | O62: =IF(O7<Inputs!$E$143,0,IF(O7=Inputs!$E$143,1,N62*(1+Inputs!O168))) -> 1.3159318 | ... T62: =IF(T7<Inputs!$E$143,0,IF(T7=Inputs!$E$143,1,S62*(1+Inputs!T168))) -> 1.6010322
B63: Surabaya SBM - volume index (1 in the first year, then x (1 + growth)) | C63: index | G63: =IF(2023<Inputs!$E$145,0,1) -> 1 | H63: =IF(H7<Inputs!$E$145,0,IF(H7=Inputs!$E$145,1,G63*(1+Inputs!H170))) -> 1 | I63: =IF(I7<Inputs!$E$145,0,IF(I7=Inputs!$E$145,1,H63*(1+Inputs!I170))) -> 1.05 | J63: =IF(J7<Inputs!$E$145,0,IF(J7=Inputs!$E$145,1,I63*(1+Inputs!J170))) -> 1.1025 | K63: =IF(K7<Inputs!$E$145,0,IF(K7=Inputs!$E$145,1,J63*(1+Inputs!K170))) -> 1.157625 | L63: =IF(L7<Inputs!$E$145,0,IF(L7=Inputs!$E$145,1,K63*(1+Inputs!L170))) -> 1.2155063 | M63: =IF(M7<Inputs!$E$145,0,IF(M7=Inputs!$E$145,1,L63*(1+Inputs!M170))) -> 1.2762816 | N63: =IF(N7<Inputs!$E$145,0,IF(N7=Inputs!$E$145,1,M63*(1+Inputs!N170))) -> 1.3400956 | O63: =IF(O7<Inputs!$E$145,0,IF(O7=Inputs!$E$145,1,N63*(1+Inputs!O170))) -> 1.4071004 | ... T63: =IF(T7<Inputs!$E$145,0,IF(T7=Inputs!$E$145,1,S63*(1+Inputs!T170))) -> 1.7958563
B64: Surabaya Soybean - volume index (1 in the first year, then x (1 + growth)) | C64: index | G64: =IF(2023<Inputs!$E$147,0,1) -> 1 | H64: =IF(H7<Inputs!$E$147,0,IF(H7=Inputs!$E$147,1,G64*(1+Inputs!H172))) -> 1 | I64: =IF(I7<Inputs!$E$147,0,IF(I7=Inputs!$E$147,1,H64*(1+Inputs!I172))) -> 1.05 | J64: =IF(J7<Inputs!$E$147,0,IF(J7=Inputs!$E$147,1,I64*(1+Inputs!J172))) -> 1.1025 | K64: =IF(K7<Inputs!$E$147,0,IF(K7=Inputs!$E$147,1,J64*(1+Inputs!K172))) -> 1.157625 | L64: =IF(L7<Inputs!$E$147,0,IF(L7=Inputs!$E$147,1,K64*(1+Inputs!L172))) -> 1.2155063 | M64: =IF(M7<Inputs!$E$147,0,IF(M7=Inputs!$E$147,1,L64*(1+Inputs!M172))) -> 1.2762816 | N64: =IF(N7<Inputs!$E$147,0,IF(N7=Inputs!$E$147,1,M64*(1+Inputs!N172))) -> 1.3400956 | O64: =IF(O7<Inputs!$E$147,0,IF(O7=Inputs!$E$147,1,N64*(1+Inputs!O172))) -> 1.4071004 | ... T64: =IF(T7<Inputs!$E$147,0,IF(T7=Inputs!$E$147,1,S64*(1+Inputs!T172))) -> 1.7958563
B65: Medan Corn - volume index (1 in the first year, then x (1 + growth)) | C65: index | G65: =IF(2023<Inputs!$E$149,0,1) -> 0 | H65: =IF(H7<Inputs!$E$149,0,IF(H7=Inputs!$E$149,1,G65*(1+Inputs!H174))) -> 0 | I65: =IF(I7<Inputs!$E$149,0,IF(I7=Inputs!$E$149,1,H65*(1+Inputs!I174))) -> 0 | J65: =IF(J7<Inputs!$E$149,0,IF(J7=Inputs!$E$149,1,I65*(1+Inputs!J174))) -> 1 | K65: =IF(K7<Inputs!$E$149,0,IF(K7=Inputs!$E$149,1,J65*(1+Inputs!K174))) -> 1.05 | L65: =IF(L7<Inputs!$E$149,0,IF(L7=Inputs!$E$149,1,K65*(1+Inputs!L174))) -> 1.1025 | M65: =IF(M7<Inputs!$E$149,0,IF(M7=Inputs!$E$149,1,L65*(1+Inputs!M174))) -> 1.157625 | N65: =IF(N7<Inputs!$E$149,0,IF(N7=Inputs!$E$149,1,M65*(1+Inputs!N174))) -> 1.2155063 | O65: =IF(O7<Inputs!$E$149,0,IF(O7=Inputs!$E$149,1,N65*(1+Inputs!O174))) -> 1.2762816 | ... T65: =IF(T7<Inputs!$E$149,0,IF(T7=Inputs!$E$149,1,S65*(1+Inputs!T174))) -> 1.6288946
B66: Medan SBM - volume index (1 in the first year, then x (1 + growth)) | C66: index | G66: =IF(2023<Inputs!$E$151,0,1) -> 1 | H66: =IF(H7<Inputs!$E$151,0,IF(H7=Inputs!$E$151,1,G66*(1+Inputs!H176))) -> 1 | I66: =IF(I7<Inputs!$E$151,0,IF(I7=Inputs!$E$151,1,H66*(1+Inputs!I176))) -> 1.05 | J66: =IF(J7<Inputs!$E$151,0,IF(J7=Inputs!$E$151,1,I66*(1+Inputs!J176))) -> 1.1025 | K66: =IF(K7<Inputs!$E$151,0,IF(K7=Inputs!$E$151,1,J66*(1+Inputs!K176))) -> 1.157625 | L66: =IF(L7<Inputs!$E$151,0,IF(L7=Inputs!$E$151,1,K66*(1+Inputs!L176))) -> 1.2155063 | M66: =IF(M7<Inputs!$E$151,0,IF(M7=Inputs!$E$151,1,L66*(1+Inputs!M176))) -> 1.2762816 | N66: =IF(N7<Inputs!$E$151,0,IF(N7=Inputs!$E$151,1,M66*(1+Inputs!N176))) -> 1.3400956 | O66: =IF(O7<Inputs!$E$151,0,IF(O7=Inputs!$E$151,1,N66*(1+Inputs!O176))) -> 1.4071004 | ... T66: =IF(T7<Inputs!$E$151,0,IF(T7=Inputs!$E$151,1,S66*(1+Inputs!T176))) -> 1.7958563
B67: Medan Soybean - volume index (1 in the first year, then x (1 + growth)) | C67: index | G67: =IF(2023<Inputs!$E$153,0,1) -> 0 | H67: =IF(H7<Inputs!$E$153,0,IF(H7=Inputs!$E$153,1,G67*(1+Inputs!H178))) -> 0 | I67: =IF(I7<Inputs!$E$153,0,IF(I7=Inputs!$E$153,1,H67*(1+Inputs!I178))) -> 0 | J67: =IF(J7<Inputs!$E$153,0,IF(J7=Inputs!$E$153,1,I67*(1+Inputs!J178))) -> 1 | K67: =IF(K7<Inputs!$E$153,0,IF(K7=Inputs!$E$153,1,J67*(1+Inputs!K178))) -> 1.05 | L67: =IF(L7<Inputs!$E$153,0,IF(L7=Inputs!$E$153,1,K67*(1+Inputs!L178))) -> 1.1025 | M67: =IF(M7<Inputs!$E$153,0,IF(M7=Inputs!$E$153,1,L67*(1+Inputs!M178))) -> 1.157625 | N67: =IF(N7<Inputs!$E$153,0,IF(N7=Inputs!$E$153,1,M67*(1+Inputs!N178))) -> 1.2155063 | O67: =IF(O7<Inputs!$E$153,0,IF(O7=Inputs!$E$153,1,N67*(1+Inputs!O178))) -> 1.2762816 | ... T67: =IF(T7<Inputs!$E$153,0,IF(T7=Inputs!$E$153,1,S67*(1+Inputs!T178))) -> 1.6288946
B68: Medan Wheat - volume index (1 in the first year, then x (1 + growth)) | C68: index | G68: =IF(2023<Inputs!$E$155,0,1) -> 1 | H68: =IF(H7<Inputs!$E$155,0,IF(H7=Inputs!$E$155,1,G68*(1+Inputs!H180))) -> 1 | I68: =IF(I7<Inputs!$E$155,0,IF(I7=Inputs!$E$155,1,H68*(1+Inputs!I180))) -> 1.05 | J68: =IF(J7<Inputs!$E$155,0,IF(J7=Inputs!$E$155,1,I68*(1+Inputs!J180))) -> 1.1025 | K68: =IF(K7<Inputs!$E$155,0,IF(K7=Inputs!$E$155,1,J68*(1+Inputs!K180))) -> 1.157625 | L68: =IF(L7<Inputs!$E$155,0,IF(L7=Inputs!$E$155,1,K68*(1+Inputs!L180))) -> 1.2155063 | M68: =IF(M7<Inputs!$E$155,0,IF(M7=Inputs!$E$155,1,L68*(1+Inputs!M180))) -> 1.2762816 | N68: =IF(N7<Inputs!$E$155,0,IF(N7=Inputs!$E$155,1,M68*(1+Inputs!N180))) -> 1.3400956 | O68: =IF(O7<Inputs!$E$155,0,IF(O7=Inputs!$E$155,1,N68*(1+Inputs!O180))) -> 1.4071004 | ... T68: =IF(T7<Inputs!$E$155,0,IF(T7=Inputs!$E$155,1,S68*(1+Inputs!T180))) -> 1.7958563
B69: Makassar sugar - tariff applied = Inputs tariff (nil in FY2034-36 as in v29) + C01 x row-852 delta (Source Data 18) | C69: IDR/t | H69: =Inputs!H167+Inputs!$E$740*'Source Data'!H958 -> 32000 | I69: =Inputs!I167+Inputs!$E$740*'Source Data'!I958 -> 32960 | J69: =Inputs!J167+Inputs!$E$740*'Source Data'!J958 -> 33948.8 | K69: =Inputs!K167+Inputs!$E$740*'Source Data'!K958 -> 34967.264 | L69: =Inputs!L167+Inputs!$E$740*'Source Data'!L958 -> 36016.282 | M69: =Inputs!M167+Inputs!$E$740*'Source Data'!M958 -> 37096.77 | N69: =Inputs!N167+Inputs!$E$740*'Source Data'!N958 -> 38209.673 | O69: =Inputs!O167+Inputs!$E$740*'Source Data'!O958 -> 39355.964 | ... T69: =Inputs!T167+Inputs!$E$740*'Source Data'!T958 -> 0
B70: Cilegon Corn - revenue = base volume x index x volume lever x tariff x tariff lever / 1e9 | C70: IDR bn | H70: =Inputs!$E$130*H56*Inputs!$E$52*Inputs!H157*Inputs!$E$53/1000000000 -> 4.4828202 | I70: =Inputs!$E$130*I56*Inputs!$E$52*Inputs!I157*Inputs!$E$53/1000000000 -> 0.9831128 | J70: =Inputs!$E$130*J56*Inputs!$E$52*Inputs!J157*Inputs!$E$53/1000000000 -> 1.0632365 | K70: =Inputs!$E$130*K56*Inputs!$E$52*Inputs!K157*Inputs!$E$53/1000000000 -> 1.1498903 | L70: =Inputs!$E$130*L56*Inputs!$E$52*Inputs!L157*Inputs!$E$53/1000000000 -> 1.2436063 | M70: =Inputs!$E$130*M56*Inputs!$E$52*Inputs!M157*Inputs!$E$53/1000000000 -> 1.3449602 | N70: =Inputs!$E$130*N56*Inputs!$E$52*Inputs!N157*Inputs!$E$53/1000000000 -> 1.4545745 | O70: =Inputs!$E$130*O56*Inputs!$E$52*Inputs!O157*Inputs!$E$53/1000000000 -> 1.5731223 | ... T70: =Inputs!$E$130*T56*Inputs!$E$52*Inputs!T157*Inputs!$E$53/1000000000 -> 2.1300188
B71: Cilegon SBM - revenue = base volume x index x volume lever x tariff x tariff lever / 1e9 | C71: IDR bn | H71: =Inputs!$E$132*H57*Inputs!$E$52*Inputs!H159*Inputs!$E$53/1000000000 -> 13.510695 | I71: =Inputs!$E$132*I57*Inputs!$E$52*Inputs!I159*Inputs!$E$53/1000000000 -> 0.89505974 | J71: =Inputs!$E$132*J57*Inputs!$E$52*Inputs!J159*Inputs!$E$53/1000000000 -> 0.96800711 | K71: =Inputs!$E$132*K57*Inputs!$E$52*Inputs!K159*Inputs!$E$53/1000000000 -> 1.0468997 | L71: =Inputs!$E$132*L57*Inputs!$E$52*Inputs!L159*Inputs!$E$53/1000000000 -> 1.132222 | M71: =Inputs!$E$132*M57*Inputs!$E$52*Inputs!M159*Inputs!$E$53/1000000000 -> 1.2244981 | N71: =Inputs!$E$132*N57*Inputs!$E$52*Inputs!N159*Inputs!$E$53/1000000000 -> 1.3242947 | O71: =Inputs!$E$132*O57*Inputs!$E$52*Inputs!O159*Inputs!$E$53/1000000000 -> 1.4322247 | ... T71: =Inputs!$E$132*T57*Inputs!$E$52*Inputs!T159*Inputs!$E$53/1000000000 -> 1.9392425
B72: Cilegon Soybean - revenue = base volume x index x volume lever x tariff x tariff lever / 1e9 | C72: IDR bn | H72: =Inputs!$E$134*H58*Inputs!$E$52*Inputs!H161*Inputs!$E$53/1000000000 -> 1.3965737 | I72: =Inputs!$E$134*I58*Inputs!$E$52*Inputs!I161*Inputs!$E$53/1000000000 -> 0.83989117 | J72: =Inputs!$E$134*J58*Inputs!$E$52*Inputs!J161*Inputs!$E$53/1000000000 -> 0.9083423 | K72: =Inputs!$E$134*K58*Inputs!$E$52*Inputs!K161*Inputs!$E$53/1000000000 -> 0.9823722 | L72: =Inputs!$E$134*L58*Inputs!$E$52*Inputs!L161*Inputs!$E$53/1000000000 -> 1.0624355 | M72: =Inputs!$E$134*M58*Inputs!$E$52*Inputs!M161*Inputs!$E$53/1000000000 -> 1.149024 | N72: =Inputs!$E$134*N58*Inputs!$E$52*Inputs!N161*Inputs!$E$53/1000000000 -> 1.2426695 | O72: =Inputs!$E$134*O58*Inputs!$E$52*Inputs!O161*Inputs!$E$53/1000000000 -> 1.3439471 | ... T72: =Inputs!$E$134*T58*Inputs!$E$52*Inputs!T161*Inputs!$E$53/1000000000 -> 1.8197139
B73: Cilegon Sugar - revenue = base volume x index x volume lever x tariff x tariff lever / 1e9 | C73: IDR bn | H73: =Inputs!$E$136*H59*Inputs!$E$52*Inputs!H163*Inputs!$E$53/1000000000 -> 12.323025 | I73: =Inputs!$E$136*I59*Inputs!$E$52*Inputs!I163*Inputs!$E$53/1000000000 -> 13.327352 | J73: =Inputs!$E$136*J59*Inputs!$E$52*Inputs!J163*Inputs!$E$53/1000000000 -> 1.0330799 | K73: =Inputs!$E$136*K59*Inputs!$E$52*Inputs!K163*Inputs!$E$53/1000000000 -> 1.1172759 | L73: =Inputs!$E$136*L59*Inputs!$E$52*Inputs!L163*Inputs!$E$53/1000000000 -> 1.2083339 | M73: =Inputs!$E$136*M59*Inputs!$E$52*Inputs!M163*Inputs!$E$53/1000000000 -> 1.3068131 | N73: =Inputs!$E$136*N59*Inputs!$E$52*Inputs!N163*Inputs!$E$53/1000000000 -> 1.4133184 | O73: =Inputs!$E$136*O59*Inputs!$E$52*Inputs!O163*Inputs!$E$53/1000000000 -> 1.5285038 | ... T73: =Inputs!$E$136*T59*Inputs!$E$52*Inputs!T163*Inputs!$E$53/1000000000 -> 2.0696051
B74: Cilegon Wheat - revenue = base volume x index x volume lever x tariff x tariff lever / 1e9 | C74: IDR bn | H74: =Inputs!$E$138*H60*Inputs!$E$52*Inputs!H165*Inputs!$E$53/1000000000 -> 12.944925 | I74: =Inputs!$E$138*I60*Inputs!$E$52*Inputs!I165*Inputs!$E$53/1000000000 -> 2.6549212 | J74: =Inputs!$E$138*J60*Inputs!$E$52*Inputs!J165*Inputs!$E$53/1000000000 -> 2.8712973 | K74: =Inputs!$E$138*K60*Inputs!$E$52*Inputs!K165*Inputs!$E$53/1000000000 -> 3.105308 | L74: =Inputs!$E$138*L60*Inputs!$E$52*Inputs!L165*Inputs!$E$53/1000000000 -> 3.3583906 | M74: =Inputs!$E$138*M60*Inputs!$E$52*Inputs!M165*Inputs!$E$53/1000000000 -> 3.6320994 | N74: =Inputs!$E$138*N60*Inputs!$E$52*Inputs!N165*Inputs!$E$53/1000000000 -> 3.9281155 | O74: =Inputs!$E$138*O60*Inputs!$E$52*Inputs!O165*Inputs!$E$53/1000000000 -> 4.248257 | ... T74: =Inputs!$E$138*T60*Inputs!$E$52*Inputs!T165*Inputs!$E$53/1000000000 -> 5.7521701
B75: Makassar Sugar - revenue = base volume x index x volume lever x tariff x tariff lever / 1e9 | C75: IDR bn | H75: =Inputs!$E$140*H61*Inputs!$E$52*H69*Inputs!$E$53/1000000000 -> 8.832 | I75: =Inputs!$E$140*I61*Inputs!$E$52*I69*Inputs!$E$53/1000000000 -> 9.4608384 | J75: =Inputs!$E$140*J61*Inputs!$E$52*J69*Inputs!$E$53/1000000000 -> 10.13445 | K75: =Inputs!$E$140*K61*Inputs!$E$52*K69*Inputs!$E$53/1000000000 -> 10.856023 | L75: =Inputs!$E$140*L61*Inputs!$E$52*L69*Inputs!$E$53/1000000000 -> 11.628972 | M75: =Inputs!$E$140*M61*Inputs!$E$52*M69*Inputs!$E$53/1000000000 -> 12.456955 | N75: =Inputs!$E$140*N61*Inputs!$E$52*N69*Inputs!$E$53/1000000000 -> 13.34389 | O75: =Inputs!$E$140*O61*Inputs!$E$52*O69*Inputs!$E$53/1000000000 -> 14.293975 | ... T75: =Inputs!$E$140*T61*Inputs!$E$52*T69*Inputs!$E$53/1000000000 -> 0
B76: Makassar Wheat - revenue = base volume x index x volume lever x tariff x tariff lever / 1e9 | C76: IDR bn | H76: =Inputs!$E$142*H62*Inputs!$E$52*Inputs!H169*Inputs!$E$53/1000000000 -> 6.752 | I76: =Inputs!$E$142*I62*Inputs!$E$52*Inputs!I169*Inputs!$E$53/1000000000 -> 7.2327424 | J76: =Inputs!$E$142*J62*Inputs!$E$52*Inputs!J169*Inputs!$E$53/1000000000 -> 7.7477137 | K76: =Inputs!$E$142*K62*Inputs!$E$52*Inputs!K169*Inputs!$E$53/1000000000 -> 8.2993509 | L76: =Inputs!$E$142*L62*Inputs!$E$52*Inputs!L169*Inputs!$E$53/1000000000 -> 8.8902647 | M76: =Inputs!$E$142*M62*Inputs!$E$52*Inputs!M169*Inputs!$E$53/1000000000 -> 9.5232515 | N76: =Inputs!$E$142*N62*Inputs!$E$52*Inputs!N169*Inputs!$E$53/1000000000 -> 10.201307 | O76: =Inputs!$E$142*O62*Inputs!$E$52*Inputs!O169*Inputs!$E$53/1000000000 -> 10.92764 | ... T76: =Inputs!$E$142*T62*Inputs!$E$52*Inputs!T169*Inputs!$E$53/1000000000 -> 14.104819
B77: Surabaya SBM - revenue = base volume x index x volume lever x tariff x tariff lever / 1e9 | C77: IDR bn | H77: =Inputs!$E$144*H63*Inputs!$E$52*Inputs!H171*Inputs!$E$53/1000000000 -> 7.8006093 | I77: =Inputs!$E$144*I63*Inputs!$E$52*Inputs!I171*Inputs!$E$53/1000000000 -> 8.436359 | J77: =Inputs!$E$144*J63*Inputs!$E$52*Inputs!J171*Inputs!$E$53/1000000000 -> 9.1239222 | K77: =Inputs!$E$144*K63*Inputs!$E$52*Inputs!K171*Inputs!$E$53/1000000000 -> 9.8675219 | L77: =Inputs!$E$144*L63*Inputs!$E$52*Inputs!L171*Inputs!$E$53/1000000000 -> 10.671725 | M77: =Inputs!$E$144*M63*Inputs!$E$52*Inputs!M171*Inputs!$E$53/1000000000 -> 11.541471 | N77: =Inputs!$E$144*N63*Inputs!$E$52*Inputs!N171*Inputs!$E$53/1000000000 -> 12.4821 | O77: =Inputs!$E$144*O63*Inputs!$E$52*Inputs!O171*Inputs!$E$53/1000000000 -> 13.499392 | ... T77: =Inputs!$E$144*T63*Inputs!$E$52*Inputs!T171*Inputs!$E$53/1000000000 -> 18.278272
B78: Surabaya Soybean - revenue = base volume x index x volume lever x tariff x tariff lever / 1e9 | C78: IDR bn | H78: =Inputs!$E$146*H64*Inputs!$E$52*Inputs!H173*Inputs!$E$53/1000000000 -> 1.39425 | I78: =Inputs!$E$146*I64*Inputs!$E$52*Inputs!I173*Inputs!$E$53/1000000000 -> 1.5078814 | J78: =Inputs!$E$146*J64*Inputs!$E$52*Inputs!J173*Inputs!$E$53/1000000000 -> 1.6307737 | K78: =Inputs!$E$146*K64*Inputs!$E$52*Inputs!K173*Inputs!$E$53/1000000000 -> 1.7636818 | L78: =Inputs!$E$146*L64*Inputs!$E$52*Inputs!L173*Inputs!$E$53/1000000000 -> 1.9074218 | M78: =Inputs!$E$146*M64*Inputs!$E$52*Inputs!M173*Inputs!$E$53/1000000000 -> 2.0628767 | N78: =Inputs!$E$146*N64*Inputs!$E$52*Inputs!N173*Inputs!$E$53/1000000000 -> 2.2310012 | O78: =Inputs!$E$146*O64*Inputs!$E$52*Inputs!O173*Inputs!$E$53/1000000000 -> 2.4128278 | ... T78: =Inputs!$E$146*T64*Inputs!$E$52*Inputs!T173*Inputs!$E$53/1000000000 -> 3.2669859
B79: Medan Corn - revenue = base volume x index x volume lever x tariff x tariff lever / 1e9 | C79: IDR bn | H79: =Inputs!$E$148*H65*Inputs!$E$52*Inputs!H175*Inputs!$E$53/1000000000 -> 0 | I79: =Inputs!$E$148*I65*Inputs!$E$52*Inputs!I175*Inputs!$E$53/1000000000 -> 0 | J79: =Inputs!$E$148*J65*Inputs!$E$52*Inputs!J175*Inputs!$E$53/1000000000 -> 1.6189178 | K79: =Inputs!$E$148*K65*Inputs!$E$52*Inputs!K175*Inputs!$E$53/1000000000 -> 1.7508596 | L79: =Inputs!$E$148*L65*Inputs!$E$52*Inputs!L175*Inputs!$E$53/1000000000 -> 1.8935547 | M79: =Inputs!$E$148*M65*Inputs!$E$52*Inputs!M175*Inputs!$E$53/1000000000 -> 2.0478794 | N79: =Inputs!$E$148*N65*Inputs!$E$52*Inputs!N175*Inputs!$E$53/1000000000 -> 2.2147816 | O79: =Inputs!$E$148*O65*Inputs!$E$52*Inputs!O175*Inputs!$E$53/1000000000 -> 2.3952863 | ... T79: =Inputs!$E$148*T65*Inputs!$E$52*Inputs!T175*Inputs!$E$53/1000000000 -> 3.2432346
B80: Medan SBM - revenue = base volume x index x volume lever x tariff x tariff lever / 1e9 | C80: IDR bn | H80: =Inputs!$E$150*H66*Inputs!$E$52*Inputs!H177*Inputs!$E$53/1000000000 -> 11.034446 | I80: =Inputs!$E$150*I66*Inputs!$E$52*Inputs!I177*Inputs!$E$53/1000000000 -> 11.933753 | J80: =Inputs!$E$150*J66*Inputs!$E$52*Inputs!J177*Inputs!$E$53/1000000000 -> 12.906354 | K80: =Inputs!$E$150*K66*Inputs!$E$52*Inputs!K177*Inputs!$E$53/1000000000 -> 13.958222 | L80: =Inputs!$E$150*L66*Inputs!$E$52*Inputs!L177*Inputs!$E$53/1000000000 -> 15.095817 | M80: =Inputs!$E$150*M66*Inputs!$E$52*Inputs!M177*Inputs!$E$53/1000000000 -> 16.326126 | N80: =Inputs!$E$150*N66*Inputs!$E$52*Inputs!N177*Inputs!$E$53/1000000000 -> 17.656705 | O80: =Inputs!$E$150*O66*Inputs!$E$52*Inputs!O177*Inputs!$E$53/1000000000 -> 19.095726 | ... T80: =Inputs!$E$150*T66*Inputs!$E$52*Inputs!T177*Inputs!$E$53/1000000000 -> 25.855749
B81: Medan Soybean - revenue = base volume x index x volume lever x tariff x tariff lever / 1e9 | C81: IDR bn | H81: =Inputs!$E$152*H67*Inputs!$E$52*Inputs!H179*Inputs!$E$53/1000000000 -> 0 | I81: =Inputs!$E$152*I67*Inputs!$E$52*Inputs!I179*Inputs!$E$53/1000000000 -> 0 | J81: =Inputs!$E$152*J67*Inputs!$E$52*Inputs!J179*Inputs!$E$53/1000000000 -> 3.2378357 | K81: =Inputs!$E$152*K67*Inputs!$E$52*Inputs!K179*Inputs!$E$53/1000000000 -> 3.5017193 | L81: =Inputs!$E$152*L67*Inputs!$E$52*Inputs!L179*Inputs!$E$53/1000000000 -> 3.7871094 | M81: =Inputs!$E$152*M67*Inputs!$E$52*Inputs!M179*Inputs!$E$53/1000000000 -> 4.0957588 | N81: =Inputs!$E$152*N67*Inputs!$E$52*Inputs!N179*Inputs!$E$53/1000000000 -> 4.4295631 | O81: =Inputs!$E$152*O67*Inputs!$E$52*Inputs!O179*Inputs!$E$53/1000000000 -> 4.7905725 | ... T81: =Inputs!$E$152*T67*Inputs!$E$52*Inputs!T179*Inputs!$E$53/1000000000 -> 6.4864693
B82: Medan Wheat - revenue = base volume x index x volume lever x tariff x tariff lever / 1e9 | C82: IDR bn | H82: =Inputs!$E$154*H68*Inputs!$E$52*Inputs!H181*Inputs!$E$53/1000000000 -> 7.4773281 | I82: =Inputs!$E$154*I68*Inputs!$E$52*Inputs!I181*Inputs!$E$53/1000000000 -> 8.0867303 | J82: =Inputs!$E$154*J68*Inputs!$E$52*Inputs!J181*Inputs!$E$53/1000000000 -> 8.7457988 | K82: =Inputs!$E$154*K68*Inputs!$E$52*Inputs!K181*Inputs!$E$53/1000000000 -> 9.4585814 | L82: =Inputs!$E$154*L68*Inputs!$E$52*Inputs!L181*Inputs!$E$53/1000000000 -> 10.229456 | M82: =Inputs!$E$154*M68*Inputs!$E$52*Inputs!M181*Inputs!$E$53/1000000000 -> 11.063156 | N82: =Inputs!$E$154*N68*Inputs!$E$52*Inputs!N181*Inputs!$E$53/1000000000 -> 11.964804 | O82: =Inputs!$E$154*O68*Inputs!$E$52*Inputs!O181*Inputs!$E$53/1000000000 -> 12.939935 | ... T82: =Inputs!$E$154*T68*Inputs!$E$52*Inputs!T181*Inputs!$E$53/1000000000 -> 17.520764
B83: Cilegon volume | C83: tons | H83: =(Inputs!$E$130*H56+Inputs!$E$132*H57+Inputs!$E$134*H58+Inputs!$E$136*H59+Inputs!$E$138*H60)*Inputs!$E$52 -> 2233921.2 | I83: =(Inputs!$E$130*I56+Inputs!$E$132*I57+Inputs!$E$134*I58+Inputs!$E$136*I59+Inputs!$E$138*I60)*Inputs!$E$52 -> 2345617.3 | J83: =(Inputs!$E$130*J56+Inputs!$E$132*J57+Inputs!$E$134*J58+Inputs!$E$136*J59+Inputs!$E$138*J60)*Inputs!$E$52 -> 2462898.2 | K83: =(Inputs!$E$130*K56+Inputs!$E$132*K57+Inputs!$E$134*K58+Inputs!$E$136*K59+Inputs!$E$138*K60)*Inputs!$E$52 -> 2586043.1 | L83: =(Inputs!$E$130*L56+Inputs!$E$132*L57+Inputs!$E$134*L58+Inputs!$E$136*L59+Inputs!$E$138*L60)*Inputs!$E$52 -> 2715345.2 | M83: =(Inputs!$E$130*M56+Inputs!$E$132*M57+Inputs!$E$134*M58+Inputs!$E$136*M59+Inputs!$E$138*M60)*Inputs!$E$52 -> 2851112.5 | N83: =(Inputs!$E$130*N56+Inputs!$E$132*N57+Inputs!$E$134*N58+Inputs!$E$136*N59+Inputs!$E$138*N60)*Inputs!$E$52 -> 2993668.1 | O83: =(Inputs!$E$130*O56+Inputs!$E$132*O57+Inputs!$E$134*O58+Inputs!$E$136*O59+Inputs!$E$138*O60)*Inputs!$E$52 -> 3143351.5 | ... T83: =(Inputs!$E$130*T56+Inputs!$E$132*T57+Inputs!$E$134*T58+Inputs!$E$136*T59+Inputs!$E$138*T60)*Inputs!$E$52 -> 4011801.6
B84: Makassar volume | C84: tons | H84: =(Inputs!$E$140*H61+Inputs!$E$142*H62)*Inputs!$E$52 -> 356000 | I84: =(Inputs!$E$140*I61+Inputs!$E$142*I62)*Inputs!$E$52 -> 370240 | J84: =(Inputs!$E$140*J61+Inputs!$E$142*J62)*Inputs!$E$52 -> 385049.6 | K84: =(Inputs!$E$140*K61+Inputs!$E$142*K62)*Inputs!$E$52 -> 400451.58 | L84: =(Inputs!$E$140*L61+Inputs!$E$142*L62)*Inputs!$E$52 -> 416469.65 | M84: =(Inputs!$E$140*M61+Inputs!$E$142*M62)*Inputs!$E$52 -> 433128.43 | N84: =(Inputs!$E$140*N61+Inputs!$E$142*N62)*Inputs!$E$52 -> 450453.57 | O84: =(Inputs!$E$140*O61+Inputs!$E$142*O62)*Inputs!$E$52 -> 468471.71 | ... T84: =(Inputs!$E$140*T61+Inputs!$E$142*T62)*Inputs!$E$52 -> 569967.47
B85: Surabaya volume | C85: tons | H85: =(Inputs!$E$144*H63+Inputs!$E$146*H64)*Inputs!$E$52 -> 747860 | I85: =(Inputs!$E$144*I63+Inputs!$E$146*I64)*Inputs!$E$52 -> 785253 | J85: =(Inputs!$E$144*J63+Inputs!$E$146*J64)*Inputs!$E$52 -> 824515.65 | K85: =(Inputs!$E$144*K63+Inputs!$E$146*K64)*Inputs!$E$52 -> 865741.43 | L85: =(Inputs!$E$144*L63+Inputs!$E$146*L64)*Inputs!$E$52 -> 909028.5 | M85: =(Inputs!$E$144*M63+Inputs!$E$146*M64)*Inputs!$E$52 -> 954479.93 | N85: =(Inputs!$E$144*N63+Inputs!$E$146*N64)*Inputs!$E$52 -> 1002203.9 | O85: =(Inputs!$E$144*O63+Inputs!$E$146*O64)*Inputs!$E$52 -> 1052314.1 | ... T85: =(Inputs!$E$144*T63+Inputs!$E$146*T64)*Inputs!$E$52 -> 1343049.1
B86: Medan volume | C86: tons | H86: =(Inputs!$E$148*H65+Inputs!$E$150*H66+Inputs!$E$152*H67+Inputs!$E$154*H68)*Inputs!$E$52 -> 1261624 | I86: =(Inputs!$E$148*I65+Inputs!$E$150*I66+Inputs!$E$152*I67+Inputs!$E$154*I68)*Inputs!$E$52 -> 1324705.2 | J86: =(Inputs!$E$148*J65+Inputs!$E$150*J66+Inputs!$E$152*J67+Inputs!$E$154*J68)*Inputs!$E$52 -> 1690940.5 | K86: =(Inputs!$E$148*K65+Inputs!$E$150*K66+Inputs!$E$152*K67+Inputs!$E$154*K68)*Inputs!$E$52 -> 1775487.5 | L86: =(Inputs!$E$148*L65+Inputs!$E$150*L66+Inputs!$E$152*L67+Inputs!$E$154*L68)*Inputs!$E$52 -> 1864261.9 | M86: =(Inputs!$E$148*M65+Inputs!$E$150*M66+Inputs!$E$152*M67+Inputs!$E$154*M68)*Inputs!$E$52 -> 1957475 | N86: =(Inputs!$E$148*N65+Inputs!$E$150*N66+Inputs!$E$152*N67+Inputs!$E$154*N68)*Inputs!$E$52 -> 2055348.7 | O86: =(Inputs!$E$148*O65+Inputs!$E$150*O66+Inputs!$E$152*O67+Inputs!$E$154*O68)*Inputs!$E$52 -> 2158116.1 | ... T86: =(Inputs!$E$148*T65+Inputs!$E$150*T66+Inputs!$E$152*T67+Inputs!$E$154*T68)*Inputs!$E$52 -> 2754363.8
B87: WIN volume | C87: tons | H87: =H83+H84+H85+H86 -> 4599405.2 | I87: =I83+I84+I85+I86 -> 4825815.5 | J87: =J83+J84+J85+J86 -> 5363403.9 | K87: =K83+K84+K85+K86 -> 5627723.6 | L87: =L83+L84+L85+L86 -> 5905105.2 | M87: =M83+M84+M85+M86 -> 6196195.8 | N87: =N83+N84+N85+N86 -> 6501674.3 | O87: =O83+O84+O85+O86 -> 6822253.5 | ... T87: =T83+T84+T85+T86 -> 8679182
B88: Cilegon revenue | C88: IDR bn | H88: =H70+H71+H72+H73+H74 -> 44.658039 | I88: =I70+I71+I72+I73+I74 -> 18.700337 | J88: =J70+J71+J72+J73+J74 -> 6.8439631 | K88: =K70+K71+K72+K73+K74 -> 7.4017461 | L88: =L70+L71+L72+L73+L74 -> 8.0049884 | M88: =M70+M71+M72+M73+M74 -> 8.6573949 | N88: =N70+N71+N72+N73+N74 -> 9.3629726 | O88: =O70+O71+O72+O73+O74 -> 10.126055 | ... T88: =T70+T71+T72+T73+T74 -> 13.71075
B89: Makassar revenue | C89: IDR bn | H89: =H75+H76 -> 15.584 | I89: =I75+I76 -> 16.693581 | J89: =J75+J76 -> 17.882164 | K89: =K75+K76 -> 19.155374 | L89: =L75+L76 -> 20.519236 | M89: =M75+M76 -> 21.980206 | N89: =N75+N76 -> 23.545197 | O89: =O75+O76 -> 25.221615 | ... T89: =T75+T76 -> 14.104819
B90: Surabaya revenue | C90: IDR bn | H90: =H77+H78 -> 9.1948593 | I90: =I77+I78 -> 9.9442404 | J90: =J77+J78 -> 10.754696 | K90: =K77+K78 -> 11.631204 | L90: =L77+L78 -> 12.579147 | M90: =M77+M78 -> 13.604347 | N90: =N77+N78 -> 14.713102 | O90: =O77+O78 -> 15.912219 | ... T90: =T77+T78 -> 21.545258
B91: Medan revenue | C91: IDR bn | H91: =H79+H80+H81+H82 -> 18.511774 | I91: =I79+I80+I81+I82 -> 20.020483 | J91: =J79+J80+J81+J82 -> 26.508906 | K91: =K79+K80+K81+K82 -> 28.669382 | L91: =L79+L80+L81+L82 -> 31.005937 | M91: =M79+M80+M81+M82 -> 33.53292 | N91: =N79+N80+N81+N82 -> 36.265853 | O91: =O79+O80+O81+O82 -> 39.22152 | ... T91: =T79+T80+T81+T82 -> 53.106217
B92: E4 Revenue = sum of the four branches | C92: IDR bn | H92: =H88+H89+H90+H91 -> 87.948672 | I92: =I88+I89+I90+I91 -> 65.358641 | J92: =J88+J89+J90+J91 -> 61.989729 | K92: =K88+K89+K90+K91 -> 66.857705 | L92: =L88+L89+L90+L91 -> 72.109308 | M92: =M88+M89+M90+M91 -> 77.774869 | N92: =N88+N89+N90+N91 -> 83.887124 | O92: =O88+O89+O90+O91 -> 90.481409 | ... T92: =T88+T89+T90+T91 -> 102.46705
B94: C. PROJECTS (P01-P11, P15) - volumes ramp up from the commencement year
B95: P01 Cigading Wharf 2 (SGT 2)
B96: Volume index (1 in the first operating year, then x (1 + growth)) | C96: index | G96: 0 | H96: =IF(H10=0,0,IF((H10*(1-G10))=1,1,G96*(1+Inputs!H192))) -> 0 | I96: =IF(I10=0,0,IF((I10*(1-H10))=1,1,H96*(1+Inputs!I192))) -> 1 | J96: =IF(J10=0,0,IF((J10*(1-I10))=1,1,I96*(1+Inputs!J192))) -> 1.03 | K96: =IF(K10=0,0,IF((K10*(1-J10))=1,1,J96*(1+Inputs!K192))) -> 1.0609 | L96: =IF(L10=0,0,IF((L10*(1-K10))=1,1,K96*(1+Inputs!L192))) -> 1.092727 | M96: =IF(M10=0,0,IF((M10*(1-L10))=1,1,L96*(1+Inputs!M192))) -> 1.1255088 | N96: =IF(N10=0,0,IF((N10*(1-M10))=1,1,M96*(1+Inputs!N192))) -> 1.1592741 | O96: =IF(O10=0,0,IF((O10*(1-N10))=1,1,N96*(1+Inputs!O192))) -> 1.1940523 | ... T96: =IF(T10=0,0,IF((T10*(1-S10))=1,1,S96*(1+Inputs!T192))) -> 1.3842339
B97: Throughput = first-year base x index x volume lever | C97: tons | H97: =Inputs!$E$191*H96*Inputs!$E$52 -> 0 | I97: =Inputs!$E$191*I96*Inputs!$E$52 -> 2449985.6 | J97: =Inputs!$E$191*J96*Inputs!$E$52 -> 2523485.1 | K97: =Inputs!$E$191*K96*Inputs!$E$52 -> 2599189.7 | L97: =Inputs!$E$191*L96*Inputs!$E$52 -> 2677165.4 | M97: =Inputs!$E$191*M96*Inputs!$E$52 -> 2757480.3 | N97: =Inputs!$E$191*N96*Inputs!$E$52 -> 2840204.8 | O97: =Inputs!$E$191*O96*Inputs!$E$52 -> 2925410.9 | ... T97: =Inputs!$E$191*T96*Inputs!$E$52 -> 3391353
B98: Tariff (annual input x tariff lever) | C98: IDR/t | H98: =Inputs!H193*Inputs!$E$53 -> 0 | I98: =Inputs!I193*Inputs!$E$53 -> 40944 | J98: =Inputs!J193*Inputs!$E$53 -> 40944 | K98: =Inputs!K193*Inputs!$E$53 -> 49132.8 | L98: =Inputs!L193*Inputs!$E$53 -> 49132.8 | M98: =Inputs!M193*Inputs!$E$53 -> 54046.08 | N98: =Inputs!N193*Inputs!$E$53 -> 54046.08 | O98: =Inputs!O193*Inputs!$E$53 -> 57288.845 | ... T98: =Inputs!T193*Inputs!$E$53 -> 60726.175
B99: P01 Revenue = throughput x tariff / 1e9 | C99: IDR bn | H99: =H97*H98/1000000000 -> 0 | I99: =I97*I98/1000000000 -> 100.31221 | J99: =J97*J98/1000000000 -> 103.32158 | K99: =K97*K98/1000000000 -> 127.70547 | L99: =L97*L98/1000000000 -> 131.53663 | M99: =M97*M98/1000000000 -> 149.031 | N99: =N97*N98/1000000000 -> 153.50193 | O99: =O97*O98/1000000000 -> 167.59341 | ... T99: =T97*T98/1000000000 -> 205.9439
B100: P02 Cigading extended conveyor (SGT 2)
B101: Volume index (1 in the first operating year) | C101: index | G101: 0 | H101: =IF(H11=0,0,IF((H11*(1-G11))=1,1,G101*(1+Inputs!H205))) -> 0 | I101: =IF(I11=0,0,IF((I11*(1-H11))=1,1,H101*(1+Inputs!I205))) -> 1 | J101: =IF(J11=0,0,IF((J11*(1-I11))=1,1,I101*(1+Inputs!J205))) -> 1.03 | K101: =IF(K11=0,0,IF((K11*(1-J11))=1,1,J101*(1+Inputs!K205))) -> 1.0609 | L101: =IF(L11=0,0,IF((L11*(1-K11))=1,1,K101*(1+Inputs!L205))) -> 1.092727 | M101: =IF(M11=0,0,IF((M11*(1-L11))=1,1,L101*(1+Inputs!M205))) -> 1.1255088 | N101: =IF(N11=0,0,IF((N11*(1-M11))=1,1,M101*(1+Inputs!N205))) -> 1.1592741 | O101: =IF(O11=0,0,IF((O11*(1-N11))=1,1,N101*(1+Inputs!O205))) -> 1.1940523 | ... T101: =IF(T11=0,0,IF((T11*(1-S11))=1,1,S101*(1+Inputs!T205))) -> 1.3842339
B102: Conveyed volume (service on Cigading cargo) = first-year base x index x volume lever | C102: tons | H102: =Inputs!$E$204*H101*Inputs!$E$52 -> 0 | I102: =Inputs!$E$204*I101*Inputs!$E$52 -> 2100000 | J102: =Inputs!$E$204*J101*Inputs!$E$52 -> 2163000 | K102: =Inputs!$E$204*K101*Inputs!$E$52 -> 2227890 | L102: =Inputs!$E$204*L101*Inputs!$E$52 -> 2294726.7 | M102: =Inputs!$E$204*M101*Inputs!$E$52 -> 2363568.5 | N102: =Inputs!$E$204*N101*Inputs!$E$52 -> 2434475.6 | O102: =Inputs!$E$204*O101*Inputs!$E$52 -> 2507509.8 | ... T102: =Inputs!$E$204*T101*Inputs!$E$52 -> 2906891.1
B103: Tariff (annual input x tariff lever) | C103: IDR/t | H103: =Inputs!H206*Inputs!$E$53 -> 0 | I103: =Inputs!I206*Inputs!$E$53 -> 15000 | J103: =Inputs!J206*Inputs!$E$53 -> 15000 | K103: =Inputs!K206*Inputs!$E$53 -> 15000 | L103: =Inputs!L206*Inputs!$E$53 -> 15000 | M103: =Inputs!M206*Inputs!$E$53 -> 15000 | N103: =Inputs!N206*Inputs!$E$53 -> 15000 | O103: =Inputs!O206*Inputs!$E$53 -> 15000 | ... T103: =Inputs!T206*Inputs!$E$53 -> 15000
B104: P02 Revenue = conveyed volume x tariff / 1e9 | C104: IDR bn | H104: =H102*H103/1000000000 -> 0 | I104: =I102*I103/1000000000 -> 31.5 | J104: =J102*J103/1000000000 -> 32.445 | K104: =K102*K103/1000000000 -> 33.41835 | L104: =L102*L103/1000000000 -> 34.420901 | M104: =M102*M103/1000000000 -> 35.453528 | N104: =N102*N103/1000000000 -> 36.517133 | O104: =O102*O103/1000000000 -> 37.612647 | ... T104: =T102*T103/1000000000 -> 43.603367
B105: P03 KBS warehouse revitalisation (SGT 2) - FSL 49% revenue share
...

Sheet Cost Calculation
B1: COST CALCULATION - cost of sales, operating expenses and EBITDA by business and project (cost drivers visible; v29 methods)
B2: Existing businesses: v29 cost lines (fixed amounts, unit costs per ton, ratios). Projects: v29 cost ratios and shared unit costs. Costs are positive here and deducted in the outputs.
B3: Go to sheet: | C3: Model Flow | D3: Inputs | E3: FS Request | F3: Revenue | G3: [Costs] | H3: BUMN Synergy | I3: Capex | J3: Work. cap. | K3: Financing | L3: Funding | M3: Out: w/o BUMN | N3: Out: With BUMN | O3: Val: w/o BUMN | P3: Val: With BUMN | Q3: Proj. CF | R3: Proj. Summary | S3: Checks | T3: Source Data
G4: Dec-23 | H4: FY | I4: FY | J4: FY | K4: FY | L4: FY | M4: FY | N4: FY | O4: FY | P4: FY | Q4: FY | R4: FY | S4: FY | T4: FY
B5: IDR bn unless stated | C5: Unit | D5: Basis | E5: Parameter | G5: 2023 | H5: 2024 | I5: 2025 | J5: 2026 | K5: 2027 | L5: 2028 | M5: 2029 | N5: 2030 | O5: 2031 | P5: 2032 | Q5: 2033 | R5: 2034 | S5: 2035 | T5: 2036 | U5: Note
B6: A. EXISTING BUSINESSES (E1-E4) - cost lines, cost of sales, operating expenses, EBITDA
B7: E1 Teluk Lamong (NPLOG)
B8: E1 cost lines (before the cost lever; 2023 column = FY2023 base x v29 uplift; each later year = prior year x (1 + that year's growth))
B9: Employee cost (payroll) | C9: IDR bn | D9: COGS fixed | G9: =Inputs!$E$317*Inputs!$F$317 -> 12.869296 | H9: =G9*(1+Inputs!H317) -> 13.319721 | I9: =H9*(1+Inputs!I317) -> 13.785911 | J9: =I9*(1+Inputs!J317) -> 14.268418 | K9: =J9*(1+Inputs!K317) -> 14.767813 | L9: =K9*(1+Inputs!L317) -> 15.284686 | M9: =L9*(1+Inputs!M317) -> 15.81965 | N9: =M9*(1+Inputs!N317) -> 16.373338 | O9: =N9*(1+Inputs!O317) -> 16.946405 | ... T9: =S9*(1+Inputs!T317) -> 20.127013
B10: Electricity - unit cost | C10: IDR/t | D10: COGS per t | G10: =Inputs!$E$318*Inputs!$F$318/Inputs!$E$107*1000000000 -> 1452.8478 | H10: =G10*(1+Inputs!H318) -> 1496.4333 | I10: =H10*(1+Inputs!I318) -> 1541.3263 | J10: =I10*(1+Inputs!J318) -> 1587.5661 | K10: =J10*(1+Inputs!K318) -> 1635.193 | L10: =K10*(1+Inputs!L318) -> 1684.2488 | M10: =L10*(1+Inputs!M318) -> 1734.7763 | N10: =M10*(1+Inputs!N318) -> 1786.8196 | O10: =N10*(1+Inputs!O318) -> 1840.4242 | ... T10: =S10*(1+Inputs!T318) -> 2133.556
B11: Fuel - unit cost | C11: IDR/t | D11: COGS per t | G11: =Inputs!$E$319*Inputs!$F$319/Inputs!$E$107*1000000000 -> 856.40404 | H11: =G11*(1+Inputs!H319) -> 882.09616 | I11: =H11*(1+Inputs!I319) -> 908.55904 | J11: =I11*(1+Inputs!J319) -> 935.81582 | K11: =J11*(1+Inputs!K319) -> 963.89029 | L11: =K11*(1+Inputs!L319) -> 992.807 | M11: =L11*(1+Inputs!M319) -> 1022.5912 | N11: =M11*(1+Inputs!N319) -> 1053.2689 | O11: =N11*(1+Inputs!O319) -> 1084.867 | ... T11: =S11*(1+Inputs!T319) -> 1257.6582
B12: Security | C12: IDR bn | D12: COGS fixed | G12: =Inputs!$E$320*Inputs!$F$320 -> 2.0920344 | H12: =G12*(1+Inputs!H320) -> 2.1652557 | I12: =H12*(1+Inputs!I320) -> 2.2410396 | J12: =I12*(1+Inputs!J320) -> 2.319476 | K12: =J12*(1+Inputs!K320) -> 2.4006576 | L12: =K12*(1+Inputs!L320) -> 2.4846807 | M12: =L12*(1+Inputs!M320) -> 2.5716445 | N12: =M12*(1+Inputs!N320) -> 2.661652 | O12: =N12*(1+Inputs!O320) -> 2.7548099 | ... T12: =S12*(1+Inputs!T320) -> 3.27185
B13: Repair & maintenance - unit cost | C13: IDR/t | D13: COGS per t | G13: =Inputs!$E$321*Inputs!$F$321/Inputs!$E$107*1000000000 -> 685.45176 | H13: =G13*(1+Inputs!H321) -> 706.01531 | I13: =H13*(1+Inputs!I321) -> 727.19577 | J13: =I13*(1+Inputs!J321) -> 749.01164 | K13: =J13*(1+Inputs!K321) -> 771.48199 | L13: =K13*(1+Inputs!L321) -> 794.62645 | M13: =L13*(1+Inputs!M321) -> 818.46525 | N13: =M13*(1+Inputs!N321) -> 843.0192 | O13: =N13*(1+Inputs!O321) -> 868.30978 | ... T13: =S13*(1+Inputs!T321) -> 1006.609
B14: Employee overtime - unit cost | C14: IDR/t | D14: COGS per t | G14: =Inputs!$E$322*Inputs!$F$322/Inputs!$E$107*1000000000 -> 348.14268 | H14: =G14*(1+Inputs!H322) -> 360.32768 | I14: =H14*(1+Inputs!I322) -> 372.93914 | J14: =I14*(1+Inputs!J322) -> 385.99201 | K14: =J14*(1+Inputs!K322) -> 399.50174 | L14: =K14*(1+Inputs!L322) -> 413.4843 | M14: =L14*(1+Inputs!M322) -> 427.95625 | N14: =M14*(1+Inputs!N322) -> 442.93471 | O14: =N14*(1+Inputs!O322) -> 458.43743 | ... T14: =S14*(1+Inputs!T322) -> 544.47986
B15: Labour (variable) - unit cost | C15: IDR/t | D15: COGS per t | G15: =Inputs!$E$323*Inputs!$F$323/Inputs!$E$107*1000000000 -> 180.19111 | H15: =G15*(1+Inputs!H323) -> 186.4978 | I15: =H15*(1+Inputs!I323) -> 193.02522 | J15: =I15*(1+Inputs!J323) -> 199.7811 | K15: =J15*(1+Inputs!K323) -> 206.77344 | L15: =K15*(1+Inputs!L323) -> 214.01051 | M15: =L15*(1+Inputs!M323) -> 221.50088 | N15: =M15*(1+Inputs!N323) -> 229.25341 | O15: =N15*(1+Inputs!O323) -> 237.27728 | ... T15: =S15*(1+Inputs!T323) -> 281.81098
B16: Other operating expense - unit cost | C16: IDR/t | D16: COGS per t | G16: =Inputs!$E$324*Inputs!$F$324/Inputs!$E$107*1000000000 -> 66.750238 | H16: =G16*(1+Inputs!H324) -> 68.752745 | I16: =H16*(1+Inputs!I324) -> 70.815327 | J16: =I16*(1+Inputs!J324) -> 72.939787 | K16: =J16*(1+Inputs!K324) -> 75.127981 | L16: =K16*(1+Inputs!L324) -> 77.38182 | M16: =L16*(1+Inputs!M324) -> 79.703275 | N16: =M16*(1+Inputs!N324) -> 82.094373 | O16: =N16*(1+Inputs!O324) -> 84.557204 | ... T16: =S16*(1+Inputs!T324) -> 98.024975
B17: Legal & professional fees | C17: IDR bn | D17: Opex | G17: =Inputs!$E$325*Inputs!$F$325 -> 6.6470019 | H17: =G17*(1+Inputs!H325) -> 6.8464119 | I17: =H17*(1+Inputs!I325) -> 7.0518043 | J17: =I17*(1+Inputs!J325) -> 7.2633584 | K17: =J17*(1+Inputs!K325) -> 7.4812592 | L17: =K17*(1+Inputs!L325) -> 7.705697 | M17: =L17*(1+Inputs!M325) -> 7.9368679 | N17: =M17*(1+Inputs!N325) -> 8.1749739 | O17: =N17*(1+Inputs!O325) -> 8.4202231 | ... T17: =S17*(1+Inputs!T325) -> 9.7613464
B18: Staff costs - G&A (payroll) (growth = Inputs row + C13 x staff-row delta, Source Data 18) | C18: IDR bn | D18: Opex | G18: =Inputs!$E$326*Inputs!$F$326 -> 2.557285 | H18: =G18*(1+Inputs!H326+Inputs!$E$751*'Source Data'!H960) -> 2.6340036 | I18: =H18*(1+Inputs!I326+Inputs!$E$751*'Source Data'!I960) -> 2.7130237 | J18: =I18*(1+Inputs!J326+Inputs!$E$751*'Source Data'!J960) -> 2.7944144 | K18: =J18*(1+Inputs!K326+Inputs!$E$751*'Source Data'!K960) -> 2.8782468 | L18: =K18*(1+Inputs!L326+Inputs!$E$751*'Source Data'!L960) -> 2.9645942 | M18: =L18*(1+Inputs!M326+Inputs!$E$751*'Source Data'!M960) -> 3.0535321 | N18: =M18*(1+Inputs!N326+Inputs!$E$751*'Source Data'!N960) -> 3.145138 | O18: =N18*(1+Inputs!O326+Inputs!$E$751*'Source Data'!O960) -> 3.2394922 | ... T18: =S18*(1+Inputs!T326+Inputs!$E$751*'Source Data'!T960) -> 3.7554593
B19: Tax fees | C19: IDR bn | D19: Opex | G19: =Inputs!$E$327*Inputs!$F$327 -> 1.0491002 | H19: =G19*(1+Inputs!H327) -> 1.0805732 | I19: =H19*(1+Inputs!I327) -> 1.1129904 | J19: =I19*(1+Inputs!J327) -> 1.1463802 | K19: =J19*(1+Inputs!K327) -> 1.1807716 | L19: =K19*(1+Inputs!L327) -> 1.2161947 | M19: =L19*(1+Inputs!M327) -> 1.2526806 | N19: =M19*(1+Inputs!N327) -> 1.290261 | O19: =N19*(1+Inputs!O327) -> 1.3289688 | ... T19: =S19*(1+Inputs!T327) -> 1.5406391
B20: Travel & entertainment | C20: IDR bn | D20: Opex | G20: =Inputs!$E$328*Inputs!$F$328 -> 0.9944918 | H20: =G20*(1+Inputs!H328) -> 1.0243266 | I20: =H20*(1+Inputs!I328) -> 1.0550564 | J20: =I20*(1+Inputs!J328) -> 1.086708 | K20: =J20*(1+Inputs!K328) -> 1.1193093 | L20: =K20*(1+Inputs!L328) -> 1.1528886 | M20: =L20*(1+Inputs!M328) -> 1.1874752 | N20: =M20*(1+Inputs!N328) -> 1.2230995 | O20: =N20*(1+Inputs!O328) -> 1.2597925 | ... T20: =S20*(1+Inputs!T328) -> 1.4604447
B21: Office expenses | C21: IDR bn | D21: Opex | G21: =Inputs!$E$329*Inputs!$F$329 -> 0.78596338 | H21: =G21*(1+Inputs!H329) -> 0.80168264 | I21: =H21*(1+Inputs!I329) -> 0.8177163 | J21: =I21*(1+Inputs!J329) -> 0.83407062 | K21: =J21*(1+Inputs!K329) -> 0.85075204 | L21: =K21*(1+Inputs!L329) -> 0.86776708 | M21: =L21*(1+Inputs!M329) -> 0.88512242 | N21: =M21*(1+Inputs!N329) -> 0.90282487 | O21: =N21*(1+Inputs!O329) -> 0.92088136 | ... T21: =S21*(1+Inputs!T329) -> 1.0167274
B22: Other administrative | C22: IDR bn | D22: Opex | G22: =Inputs!$E$330*Inputs!$F$330 -> 0.65834446 | H22: =G22*(1+Inputs!H330) -> 0.6780948 | I22: =H22*(1+Inputs!I330) -> 0.69843764 | J22: =I22*(1+Inputs!J330) -> 0.71939077 | K22: =J22*(1+Inputs!K330) -> 0.74097249 | L22: =K22*(1+Inputs!L330) -> 0.76320167 | M22: =L22*(1+Inputs!M330) -> 0.78609772 | N22: =M22*(1+Inputs!N330) -> 0.80968065 | O22: =N22*(1+Inputs!O330) -> 0.83397107 | ... T22: =S22*(1+Inputs!T330) -> 0.96680104
B23: Rental - G&A | C23: IDR bn | D23: Opex | G23: =Inputs!$E$331*Inputs!$F$331 -> 0.27408379 | H23: =G23*(1+Inputs!H331) -> 0.27956546 | I23: =H23*(1+Inputs!I331) -> 0.28515677 | J23: =I23*(1+Inputs!J331) -> 0.29085991 | K23: =J23*(1+Inputs!K331) -> 0.29667711 | L23: =K23*(1+Inputs!L331) -> 0.30261065 | M23: =L23*(1+Inputs!M331) -> 0.30866286 | N23: =M23*(1+Inputs!N331) -> 0.31483612 | O23: =N23*(1+Inputs!O331) -> 0.32113284 | ... T23: =S23*(1+Inputs!T331) -> 0.35455661
B24: Depreciation - G&A | C24: IDR bn | D24: D&A | G24: =Inputs!$E$332*Inputs!$F$332 -> 0.2683397 | H24: =G24*(1+Inputs!H332) -> 0.27370649 | I24: =H24*(1+Inputs!I332) -> 0.27918062 | J24: =I24*(1+Inputs!J332) -> 0.28476424 | K24: =J24*(1+Inputs!K332) -> 0.29045952 | L24: =K24*(1+Inputs!L332) -> 0.29626871 | M24: =L24*(1+Inputs!M332) -> 0.30219409 | N24: =M24*(1+Inputs!N332) -> 0.30823797 | O24: =N24*(1+Inputs!O332) -> 0.31440273 | ... T24: =S24*(1+Inputs!T332) -> 0.34712601
B25: Communication | C25: IDR bn | D25: Opex | G25: =Inputs!$E$333*Inputs!$F$333 -> 0.22527943 | H25: =G25*(1+Inputs!H333) -> 0.22978501 | I25: =H25*(1+Inputs!I333) -> 0.23438071 | J25: =I25*(1+Inputs!J333) -> 0.23906833 | K25: =J25*(1+Inputs!K333) -> 0.2438497 | L25: =K25*(1+Inputs!L333) -> 0.24872669 | M25: =L25*(1+Inputs!M333) -> 0.25370122 | N25: =M25*(1+Inputs!N333) -> 0.25877525 | O25: =N25*(1+Inputs!O333) -> 0.26395075 | ... T25: =S25*(1+Inputs!T333) -> 0.29142296
B26: Security services | C26: IDR bn | D26: Opex | G26: =Inputs!$E$334*Inputs!$F$334 -> 0.21282385 | H26: =G26*(1+Inputs!H334) -> 0.21920857 | I26: =H26*(1+Inputs!I334) -> 0.22578483 | J26: =I26*(1+Inputs!J334) -> 0.23255837 | K26: =J26*(1+Inputs!K334) -> 0.23953512 | L26: =K26*(1+Inputs!L334) -> 0.24672118 | M26: =L26*(1+Inputs!M334) -> 0.25412281 | N26: =M26*(1+Inputs!N334) -> 0.2617465 | O26: =N26*(1+Inputs!O334) -> 0.26959889 | ... T26: =S26*(1+Inputs!T334) -> 0.31253901
B27: Donation & CSR | C27: IDR bn | D27: Opex | G27: =Inputs!$E$335*Inputs!$F$335 -> 0.1923315 | H27: =G27*(1+Inputs!H335) -> 0.19810144 | I27: =H27*(1+Inputs!I335) -> 0.20404449 | J27: =I27*(1+Inputs!J335) -> 0.21016582 | K27: =J27*(1+Inputs!K335) -> 0.2164708 | L27: =K27*(1+Inputs!L335) -> 0.22296492 | M27: =L27*(1+Inputs!M335) -> 0.22965387 | N27: =M27*(1+Inputs!N335) -> 0.23654348 | O27: =N27*(1+Inputs!O335) -> 0.24363979 | ... T27: =S27*(1+Inputs!T335) -> 0.28244529
B28: Utilities | C28: IDR bn | D28: Opex | G28: =Inputs!$E$336*Inputs!$F$336 -> 0.0021012075 | H28: =G28*(1+Inputs!H336) -> 0.0021432317 | I28: =H28*(1+Inputs!I336) -> 0.0021860963 | J28: =I28*(1+Inputs!J336) -> 0.0022298182 | K28: =J28*(1+Inputs!K336) -> 0.0022744146 | L28: =K28*(1+Inputs!L336) -> 0.0023199029 | M28: =L28*(1+Inputs!M336) -> 0.0023663009 | N28: =M28*(1+Inputs!N336) -> 0.0024136269 | O28: =N28*(1+Inputs!O336) -> 0.0024618995 | ... T28: =S28*(1+Inputs!T336) -> 0.002718136
B29: Memo: scheduled depreciation of existing assets (insurance base; Inputs 4) | C29: IDR bn | H29: =Inputs!H112 -> 41.467076 | I29: =Inputs!I112 -> 41.467076 | J29: =Inputs!J112 -> 42.467076 | K29: =Inputs!K112 -> 42.467076 | L29: =Inputs!L112 -> 42.467076 | M29: =Inputs!M112 -> 43.467076 | N29: =Inputs!N112 -> 43.467076 | O29: =Inputs!O112 -> 43.467076 | ... T29: =Inputs!T112 -> 44.467076
B30: Cost of sales - fixed lines (employees, security) x cost lever | C30: IDR bn | H30: =SUMIF($D$9:$D$28,"COGS fixed",H$9:H$28)*Inputs!$E$54 -> 15.484977 | I30: =SUMIF($D$9:$D$28,"COGS fixed",I$9:I$28)*Inputs!$E$54 -> 16.026951 | J30: =SUMIF($D$9:$D$28,"COGS fixed",J$9:J$28)*Inputs!$E$54 -> 16.587894 | K30: =SUMIF($D$9:$D$28,"COGS fixed",K$9:K$28)*Inputs!$E$54 -> 17.16847 | L30: =SUMIF($D$9:$D$28,"COGS fixed",L$9:L$28)*Inputs!$E$54 -> 17.769367 | M30: =SUMIF($D$9:$D$28,"COGS fixed",M$9:M$28)*Inputs!$E$54 -> 18.391295 | N30: =SUMIF($D$9:$D$28,"COGS fixed",N$9:N$28)*Inputs!$E$54 -> 19.03499 | O30: =SUMIF($D$9:$D$28,"COGS fixed",O$9:O$28)*Inputs!$E$54 -> 19.701215 | ... T30: =SUMIF($D$9:$D$28,"COGS fixed",T$9:T$28)*Inputs!$E$54 -> 23.398863
B31: Cost of sales - volume-driven (sum of unit costs x throughput / 1e9) x cost lever | C31: IDR bn | H31: =SUMIF($D$9:$D$28,"COGS per t",H$9:H$28)*'Revenue Calculation'!H38/1000000000*Inputs!$E$54 -> 13.565484 | I31: =SUMIF($D$9:$D$28,"COGS per t",I$9:I$28)*'Revenue Calculation'!I38/1000000000*Inputs!$E$54 -> 14.401947 | J31: =SUMIF($D$9:$D$28,"COGS per t",J$9:J$28)*'Revenue Calculation'!J38/1000000000*Inputs!$E$54 -> 15.290032 | K31: =SUMIF($D$9:$D$28,"COGS per t",K$9:K$28)*'Revenue Calculation'!K38/1000000000*Inputs!$E$54 -> 16.232929 | L31: =SUMIF($D$9:$D$28,"COGS per t",L$9:L$28)*'Revenue Calculation'!L38/1000000000*Inputs!$E$54 -> 17.234023 | M31: =SUMIF($D$9:$D$28,"COGS per t",M$9:M$28)*'Revenue Calculation'!M38/1000000000*Inputs!$E$54 -> 18.296909 | N31: =SUMIF($D$9:$D$28,"COGS per t",N$9:N$28)*'Revenue Calculation'!N38/1000000000*Inputs!$E$54 -> 19.425407 | O31: =SUMIF($D$9:$D$28,"COGS per t",O$9:O$28)*'Revenue Calculation'!O38/1000000000*Inputs!$E$54 -> 20.623568 | ... T31: =SUMIF($D$9:$D$28,"COGS per t",T$9:T$28)*'Revenue Calculation'!T38/1000000000*Inputs!$E$54 -> 27.819676
B32: Cost of sales - insurance (% of scheduled depreciation) | C32: IDR bn | H32: =Inputs!H410*H29*Inputs!$E$54 -> 0.88334427 | I32: =Inputs!I410*I29*Inputs!$E$54 -> 0.88334427 | J32: =Inputs!J410*J29*Inputs!$E$54 -> 0.90464657 | K32: =Inputs!K410*K29*Inputs!$E$54 -> 0.90464657 | L32: =Inputs!L410*L29*Inputs!$E$54 -> 0.90464657 | M32: =Inputs!M410*M29*Inputs!$E$54 -> 0.92594888 | N32: =Inputs!N410*N29*Inputs!$E$54 -> 0.92594888 | O32: =Inputs!O410*O29*Inputs!$E$54 -> 0.92594888 | ... T32: =Inputs!T410*T29*Inputs!$E$54 -> 0.94725118
B33: E1 Cost of sales | C33: IDR bn | H33: =H30+H31+H32 -> 29.933805 | I33: =I30+I31+I32 -> 31.312242 | J33: =J30+J31+J32 -> 32.782573 | K33: =K30+K31+K32 -> 34.306046 | L33: =L30+L31+L32 -> 35.908036 | M33: =M30+M31+M32 -> 37.614153 | N33: =N30+N31+N32 -> 39.386346 | O33: =O30+O31+O32 -> 41.250732 | ... T33: =T30+T31+T32 -> 52.16579
B34: E1 Operating expenses (G&A lines) x cost lever | C34: IDR bn | H34: =SUMIF($D$9:$D$28,"Opex",H$9:H$28)*Inputs!$E$54 -> 13.993896 | I34: =SUMIF($D$9:$D$28,"Opex",I$9:I$28)*Inputs!$E$54 -> 14.400582 | J34: =SUMIF($D$9:$D$28,"Opex",J$9:J$28)*Inputs!$E$54 -> 14.819205 | K34: =SUMIF($D$9:$D$28,"Opex",K$9:K$28)*Inputs!$E$54 -> 15.250119 | L34: =SUMIF($D$9:$D$28,"Opex",L$9:L$28)*Inputs!$E$54 -> 15.693687 | M34: =SUMIF($D$9:$D$28,"Opex",M$9:M$28)*Inputs!$E$54 -> 16.150283 | N34: =SUMIF($D$9:$D$28,"Opex",N$9:N$28)*Inputs!$E$54 -> 16.620293 | O34: =SUMIF($D$9:$D$28,"Opex",O$9:O$28)*Inputs!$E$54 -> 17.104113 | ... T34: =SUMIF($D$9:$D$28,"Opex",T$9:T$28)*Inputs!$E$54 -> 19.7451
B35: E1 EBITDA = revenue - cost of sales - operating expenses | C35: IDR bn | H35: ='Revenue Calculation'!H41-H33-H34 -> 112.5108 | I35: ='Revenue Calculation'!I41-I33-I34 -> 115.41884 | J35: ='Revenue Calculation'!J41-J33-J34 -> 118.36383 | K35: ='Revenue Calculation'!K41-K33-K34 -> 121.38841 | L35: ='Revenue Calculation'!L41-L33-L34 -> 124.47119 | M35: ='Revenue Calculation'!M41-M33-M34 -> 133.03132 | N35: ='Revenue Calculation'!N41-N33-N34 -> 136.39299 | O35: ='Revenue Calculation'!O41-O33-O34 -> 139.81677 | ... T35: ='Revenue Calculation'!T41-T33-T34 -> 164.71638
B36: Memo: G&A depreciation line (non-cash; in D&A) | C36: IDR bn | H36: =SUMIF($D$9:$D$28,"D&A",H$9:H$28) -> 0.27370649 | I36: =SUMIF($D$9:$D$28,"D&A",I$9:I$28) -> 0.27918062 | J36: =SUMIF($D$9:$D$28,"D&A",J$9:J$28) -> 0.28476424 | K36: =SUMIF($D$9:$D$28,"D&A",K$9:K$28) -> 0.29045952 | L36: =SUMIF($D$9:$D$28,"D&A",L$9:L$28) -> 0.29626871 | M36: =SUMIF($D$9:$D$28,"D&A",M$9:M$28) -> 0.30219409 | N36: =SUMIF($D$9:$D$28,"D&A",N$9:N$28) -> 0.30823797 | O36: =SUMIF($D$9:$D$28,"D&A",O$9:O$28) -> 0.31440273 | ... T36: =SUMIF($D$9:$D$28,"D&A",T$9:T$28) -> 0.34712601
B38: E2 Cigading existing (SGT 2) - the unit costs for electricity, R&M and solar / equipment rental also drive P01 / P02
B39: E2 cost lines (before the cost lever; 2023 column = FY2023 base x v29 uplift; each later year = prior year x (1 + that year's growth))
B40: Employee cost (payroll) | C40: IDR bn | D40: COGS fixed | G40: =Inputs!$E$339*Inputs!$F$339 -> 5.423 | H40: =G40*(1+Inputs!H339) -> 5.612805 | I40: =H40*(1+Inputs!I339) -> 5.8092532 | J40: =I40*(1+Inputs!J339) -> 6.012577 | K40: =J40*(1+Inputs!K339) -> 6.2230172 | L40: =K40*(1+Inputs!L339) -> 6.4408228 | M40: =L40*(1+Inputs!M339) -> 6.6662516 | N40: =M40*(1+Inputs!N339) -> 6.8995704 | O40: =N40*(1+Inputs!O339) -> 7.1410554 | ... T40: =S40*(1+Inputs!T339) -> 8.4813337
B41: Electricity - unit cost | C41: IDR/t | D41: COGS per t | G41: =Inputs!$E$340*Inputs!$F$340/Inputs!$E$116*1000000000 -> 1958.7254 | H41: =G41*(1+Inputs!H340) -> 2017.4871 | I41: =H41*(1+Inputs!I340) -> 2078.0117 | J41: =I41*(1+Inputs!J340) -> 2140.3521 | K41: =J41*(1+Inputs!K340) -> 2204.5627 | L41: =K41*(1+Inputs!L340) -> 2270.6995 | M41: =L41*(1+Inputs!M340) -> 2338.8205 | N41: =M41*(1+Inputs!N340) -> 2408.9851 | O41: =N41*(1+Inputs!O340) -> 2481.2547 | ... T41: =S41*(1+Inputs!T340) -> 2876.4542
B42: Security | C42: IDR bn | D42: COGS fixed | G42: =Inputs!$E$341*Inputs!$F$341 -> 2.1486997 | H42: =G42*(1+Inputs!H341) -> 2.2239042 | I42: =H42*(1+Inputs!I341) -> 2.3017409 | J42: =I42*(1+Inputs!J341) -> 2.3823018 | K42: =J42*(1+Inputs!K341) -> 2.4656824 | L42: =K42*(1+Inputs!L341) -> 2.5519812 | M42: =L42*(1+Inputs!M341) -> 2.6413006 | N42: =M42*(1+Inputs!N341) -> 2.7337461 | O42: =N42*(1+Inputs!O341) -> 2.8294272 | ... T42: =S42*(1+Inputs!T341) -> 3.360472
B43: Repair & maintenance - unit cost | C43: IDR/t | D43: COGS per t | G43: =Inputs!$E$342*Inputs!$F$342/Inputs!$E$116*1000000000 -> 699.28161 | H43: =G43*(1+Inputs!H342) -> 720.26006 | I43: =H43*(1+Inputs!I342) -> 741.86786 | J43: =I43*(1+Inputs!J342) -> 764.1239 | K43: =J43*(1+Inputs!K342) -> 787.04762 | L43: =K43*(1+Inputs!L342) -> 810.65904 | M43: =L43*(1+Inputs!M342) -> 834.97882 | N43: =M43*(1+Inputs!N342) -> 860.02818 | O43: =N43*(1+Inputs!O342) -> 885.82903 | ... T43: =S43*(1+Inputs!T342) -> 1026.9186
B44: Solar / heavy-equipment rental - unit cost | C44: IDR/t | D44: COGS per t | G44: =Inputs!$E$343*Inputs!$F$343/Inputs!$E$116*1000000000 -> 602.23322 | H44: =G44*(1+Inputs!H343) -> 620.30022 | I44: =H44*(1+Inputs!I343) -> 638.90923 | J44: =I44*(1+Inputs!J343) -> 658.0765 | K44: =J44*(1+Inputs!K343) -> 677.8188 | L44: =K44*(1+Inputs!L343) -> 698.15336 | M44: =L44*(1+Inputs!M343) -> 719.09796 | N44: =M44*(1+Inputs!N343) -> 740.6709 | O44: =N44*(1+Inputs!O343) -> 762.89103 | ... T44: =S44*(1+Inputs!T343) -> 884.39979
B45: Other operating expense - unit cost | C45: IDR/t | D45: COGS per t | G45: =Inputs!$E$344*Inputs!$F$344/Inputs!$E$116*1000000000 -> 331.60748 | H45: =G45*(1+Inputs!H344) -> 338.23963 | I45: =H45*(1+Inputs!I344) -> 345.00442 | J45: =I45*(1+Inputs!J344) -> 351.90451 | K45: =J45*(1+Inputs!K344) -> 358.9426 | L45: =K45*(1+Inputs!L344) -> 366.12145 | M45: =L45*(1+Inputs!M344) -> 373.44388 | N45: =M45*(1+Inputs!N344) -> 380.91276 | O45: =N45*(1+Inputs!O344) -> 388.53101 | ... T45: =S45*(1+Inputs!T344) -> 428.96963
B46: Employee overtime - unit cost | C46: IDR/t | D46: COGS per t | G46: =Inputs!$E$345*Inputs!$F$345/Inputs!$E$116*1000000000 -> 107.08021 | H46: =G46*(1+Inputs!H345) -> 110.82802 | I46: =H46*(1+Inputs!I345) -> 114.707 | J46: =I46*(1+Inputs!J345) -> 118.72175 | K46: =J46*(1+Inputs!K345) -> 122.87701 | L46: =K46*(1+Inputs!L345) -> 127.1777 | M46: =L46*(1+Inputs!M345) -> 131.62892 | N46: =M46*(1+Inputs!N345) -> 136.23593 | O46: =N46*(1+Inputs!O345) -> 141.00419 | ... T46: =S46*(1+Inputs!T345) -> 167.46875
B47: Labour (variable) - unit cost | C47: IDR/t | D47: COGS per t | G47: =Inputs!$E$346*Inputs!$F$346/Inputs!$E$116*1000000000 -> 35.500215 | H47: =G47*(1+Inputs!H346) -> 36.742722 | I47: =H47*(1+Inputs!I346) -> 38.028718 | J47: =I47*(1+Inputs!J346) -> 39.359723 | K47: =J47*(1+Inputs!K346) -> 40.737313 | L47: =K47*(1+Inputs!L346) -> 42.163119 | M47: =L47*(1+Inputs!M346) -> 43.638828 | N47: =M47*(1+Inputs!N346) -> 45.166187 | O47: =N47*(1+Inputs!O346) -> 46.747004 | ... T47: =S47*(1+Inputs!T346) -> 55.520776
B48: Pest control | C48: IDR bn | D48: COGS fixed | G48: =Inputs!$E$347*Inputs!$F$347 -> 0.0025 | H48: =G48*(1+Inputs!H347) -> 0.00255 | I48: =H48*(1+Inputs!I347) -> 0.002601 | J48: =I48*(1+Inputs!J347) -> 0.00265302 | K48: =J48*(1+Inputs!K347) -> 0.0027060804 | L48: =K48*(1+Inputs!L347) -> 0.002760202 | M48: =L48*(1+Inputs!M347) -> 0.002815406 | N48: =M48*(1+Inputs!N347) -> 0.0028717142 | O48: =N48*(1+Inputs!O347) -> 0.0029291485 | ... T48: =S48*(1+Inputs!T347) -> 0.0032340166
B49: Staff costs - G&A (payroll) | C49: IDR bn | D49: Opex | G49: =Inputs!$E$348*Inputs!$F$348 -> 4.2735 | H49: =G49*(1+Inputs!H348) -> 4.4230725 | I49: =H49*(1+Inputs!I348) -> 4.57788 | J49: =I49*(1+Inputs!J348) -> 4.7381058 | K49: =J49*(1+Inputs!K348) -> 4.9039395 | L49: =K49*(1+Inputs!L348) -> 5.0755774 | M49: =L49*(1+Inputs!M348) -> 5.2532226 | N49: =M49*(1+Inputs!N348) -> 5.4370854 | O49: =N49*(1+Inputs!O348) -> 5.6273834 | ... T49: =S49*(1+Inputs!T348) -> 6.6835662
B50: Legal & professional fees | C50: IDR bn | D50: Opex | G50: =Inputs!$E$349*Inputs!$F$349 -> 3.0775133 | H50: =G50*(1+Inputs!H349) -> 3.1698387 | I50: =H50*(1+Inputs!I349) -> 3.2649339 | J50: =I50*(1+Inputs!J349) -> 3.3628819 | K50: =J50*(1+Inputs!K349) -> 3.4637684 | L50: =K50*(1+Inputs!L349) -> 3.5676814 | M50: =L50*(1+Inputs!M349) -> 3.6747119 | N50: =M50*(1+Inputs!N349) -> 3.7849532 | O50: =N50*(1+Inputs!O349) -> 3.8985018 | ... T50: =S50*(1+Inputs!T349) -> 4.5194321
B51: Security services | C51: IDR bn | D51: Opex | G51: =Inputs!$E$350*Inputs!$F$350 -> 0.43463408 | H51: =G51*(1+Inputs!H350) -> 0.4476731 | I51: =H51*(1+Inputs!I350) -> 0.4611033 | J51: =I51*(1+Inputs!J350) -> 0.4749364 | K51: =J51*(1+Inputs!K350) -> 0.48918449 | L51: =K51*(1+Inputs!L350) -> 0.50386002 | M51: =L51*(1+Inputs!M350) -> 0.51897582 | N51: =M51*(1+Inputs!N350) -> 0.5345451 | O51: =N51*(1+Inputs!O350) -> 0.55058145 | ... T51: =S51*(1+Inputs!T350) -> 0.6382748
B52: Other administrative | C52: IDR bn | D52: Opex | G52: =Inputs!$E$351*Inputs!$F$351 -> 0.38632713 | H52: =G52*(1+Inputs!H351) -> 0.39791694 | I52: =H52*(1+Inputs!I351) -> 0.40985445 | J52: =I52*(1+Inputs!J351) -> 0.42215009 | K52: =J52*(1+Inputs!K351) -> 0.43481459 | L52: =K52*(1+Inputs!L351) -> 0.44785903 | M52: =L52*(1+Inputs!M351) -> 0.4612948 | N52: =M52*(1+Inputs!N351) -> 0.47513364 | O52: =N52*(1+Inputs!O351) -> 0.48938765 | ... T52: =S52*(1+Inputs!T351) -> 0.56733441
B53: Tax fees | C53: IDR bn | D53: Opex | G53: =Inputs!$E$352*Inputs!$F$352 -> 0.35 | H53: =G53*(1+Inputs!H352) -> 0.3605 | I53: =H53*(1+Inputs!I352) -> 0.371315 | J53: =I53*(1+Inputs!J352) -> 0.38245445 | K53: =J53*(1+Inputs!K352) -> 0.39392808 | L53: =K53*(1+Inputs!L352) -> 0.40574593 | M53: =L53*(1+Inputs!M352) -> 0.4179183 | N53: =M53*(1+Inputs!N352) -> 0.43045585 | O53: =N53*(1+Inputs!O352) -> 0.44336953 | ... T53: =S53*(1+Inputs!T352) -> 0.5139868
B54: Travel & entertainment | C54: IDR bn | D54: Opex | G54: =Inputs!$E$353*Inputs!$F$353 -> 0.24578809 | H54: =G54*(1+Inputs!H353) -> 0.25316173 | I54: =H54*(1+Inputs!I353) -> 0.26075658 | J54: =I54*(1+Inputs!J353) -> 0.26857928 | K54: =J54*(1+Inputs!K353) -> 0.27663666 | L54: =K54*(1+Inputs!L353) -> 0.28493576 | M54: =L54*(1+Inputs!M353) -> 0.29348383 | N54: =M54*(1+Inputs!N353) -> 0.30228835 | O54: =N54*(1+Inputs!O353) -> 0.311357 | ... T54: =S54*(1+Inputs!T353) -> 0.3609481
B55: Depreciation - G&A | C55: IDR bn | D55: D&A | G55: =Inputs!$E$354*Inputs!$F$354 -> 0.12710661 | H55: =G55*(1+Inputs!H354) -> 0.12964875 | I55: =H55*(1+Inputs!I354) -> 0.13224172 | J55: =I55*(1+Inputs!J354) -> 0.13488655 | K55: =J55*(1+Inputs!K354) -> 0.13758429 | L55: =K55*(1+Inputs!L354) -> 0.14033597 | M55: =L55*(1+Inputs!M354) -> 0.14314269 | N55: =M55*(1+Inputs!N354) -> 0.14600554 | O55: =N55*(1+Inputs!O354) -> 0.14892566 | ... T55: =S55*(1+Inputs!T354) -> 0.16442596
B56: Donation & CSR | C56: IDR bn | D56: Opex | G56: =Inputs!$E$355*Inputs!$F$355 -> 0.0474447 | H56: =G56*(1+Inputs!H355) -> 0.048868041 | I56: =H56*(1+Inputs!I355) -> 0.050334082 | J56: =I56*(1+Inputs!J355) -> 0.051844105 | K56: =J56*(1+Inputs!K355) -> 0.053399428 | L56: =K56*(1+Inputs!L355) -> 0.055001411 | M56: =L56*(1+Inputs!M355) -> 0.056651453 | N56: =M56*(1+Inputs!N355) -> 0.058350997 | O56: =N56*(1+Inputs!O355) -> 0.060101526 | ... T56: =S56*(1+Inputs!T355) -> 0.069674141
B57: Office expenses | C57: IDR bn | D57: Opex | G57: =Inputs!$E$356*Inputs!$F$356 -> 0.020640442 | H57: =G57*(1+Inputs!H356) -> 0.021053251 | I57: =H57*(1+Inputs!I356) -> 0.021474316 | J57: =I57*(1+Inputs!J356) -> 0.021903802 | K57: =J57*(1+Inputs!K356) -> 0.022341878 | L57: =K57*(1+Inputs!L356) -> 0.022788716 | M57: =L57*(1+Inputs!M356) -> 0.02324449 | N57: =M57*(1+Inputs!N356) -> 0.02370938 | O57: =N57*(1+Inputs!O356) -> 0.024183567 | ... T57: =S57*(1+Inputs!T356) -> 0.026700613
B58: Communication | C58: IDR bn | D58: Opex | G58: =Inputs!$E$357*Inputs!$F$357 -> 0.017084204 | H58: =G58*(1+Inputs!H357) -> 0.017425888 | I58: =H58*(1+Inputs!I357) -> 0.017774406 | J58: =I58*(1+Inputs!J357) -> 0.018129894 | K58: =J58*(1+Inputs!K357) -> 0.018492492 | L58: =K58*(1+Inputs!L357) -> 0.018862342 | M58: =L58*(1+Inputs!M357) -> 0.019239589 | N58: =M58*(1+Inputs!N357) -> 0.01962438 | O58: =N58*(1+Inputs!O357) -> 0.020016868 | ... T58: =S58*(1+Inputs!T357) -> 0.02210024
B59: Rental - G&A | C59: IDR bn | D59: Opex | G59: =Inputs!$E$358*Inputs!$F$358 -> 0.0129 | H59: =G59*(1+Inputs!H358) -> 0.013158 | I59: =H59*(1+Inputs!I358) -> 0.01342116 | J59: =I59*(1+Inputs!J358) -> 0.013689583 | K59: =J59*(1+Inputs!K358) -> 0.013963375 | L59: =K59*(1+Inputs!L358) -> 0.014242642 | M59: =L59*(1+Inputs!M358) -> 0.014527495 | N59: =M59*(1+Inputs!N358) -> 0.014818045 | O59: =N59*(1+Inputs!O358) -> 0.015114406 | ... T59: =S59*(1+Inputs!T358) -> 0.016687526
B60: Memo: scheduled depreciation of existing assets (insurance base; Inputs 4) | C60: IDR bn | H60: =Inputs!H119 -> 40.829177 | I60: =Inputs!I119 -> 40.829177 | J60: =Inputs!J119 -> 41.829177 | K60: =Inputs!K119 -> 41.829177 | L60: =Inputs!L119 -> 41.829177 | M60: =Inputs!M119 -> 42.829177 | N60: =Inputs!N119 -> 42.829177 | O60: =Inputs!O119 -> 42.829177 | ... T60: =Inputs!T119 -> 43.829177
B61: Cost of sales - fixed lines x cost lever | C61: IDR bn | H61: =SUMIF($D$40:$D$59,"COGS fixed",H$40:H$59)*Inputs!$E$54 -> 7.8392592 | I61: =SUMIF($D$40:$D$59,"COGS fixed",I$40:I$59)*Inputs!$E$54 -> 8.113595 | J61: =SUMIF($D$40:$D$59,"COGS fixed",J$40:J$59)*Inputs!$E$54 -> 8.3975319 | K61: =SUMIF($D$40:$D$59,"COGS fixed",K$40:K$59)*Inputs!$E$54 -> 8.6914057 | L61: =SUMIF($D$40:$D$59,"COGS fixed",L$40:L$59)*Inputs!$E$54 -> 8.9955643 | M61: =SUMIF($D$40:$D$59,"COGS fixed",M$40:M$59)*Inputs!$E$54 -> 9.3103676 | N61: =SUMIF($D$40:$D$59,"COGS fixed",N$40:N$59)*Inputs!$E$54 -> 9.6361883 | O61: =SUMIF($D$40:$D$59,"COGS fixed",O$40:O$59)*Inputs!$E$54 -> 9.9734118 | ... T61: =SUMIF($D$40:$D$59,"COGS fixed",T$40:T$59)*Inputs!$E$54 -> 11.84504
B62: Cost of sales - volume-driven (unit costs x throughput / 1e9) x cost lever | C62: IDR bn | H62: =SUMIF($D$40:$D$59,"COGS per t",H$40:H$59)*'Revenue Calculation'!H45/1000000000*Inputs!$E$54 -> 4.2282436 | I62: =SUMIF($D$40:$D$59,"COGS per t",I$40:I$59)*'Revenue Calculation'!I45/1000000000*Inputs!$E$54 -> 4.4827473 | J62: =SUMIF($D$40:$D$59,"COGS per t",J$40:J$59)*'Revenue Calculation'!J45/1000000000*Inputs!$E$54 -> 4.7526117 | K62: =SUMIF($D$40:$D$59,"COGS per t",K$40:K$59)*'Revenue Calculation'!K45/1000000000*Inputs!$E$54 -> 5.0387659 | L62: =SUMIF($D$40:$D$59,"COGS per t",L$40:L$59)*'Revenue Calculation'!L45/1000000000*Inputs!$E$54 -> 5.3421956 | M62: =SUMIF($D$40:$D$59,"COGS per t",M$40:M$59)*'Revenue Calculation'!M45/1000000000*Inputs!$E$54 -> 5.6639463 | N62: =SUMIF($D$40:$D$59,"COGS per t",N$40:N$59)*'Revenue Calculation'!N45/1000000000*Inputs!$E$54 -> 6.0051266 | O62: =SUMIF($D$40:$D$59,"COGS per t",O$40:O$59)*'Revenue Calculation'!O45/1000000000*Inputs!$E$54 -> 6.3669127 | ... T62: =SUMIF($D$40:$D$59,"COGS per t",T$40:T$59)*'Revenue Calculation'!T45/1000000000*Inputs!$E$54 -> 8.5313325
B63: Cost of sales - insurance (% of scheduled depreciation) | C63: IDR bn | H63: =Inputs!H411*H60*Inputs!$E$54 -> 1.3542028 | I63: =Inputs!I411*I60*Inputs!$E$54 -> 1.3542028 | J63: =Inputs!J411*J60*Inputs!$E$54 -> 1.3873703 | K63: =Inputs!K411*K60*Inputs!$E$54 -> 1.3873703 | L63: =Inputs!L411*L60*Inputs!$E$54 -> 1.3873703 | M63: =Inputs!M411*M60*Inputs!$E$54 -> 1.4205378 | N63: =Inputs!N411*N60*Inputs!$E$54 -> 1.4205378 | O63: =Inputs!O411*O60*Inputs!$E$54 -> 1.4205378 | ... T63: =Inputs!T411*T60*Inputs!$E$54 -> 1.4537053
B64: E2 Cost of sales | C64: IDR bn | H64: =H61+H62+H63 -> 13.421706 | I64: =I61+I62+I63 -> 13.950545 | J64: =J61+J62+J63 -> 14.537514 | K64: =K61+K62+K63 -> 15.117542 | L64: =L61+L62+L63 -> 15.72513 | M64: =M61+M62+M63 -> 16.394852 | N64: =N61+N62+N63 -> 17.061853 | O64: =O61+O62+O63 -> 17.760862 | ... T64: =T61+T62+T63 -> 21.830078
B65: E2 Operating expenses (G&A lines) x cost lever | C65: IDR bn | H65: =SUMIF($D$40:$D$59,"Opex",H$40:H$59)*Inputs!$E$54 -> 9.1526682 | I65: =SUMIF($D$40:$D$59,"Opex",I$40:I$59)*Inputs!$E$54 -> 9.4488472 | J65: =SUMIF($D$40:$D$59,"Opex",J$40:J$59)*Inputs!$E$54 -> 9.7546753 | K65: =SUMIF($D$40:$D$59,"Opex",K$40:K$59)*Inputs!$E$54 -> 10.070469 | L65: =SUMIF($D$40:$D$59,"Opex",L$40:L$59)*Inputs!$E$54 -> 10.396555 | M65: =SUMIF($D$40:$D$59,"Opex",M$40:M$59)*Inputs!$E$54 -> 10.73327 | N65: =SUMIF($D$40:$D$59,"Opex",N$40:N$59)*Inputs!$E$54 -> 11.080964 | O65: =SUMIF($D$40:$D$59,"Opex",O$40:O$59)*Inputs!$E$54 -> 11.439997 | ... T65: =SUMIF($D$40:$D$59,"Opex",T$40:T$59)*Inputs!$E$54 -> 13.418705
B66: E2 EBITDA | C66: IDR bn | H66: ='Revenue Calculation'!H47-H64-H65 -> 16.083586 | I66: ='Revenue Calculation'!I47-I64-I65 -> 22.99016 | J66: ='Revenue Calculation'!J47-J64-J65 -> 23.489049 | K66: ='Revenue Calculation'!K47-K64-K65 -> 33.8696 | L66: ='Revenue Calculation'!L47-L64-L65 -> 34.707654 | M66: ='Revenue Calculation'!M47-M64-M65 -> 41.791519 | N66: ='Revenue Calculation'!N47-N64-N65 -> 42.844413 | O66: ='Revenue Calculation'!O47-O64-O65 -> 48.302999 | ... T66: ='Revenue Calculation'!T47-T64-T65 -> 59.990324
B67: Memo: G&A depreciation line (non-cash; in D&A) | C67: IDR bn | H67: =SUMIF($D$40:$D$59,"D&A",H$40:H$59) -> 0.12964875 | I67: =SUMIF($D$40:$D$59,"D&A",I$40:I$59) -> 0.13224172 | J67: =SUMIF($D$40:$D$59,"D&A",J$40:J$59) -> 0.13488655 | K67: =SUMIF($D$40:$D$59,"D&A",K$40:K$59) -> 0.13758429 | L67: =SUMIF($D$40:$D$59,"D&A",L$40:L$59) -> 0.14033597 | M67: =SUMIF($D$40:$D$59,"D&A",M$40:M$59) -> 0.14314269 | N67: =SUMIF($D$40:$D$59,"D&A",N$40:N$59) -> 0.14600554 | O67: =SUMIF($D$40:$D$59,"D&A",O$40:O$59) -> 0.14892566 | ... T67: =SUMIF($D$40:$D$59,"D&A",T$40:T$59) -> 0.16442596
B69: E3 Belawan existing - per-ton lines are shared with the P07 expansion volume
B70: E3 cost lines (before the cost lever; 2023 column = FY2023 base x v29 uplift; each later year = prior year x (1 + that year's growth))
B71: Employee cost (payroll) | C71: IDR bn | D71: COGS fixed | G71: =Inputs!$E$361*Inputs!$F$361 -> 3.2796205 | H71: =G71*(1+Inputs!H361) -> 3.3944072 | I71: =H71*(1+Inputs!I361) -> 3.5132115 | J71: =I71*(1+Inputs!J361) -> 3.6361739 | K71: =J71*(1+Inputs!K361) -> 3.76344 | L71: =K71*(1+Inputs!L361) -> 3.8951604 | M71: =L71*(1+Inputs!M361) -> 4.031491 | N71: =M71*(1+Inputs!N361) -> 4.1725932 | O71: =N71*(1+Inputs!O361) -> 4.3186339 | ... T71: =S71*(1+Inputs!T361) -> 5.1291824
B72: Security | C72: IDR bn | D72: COGS fixed | G72: =Inputs!$E$362*Inputs!$F$362 -> 1.9301774 | H72: =G72*(1+Inputs!H362) -> 1.9977336 | I72: =H72*(1+Inputs!I362) -> 2.0676543 | J72: =I72*(1+Inputs!J362) -> 2.1400222 | K72: =J72*(1+Inputs!K362) -> 2.214923 | L72: =K72*(1+Inputs!L362) -> 2.2924453 | M72: =L72*(1+Inputs!M362) -> 2.3726809 | N72: =M72*(1+Inputs!N362) -> 2.4557247 | O72: =N72*(1+Inputs!O362) -> 2.5416751 | ... T72: =S72*(1+Inputs!T362) -> 3.0187127
B73: Fuel - unit cost | C73: IDR/t | D73: COGS per t | G73: =Inputs!$E$363*Inputs!$F$363/Inputs!$E$123*1000000000 -> 894.79011 | H73: =G73*(1+Inputs!H363) -> 921.63382 | I73: =H73*(1+Inputs!I363) -> 949.28283 | J73: =I73*(1+Inputs!J363) -> 977.76132 | K73: =J73*(1+Inputs!K363) -> 1007.0942 | L73: =K73*(1+Inputs!L363) -> 1037.307 | M73: =L73*(1+Inputs!M363) -> 1068.4262 | N73: =M73*(1+Inputs!N363) -> 1100.479 | O73: =N73*(1+Inputs!O363) -> 1133.4933 | ... T73: =S73*(1+Inputs!T363) -> 1314.0295
B74: Utilities - unit cost | C74: IDR/t | D74: COGS per t | G74: =Inputs!$E$364*Inputs!$F$364/Inputs!$E$123*1000000000 -> 683.82504 | H74: =G74*(1+Inputs!H364) -> 704.33979 | I74: =H74*(1+Inputs!I364) -> 725.46999 | J74: =I74*(1+Inputs!J364) -> 747.23409 | K74: =J74*(1+Inputs!K364) -> 769.65111 | L74: =K74*(1+Inputs!L364) -> 792.74064 | M74: =L74*(1+Inputs!M364) -> 816.52286 | N74: =M74*(1+Inputs!N364) -> 841.01855 | O74: =N74*(1+Inputs!O364) -> 866.24911 | ... T74: =S74*(1+Inputs!T364) -> 1004.2201
B75: Other operating expense - unit cost | C75: IDR/t | D75: COGS per t | G75: =Inputs!$E$365*Inputs!$F$365/Inputs!$E$123*1000000000 -> 446.81154 | H75: =G75*(1+Inputs!H365) -> 460.21589 | I75: =H75*(1+Inputs!I365) -> 474.02237 | J75: =I75*(1+Inputs!J365) -> 488.24304 | K75: =J75*(1+Inputs!K365) -> 502.89033 | L75: =K75*(1+Inputs!L365) -> 517.97704 | M75: =L75*(1+Inputs!M365) -> 533.51635 | N75: =M75*(1+Inputs!N365) -> 549.52184 | O75: =N75*(1+Inputs!O365) -> 566.0075 | ... T75: =S75*(1+Inputs!T365) -> 656.15782
B76: Repair & maintenance - unit cost | C76: IDR/t | D76: COGS per t | G76: =Inputs!$E$366*Inputs!$F$366/Inputs!$E$123*1000000000 -> 310.56291 | H76: =G76*(1+Inputs!H366) -> 319.8798 | I76: =H76*(1+Inputs!I366) -> 329.47619 | J76: =I76*(1+Inputs!J366) -> 339.36048 | K76: =J76*(1+Inputs!K366) -> 349.54129 | L76: =K76*(1+Inputs!L366) -> 360.02753 | M76: =L76*(1+Inputs!M366) -> 370.82836 | N76: =M76*(1+Inputs!N366) -> 381.95321 | O76: =N76*(1+Inputs!O366) -> 393.4118 | ... T76: =S76*(1+Inputs!T366) -> 456.0721
B77: Employee overtime - unit cost | C77: IDR/t | D77: COGS per t | G77: =Inputs!$E$367*Inputs!$F$367/Inputs!$E$123*1000000000 -> 265.96008 | H77: =G77*(1+Inputs!H367) -> 275.26869 | I77: =H77*(1+Inputs!I367) -> 284.90309 | J77: =I77*(1+Inputs!J367) -> 294.8747 | K77: =J77*(1+Inputs!K367) -> 305.19531 | L77: =K77*(1+Inputs!L367) -> 315.87715 | M77: =L77*(1+Inputs!M367) -> 326.93285 | N77: =M77*(1+Inputs!N367) -> 338.3755 | O77: =N77*(1+Inputs!O367) -> 350.21864 | ... T77: =S77*(1+Inputs!T367) -> 415.94988
B78: Labour (variable) - unit cost | C78: IDR/t | D78: COGS per t | G78: =Inputs!$E$368*Inputs!$F$368/Inputs!$E$123*1000000000 -> 12.570683 | H78: =G78*(1+Inputs!H368) -> 13.010657 | I78: =H78*(1+Inputs!I368) -> 13.46603 | J78: =I78*(1+Inputs!J368) -> 13.937341 | K78: =J78*(1+Inputs!K368) -> 14.425148 | L78: =K78*(1+Inputs!L368) -> 14.930028 | M78: =L78*(1+Inputs!M368) -> 15.452579 | N78: =M78*(1+Inputs!N368) -> 15.993419 | O78: =N78*(1+Inputs!O368) -> 16.553189 | ... T78: =S78*(1+Inputs!T368) -> 19.659996
B79: Legal & professional fees | C79: IDR bn | D79: Opex | G79: =Inputs!$E$369*Inputs!$F$369 -> 1.702367 | H79: =G79*(1+Inputs!H369) -> 1.753438 | I79: =H79*(1+Inputs!I369) -> 1.8060412 | J79: =I79*(1+Inputs!J369) -> 1.8602224 | K79: =J79*(1+Inputs!K369) -> 1.9160291 | L79: =K79*(1+Inputs!L369) -> 1.9735099 | M79: =L79*(1+Inputs!M369) -> 2.0327152 | N79: =M79*(1+Inputs!N369) -> 2.0936967 | O79: =N79*(1+Inputs!O369) -> 2.1565076 | ... T79: =S79*(1+Inputs!T369) -> 2.4999833
B80: Office expenses | C80: IDR bn | D80: Opex | G80: =Inputs!$E$370*Inputs!$F$370 -> 0.25867063 | H80: =G80*(1+Inputs!H370) -> 0.26384405 | I80: =H80*(1+Inputs!I370) -> 0.26912093 | J80: =I80*(1+Inputs!J370) -> 0.27450335 | K80: =J80*(1+Inputs!K370) -> 0.27999341 | L80: =K80*(1+Inputs!L370) -> 0.28559328 | M80: =L80*(1+Inputs!M370) -> 0.29130515 | N80: =M80*(1+Inputs!N370) -> 0.29713125 | O80: =N80*(1+Inputs!O370) -> 0.30307387 | ... T80: =S80*(1+Inputs!T370) -> 0.33461805
B81: Travel & entertainment | C81: IDR bn | D81: Opex | G81: =Inputs!$E$371*Inputs!$F$371 -> 0.23960182 | H81: =G81*(1+Inputs!H371) -> 0.24678988 | I81: =H81*(1+Inputs!I371) -> 0.25419357 | J81: =I81*(1+Inputs!J371) -> 0.26181938 | K81: =J81*(1+Inputs!K371) -> 0.26967396 | L81: =K81*(1+Inputs!L371) -> 0.27776418 | M81: =L81*(1+Inputs!M371) -> 0.28609711 | N81: =M81*(1+Inputs!N371) -> 0.29468002 | O81: =N81*(1+Inputs!O371) -> 0.30352042 | ... T81: =S81*(1+Inputs!T371) -> 0.35186335
B82: Donation & CSR | C82: IDR bn | D82: Opex | G82: =Inputs!$E$372*Inputs!$F$372 -> 0.17580519 | H82: =G82*(1+Inputs!H372) -> 0.18107934 | I82: =H82*(1+Inputs!I372) -> 0.18651172 | J82: =I82*(1+Inputs!J372) -> 0.19210708 | K82: =J82*(1+Inputs!K372) -> 0.19787029 | L82: =K82*(1+Inputs!L372) -> 0.2038064 | M82: =L82*(1+Inputs!M372) -> 0.20992059 | N82: =M82*(1+Inputs!N372) -> 0.21621821 | O82: =N82*(1+Inputs!O372) -> 0.22270475 | ... T82: =S82*(1+Inputs!T372) -> 0.25817585
B83: Rental - G&A | C83: IDR bn | D83: Opex | G83: =Inputs!$E$373*Inputs!$F$373 -> 0.14777611 | H83: =G83*(1+Inputs!H373) -> 0.15073164 | I83: =H83*(1+Inputs!I373) -> 0.15374627 | J83: =I83*(1+Inputs!J373) -> 0.15682119 | K83: =J83*(1+Inputs!K373) -> 0.15995762 | L83: =K83*(1+Inputs!L373) -> 0.16315677 | M83: =L83*(1+Inputs!M373) -> 0.16641991 | N83: =M83*(1+Inputs!N373) -> 0.1697483 | O83: =N83*(1+Inputs!O373) -> 0.17314327 | ... T83: =S83*(1+Inputs!T373) -> 0.19116416
B84: Communication | C84: IDR bn | D84: Opex | G84: =Inputs!$E$374*Inputs!$F$374 -> 0.14639246 | H84: =G84*(1+Inputs!H374) -> 0.1493203 | I84: =H84*(1+Inputs!I374) -> 0.15230671 | J84: =I84*(1+Inputs!J374) -> 0.15535284 | K84: =J84*(1+Inputs!K374) -> 0.1584599 | L84: =K84*(1+Inputs!L374) -> 0.1616291 | M84: =L84*(1+Inputs!M374) -> 0.16486168 | N84: =M84*(1+Inputs!N374) -> 0.16815891 | O84: =N84*(1+Inputs!O374) -> 0.17152209 | ... T84: =S84*(1+Inputs!T374) -> 0.18937425
B85: Staff costs - G&A (payroll) | C85: IDR bn | D85: Opex | G85: =Inputs!$E$375*Inputs!$F$375 -> 0.14099321 | H85: =G85*(1+Inputs!H375) -> 0.14592798 | I85: =H85*(1+Inputs!I375) -> 0.15103545 | J85: =I85*(1+Inputs!J375) -> 0.1563217 | K85: =J85*(1+Inputs!K375) -> 0.16179295 | L85: =K85*(1+Inputs!L375) -> 0.16745571 | M85: =L85*(1+Inputs!M375) -> 0.17331666 | N85: =M85*(1+Inputs!N375) -> 0.17938274 | O85: =N85*(1+Inputs!O375) -> 0.18566114 | ... T85: =S85*(1+Inputs!T375) -> 0.22050719
B86: Security services | C86: IDR bn | D86: Opex | G86: =Inputs!$E$376*Inputs!$F$376 -> 0.13922671 | H86: =G86*(1+Inputs!H376) -> 0.14340351 | I86: =H86*(1+Inputs!I376) -> 0.14770562 | J86: =I86*(1+Inputs!J376) -> 0.15213679 | K86: =J86*(1+Inputs!K376) -> 0.15670089 | L86: =K86*(1+Inputs!L376) -> 0.16140192 | M86: =L86*(1+Inputs!M376) -> 0.16624397 | N86: =M86*(1+Inputs!N376) -> 0.17123129 | O86: =N86*(1+Inputs!O376) -> 0.17636823 | ... T86: =S86*(1+Inputs!T376) -> 0.20445912
B87: Audit fees | C87: IDR bn | D87: Opex | G87: =Inputs!$E$377*Inputs!$F$377 -> 0.036134992 | H87: =G87*(1+Inputs!H377) -> 0.037219042 | I87: =H87*(1+Inputs!I377) -> 0.038335613 | J87: =I87*(1+Inputs!J377) -> 0.039485681 | K87: =J87*(1+Inputs!K377) -> 0.040670252 | L87: =K87*(1+Inputs!L377) -> 0.041890359 | M87: =L87*(1+Inputs!M377) -> 0.04314707 | N87: =M87*(1+Inputs!N377) -> 0.044441482 | O87: =N87*(1+Inputs!O377) -> 0.045774727 | ... T87: =S87*(1+Inputs!T377) -> 0.053065454
B88: Unit cost - sum of volume-driven lines (before the cost lever) | C88: IDR/t | H88: =SUMIF($D$71:$D$87,"COGS per t",H$71:H$87) -> 2694.3486 | I88: =SUMIF($D$71:$D$87,"COGS per t",I$71:I$87) -> 2776.6205 | J88: =SUMIF($D$71:$D$87,"COGS per t",J$71:J$87) -> 2861.411 | K88: =SUMIF($D$71:$D$87,"COGS per t",K$71:K$87) -> 2948.7974 | L88: =SUMIF($D$71:$D$87,"COGS per t",L$71:L$87) -> 3038.8594 | M88: =SUMIF($D$71:$D$87,"COGS per t",M$71:M$87) -> 3131.6792 | N88: =SUMIF($D$71:$D$87,"COGS per t",N$71:N$87) -> 3227.3415 | O88: =SUMIF($D$71:$D$87,"COGS per t",O$71:O$87) -> 3325.9336 | ... T88: =SUMIF($D$71:$D$87,"COGS per t",T$71:T$87) -> 3866.0894
B89: Cost of sales - fixed lines x cost lever | C89: IDR bn | H89: =SUMIF($D$71:$D$87,"COGS fixed",H$71:H$87)*Inputs!$E$54 -> 5.3921409 | I89: =SUMIF($D$71:$D$87,"COGS fixed",I$71:I$87)*Inputs!$E$54 -> 5.5808658 | J89: =SUMIF($D$71:$D$87,"COGS fixed",J$71:J$87)*Inputs!$E$54 -> 5.7761961 | K89: =SUMIF($D$71:$D$87,"COGS fixed",K$71:K$87)*Inputs!$E$54 -> 5.978363 | L89: =SUMIF($D$71:$D$87,"COGS fixed",L$71:L$87)*Inputs!$E$54 -> 6.1876057 | M89: =SUMIF($D$71:$D$87,"COGS fixed",M$71:M$87)*Inputs!$E$54 -> 6.4041719 | N89: =SUMIF($D$71:$D$87,"COGS fixed",N$71:N$87)*Inputs!$E$54 -> 6.6283179 | O89: =SUMIF($D$71:$D$87,"COGS fixed",O$71:O$87)*Inputs!$E$54 -> 6.860309 | ... T89: =SUMIF($D$71:$D$87,"COGS fixed",T$71:T$87)*Inputs!$E$54 -> 8.1478951
B90: Cost of sales - volume-driven (unit cost x existing throughput / 1e9) x cost lever | C90: IDR bn | H90: =H88*'Revenue Calculation'!H51/1000000000*Inputs!$E$54 -> 2.0207615 | I90: =I88*'Revenue Calculation'!I51/1000000000*Inputs!$E$54 -> 2.1449393 | J90: =J88*'Revenue Calculation'!J51/1000000000*Inputs!$E$54 -> 2.2767532 | K90: =K88*'Revenue Calculation'!K51/1000000000*Inputs!$E$54 -> 2.4166729 | L90: =L88*'Revenue Calculation'!L51/1000000000*Inputs!$E$54 -> 2.5651972 | M90: =M88*'Revenue Calculation'!M51/1000000000*Inputs!$E$54 -> 2.7228559 | N90: =N88*'Revenue Calculation'!N51/1000000000*Inputs!$E$54 -> 2.8902109 | O90: =O88*'Revenue Calculation'!O51/1000000000*Inputs!$E$54 -> 3.0678591 | ... T90: =T88*'Revenue Calculation'!T51/1000000000*Inputs!$E$54 -> 4.1340893
B91: Cost of sales - concession fee (% revenue) and insurance (% of scheduled depreciation) | C91: IDR bn | H91: =(Inputs!H412*'Revenue Calculation'!H53+Inputs!H127*Inputs!H126)*Inputs!$E$54 -> 0.61323873 | I91: =(Inputs!I412*'Revenue Calculation'!I53+Inputs!I127*Inputs!I126)*Inputs!$E$54 -> 0.62992135 | J91: =(Inputs!J412*'Revenue Calculation'!J53+Inputs!J127*Inputs!J126)*Inputs!$E$54 -> 0.90277379 | K91: =(Inputs!K412*'Revenue Calculation'!K53+Inputs!K127*Inputs!K126)*Inputs!$E$54 -> 0.90042412 | L91: =(Inputs!L412*'Revenue Calculation'!L53+Inputs!L127*Inputs!L126)*Inputs!$E$54 -> 0.95525995 | M91: =(Inputs!M412*'Revenue Calculation'!M53+Inputs!M127*Inputs!M126)*Inputs!$E$54 -> 1.0134353 | N91: =(Inputs!N412*'Revenue Calculation'!N53+Inputs!N127*Inputs!N126)*Inputs!$E$54 -> 1.0751535 | O91: =(Inputs!O412*'Revenue Calculation'!O53+Inputs!O127*Inputs!O126)*Inputs!$E$54 -> 1.1406303 | ... T91: =(Inputs!T412*'Revenue Calculation'!T53+Inputs!T127*Inputs!T126)*Inputs!$E$54 -> 1.5329118
B92: E3 Cost of sales | C92: IDR bn | H92: =H89+H90+H91 -> 8.0261411 | I92: =I89+I90+I91 -> 8.3557265 | J92: =J89+J90+J91 -> 8.9557231 | K92: =K89+K90+K91 -> 9.29546 | L92: =L89+L90+L91 -> 9.7080629 | M92: =M89+M90+M91 -> 10.140463 | N92: =N89+N90+N91 -> 10.593682 | O92: =O89+O90+O91 -> 11.068798 | ... T92: =T89+T90+T91 -> 13.814896
B93: E3 Operating expenses (G&A lines) x cost lever | C93: IDR bn | H93: =SUMIF($D$71:$D$87,"Opex",H$71:H$87)*Inputs!$E$54 -> 3.0717538 | I93: =SUMIF($D$71:$D$87,"Opex",I$71:I$87)*Inputs!$E$54 -> 3.158997 | J93: =SUMIF($D$71:$D$87,"Opex",J$71:J$87)*Inputs!$E$54 -> 3.2487704 | K93: =SUMIF($D$71:$D$87,"Opex",K$71:K$87)*Inputs!$E$54 -> 3.3411483 | L93: =SUMIF($D$71:$D$87,"Opex",L$71:L$87)*Inputs!$E$54 -> 3.4362076 | M93: =SUMIF($D$71:$D$87,"Opex",M$71:M$87)*Inputs!$E$54 -> 3.5340274 | N93: =SUMIF($D$71:$D$87,"Opex",N$71:N$87)*Inputs!$E$54 -> 3.6346889 | O93: =SUMIF($D$71:$D$87,"Opex",O$71:O$87)*Inputs!$E$54 -> 3.7382761 | ... T93: =SUMIF($D$71:$D$87,"Opex",T$71:T$87)*Inputs!$E$54 -> 4.3032108
B94: E3 EBITDA | C94: IDR bn | H94: ='Revenue Calculation'!H53-H92-H93 -> 11.145605 | I94: ='Revenue Calculation'!I53-I92-I93 -> 11.396081 | J94: ='Revenue Calculation'!J53-J92-J93 -> 22.763434 | K94: ='Revenue Calculation'!K53-K92-K93 -> 23.380357 | L94: ='Revenue Calculation'!L53-L92-L93 -> 25.066128 | M94: ='Revenue Calculation'!M53-M92-M93 -> 26.862921 | N94: ='Revenue Calculation'!N53-N92-N93 -> 28.777768 | O94: ='Revenue Calculation'!O53-O92-O93 -> 30.818139 | ... T94: ='Revenue Calculation'!T53-T92-T93 -> 43.198365
B96: E4 WIN stevedoring
B97: E4 cost lines (before the cost lever; 2023 column = FY2023 base; each later year = prior year x (1 + that year's growth); branch in brackets)
B98: Employee cost (payroll) [Cilegon] | C98: IDR bn | D98: COGS fixed | G98: =Inputs!$E$380*Inputs!$F$380 -> 2.5544369 | H98: =G98*(1+Inputs!H380) -> 2.6438422 | I98: =H98*(1+Inputs!I380) -> 2.7363767 | J98: =I98*(1+Inputs!J380) -> 2.8321499 | K98: =J98*(1+Inputs!K380) -> 2.9312751 | L98: =K98*(1+Inputs!L380) -> 3.0338698 | M98: =L98*(1+Inputs!M380) -> 3.1400552 | N98: =M98*(1+Inputs!N380) -> 3.2499571 | O98: =N98*(1+Inputs!O380) -> 3.3637056 | ... T98: =S98*(1+Inputs!T380) -> 3.9950271
B99: Maintenance [Cilegon] | C99: IDR bn | D99: COGS fixed | G99: =Inputs!$E$381*Inputs!$F$381 -> 0.0085200651 | H99: =G99*(1+Inputs!H381) -> 0.0086052658 | I99: =H99*(1+Inputs!I381) -> 0.0086913184 | J99: =I99*(1+Inputs!J381) -> 0.0087782316 | K99: =J99*(1+Inputs!K381) -> 0.0088660139 | L99: =K99*(1+Inputs!L381) -> 0.008954674 | M99: =L99*(1+Inputs!M381) -> 0.0090442208 | N99: =M99*(1+Inputs!N381) -> 0.009134663 | O99: =N99*(1+Inputs!O381) -> 0.0092260096 | ... T99: =S99*(1+Inputs!T381) -> 0.0096966288
B100: Employee cost (payroll) [Makassar] | C100: IDR bn | D100: COGS fixed | G100: =Inputs!$E$382*Inputs!$F$382 -> 0.8071649 | H100: =G100*(1+Inputs!H382) -> 0.83541567 | I100: =H100*(1+Inputs!I382) -> 0.86465522 | J100: =I100*(1+Inputs!J382) -> 0.89491815 | K100: =J100*(1+Inputs!K382) -> 0.92624028 | L100: =K100*(1+Inputs!L382) -> 0.95865869 | M100: =L100*(1+Inputs!M382) -> 0.99221175 | N100: =M100*(1+Inputs!N382) -> 1.0269392 | O100: =N100*(1+Inputs!O382) -> 1.062882 | ... T100: =S100*(1+Inputs!T382) -> 1.2623704
B101: Insurance [Makassar] | C101: IDR bn | D101: COGS fixed | G101: =Inputs!$E$383*Inputs!$F$383 -> 0.004470121 | H101: =G101*(1+Inputs!H383) -> 0.004470121 | I101: =H101*(1+Inputs!I383) -> 0.004470121 | J101: =I101*(1+Inputs!J383) -> 0.004470121 | K101: =J101*(1+Inputs!K383) -> 0.004470121 | L101: =K101*(1+Inputs!L383) -> 0.004470121 | M101: =L101*(1+Inputs!M383) -> 0.004470121 | N101: =M101*(1+Inputs!N383) -> 0.004470121 | O101: =N101*(1+Inputs!O383) -> 0.004470121 | ... T101: =S101*(1+Inputs!T383) -> 0.004470121
B102: Employee cost (payroll) [Surabaya] | C102: IDR bn | D102: COGS fixed | G102: =Inputs!$E$384*Inputs!$F$384 -> 0.33450116 | H102: =G102*(1+Inputs!H384) -> 0.3462087 | I102: =H102*(1+Inputs!I384) -> 0.358326 | J102: =I102*(1+Inputs!J384) -> 0.37086741 | K102: =J102*(1+Inputs!K384) -> 0.38384777 | L102: =K102*(1+Inputs!L384) -> 0.39728245 | M102: =L102*(1+Inputs!M384) -> 0.41118733 | N102: =M102*(1+Inputs!N384) -> 0.42557889 | O102: =N102*(1+Inputs!O384) -> 0.44047415 | ... T102: =S102*(1+Inputs!T384) -> 0.52314512
B103: Insurance [Surabaya] | C103: IDR bn | D103: COGS fixed | G103: =Inputs!$E$385*Inputs!$F$385 -> 0.002652611 | H103: =G103*(1+Inputs!H385) -> 0.002652611 | I103: =H103*(1+Inputs!I385) -> 0.002652611 | J103: =I103*(1+Inputs!J385) -> 0.002652611 | K103: =J103*(1+Inputs!K385) -> 0.002652611 | L103: =K103*(1+Inputs!L385) -> 0.002652611 | M103: =L103*(1+Inputs!M385) -> 0.002652611 | N103: =M103*(1+Inputs!N385) -> 0.002652611 | O103: =N103*(1+Inputs!O385) -> 0.002652611 | ... T103: =S103*(1+Inputs!T385) -> 0.002652611
...

Sheet BUMN Synergy Calculation
B1: BUMN SYNERGY CALCULATION - operatorship schemes with the SOEs (P12-P14): total benefit, FSL entitlement, costs and requirements
B2: Per-ton rows are SOE-level economics. Part of the SOE tariff (the FSL entitlement) moves to FSL, which takes over O&M. Only the entitlement less FSL cost enters the FSL statements; the SOE-retained share is information only.
B3: Go to sheet: | C3: Model Flow | D3: Inputs | E3: FS Request | F3: Revenue | G3: Costs | H3: [BUMN Synergy] | I3: Capex | J3: Work. cap. | K3: Financing | L3: Funding | M3: Out: w/o BUMN | N3: Out: With BUMN | O3: Val: w/o BUMN | P3: Val: With BUMN | Q3: Proj. CF | R3: Proj. Summary | S3: Checks | T3: Source Data
G4: Dec-23 | H4: FY | I4: FY | J4: FY | K4: FY | L4: FY | M4: FY | N4: FY | O4: FY | P4: FY | Q4: FY | R4: FY | S4: FY | T4: FY
B5: IDR per ton (per-ton rows) / IDR bn (annual rows) | C5: Unit | D5: Basis | E5: Parameter | G5: 2023 | H5: 2024 | I5: 2025 | J5: 2026 | K5: 2027 | L5: 2028 | M5: 2029 | N5: 2030 | O5: 2031 | P5: 2032 | Q5: 2033 | R5: 2034 | S5: 2035 | T5: 2036 | U5: Note
B6: A. P12 PELINDO TELUK LAMONG OPERATORSHIP (entity NPLOG, FSL 65%) - per-ton economics by year, then annual amounts
B7: Grains - per ton
B8: Grains: SOE tariff - current scheme (six components, Inputs 7) | C8: IDR/t | H8: =Inputs!H431+Inputs!H432+Inputs!H433+Inputs!H434+Inputs!H435+Inputs!H436 -> 78259 | I8: =Inputs!I431+Inputs!I432+Inputs!I433+Inputs!I434+Inputs!I435+Inputs!I436 -> 78259 | J8: =Inputs!J431+Inputs!J432+Inputs!J433+Inputs!J434+Inputs!J435+Inputs!J436 -> 78259 | K8: =Inputs!K431+Inputs!K432+Inputs!K433+Inputs!K434+Inputs!K435+Inputs!K436 -> 78259 | L8: =Inputs!L431+Inputs!L432+Inputs!L433+Inputs!L434+Inputs!L435+Inputs!L436 -> 78259 | M8: =Inputs!M431+Inputs!M432+Inputs!M433+Inputs!M434+Inputs!M435+Inputs!M436 -> 78259 | N8: =Inputs!N431+Inputs!N432+Inputs!N433+Inputs!N434+Inputs!N435+Inputs!N436 -> 78259 | O8: =Inputs!O431+Inputs!O432+Inputs!O433+Inputs!O434+Inputs!O435+Inputs!O436 -> 78259 | ... T8: =Inputs!T431+Inputs!T432+Inputs!T433+Inputs!T434+Inputs!T435+Inputs!T436 -> 78259
B9: Grains: SOE cost - current (tariff x (1 - SOE margin)) | C9: IDR/t | H9: =H8*(1-Inputs!H430) -> 57129.07 | I9: =I8*(1-Inputs!I430) -> 57129.07 | J9: =J8*(1-Inputs!J430) -> 57129.07 | K9: =K8*(1-Inputs!K430) -> 57129.07 | L9: =L8*(1-Inputs!L430) -> 57129.07 | M9: =M8*(1-Inputs!M430) -> 57129.07 | N9: =N8*(1-Inputs!N430) -> 57129.07 | O9: =O8*(1-Inputs!O430) -> 57129.07 | ... T9: =T8*(1-Inputs!T430) -> 57129.07
B10: Grains: SOE other cost - current (balancing item) | C10: IDR/t | H10: =H9-Inputs!H443-Inputs!H444-Inputs!H445 -> 33624.53 | I10: =I9-Inputs!I443-Inputs!I444-Inputs!I445 -> 33624.53 | J10: =J9-Inputs!J443-Inputs!J444-Inputs!J445 -> 33624.53 | K10: =K9-Inputs!K443-Inputs!K444-Inputs!K445 -> 33624.53 | L10: =L9-Inputs!L443-Inputs!L444-Inputs!L445 -> 33624.53 | M10: =M9-Inputs!M443-Inputs!M444-Inputs!M445 -> 33624.53 | N10: =N9-Inputs!N443-Inputs!N444-Inputs!N445 -> 33624.53 | O10: =O9-Inputs!O443-Inputs!O444-Inputs!O445 -> 33624.53 | ... T10: =T9-Inputs!T443-Inputs!T444-Inputs!T445 -> 33624.53
B11: Grains: ship-unloader tariff kept by the SOE | C11: IDR/t | H11: =(Inputs!H449+Inputs!H450)/(1-Inputs!H430) -> 8584.6811 | I11: =(Inputs!I449+Inputs!I450)/(1-Inputs!I430) -> 8584.6811 | J11: =(Inputs!J449+Inputs!J450)/(1-Inputs!J430) -> 8584.6811 | K11: =(Inputs!K449+Inputs!K450)/(1-Inputs!K430) -> 8584.6811 | L11: =(Inputs!L449+Inputs!L450)/(1-Inputs!L430) -> 8584.6811 | M11: =(Inputs!M449+Inputs!M450)/(1-Inputs!M430) -> 8584.6811 | N11: =(Inputs!N449+Inputs!N450)/(1-Inputs!N430) -> 8584.6811 | O11: =(Inputs!O449+Inputs!O450)/(1-Inputs!O430) -> 8584.6811 | ... T11: =(Inputs!T449+Inputs!T450)/(1-Inputs!T430) -> 8584.6811 | U11: v29 Calculation_FSL F1220 / F1244
B12: Grains: conveyor tariff kept by the SOE | C12: IDR/t | H12: =(Inputs!H451+Inputs!H452)/(1-Inputs!H430) -> 6393.8535 | I12: =(Inputs!I451+Inputs!I452)/(1-Inputs!I430) -> 6393.8535 | J12: =(Inputs!J451+Inputs!J452)/(1-Inputs!J430) -> 6393.8535 | K12: =(Inputs!K451+Inputs!K452)/(1-Inputs!K430) -> 6393.8535 | L12: =(Inputs!L451+Inputs!L452)/(1-Inputs!L430) -> 6393.8535 | M12: =(Inputs!M451+Inputs!M452)/(1-Inputs!M430) -> 6393.8535 | N12: =(Inputs!N451+Inputs!N452)/(1-Inputs!N430) -> 6393.8535 | O12: =(Inputs!O451+Inputs!O452)/(1-Inputs!O430) -> 6393.8535 | ... T12: =(Inputs!T451+Inputs!T452)/(1-Inputs!T430) -> 6393.8535 | U12: v29 F1221 / F1245
B13: Grains: SOE tariff - new scheme | C13: IDR/t | H13: =Inputs!H431+Inputs!H432+H11+H12+Inputs!H435+Inputs!H436 -> 61039.535 | I13: =Inputs!I431+Inputs!I432+I11+I12+Inputs!I435+Inputs!I436 -> 61039.535 | J13: =Inputs!J431+Inputs!J432+J11+J12+Inputs!J435+Inputs!J436 -> 61039.535 | K13: =Inputs!K431+Inputs!K432+K11+K12+Inputs!K435+Inputs!K436 -> 61039.535 | L13: =Inputs!L431+Inputs!L432+L11+L12+Inputs!L435+Inputs!L436 -> 61039.535 | M13: =Inputs!M431+Inputs!M432+M11+M12+Inputs!M435+Inputs!M436 -> 61039.535 | N13: =Inputs!N431+Inputs!N432+N11+N12+Inputs!N435+Inputs!N436 -> 61039.535 | O13: =Inputs!O431+Inputs!O432+O11+O12+Inputs!O435+Inputs!O436 -> 61039.535 | ... T13: =Inputs!T431+Inputs!T432+T11+T12+Inputs!T435+Inputs!T436 -> 61039.535
B14: Grains: FSL ENTITLEMENT per ton (tariff transferred to FSL) = current - new SOE tariff | C14: IDR/t | H14: =(Inputs!H433-H11)+(Inputs!H434-H12) -> 17219.465 | I14: =(Inputs!I433-I11)+(Inputs!I434-I12) -> 17219.465 | J14: =(Inputs!J433-J11)+(Inputs!J434-J12) -> 17219.465 | K14: =(Inputs!K433-K11)+(Inputs!K434-K12) -> 17219.465 | L14: =(Inputs!L433-L11)+(Inputs!L434-L12) -> 17219.465 | M14: =(Inputs!M433-M11)+(Inputs!M434-M12) -> 17219.465 | N14: =(Inputs!N433-N11)+(Inputs!N434-N12) -> 17219.465 | O14: =(Inputs!O433-O11)+(Inputs!O434-O12) -> 17219.465 | ... T14: =(Inputs!T433-T11)+(Inputs!T434-T12) -> 17219.465 | U14: v29 F1409 / F1414
B15: Grains: SOE other cost - new scheme (same % of tariff) | C15: IDR/t | H15: =H10/H8*H13 -> 26226.066 | I15: =I10/I8*I13 -> 26226.066 | J15: =J10/J8*J13 -> 26226.066 | K15: =K10/K8*K13 -> 26226.066 | L15: =L10/L8*L13 -> 26226.066 | M15: =M10/M8*M13 -> 26226.066 | N15: =N10/N8*N13 -> 26226.066 | O15: =O10/O8*O13 -> 26226.066 | ... T15: =T10/T8*T13 -> 26226.066 | U15: v29 F1230
B16: Grains: SOE cost - new scheme (O&M moves to FSL) | C16: IDR/t | H16: =Inputs!H443+Inputs!H444+H15 -> 37160.396 | I16: =Inputs!I443+Inputs!I444+I15 -> 37160.396 | J16: =Inputs!J443+Inputs!J444+J15 -> 37160.396 | K16: =Inputs!K443+Inputs!K444+K15 -> 37160.396 | L16: =Inputs!L443+Inputs!L444+L15 -> 37160.396 | M16: =Inputs!M443+Inputs!M444+M15 -> 37160.396 | N16: =Inputs!N443+Inputs!N444+N15 -> 37160.396 | O16: =Inputs!O443+Inputs!O444+O15 -> 37160.396 | ... T16: =Inputs!T443+Inputs!T444+T15 -> 37160.396
B17: Grains: check - new SOE tariff + FSL entitlement - current tariff (must be 0: no double counting) | C17: IDR/t | H17: =ROUND(H13+H14-H8,6) -> 0 | I17: =ROUND(I13+I14-I8,6) -> 0 | J17: =ROUND(J13+J14-J8,6) -> 0 | K17: =ROUND(K13+K14-K8,6) -> 0 | L17: =ROUND(L13+L14-L8,6) -> 0 | M17: =ROUND(M13+M14-M8,6) -> 0 | N17: =ROUND(N13+N14-N8,6) -> 0 | O17: =ROUND(O13+O14-O8,6) -> 0 | ... T17: =ROUND(T13+T14-T8,6) -> 0
B18: Meals - per ton
B19: Meals: SOE tariff - current scheme (six components, Inputs 7) | C19: IDR/t | H19: =Inputs!H437+Inputs!H438+Inputs!H439+Inputs!H440+Inputs!H441+Inputs!H442 -> 84841 | I19: =Inputs!I437+Inputs!I438+Inputs!I439+Inputs!I440+Inputs!I441+Inputs!I442 -> 84841 | J19: =Inputs!J437+Inputs!J438+Inputs!J439+Inputs!J440+Inputs!J441+Inputs!J442 -> 84841 | K19: =Inputs!K437+Inputs!K438+Inputs!K439+Inputs!K440+Inputs!K441+Inputs!K442 -> 84841 | L19: =Inputs!L437+Inputs!L438+Inputs!L439+Inputs!L440+Inputs!L441+Inputs!L442 -> 84841 | M19: =Inputs!M437+Inputs!M438+Inputs!M439+Inputs!M440+Inputs!M441+Inputs!M442 -> 84841 | N19: =Inputs!N437+Inputs!N438+Inputs!N439+Inputs!N440+Inputs!N441+Inputs!N442 -> 84841 | O19: =Inputs!O437+Inputs!O438+Inputs!O439+Inputs!O440+Inputs!O441+Inputs!O442 -> 84841 | ... T19: =Inputs!T437+Inputs!T438+Inputs!T439+Inputs!T440+Inputs!T441+Inputs!T442 -> 84841
B20: Meals: SOE cost - current (tariff x (1 - SOE margin)) | C20: IDR/t | H20: =H19*(1-Inputs!H430) -> 61933.93 | I20: =I19*(1-Inputs!I430) -> 61933.93 | J20: =J19*(1-Inputs!J430) -> 61933.93 | K20: =K19*(1-Inputs!K430) -> 61933.93 | L20: =L19*(1-Inputs!L430) -> 61933.93 | M20: =M19*(1-Inputs!M430) -> 61933.93 | N20: =N19*(1-Inputs!N430) -> 61933.93 | O20: =O19*(1-Inputs!O430) -> 61933.93 | ... T20: =T19*(1-Inputs!T430) -> 61933.93
B21: Meals: SOE other cost - current (balancing item) | C21: IDR/t | H21: =H20-Inputs!H446-Inputs!H447-Inputs!H448 -> 38955.72 | I21: =I20-Inputs!I446-Inputs!I447-Inputs!I448 -> 38955.72 | J21: =J20-Inputs!J446-Inputs!J447-Inputs!J448 -> 38955.72 | K21: =K20-Inputs!K446-Inputs!K447-Inputs!K448 -> 38955.72 | L21: =L20-Inputs!L446-Inputs!L447-Inputs!L448 -> 38955.72 | M21: =M20-Inputs!M446-Inputs!M447-Inputs!M448 -> 38955.72 | N21: =N20-Inputs!N446-Inputs!N447-Inputs!N448 -> 38955.72 | O21: =O20-Inputs!O446-Inputs!O447-Inputs!O448 -> 38955.72 | ... T21: =T20-Inputs!T446-Inputs!T447-Inputs!T448 -> 38955.72
B22: Meals: ship-unloader tariff kept by the SOE | C22: IDR/t | H22: =(Inputs!H453+Inputs!H454)/(1-Inputs!H430) -> 10083.501 | I22: =(Inputs!I453+Inputs!I454)/(1-Inputs!I430) -> 10083.501 | J22: =(Inputs!J453+Inputs!J454)/(1-Inputs!J430) -> 10083.501 | K22: =(Inputs!K453+Inputs!K454)/(1-Inputs!K430) -> 10083.501 | L22: =(Inputs!L453+Inputs!L454)/(1-Inputs!L430) -> 10083.501 | M22: =(Inputs!M453+Inputs!M454)/(1-Inputs!M430) -> 10083.501 | N22: =(Inputs!N453+Inputs!N454)/(1-Inputs!N430) -> 10083.501 | O22: =(Inputs!O453+Inputs!O454)/(1-Inputs!O430) -> 10083.501 | ... T22: =(Inputs!T453+Inputs!T454)/(1-Inputs!T430) -> 10083.501 | U22: v29 Calculation_FSL F1220 / F1244
B23: Meals: conveyor tariff kept by the SOE | C23: IDR/t | H23: =(Inputs!H455+Inputs!H456)/(1-Inputs!H430) -> 8152.9505 | I23: =(Inputs!I455+Inputs!I456)/(1-Inputs!I430) -> 8152.9505 | J23: =(Inputs!J455+Inputs!J456)/(1-Inputs!J430) -> 8152.9505 | K23: =(Inputs!K455+Inputs!K456)/(1-Inputs!K430) -> 8152.9505 | L23: =(Inputs!L455+Inputs!L456)/(1-Inputs!L430) -> 8152.9505 | M23: =(Inputs!M455+Inputs!M456)/(1-Inputs!M430) -> 8152.9505 | N23: =(Inputs!N455+Inputs!N456)/(1-Inputs!N430) -> 8152.9505 | O23: =(Inputs!O455+Inputs!O456)/(1-Inputs!O430) -> 8152.9505 | ... T23: =(Inputs!T455+Inputs!T456)/(1-Inputs!T430) -> 8152.9505 | U23: v29 F1221 / F1245
B24: Meals: SOE tariff - new scheme | C24: IDR/t | H24: =Inputs!H437+Inputs!H438+H22+H23+Inputs!H441+Inputs!H442 -> 71600.451 | I24: =Inputs!I437+Inputs!I438+I22+I23+Inputs!I441+Inputs!I442 -> 71600.451 | J24: =Inputs!J437+Inputs!J438+J22+J23+Inputs!J441+Inputs!J442 -> 71600.451 | K24: =Inputs!K437+Inputs!K438+K22+K23+Inputs!K441+Inputs!K442 -> 71600.451 | L24: =Inputs!L437+Inputs!L438+L22+L23+Inputs!L441+Inputs!L442 -> 71600.451 | M24: =Inputs!M437+Inputs!M438+M22+M23+Inputs!M441+Inputs!M442 -> 71600.451 | N24: =Inputs!N437+Inputs!N438+N22+N23+Inputs!N441+Inputs!N442 -> 71600.451 | O24: =Inputs!O437+Inputs!O438+O22+O23+Inputs!O441+Inputs!O442 -> 71600.451 | ... T24: =Inputs!T437+Inputs!T438+T22+T23+Inputs!T441+Inputs!T442 -> 71600.451
B25: Meals: FSL ENTITLEMENT per ton (tariff transferred to FSL) = current - new SOE tariff | C25: IDR/t | H25: =(Inputs!H439-H22)+(Inputs!H440-H23) -> 13240.549 | I25: =(Inputs!I439-I22)+(Inputs!I440-I23) -> 13240.549 | J25: =(Inputs!J439-J22)+(Inputs!J440-J23) -> 13240.549 | K25: =(Inputs!K439-K22)+(Inputs!K440-K23) -> 13240.549 | L25: =(Inputs!L439-L22)+(Inputs!L440-L23) -> 13240.549 | M25: =(Inputs!M439-M22)+(Inputs!M440-M23) -> 13240.549 | N25: =(Inputs!N439-N22)+(Inputs!N440-N23) -> 13240.549 | O25: =(Inputs!O439-O22)+(Inputs!O440-O23) -> 13240.549 | ... T25: =(Inputs!T439-T22)+(Inputs!T440-T23) -> 13240.549 | U25: v29 F1409 / F1414
B26: Meals: SOE other cost - new scheme (% of the first four components) | C26: IDR/t | H26: =H21/(Inputs!H437+Inputs!H438+Inputs!H439+Inputs!H440)*(Inputs!H437+Inputs!H438+H22+H23) -> 32323.405 | I26: =I21/(Inputs!I437+Inputs!I438+Inputs!I439+Inputs!I440)*(Inputs!I437+Inputs!I438+I22+I23) -> 32323.405 | J26: =J21/(Inputs!J437+Inputs!J438+Inputs!J439+Inputs!J440)*(Inputs!J437+Inputs!J438+J22+J23) -> 32323.405 | K26: =K21/(Inputs!K437+Inputs!K438+Inputs!K439+Inputs!K440)*(Inputs!K437+Inputs!K438+K22+K23) -> 32323.405 | L26: =L21/(Inputs!L437+Inputs!L438+Inputs!L439+Inputs!L440)*(Inputs!L437+Inputs!L438+L22+L23) -> 32323.405 | M26: =M21/(Inputs!M437+Inputs!M438+Inputs!M439+Inputs!M440)*(Inputs!M437+Inputs!M438+M22+M23) -> 32323.405 | N26: =N21/(Inputs!N437+Inputs!N438+Inputs!N439+Inputs!N440)*(Inputs!N437+Inputs!N438+N22+N23) -> 32323.405 | O26: =O21/(Inputs!O437+Inputs!O438+Inputs!O439+Inputs!O440)*(Inputs!O437+Inputs!O438+O22+O23) -> 32323.405 | ... T26: =T21/(Inputs!T437+Inputs!T438+Inputs!T439+Inputs!T440)*(Inputs!T437+Inputs!T438+T22+T23) -> 32323.405 | U26: v29 F1254
B27: Meals: SOE cost - new scheme (O&M moves to FSL) | C27: IDR/t | H27: =Inputs!H446+Inputs!H447+H26 -> 45636.015 | I27: =Inputs!I446+Inputs!I447+I26 -> 45636.015 | J27: =Inputs!J446+Inputs!J447+J26 -> 45636.015 | K27: =Inputs!K446+Inputs!K447+K26 -> 45636.015 | L27: =Inputs!L446+Inputs!L447+L26 -> 45636.015 | M27: =Inputs!M446+Inputs!M447+M26 -> 45636.015 | N27: =Inputs!N446+Inputs!N447+N26 -> 45636.015 | O27: =Inputs!O446+Inputs!O447+O26 -> 45636.015 | ... T27: =Inputs!T446+Inputs!T447+T26 -> 45636.015
B28: Meals: check - new SOE tariff + FSL entitlement - current tariff (must be 0: no double counting) | C28: IDR/t | H28: =ROUND(H24+H25-H19,6) -> 0 | I28: =ROUND(I24+I25-I19,6) -> 0 | J28: =ROUND(J24+J25-J19,6) -> 0 | K28: =ROUND(K24+K25-K19,6) -> 0 | L28: =ROUND(L24+L25-L19,6) -> 0 | M28: =ROUND(M24+M25-M19,6) -> 0 | N28: =ROUND(N24+N25-N19,6) -> 0 | O28: =ROUND(O24+O25-O19,6) -> 0 | ... T28: =ROUND(T24+T25-T19,6) -> 0
B29: Annual amounts (volumes from Revenue Calculation; the scheme applies from the P12 commencement year)
B30: Volume served (Teluk Lamong grains + meals) x operating flag | C30: tons | H30: ='Revenue Calculation'!H38*'Revenue Calculation'!H21 -> 0 | I30: ='Revenue Calculation'!I38*'Revenue Calculation'!I21 -> 0 | J30: ='Revenue Calculation'!J38*'Revenue Calculation'!J21 -> 3889498.4 | K30: ='Revenue Calculation'!K38*'Revenue Calculation'!K21 -> 4006183.3 | L30: ='Revenue Calculation'!L38*'Revenue Calculation'!L21 -> 4126368.8 | M30: ='Revenue Calculation'!M38*'Revenue Calculation'!M21 -> 4250159.9 | N30: ='Revenue Calculation'!N38*'Revenue Calculation'!N21 -> 4377664.7 | O30: ='Revenue Calculation'!O38*'Revenue Calculation'!O21 -> 4508994.7 | ... T30: ='Revenue Calculation'!T38*'Revenue Calculation'!T21 -> 5227160.6
B31: SOE revenue - current scheme (baseline) | C31: IDR bn | H31: =('Revenue Calculation'!H37*H8+'Revenue Calculation'!H36*H19)/1000000000 -> 300.49808 | I31: =('Revenue Calculation'!I37*I8+'Revenue Calculation'!I36*I19)/1000000000 -> 309.51302 | J31: =('Revenue Calculation'!J37*J8+'Revenue Calculation'!J36*J19)/1000000000 -> 318.79841 | K31: =('Revenue Calculation'!K37*K8+'Revenue Calculation'!K36*K19)/1000000000 -> 328.36236 | L31: =('Revenue Calculation'!L37*L8+'Revenue Calculation'!L36*L19)/1000000000 -> 338.21323 | M31: =('Revenue Calculation'!M37*M8+'Revenue Calculation'!M36*M19)/1000000000 -> 348.35963 | N31: =('Revenue Calculation'!N37*N8+'Revenue Calculation'!N36*N19)/1000000000 -> 358.81042 | O31: =('Revenue Calculation'!O37*O8+'Revenue Calculation'!O36*O19)/1000000000 -> 369.57473 | ... T31: =('Revenue Calculation'!T37*T8+'Revenue Calculation'!T36*T19)/1000000000 -> 428.4384
B32: SOE EBITDA - current scheme (baseline) | C32: IDR bn | H32: =('Revenue Calculation'!H37*(H8-H9+Inputs!H443)+'Revenue Calculation'!H36*(H19-H20+Inputs!H446))/1000000000 -> 110.9777 | I32: =('Revenue Calculation'!I37*(I8-I9+Inputs!I443)+'Revenue Calculation'!I36*(I19-I20+Inputs!I446))/1000000000 -> 114.30703 | J32: =('Revenue Calculation'!J37*(J8-J9+Inputs!J443)+'Revenue Calculation'!J36*(J19-J20+Inputs!J446))/1000000000 -> 117.73624 | K32: =('Revenue Calculation'!K37*(K8-K9+Inputs!K443)+'Revenue Calculation'!K36*(K19-K20+Inputs!K446))/1000000000 -> 121.26833 | L32: =('Revenue Calculation'!L37*(L8-L9+Inputs!L443)+'Revenue Calculation'!L36*(L19-L20+Inputs!L446))/1000000000 -> 124.90638 | M32: =('Revenue Calculation'!M37*(M8-M9+Inputs!M443)+'Revenue Calculation'!M36*(M19-M20+Inputs!M446))/1000000000 -> 128.65357 | N32: =('Revenue Calculation'!N37*(N8-N9+Inputs!N443)+'Revenue Calculation'!N36*(N19-N20+Inputs!N446))/1000000000 -> 132.51317 | O32: =('Revenue Calculation'!O37*(O8-O9+Inputs!O443)+'Revenue Calculation'!O36*(O19-O20+Inputs!O446))/1000000000 -> 136.48857 | ... T32: =('Revenue Calculation'!T37*(T8-T9+Inputs!T443)+'Revenue Calculation'!T36*(T19-T20+Inputs!T446))/1000000000 -> 158.22766
B33: SOE EBITDA - new scheme (baseline while the scheme is not active) | C33: IDR bn | H33: =IF('Revenue Calculation'!H21=1,('Revenue Calculation'!H37*(H13-H16+Inputs!H443)+'Revenue Calculation'!H36*(H24-H27+Inputs!H446))/1000000000,H32) -> 110.9777 | I33: =IF('Revenue Calculation'!I21=1,('Revenue Calculation'!I37*(I13-I16+Inputs!I443)+'Revenue Calculation'!I36*(I24-I27+Inputs!I446))/1000000000,I32) -> 114.30703 | J33: =IF('Revenue Calculation'!J21=1,('Revenue Calculation'!J37*(J13-J16+Inputs!J443)+'Revenue Calculation'!J36*(J24-J27+Inputs!J446))/1000000000,J32) -> 129.10394 | K33: =IF('Revenue Calculation'!K21=1,('Revenue Calculation'!K37*(K13-K16+Inputs!K443)+'Revenue Calculation'!K36*(K24-K27+Inputs!K446))/1000000000,K32) -> 132.97706 | L33: =IF('Revenue Calculation'!L21=1,('Revenue Calculation'!L37*(L13-L16+Inputs!L443)+'Revenue Calculation'!L36*(L24-L27+Inputs!L446))/1000000000,L32) -> 136.96637 | M33: =IF('Revenue Calculation'!M21=1,('Revenue Calculation'!M37*(M13-M16+Inputs!M443)+'Revenue Calculation'!M36*(M24-M27+Inputs!M446))/1000000000,M32) -> 141.07536 | N33: =IF('Revenue Calculation'!N21=1,('Revenue Calculation'!N37*(N13-N16+Inputs!N443)+'Revenue Calculation'!N36*(N24-N27+Inputs!N446))/1000000000,N32) -> 145.30762 | O33: =IF('Revenue Calculation'!O21=1,('Revenue Calculation'!O37*(O13-O16+Inputs!O443)+'Revenue Calculation'!O36*(O24-O27+Inputs!O446))/1000000000,O32) -> 149.66685 | ... T33: =IF('Revenue Calculation'!T21=1,('Revenue Calculation'!T37*(T13-T16+Inputs!T443)+'Revenue Calculation'!T36*(T24-T27+Inputs!T446))/1000000000,T32) -> 173.5049
B34: P12 FSL revenue = FSL entitlement per ton x volume served x tariff lever / 1e9 | C34: IDR bn | H34: =('Revenue Calculation'!H37*H14+'Revenue Calculation'!H36*H25)*'Revenue Calculation'!H21*Inputs!$E$53/1000000000 -> 0 | I34: =('Revenue Calculation'!I37*I14+'Revenue Calculation'!I36*I25)*'Revenue Calculation'!I21*Inputs!$E$53/1000000000 -> 0 | J34: =('Revenue Calculation'!J37*J14+'Revenue Calculation'!J36*J25)*'Revenue Calculation'!J21*Inputs!$E$53/1000000000 -> 58.263932 | K34: =('Revenue Calculation'!K37*K14+'Revenue Calculation'!K36*K25)*'Revenue Calculation'!K21*Inputs!$E$53/1000000000 -> 60.011849 | L34: =('Revenue Calculation'!L37*L14+'Revenue Calculation'!L36*L25)*'Revenue Calculation'!L21*Inputs!$E$53/1000000000 -> 61.812205 | M34: =('Revenue Calculation'!M37*M14+'Revenue Calculation'!M36*M25)*'Revenue Calculation'!M21*Inputs!$E$53/1000000000 -> 63.666571 | N34: =('Revenue Calculation'!N37*N14+'Revenue Calculation'!N36*N25)*'Revenue Calculation'!N21*Inputs!$E$53/1000000000 -> 65.576568 | O34: =('Revenue Calculation'!O37*O14+'Revenue Calculation'!O36*O25)*'Revenue Calculation'!O21*Inputs!$E$53/1000000000 -> 67.543865 | ... T34: =('Revenue Calculation'!T37*T14+'Revenue Calculation'!T36*T25)*'Revenue Calculation'!T21*Inputs!$E$53/1000000000 -> 78.301852
B35: P12 FSL cost of sales (none in v29) | C35: IDR bn | H35: =0 -> 0 | I35: =0 -> 0 | J35: =0 -> 0 | K35: =0 -> 0 | L35: =0 -> 0 | M35: =0 -> 0 | N35: =0 -> 0 | O35: =0 -> 0 | ... T35: =0 -> 0
B36: P12 FSL operating cost = (1 - FSL margin) x revenue x cost lever (O&M taken over; v29 books it in opex) | C36: IDR bn | H36: =(1-Inputs!H457)*H34*Inputs!$E$54 -> 0 | I36: =(1-Inputs!I457)*I34*Inputs!$E$54 -> 0 | J36: =(1-Inputs!J457)*J34*Inputs!$E$54 -> 29.714605 | K36: =(1-Inputs!K457)*K34*Inputs!$E$54 -> 30.606043 | L36: =(1-Inputs!L457)*L34*Inputs!$E$54 -> 31.524225 | M36: =(1-Inputs!M457)*M34*Inputs!$E$54 -> 32.469951 | N36: =(1-Inputs!N457)*N34*Inputs!$E$54 -> 33.44405 | O36: =(1-Inputs!O457)*O34*Inputs!$E$54 -> 34.447371 | ... T36: =(1-Inputs!T457)*T34*Inputs!$E$54 -> 39.933944
B37: P12 FSL EBITDA | C37: IDR bn | H37: =H34-H35-H36 -> 0 | I37: =I34-I35-I36 -> 0 | J37: =J34-J35-J36 -> 28.549326 | K37: =K34-K35-K36 -> 29.405806 | L37: =L34-L35-L36 -> 30.28798 | M37: =M34-M35-M36 -> 31.19662 | N37: =N34-N35-N36 -> 32.132518 | O37: =O34-O35-O36 -> 33.096494 | ... T37: =T34-T35-T36 -> 38.367907
B38: TOTAL incremental benefit vs baseline (SOE new EBITDA + FSL EBITDA - SOE baseline EBITDA) | C38: IDR bn | H38: =H33+H37-H32 -> 0 | I38: =I33+I37-I32 -> 0 | J38: =J33+J37-J32 -> 39.917028 | K38: =K33+K37-K32 -> 41.114539 | L38: =L33+L37-L32 -> 42.347975 | M38: =M33+M37-M32 -> 43.618414 | N38: =N33+N37-N32 -> 44.926966 | O38: =O33+O37-O32 -> 46.274775 | ... T38: =T33+T37-T32 -> 53.645147
B39: of which attributable to FSL (enters the FSL statements) | C39: IDR bn | H39: =H37 -> 0 | I39: =I37 -> 0 | J39: =J37 -> 28.549326 | K39: =K37 -> 29.405806 | L39: =L37 -> 30.28798 | M39: =M37 -> 31.19662 | N39: =N37 -> 32.132518 | O39: =O37 -> 33.096494 | ... T39: =T37 -> 38.367907
B40: of which retained by the SOE (information only) | C40: IDR bn | H40: =H33-H32 -> 0 | I40: =I33-I32 -> 0 | J40: =J33-J32 -> 11.367701 | K40: =K33-K32 -> 11.708732 | L40: =L33-L32 -> 12.059994 | M40: =M33-M32 -> 12.421794 | N40: =N33-N32 -> 12.794448 | O40: =O33-O32 -> 13.178281 | ... T40: =T33-T32 -> 15.27724
B42: B. P13 KBS CIGADING OPERATORSHIP (entity SGT 2, FSL 100%)
B43: Per ton
B44: Ship-unloader component of the all-in tariff | C44: IDR/t | H44: =Inputs!H458*Inputs!H459 -> 24416 | I44: =Inputs!I458*Inputs!I459 -> 24416 | J44: =Inputs!J458*Inputs!J459 -> 24416 | K44: =Inputs!K458*Inputs!K459 -> 24416 | L44: =Inputs!L458*Inputs!L459 -> 24416 | M44: =Inputs!M458*Inputs!M459 -> 24416 | N44: =Inputs!N458*Inputs!N459 -> 24416 | O44: =Inputs!O458*Inputs!O459 -> 24416 | ... T44: =Inputs!T458*Inputs!T459 -> 24416 | U44: v29 F1283
B45: Berth component (balance) | C45: IDR/t | H45: =Inputs!H458-H44 -> 10464 | I45: =Inputs!I458-I44 -> 10464 | J45: =Inputs!J458-J44 -> 10464 | K45: =Inputs!K458-K44 -> 10464 | L45: =Inputs!L458-L44 -> 10464 | M45: =Inputs!M458-M44 -> 10464 | N45: =Inputs!N458-N44 -> 10464 | O45: =Inputs!O458-O44 -> 10464 | ... T45: =Inputs!T458-T44 -> 10464 | U45: v29 F1281
B46: SOE cost - current (tariff x (1 - SOE margin)) | C46: IDR/t | H46: =Inputs!H458*(1-Inputs!H430) -> 25462.4 | I46: =Inputs!I458*(1-Inputs!I430) -> 25462.4 | J46: =Inputs!J458*(1-Inputs!J430) -> 25462.4 | K46: =Inputs!K458*(1-Inputs!K430) -> 25462.4 | L46: =Inputs!L458*(1-Inputs!L430) -> 25462.4 | M46: =Inputs!M458*(1-Inputs!M430) -> 25462.4 | N46: =Inputs!N458*(1-Inputs!N430) -> 25462.4 | O46: =Inputs!O458*(1-Inputs!O430) -> 25462.4 | ... T46: =Inputs!T458*(1-Inputs!T430) -> 25462.4
B47: SOE other cost - current (balancing item) | C47: IDR/t | H47: =H46-Inputs!H460-Inputs!H461-Inputs!H462 -> 7639.177 | I47: =I46-Inputs!I460-Inputs!I461-Inputs!I462 -> 7639.177 | J47: =J46-Inputs!J460-Inputs!J461-Inputs!J462 -> 7639.177 | K47: =K46-Inputs!K460-Inputs!K461-Inputs!K462 -> 7639.177 | L47: =L46-Inputs!L460-Inputs!L461-Inputs!L462 -> 7639.177 | M47: =M46-Inputs!M460-Inputs!M461-Inputs!M462 -> 7639.177 | N47: =N46-Inputs!N460-Inputs!N461-Inputs!N462 -> 7639.177 | O47: =O46-Inputs!O460-Inputs!O461-Inputs!O462 -> 7639.177 | ... T47: =T46-Inputs!T460-Inputs!T461-Inputs!T462 -> 7639.177
B48: Ship-unloader tariff kept by the SOE ((crane + overhead) / (1 - margin) x mark-up) | C48: IDR/t | H48: =(Inputs!H463+Inputs!H461)/(1-Inputs!H430)*Inputs!H464 -> 9125.8142 | I48: =(Inputs!I463+Inputs!I461)/(1-Inputs!I430)*Inputs!I464 -> 9125.8142 | J48: =(Inputs!J463+Inputs!J461)/(1-Inputs!J430)*Inputs!J464 -> 9125.8142 | K48: =(Inputs!K463+Inputs!K461)/(1-Inputs!K430)*Inputs!K464 -> 9125.8142 | L48: =(Inputs!L463+Inputs!L461)/(1-Inputs!L430)*Inputs!L464 -> 9125.8142 | M48: =(Inputs!M463+Inputs!M461)/(1-Inputs!M430)*Inputs!M464 -> 9125.8142 | N48: =(Inputs!N463+Inputs!N461)/(1-Inputs!N430)*Inputs!N464 -> 9125.8142 | O48: =(Inputs!O463+Inputs!O461)/(1-Inputs!O430)*Inputs!O464 -> 9125.8142 | ... T48: =(Inputs!T463+Inputs!T461)/(1-Inputs!T430)*Inputs!T464 -> 9125.8142 | U48: v29 F1307
B49: SOE tariff - new scheme | C49: IDR/t | H49: =H45+H48 -> 19589.814 | I49: =I45+I48 -> 19589.814 | J49: =J45+J48 -> 19589.814 | K49: =K45+K48 -> 19589.814 | L49: =L45+L48 -> 19589.814 | M49: =M45+M48 -> 19589.814 | N49: =N45+N48 -> 19589.814 | O49: =O45+O48 -> 19589.814 | ... T49: =T45+T48 -> 19589.814
B50: FSL ENTITLEMENT per ton (tariff transferred to FSL) | C50: IDR/t | H50: =H44-H48 -> 15290.186 | I50: =I44-I48 -> 15290.186 | J50: =J44-J48 -> 15290.186 | K50: =K44-K48 -> 15290.186 | L50: =L44-L48 -> 15290.186 | M50: =M44-M48 -> 15290.186 | N50: =N44-N48 -> 15290.186 | O50: =O44-O48 -> 15290.186 | ... T50: =T44-T48 -> 15290.186 | U50: v29 F1426
B51: SOE other cost - new scheme (same % of tariff) | C51: IDR/t | H51: =H47/Inputs!H458*H49 -> 4290.426 | I51: =I47/Inputs!I458*I49 -> 4290.426 | J51: =J47/Inputs!J458*J49 -> 4290.426 | K51: =K47/Inputs!K458*K49 -> 4290.426 | L51: =L47/Inputs!L458*L49 -> 4290.426 | M51: =M47/Inputs!M458*M49 -> 4290.426 | N51: =N47/Inputs!N458*N49 -> 4290.426 | O51: =O47/Inputs!O458*O49 -> 4290.426 | ... T51: =T47/Inputs!T458*T49 -> 4290.426 | U51: v29 F1317
B52: SOE cost - new scheme (O&M moves to FSL) | C52: IDR/t | H52: =Inputs!H460+Inputs!H461+H51 -> 9841.506 | I52: =Inputs!I460+Inputs!I461+I51 -> 9841.506 | J52: =Inputs!J460+Inputs!J461+J51 -> 9841.506 | K52: =Inputs!K460+Inputs!K461+K51 -> 9841.506 | L52: =Inputs!L460+Inputs!L461+L51 -> 9841.506 | M52: =Inputs!M460+Inputs!M461+M51 -> 9841.506 | N52: =Inputs!N460+Inputs!N461+N51 -> 9841.506 | O52: =Inputs!O460+Inputs!O461+O51 -> 9841.506 | ... T52: =Inputs!T460+Inputs!T461+T51 -> 9841.506
B53: Check - new SOE tariff + FSL entitlement - current tariff (must be 0) | C53: IDR/t | H53: =ROUND(H49+H50-Inputs!H458,6) -> 0 | I53: =ROUND(I49+I50-Inputs!I458,6) -> 0 | J53: =ROUND(J49+J50-Inputs!J458,6) -> 0 | K53: =ROUND(K49+K50-Inputs!K458,6) -> 0 | L53: =ROUND(L49+L50-Inputs!L458,6) -> 0 | M53: =ROUND(M49+M50-Inputs!M458,6) -> 0 | N53: =ROUND(N49+N50-Inputs!N458,6) -> 0 | O53: =ROUND(O49+O50-Inputs!O458,6) -> 0 | ... T53: =ROUND(T49+T50-Inputs!T458,6) -> 0
B54: Annual amounts
