Workbook

Sheet Navigation
B1: FSL — FKS Solusi Logistik — Financial Model (revised from v29)
B2: Valuation date 31-Dec-2026 · IDR bn unless stated · Sapphire excluded · two BUMN cases · built with live Excel formulas
B4: Start here
B5: Model Flow | C5: How the model is organised, what changed versus v29, how to use the controls, tests performed.
B6: Global Inputs | C6: Shared assumptions, switches (depreciation method, funding case, Badas funding), valuation parameters, project register (inclusion / case / interest).
B7: Project Summary | C7: One section per project (income statement, FCFF, capex, funding need, returns) + comparison table.
B8: FSL Financials — Without BUMN | C8: Integrated statements — Without BUMN case.
B9: FSL Financials — With BUMN | C9: Integrated statements — With BUMN case.
B10: Funding Requirement | C10: How much equity do we need and when: cash roll-forward, requirement at the injection date, capex-only projects, bridge, use of proceeds.
B11: Financing | C11: Corporate loans: LT loan carried until the capital injection; interest to the repayment date; injection booking.
B12: Valuation — Without BUMN | C12: DCF from FY2027 at 31-Dec-2026 — Without BUMN.
B13: Valuation — With BUMN | C13: DCF from FY2027 at 31-Dec-2026 — With BUMN.
B14: Checks | C14: Formula-based integrity checks (balance sheet, cash, consolidation, funding, valuation timing, capex allocation).
B15: Reconciliation v29 | C15: Line-by-line reconciliation to v29 (Output_FSL) with explanations of the differences.
B17: Project | C17: Description | D17: Input | E17: Calc | F17: Output | G17: Category / notes
B18: E1 Teluk Lamong (NPLOG) cargodoring & delivery | C18: Existing grain and meal terminal operations at Teluk Lamong (conveyor, warehouse, delivery): volume x tariff for meals and grains; variable costs per ton indexed from FY2023; fixed G&A lines; depreciation of existing assets. | D18: Input | E18: Calc | F18: Output | G18: Existing business — NPLOG Teluk Lamong
B19: E2 Cigading Existing Terminal (SGT 2) | C19: Existing grain terminal at Cigading: stevedoring / cargodoring volume at a per-ton tariff (Wharf 2 tariff from FY2025), variable costs per ton indexed from FY2023 actuals, fixed G&A lines, depreciation of existing assets. | D19: Input | E19: Calc | F19: Output | G19: Existing business — SGT Cigading
B20: E3 Belawan terminal (SGT3) incl. Belawan expansion | C20: Existing grain terminal at Belawan plus its expansion: existing volume (3% growth) and typed additional expansion volume from FY2027 at a per-ton tariff; fixed and per-ton costs indexed from FY2023, concession fee 2.5% of revenue, insurance; nine fixed G&A lines; existing-asset depreciation plus 14.0 USD m of new assets depreciated from FY2026. | D20: Input | E20: Calc | F20: Output | G20: Existing business — SGT Belawan
B21: E4 WIN stevedoring (Cilegon, Makassar, Surabaya, Medan) | C21: Existing stevedoring business at four ports: per-commodity volume (FY2023 base x growth index) x stevedoring tariff; cost of sales = dock & port facilities fee (share of sales), employee cost, maintenance and insurance; fixed G&A lines; fixed depreciation of existing assets per site. | D21: Input | E21: Calc | F21: Output | G21: Existing business — WIN
B22: P01 Cigading Wharf 2 | C22: Second wharf at Cigading: additional meals/grains volume at a stevedoring tariff; variable costs use the existing terminal's cost per ton, opex 20% of revenue, insurance on new assets. | D22: Input | E22: Calc | F22: Output | G22: Committed project — SGT Cigading
B23: P02 Cigading Extended Conveyor | C23: Conveyor extension at Cigading: additional cargodoring volume charged at a per-ton tariff; costs are electricity and maintenance shares of the existing terminal's cost per ton plus insurance on the new assets. | D23: Input | E23: Calc | F23: Output | G23: Committed project — SGT Cigading
B24: P03 KBS Warehouse Revitalisation (Cigading) | C24: Revitalisation of the KBS warehouse at Cigading: handling/bagging, weighing and storage fees per ton on an indexed 1.7 m t base; FKS books 49% of gross revenue, with cost of sales 10% and opex 50% of that revenue. | D24: Input | E24: Calc | F24: Output | G24: Planned project — SGT Cigading / KBS
B25: P04 Teluk Lamong Silo | C25: Two 8,500 t/month silos at Teluk Lamong charging a bagging/storage fee of 65,000 IDR per ton per month from 2027; a 300 IDR/t handling cost (booked as opex in v29) and depreciation of the 3.76 USD m capex (building 63% / 20 yrs, equipment 37% / 10 yrs). | D25: Input | E25: Calc | F25: Output | G25: Planned project — NPLOG Teluk Lamong
B26: P05 Dumai bagging & weighbridge | C26: Bagging and weighbridge services at Dumai from FY2026: a typed volume schedule (1.3 m t, stepping up 3% every four years) charged a bagging tariff (35,000 IDR/t, +4% every four years) and a weighbridge tariff (2,000 IDR/t); opex = insurance on the 6.81 USD m capex plus operational cost as a typed % of each revenue stream; cost of sales nil in v29. | D26: Input | E26: Calc | F26: Output | G26: Planned project — FSL Dumai
B27: P06 Ciwandan Expansion | C27: Expansion at Ciwandan from FY2028: 1.6 m t growing 10% p.a. (6% from 2032) at an ASP of 36,411 IDR/t stepping up with the Cigading tariff; cost of sales and opex are the existing Cigading terminal's cost-to-revenue ratios applied to the expansion revenue; depreciation of the 5.02 USD m capex (50% building / 20 yrs, 50% equipment / 8 yrs). | D27: Input | E27: Calc | F27: Output | G27: Planned project — FSL Ciwandan
B28: P08 DMS trucking fee (Teluk Lamong, Cigading, Ciwandan, Belawan) | C28: Digital trucking management service at four terminals: FKS earns a 2% service fee on the trucking cost per ton of each terminal's volume and keeps 50% of the fee; opex 20% of FKS revenue; small equipment depreciated per site (no capex in v29). | D28: Input | E28: Calc | F28: Output | G28: Planned project — DMS trucking
... B31: P19 Badas bulk terminal (FS pending — DUMMY data) | C31: Bulk cargo terminal at Badas: capacity x utilisation -> throughput; handling, storage and ancillary tariffs; variable, staff, fixed, maintenance, insurance and concession costs; 10 USD m provisional capex; project debt option. ALL operating inputs are DUMMY placeholders until the feasibility study is received. | D31: Input | E31: Calc | F31: Output | G31: Pipeline — FS pending (DUMMY inputs, excluded from headline valuation) — Badas (new)
B33: Colour conventions
C34: Blue text on pale yellow = hard-coded input (v29 source or derived)
C35: Bold blue on gold = control / switch
C36: Light blue = user-requested modelling change
C37: Light green = updated information supplied by the user
C38: Orange = provisional — to confirm
C39: Salmon = DUMMY — REPLACE WITH FS DATA (Badas)
C40: Black text = formula; green text = link from another sheet; blue underlined = navigation link

Sheet Model Flow
B1: MODEL FLOW — architecture, changes versus v29, controls, tests
B2: Detailed explanations live here so that calculation sheets stay focused on drivers and numbers.
B4: 1. Purpose | C4: Revised FSL model built from V29_Ruby_FM_Danantara.xlsm (v29) with live formulas. v29 remains the source of business assumptions and calculation logic; the changes requested by the user are: valuation date 31-Dec-2026 with a DCF from FY2027, LT loan repaid when the capital injection is received, capex spending controlled by annual percentages, Badas built as a feasibility-study working paper, a funding requirement sheet with five capex-only placeholders, and separate With / Without BUMN cases. Sapphire stays excluded.
B5: 2. Architecture | C5: Global Inputs (shared assumptions and the project register) -> one Input / Calc / Output triplet per project -> Project Summary and the two FSL Financials sheets (sum of project outputs x case flags + corporate items) -> Funding Requirement and Financing (LT loan, injection) -> two Valuation sheets -> Checks and Reconciliation. Sheet names carry the project ID and code (e.g. 'P02 CigConveyor Input / Calc / Output'). Every time-series sheet uses the same columns: F = 2023 (opening / pre-2024), G..S = 2024..2036.
B6: 3. Inputs and classification | C6: Column D on every input row classifies the assumption: v29 (value and cell reference from v29, including effective values typed inside v29 formulas), DERIVED (computed from v29), UPDATED (information supplied by the user, e.g. the board-deck use of proceeds), CHANGE (user-requested modelling change), DUMMY (Badas placeholders to be replaced with FS data), PROV (provisional, to confirm), CONTROL (switch). Annual assumptions have one editable cell per year; genuine one-off parameters sit in column E.
B7: 4. Project sheets | C7: Input: register, controls (links to Global Inputs), commissioning year, operating assumptions, capex allocation (total USD m, % by year, USD and IDR schedules, pre- vs post-valuation split, allocation check, building share, useful lives). Calc: operating flag, revenue and cost drivers exactly as v29 computes them, capex and depreciation, working capital. Output: unlevered project income statement (tax on project EBIT, v29 line method), FCFF, net operating assets (no project-level cash or debt), funding need, returns (NPV at the valuation date, full-life IRR with and without terminal value, payback), case inclusion flags.
B8: 5. Two BUMN cases | C8: v29 Output_FSL is the With-BUMN case: it includes the 'Operatorship with BUMN' block (FSL's entitlement under the Pelindo Teluk Lamong, KBS Cigading and Pelindo Belawan operatorship schemes; v29 Output_FSL!F35 = 1). The Without-BUMN case removes the case-2 projects (register column 'Case' = 2). Both cases are computed at the same time on their own Financials and Valuation sheets; the Funding Requirement uses the case selected on Global Inputs (default: Without BUMN, conservative). DMS trucking fees are shared 50/50 with the port operator but are kept in both cases as in v8; set their case to 2 on the register to treat them as BUMN-dependent.
B9: 6. Valuation date and DCF | C9: Valuation date 31-Dec-2026 (Global Inputs). Only FCFF of years after the valuation date enters the DCF (flag row 'DCF window'); FY2027 is discounted one full year (year-end convention). FCFF = EBIT - tax on EBIT (sum of project line taxes) + D&A - capex - increase in working capital, unlevered and consistent with WACC. Terminal value: Gordon growth on a normalised FY2036 cash flow (capex = factor x depreciation, working capital growing with g). Equity bridge at 31-Dec-2026: + cash, - LT loan outstanding at that date (depends on whether the injection date falls before or after it), +/- other balances (switch), - non-controlling interests (35% of NPLOG line values).
B10: 7. LT loan and capital injection | C10: The 12 USD m LT loan (195.2 IDR bn) is carried until the capital injection. Injection date and mode are inputs on Global Inputs (provisional 30-Jun-2027). Mode 1 sizes the injection to the equity requirement of the funding case; mode 2 uses a fixed amount. Repayment = planned share of the balance in the injection year, limited in mode 2 to the proceeds received; any unpaid balance is retained, flagged, and keeps accruing interest. Interest accrues on the repaid part to the injection date and on the remaining balance for the full year. The equity receipt and the loan repayment are separate lines in the cash-flow statement. No circular references: the requirement is computed on a pre-equity cash path; dividends are capped by that path so they are never paid out of the injection.
B11: 8. Capex percentages | C11: Each project's capex = total (USD m) x annual % of total (Input sheet). The 2023 column is pre-2024 (sunk) spend; columns up to the valuation year are pre-valuation estimates (v29 projected timing; actuals not supplied — flag 'historical spend confirmed' = 0). Only spend after the valuation date enters the 2027+ DCF. Depreciation method switch: 2 (default) depreciates each year's spend over its life from MAX(spend year, commissioning); 1 reproduces v29 (total x share / life from commissioning, no end).
B12: 9. Badas | C12: P19 Badas is a complete project template with DUMMY inputs (salmon rows, 'DUMMY — REPLACE WITH FS DATA'). Its working paper lists definition, unit, period, status and destination for every requested input plus questions for the operations team. Badas is excluded from the headline valuation by default (register 'In valuation' = 0) while its capex (provisional 10 USD m from the board deck) enters the funding request through the separate 'Badas in funding' switch.
B13: 10. Funding-only placeholders | C13: F01-F05 on the Funding Requirement sheet accept a name, total capex (USD m), annual % and an include switch. They add to the equity request only; they never enter the statements or the valuation and carry no revenue, profit or return ('FS not available').
B14: 11. Corporate and unallocated items | C14: Existing fixed assets (Dec-23 NBV 826.0), other assets, other liabilities, inventory, the loans and paid-in capital are company-level balances from v29 and are not allocated to projects. Dec-23 receivables and payables are allocated to the existing businesses pro rata FY2024 activity (labelled as an allocation). Pre-2024 project spend on Wharf 2 and the conveyor (assets under construction) is reclassified from other assets to project fixed assets.
B15: 12. Reconciliation to v29 | C15: The Reconciliation sheet compares the With-BUMN case with v29 Output_FSL line by line and explains each difference (valuation date, LT loan timing and interest, depreciation method, injection basis, inventory and other v29 formula breaks). Setting depreciation method = 1 and the injection date to 31-Dec-2025 reproduces v29's income statement through EBIT; v29's two equity tranches (FY2026-27 capex) are replaced by one requirement-based injection.
... B17: 14. Calculation engine and tests | C17: Recalculated and tested with LibreOffice Calc (headless), not Microsoft Excel. Tests: injection date moved (2026 / 2028) moves the repayment and interest; zero / insufficient proceeds keep the loan outstanding; capex % moved between years updates capex, depreciation, cash and funding; Badas dummy inputs replaced update its sheets; inclusion switches affect the correct case; funding-only placeholders change the request but not the valuation; project outputs reconcile to company outputs; balance sheets and cash reconcile. Settings were restored to the delivery values after testing (see model/tests/).

Sheet Global Inputs
B1: GLOBAL INPUTS — shared assumptions, controls and project register
B2: Single source for every assumption used by more than one sheet. Blue = input (yellow fill); bold blue on gold = control switch; orange = provisional; light blue = user-requested change. Black = formula.
B3: Go to: | C3: Navigation | D3: Global Inputs | E3: Project Summary | F3: Funding | G3: FSL w/o BUMN | H3: FSL w/ BUMN | I3: Val w/o BUMN | J3: Val w/ BUMN | K3: Checks | L3: Model Flow
B5: Year | C5: Unit | D5: Type | E5: Value / total | F5: 2023 | G5: 2024 | H5: 2025 | I5: 2026 | J5: 2027 | K5: 2028 | L5: 2029 | M5: 2030 | N5: 2031 | O5: 2032 | P5: 2033 | Q5: 2034 | R5: 2035 | S5: 2036 | T5: Source (v29 reference / basis) | U5: Note
B6: Period end | F6: =DATE(F5,12,31) -> 45291 | G6: =DATE(G5,12,31) -> 45657 | H6: =DATE(H5,12,31) -> 46022 | I6: =DATE(I5,12,31) -> 46387 | J6: =DATE(J5,12,31) -> 46752 | K6: =DATE(K5,12,31) -> 47118 | L6: =DATE(L5,12,31) -> 47483 | M6: =DATE(M5,12,31) -> 47848 | ... S6: =DATE(S5,12,31) -> 50040
B7: Days in year | F7: =F6-DATE(F5,1,1)+1 -> 365 | G7: =G6-DATE(G5,1,1)+1 -> 366 | H7: =H6-DATE(H5,1,1)+1 -> 365 | I7: =I6-DATE(I5,1,1)+1 -> 365 | J7: =J6-DATE(J5,1,1)+1 -> 365 | K7: =K6-DATE(K5,1,1)+1 -> 366 | L7: =L6-DATE(L5,1,1)+1 -> 365 | M7: =M6-DATE(M5,1,1)+1 -> 365 | ... S7: =S6-DATE(S5,1,1)+1 -> 366
B8: Forecast flag (1 = forecast year) | F8: 0 | G8: 1 | H8: 1 | I8: 1 | J8: 1 | K8: 1 | L8: 1 | M8: 1 | N8: 1 | O8: 1 | P8: 1 | Q8: 1 | R8: 1 | S8: 1
B10: 1. Timeline and valuation date
B11: Valuation date | C11: date | D11: CHANGE | E11: 46387 | T11: User instruction (change from v29 which valued at model start) | U11: Company DCF uses FCFF from the year after this date (FY2027+). Balances at this date enter the equity bridge.
B12: Valuation year (financial year ending on the valuation date) | C12: year | D12: formula | E12: =YEAR($E$11) -> 2026 | T12: Formula
B13: First year of DCF cash flows | C13: year | D13: formula | E13: =$E$12+1 -> 2027 | T13: Formula
B14: Last explicit forecast year | C14: year | D14: formula | E14: =MAX(F5:S5) -> 2036 | T14: Formula
B15: Model year (header) | C15: year | D15: formula | F15: =F$5 -> 2023 | G15: =G$5 -> 2024 | H15: =H$5 -> 2025 | I15: =I$5 -> 2026 | J15: =J$5 -> 2027 | K15: =K$5 -> 2028 | L15: =L$5 -> 2029 | M15: =M$5 -> 2030 | ... S15: =S$5 -> 2036 | T15: Timeline
B16: DCF window flag (1 = year after the valuation date) | C16: flag | D16: formula | F16: =IF(F$5>$E$12,1,0) -> 0 | G16: =IF(G$5>$E$12,1,0) -> 0 | H16: =IF(H$5>$E$12,1,0) -> 0 | I16: =IF(I$5>$E$12,1,0) -> 0 | J16: =IF(J$5>$E$12,1,0) -> 1 | K16: =IF(K$5>$E$12,1,0) -> 1 | L16: =IF(L$5>$E$12,1,0) -> 1 | M16: =IF(M$5>$E$12,1,0) -> 1 | ... S16: =IF(S$5>$E$12,1,0) -> 1 | T16: Formula
B17: Discount period (years from the valuation date; year-end convention) | C17: years | D17: formula | F17: =IF(F$5>$E$12,F$5-$E$12,0) -> 0 | G17: =IF(G$5>$E$12,G$5-$E$12,0) -> 0 | H17: =IF(H$5>$E$12,H$5-$E$12,0) -> 0 | I17: =IF(I$5>$E$12,I$5-$E$12,0) -> 0 | J17: =IF(J$5>$E$12,J$5-$E$12,0) -> 1 | K17: =IF(K$5>$E$12,K$5-$E$12,0) -> 2 | L17: =IF(L$5>$E$12,L$5-$E$12,0) -> 3 | M17: =IF(M$5>$E$12,M$5-$E$12,0) -> 4 | ... S17: =IF(S$5>$E$12,S$5-$E$12,0) -> 10 | T17: Formula | U17: FY2027 cash flow is discounted one full year from 31-Dec-2026.
B18: Discount factor at WACC (0 before / at the valuation date) | C18: x | D18: formula | F18: =IF(F$5>$E$12,1/(1+$E$53)^F17,0) -> 0 | G18: =IF(G$5>$E$12,1/(1+$E$53)^G17,0) -> 0 | H18: =IF(H$5>$E$12,1/(1+$E$53)^H17,0) -> 0 | I18: =IF(I$5>$E$12,1/(1+$E$53)^I17,0) -> 0 | J18: =IF(J$5>$E$12,1/(1+$E$53)^J17,0) -> 0.89392257 | K18: =IF(K$5>$E$12,1/(1+$E$53)^K17,0) -> 0.79909756 | L18: =IF(L$5>$E$12,1/(1+$E$53)^L17,0) -> 0.71433135 | M18: =IF(M$5>$E$12,1/(1+$E$53)^M17,0) -> 0.63855691 | ... S18: =IF(S$5>$E$12,1/(1+$E$53)^S17,0) -> 0.32583597 | T18: Formula
B19: Pre-valuation flag (1 = up to and including the valuation year) | C19: flag | D19: formula | F19: =IF(F$5<=$E$12,1,0) -> 1 | G19: =IF(G$5<=$E$12,1,0) -> 1 | H19: =IF(H$5<=$E$12,1,0) -> 1 | I19: =IF(I$5<=$E$12,1,0) -> 1 | J19: =IF(J$5<=$E$12,1,0) -> 0 | K19: =IF(K$5<=$E$12,1,0) -> 0 | L19: =IF(L$5<=$E$12,1,0) -> 0 | M19: =IF(M$5<=$E$12,1,0) -> 0 | ... S19: =IF(S$5<=$E$12,1,0) -> 0 | T19: Formula
B21: 2. Exchange rate
B22: Exchange rate USD/IDR (applied to capex, USD presentation) | C22: IDR/USD | D22: v29 | F22: 16265 | G22: 16265 | H22: 16265 | I22: 16265 | J22: 16265 | K22: 16265 | L22: 16265 | M22: 16265 | N22: 16265 | O22: 16265 | P22: 16265 | Q22: 16265 | R22: 16265 | S22: 16265 | T22: Calculation_FSL!F17 (USD_IDR = 16,265, single rate in v29) | U22: v29 uses one rate for all years; each year is independently editable here.
B23: Exchange rate of the valuation year (USD presentation of values) | C23: IDR/USD | D23: formula | E23: =INDEX($F$22:$S$22,MATCH($E$12,$F$15:$S$15,0)) -> 16265 | T23: Formula
B24: Exchange rate of the opening column (FY2023) — used for Dec-23 USD balances | C24: IDR/USD | D24: formula | E24: =INDEX($F$22:$S$22,1) -> 16265 | T24: Formula
B26: 3. Tax and working capital
B27: Corporate income tax rate | C27: % | D27: v29 | E27: 0.22 | T27: Output_Standalone (IDR)!J33 etc. (22% typed in each v29 tax formula) | U27: Applied per project line to MAX(0, EBIT) — v29 method, no loss relief between lines.
B28: Receivable days (on revenue) | C28: days | D28: v29 | E28: 45 | T28: Calculation_FSL!F1454 | U28: Applied to every project line (v29 applies it to company revenue; result identical).
B29: Payable days (on cost of sales) | C29: days | D29: v29 | E29: 30 | T29: Calculation_FSL!F1464
B30: Inventory balance (held at the Dec-23 level; centrally held, not allocated to projects) | C30: IDR bn | D30: v29 | E30: 0.519811 | T30: Output_FSL!I96 (BS_Historical!V10/1000) | U30: v29 holds this balance to FY2033 and drops it to nil from FY2034 through a formula break (Calculation_FSL!T1460:V1460); held flat here — see Reconciliation.
B32: 4. Model switches
B33: Depreciation method for project capex: 1 = v29 (total capex x share / life from commissioning, no end), 2 = by year of spend over the useful life from MAX(spend year, commissioning) | C33: 1/2 | D33: CONTROL | E33: 2 | T33: User request (capex % allocation linked to depreciation); v29 method retained as option 1 | U33: Method 2 links depreciation to the capex allocation and stops at the end of the useful life. Set 1 to reproduce v29 depreciation.
B34: Corporate LT-loan interest tax shield at company level: 1 = deductible at the tax rate, 0 = no shield | C34: 0/1 | D34: CONTROL | E34: 1 | T34: Modelling judgement (v29 charged the interest to the Cigading existing / Wharf 2 lines and taxed each line separately)
B35: Dividend policy: 1 = v29 rules (30% of attributable profit, limited by reserve and cash before new equity), 0 = no dividends | C35: 0/1 | D35: CONTROL | E35: 1 | T35: Calculation_FSL rows 1527-1557
B36: Operating case underlying the Funding Requirement roll-forward: 1 = Without BUMN (conservative), 2 = With BUMN | C36: 1/2 | D36: CONTROL | E36: 1 | T36: User instruction: show which BUMN case underlies the funding calculation
B37: Include Badas capex in the funding request while Badas is outside the valuation (1 = yes) | C37: 0/1 | D37: CONTROL | E37: 1 | T37: User instruction (separate funding-inclusion control) | U37: When Badas is inside the valuation its capex is already in the company statements and this control is ignored.
B38: Include Dec-23 other assets / other liabilities (held flat) in the equity bridge: 1 = yes, 0 = no | C38: 0/1 | D38: PROV | E38: 0 | T38: Modelling judgement — classification of these balances (deposits, deferred tax, accruals) not available
B40: 5. Valuation parameters (discount rate build-up, terminal value) — PROVISIONAL, not in v29
B41: IDR 10-year government bond yield | C41: % | D41: PROV | E41: 0.0701 | T41: Not in v29 — provisional market parameter
B42: Indonesia sovereign default spread (removed from the bond yield) | C42: % | D42: PROV | E42: 0.0162 | T42: Not in v29 — provisional
B43: Equity risk premium incl. country risk | C43: % | D43: PROV | E43: 0.0669 | T43: Not in v29 — provisional
B44: Unlevered beta (port / logistics infrastructure) | C44: x | D44: PROV | E44: 0.8 | T44: Not in v29 — provisional
B45: Target debt / (debt + equity) | C45: % | D45: PROV | E45: 0.2 | T45: Not in v29 — provisional
B46: Pre-tax cost of debt | C46: % | D46: PROV | E46: 0.105 | T46: Call Rights!H71 note '10%-11%' (IDR) — provisional
B47: Company-specific risk premium | C47: % | D47: PROV | E47: 0.01 | T47: Not in v29 — provisional
B48: Risk-free rate net of the sovereign spread | C48: % | D48: formula | E48: =$E$41-$E$42 -> 0.0539 | T48: Formula
B49: Target debt / equity | C49: x | D49: formula | E49: =$E$45/(1-$E$45) -> 0.25 | T49: Formula
B50: Relevered beta (Hamada) | C50: x | D50: formula | E50: =$E$44*(1+(1-$E$27)*$E$49) -> 0.956 | T50: Formula
B51: Cost of equity = rf + beta x ERP + specific premium | C51: % | D51: formula | E51: =$E$48+$E$50*$E$43+$E$47 -> 0.1278564 | T51: Formula
B52: After-tax cost of debt | C52: % | D52: formula | E52: =$E$46*(1-$E$27) -> 0.0819 | T52: Formula
B53: WACC (nominal IDR) | C53: % | D53: formula | E53: =(1-$E$45)*$E$51+$E$45*$E$52 -> 0.11866512 | T53: Formula | U53: Used by both valuation sheets and all project NPVs.
B54: Terminal growth rate after the last forecast year (nominal IDR) | C54: % | D54: PROV | E54: 0.03 | T54: Not in v29 — provisional
B55: Terminal-year normalised capex as a multiple of terminal-year depreciation (1.00 = capex replaces depreciation) | C55: x | D55: PROV | E55: 1 | T55: Not in v29 — provisional | U55: v29 forecasts no capex after FY2028; the terminal cash flow is normalised so that reinvestment sustains the asset base.
B57: 6. Opening balance sheet at 31-Dec-2023 (v29 Output_FSL column I) — company level; not allocated to projects
B58: Cash and equivalents | C58: IDR bn | D58: v29 | E58: 60.6389 | T58: Output_FSL!I88 (BS_Historical!V7/1000)
B59: Inventory | C59: IDR bn | D59: formula | E59: =$E$30 -> 0.519811 | T59: Output_FSL!I96
B60: Trade receivables (typed in v29; BS_Historical shows 104.1) | C60: IDR bn | D60: v29 | E60: 45 | T60: Output_FSL!I97 (typed value) | U60: Kept as v29; source issue — see Checks / Reconciliation.
B61: Fixed assets, net (existing businesses; not allocated by business) | C61: IDR bn | D61: v29 | E61: 826.022 | T61: Output_FSL!I98 (BS_Historical!V17/1000)
B62: Other assets as reported in v29 (includes assets under construction of Wharf 2 / conveyor) | C62: IDR bn | D62: v29 | E62: 331.263 | T62: Output_FSL!I99 (BS_Historical!V23/1000)
B63: Trade payables (typed in v29; BS_Historical shows 23.3) | C63: IDR bn | D63: v29 | E63: 14.671986 | T63: Output_FSL!I103 (typed value)
B64: Bank loans (LT loan 12 USD m + other loans) | C64: IDR bn | D64: v29 | E64: 224.518 | T64: Output_FSL!I104 (BS_Historical!V27/1000)
B65: Other liabilities (held flat) | C65: IDR bn | D65: v29 | E65: 55.9245 | T65: Output_FSL!I105 (= BS_Historical!V28/1000 - 65.83 + 15.32, a v29 plug) | U65: Source issue — see Checks.
B66: Paid-in capital | C66: IDR bn | D66: v29 | E66: 677.731 | T66: Output_FSL!I109 (BS_Historical!V32/1000)
B67: Retained earnings | C67: IDR bn | D67: v29 | E67: 290.592 | T67: Output_FSL!I111 (BS_Historical!V33/1000)
B68: Opening balance residual = assets - liabilities - equity (v29 source imbalance, not plugged) | C68: IDR bn | D68: formula | E68: =$E$58+$E$59+$E$60+$E$61+$E$62-$E$63-$E$64-$E$65-$E$66-$E$67 -> 0.0062250171 | T68: Formula | U68: v29 hides this 0.006 residual with ROUNDDOWN; shown explicitly here and tolerated in the balance check.
B70: 7. Financing, capital injection, cash and dividend policy
B71: Existing long-term loan — principal (USD m); v29 'FSL Loan Repayment' 12 USD m, shown as repaid in FY2025 but NOT repaid | C71: USD m | D71: v29 | E71: 12 | T71: Input!K1237 / Calculation_FSL!K1511
B72: Existing long-term loan — principal (IDR bn) at the opening exchange rate | C72: IDR bn | D72: formula | E72: =$E$71*$E$24/1000 -> 195.18 | T72: Calculation_FSL!K1513 (= 195.18)
B73: Other bank loans at Dec-23 = total loans - LT loan; repaid in FY2024 as in v29 | C73: IDR bn | D73: formula | E73: =$E$64-$E$72 -> 29.338 | T73: Calculation_FSL!J1516 (29.34 repaid FY2024)
B74: LT loan interest rate (p.a.) — implied by v29 FY2025 interest 15.27 / 195.18 | C74: % | D74: PROV | E74: 0.07825321 | T74: Derived: (Input!L388 + Input!L433) / Calculation_FSL!K1513 | U74: Loan terms (rate, currency, maturity) to be confirmed; v29 shows no maturity.
B75: FY2024 interest on all existing loans (v29 figure kept for the historical year) | C75: IDR bn | D75: v29 | E75: 5.4709055 | T75: Input!K388 -> Output_Standalone (IDR)!J125
B76: Capital injection — date proceeds are received (PROVISIONAL — confirm with the transaction timetable) | C76: date | D76: PROV | E76: 46568 | T76: User instruction: loan repaid when the injection is received; timing provisional | U76: Moving this date moves the loan repayment, the interest charge and the year in which equity is received.
B77: Capital injection — financial year of receipt | C77: year | D77: formula | E77: =YEAR($E$76) -> 2027 | T77: Formula
B78: Fraction of the injection year elapsed before receipt (interest accrues on the repaid amount for this fraction) | C78: % | D78: formula | E78: =(($E$76-DATE($E$77,1,1))+1)/(DATE($E$77,12,31)-DATE($E$77,1,1)+1) -> 0.49589041 | T78: Formula
B79: Capital injection amount: 1 = equal to the computed equity requirement (Funding Requirement), 2 = fixed amount below | C79: 1/2 | D79: CONTROL | E79: 1 | T79: User instruction: editable amount; mode 1 self-sizes to the funding gap
B80: Capital injection — fixed amount received (USD m), used only in mode 2 | C80: USD m | D80: CONTROL | E80: 0 | T80: User input | U80: Set mode = 2 to test a fixed amount (e.g. 0 to test that the loan is not extinguished without proceeds).
B81: Planned repayment of the LT loan out of the injection proceeds (% of the balance outstanding at the injection date) | C81: % | D81: UPDATED | E81: 1 | T81: Board deck Dec-2024 use of proceeds: LT loan repayment 12 USD m
B82: Minimum operating cash balance | C82: IDR bn | D82: v29 | E82: 3 | T82: Calculation_FSL!J1531 (-3.00, sign reversed)
B83: Dividend payout ratio (x profit attributable to FSL shareholders) | C83: % | D83: v29 | E83: 0.3 | T83: Calculation_FSL!F1550
B84: Capital base for the statutory reserve test (USD m) | C84: USD m | D84: v29 | E84: 18 | T84: Calculation_FSL!F1537 (18 USD m)
B85: Minimum reserve as % of the capital base | C85: % | D85: v29 | E85: 0.2 | T85: Calculation_FSL!F1538
B87: 8. Project register — inclusion in valuation, case membership, FSL economic interest (edit the blue cells)
B88: ID Project | C88: Entity | D88: Category | E88: In valuation (1/0) | F88: Case (1 both / 2 With-BUMN only) | G88: FSL econ. interest | H88: Commissioning year | I88: Total capex USD m | J88: Capex after val. date USD m | K88: Included w/o BUMN | L88: Included w/ BUMN | M88: Input | N88: Calc | O88: Output
B89: E1 Teluk Lamong (NPLOG) cargodoring & delivery | C89: NPLOG Teluk Lamong | D89: Existing business | E89: 1 | F89: 1 | G89: 0.65 | H89: existing | I89: 0 | J89: 0 | K89: =E89*IF(F89=1,1,0) -> 1 | L89: =E89 -> 1 | M89: open | N89: open | O89: open
B90: E2 Cigading Existing Terminal (SGT 2) | C90: SGT Cigading | D90: Existing business | E90: 1 | F90: 1 | G90: 1 | H90: existing | I90: 0 | J90: 0 | K90: =E90*IF(F90=1,1,0) -> 1 | L90: =E90 -> 1 | M90: open | N90: open | O90: open
B91: E3 Belawan terminal (SGT3) incl. Belawan expansion | C91: SGT Belawan | D91: Existing business | E91: 1 | F91: 1 | G91: 1 | H91: existing | I91: ='E3 Belawan Input'!$E$76 -> 14.024593 | J91: ='E3 Belawan Input'!$E$82 -> 7 | K91: =E91*IF(F91=1,1,0) -> 1 | L91: =E91 -> 1 | M91: open | N91: open | O91: open
B92: E4 WIN stevedoring (Cilegon, Makassar, Surabaya, Medan) | C92: WIN | D92: Existing business | E92: 1 | F92: 1 | G92: 1 | H92: existing | I92: 0 | J92: 0 | K92: =E92*IF(F92=1,1,0) -> 1 | L92: =E92 -> 1 | M92: open | N92: open | O92: open
B93: P01 Cigading Wharf 2 | C93: SGT Cigading | D93: Committed project | E93: 1 | F93: 1 | G93: 1 | H93: ='P01 CigWharf2 Input'!$E$25 -> 2025 | I93: ='P01 CigWharf2 Input'!$E$36 -> 12.8 | J93: ='P01 CigWharf2 Input'!$E$42 -> 0 | K93: =E93*IF(F93=1,1,0) -> 1 | L93: =E93 -> 1 | M93: open | N93: open | O93: open
B94: P02 Cigading Extended Conveyor | C94: SGT Cigading | D94: Committed project | E94: 1 | F94: 1 | G94: 1 | H94: ='P02 CigConveyor Input'!$E$25 -> 2025 | I94: ='P02 CigConveyor Input'!$E$36 -> 8 | J94: ='P02 CigConveyor Input'!$E$42 -> 0 | K94: =E94*IF(F94=1,1,0) -> 1 | L94: =E94 -> 1 | M94: open | N94: open | O94: open
B95: P03 KBS Warehouse Revitalisation (Cigading) | C95: SGT Cigading / KBS | D95: Planned project | E95: 1 | F95: 1 | G95: 1 | H95: ='P03 KBSWarehouse Input'!$E$25 -> 2027 | I95: ='P03 KBSWarehouse Input'!$E$40 -> 6.02459 | J95: ='P03 KBSWarehouse Input'!$E$46 -> 0 | K95: =E95*IF(F95=1,1,0) -> 1 | L95: =E95 -> 1 | M95: open | N95: open | O95: open
B96: P04 Teluk Lamong Silo | C96: NPLOG Teluk Lamong | D96: Planned project | E96: 1 | F96: 1 | G96: 1 | H96: ='P04 TTLSilo Input'!$E$25 -> 2027 | I96: ='P04 TTLSilo Input'!$E$39 -> 3.7623 | J96: ='P04 TTLSilo Input'!$E$45 -> 0 | K96: =E96*IF(F96=1,1,0) -> 1 | L96: =E96 -> 1 | M96: open | N96: open | O96: open
B97: P05 Dumai bagging & weighbridge | C97: FSL Dumai | D97: Planned project | E97: 1 | F97: 1 | G97: 1 | H97: ='P05 Dumai Input'!$E$25 -> 2026 | I97: ='P05 Dumai Input'!$E$39 -> 6.8095238 | J97: ='P05 Dumai Input'!$E$45 -> 0.325 | K97: =E97*IF(F97=1,1,0) -> 1 | L97: =E97 -> 1 | M97: open | N97: open | O97: open
B98: P06 Ciwandan Expansion | C98: FSL Ciwandan | D98: Planned project | E98: 1 | F98: 1 | G98: 1 | H98: ='P06 Ciwandan Input'!$E$25 -> 2028 | I98: ='P06 Ciwandan Input'!$E$33 -> 5.0245927 | J98: ='P06 Ciwandan Input'!$E$39 -> 2.5122963 | K98: =E98*IF(F98=1,1,0) -> 1 | L98: =E98 -> 1 | M98: open | N98: open | O98: open
B99: P08 DMS trucking fee (Teluk Lamong, Cigading, Ciwandan, Belawan) | C99: DMS trucking | D99: Planned project | E99: 1 | F99: 1 | G99: 1 | H99: ='P08 DMSTrucking Input'!$E$25 -> 2027 | I99: 0 | J99: 0 | K99: =E99*IF(F99=1,1,0) -> 1 | L99: =E99 -> 1 | M99: open | N99: open | O99: open
B100: P12 BUMN operatorship schemes (Pelindo Teluk Lamong, KBS Cigading, Pelindo Belawan) | C100: FSL / Pelindo / KBS | D100: BUMN synergy | E100: 1 | F100: 2 | G100: 1 | H100: ='P12 BUMNOps Input'!$E$25 -> 2026 | I100: 0 | J100: 0 | K100: =E100*IF(F100=1,1,0) -> 0 | L100: =E100 -> 1 | M100: open | N100: open | O100: open
B101: P15 TBM — Tanjung Batu / Pelindo land lease, warehousing and cargo handling | C101: TBM (pipeline) | D101: Pipeline (excluded by default) | E101: 0 | F101: 1 | G101: 1 | H101: ='P15 TBM Input'!$E$25 -> 2027 | I101: ='P15 TBM Input'!$E$53 -> 40.024593 | J101: ='P15 TBM Input'!$E$59 -> 0 | K101: =E101*IF(F101=1,1,0) -> 0 | L101: =E101 -> 0 | M101: open | N101: open | O101: open
B102: P19 Badas bulk terminal (FS pending — DUMMY data) | C102: Badas (new) | D102: Pipeline — FS pending (DUMMY inputs, excluded from headline valuation) | E102: 0 | F102: 1 | G102: 1 | H102: ='P19 Badas FS Working Paper'!$E$25 -> 2029 | I102: ='P19 Badas FS Working Paper'!$E$57 -> 10 | J102: ='P19 Badas FS Working Paper'!$E$63 -> 10 | K102: =E102*IF(F102=1,1,0) -> 0 | L102: =E102 -> 0 | M102: open | N102: open | O102: open
B103: Case 1 = the project is in both company cases; case 2 = only in the With-BUMN case (BUMN operatorship schemes). 'In valuation' = 0 removes the project from both cases, the funding roll-forward and the valuations (its sheets keep calculating for information).
B105: 9. Allocation bases (formulas) — Dec-23 company receivables / payables allocated to existing businesses pro rata FY2024 activity; assets under construction reclassified
B106: FY2024 revenue of existing businesses (sum) | C106: IDR bn | D106: formula | E106: ='E1 TelukLamong Calc'!$G$23+'E2 CigadingExist Calc'!$G$17+'E3 Belawan Calc'!$G$19+'E4 WIN Calc'!$G$193 -> 305.28841
B107: FY2024 cost of sales of existing businesses (sum) | C107: IDR bn | D107: formula | E107: ='E1 TelukLamong Calc'!$G$55+'E2 CigadingExist Calc'!$G$51+'E3 Belawan Calc'!$G$53+'E4 WIN Calc'!$G$194 -> 122.54304
B108: Pre-2024 project capex (assets under construction at Dec-23) reclassified from other assets to project fixed assets | C108: IDR bn | D108: formula | E108: ='E3 Belawan Calc'!$F$83+'P01 CigWharf2 Calc'!$F$35+'P02 CigConveyor Calc'!$F$30+'P03 KBSWarehouse Calc'!$F$30+'P04 TTLSilo Calc'!$F$36+'P05 Dumai Calc'!$F$40+'P06 Ciwandan Calc'!$F$34+'P15 TBM Calc'!$F$57+'P19 Badas Calculation'!$F$48 -> 198.433
B109: Other assets at Dec-23 excluding the reclassified assets under construction | C109: IDR bn | D109: formula | E109: =$E$62-$E$108 -> 132.83
B111: Legend — input classification (column D)
...

Sheet Project Summary
B1: PROJECT SUMMARY — project-by-project results (concept of v29 Output_Standalone)
B2: Each section links to the project's Output sheet; the comparison table gives the headline numbers side by side. IDR bn unless stated.
B3: Go to: | C3: Navigation | D3: Global Inputs | E3: Project Summary | F3: Funding | G3: FSL w/o BUMN | H3: FSL w/ BUMN | I3: Val w/o BUMN | J3: Val w/ BUMN | K3: Checks | L3: Model Flow
B5: Year | C5: Unit | D5: Type | E5: Value / total | F5: ='Global Inputs'!F$5 -> 2023 | G5: ='Global Inputs'!G$5 -> 2024 | H5: ='Global Inputs'!H$5 -> 2025 | I5: ='Global Inputs'!I$5 -> 2026 | J5: ='Global Inputs'!J$5 -> 2027 | K5: ='Global Inputs'!K$5 -> 2028 | L5: ='Global Inputs'!L$5 -> 2029 | M5: ='Global Inputs'!M$5 -> 2030 | ... S5: ='Global Inputs'!S$5 -> 2036 | T5: Source (v29 reference / basis) | U5: Note
B6: Period end | F6: ='Global Inputs'!F$6 -> 45291 | G6: ='Global Inputs'!G$6 -> 45657 | H6: ='Global Inputs'!H$6 -> 46022 | I6: ='Global Inputs'!I$6 -> 46387 | J6: ='Global Inputs'!J$6 -> 46752 | K6: ='Global Inputs'!K$6 -> 47118 | L6: ='Global Inputs'!L$6 -> 47483 | M6: ='Global Inputs'!M$6 -> 47848 | ... S6: ='Global Inputs'!S$6 -> 50040
B7: Days in year | F7: ='Global Inputs'!F$7 -> 365 | G7: ='Global Inputs'!G$7 -> 366 | H7: ='Global Inputs'!H$7 -> 365 | I7: ='Global Inputs'!I$7 -> 365 | J7: ='Global Inputs'!J$7 -> 365 | K7: ='Global Inputs'!K$7 -> 366 | L7: ='Global Inputs'!L$7 -> 365 | M7: ='Global Inputs'!M$7 -> 365 | ... S7: ='Global Inputs'!S$7 -> 366
B8: Forecast flag (1 = forecast year) | F8: ='Global Inputs'!F$8 -> 0 | G8: ='Global Inputs'!G$8 -> 1 | H8: ='Global Inputs'!H$8 -> 1 | I8: ='Global Inputs'!I$8 -> 1 | J8: ='Global Inputs'!J$8 -> 1 | K8: ='Global Inputs'!K$8 -> 1 | L8: ='Global Inputs'!L$8 -> 1 | M8: ='Global Inputs'!M$8 -> 1 | ... S8: ='Global Inputs'!S$8 -> 1
B10: A. Comparison table — all projects (links to the project Output sheets; values in IDR bn unless stated)
B11: Project | C11: Category | D11: In val. | E11: Case | F11: FSL int. | G11: Start yr | H11: Capex USD m | I11: Capex post-val USD m | J11: Revenue 2027 | K11: Revenue 2030 | L11: EBITDA 2030 | M11: NPV @ 31-Dec-26 | N11: IRR full life | O11: Payback yr | P11: Input | Q11: Calc | R11: Output
B12: E1 Teluk Lamong (NPLOG) cargodoring & delivery | C12: Existing business | D12: ='Global Inputs'!$E$89 -> 1 | E12: ='Global Inputs'!$F$89 -> 1 | F12: ='Global Inputs'!$G$89 -> 0.65 | G12: ="existing" -> existing | H12: =0 -> 0 | I12: =0 -> 0 | J12: ='E1 TelukLamong Output'!$J$11 -> 170.94433 | K12: ='E1 TelukLamong Output'!$M$11 -> 192.39935 | L12: ='E1 TelukLamong Output'!$M$15 -> 136.39274 | M12: ='E1 TelukLamong Output'!$E$48 -> 1190.2163 | N12: =IF(ISNUMBER('E1 TelukLamong Output'!$E$50),'E1 TelukLamong Output'!$E$50,"n/a") -> n/a | O12: =IF(ISNUMBER('E1 TelukLamong Output'!$E$53),'E1 TelukLamong Output'!$E$53,"n/a") -> n/a | P12: open | Q12: open | R12: open
B13: E2 Cigading Existing Terminal (SGT 2) | C13: Existing business | D13: ='Global Inputs'!$E$90 -> 1 | E13: ='Global Inputs'!$F$90 -> 1 | F13: ='Global Inputs'!$G$90 -> 1 | G13: ="existing" -> existing | H13: =0 -> 0 | I13: =0 -> 0 | J13: ='E2 CigadingExist Output'!$J$11 -> 59.057611 | K13: ='E2 CigadingExist Output'!$M$11 -> 70.987231 | L13: ='E2 CigadingExist Output'!$M$15 -> 42.844418 | M13: ='E2 CigadingExist Output'!$E$48 -> 461.15059 | N13: =IF(ISNUMBER('E2 CigadingExist Output'!$E$50),'E2 CigadingExist Output'!$E$50,"n/a") -> n/a | O13: =IF(ISNUMBER('E2 CigadingExist Output'!$E$53),'E2 CigadingExist Output'!$E$53,"n/a") -> n/a | P13: open | Q13: open | R13: open
B14: E3 Belawan terminal (SGT3) incl. Belawan expansion | C14: Existing business | D14: ='Global Inputs'!$E$91 -> 1 | E14: ='Global Inputs'!$F$91 -> 1 | F14: ='Global Inputs'!$G$91 -> 1 | G14: ="existing" -> existing | H14: ='E3 Belawan Input'!$E$76 -> 14.024593 | I14: ='E3 Belawan Input'!$E$82 -> 7 | J14: ='E3 Belawan Output'!$J$11 -> 44.806465 | K14: ='E3 Belawan Output'!$M$11 -> 59.814057 | L14: ='E3 Belawan Output'!$M$15 -> 43.579698 | M14: ='E3 Belawan Output'!$E$48 -> 237.96397 | N14: =IF(ISNUMBER('E3 Belawan Output'!$E$50),'E3 Belawan Output'!$E$50,"n/a") -> n/a | O14: =IF(ISNUMBER('E3 Belawan Output'!$E$53),'E3 Belawan Output'!$E$53,"n/a") -> 2032 | P14: open | Q14: open | R14: open
B15: E4 WIN stevedoring (Cilegon, Makassar, Surabaya, Medan) | C15: Existing business | D15: ='Global Inputs'!$E$92 -> 1 | E15: ='Global Inputs'!$F$92 -> 1 | F15: ='Global Inputs'!$G$92 -> 1 | G15: ="existing" -> existing | H15: =0 -> 0 | I15: =0 -> 0 | J15: ='E4 WIN Output'!$J$11 -> 66.857705 | K15: ='E4 WIN Output'!$M$11 -> 83.887124 | L15: ='E4 WIN Output'!$M$15 -> 24.471909 | M15: ='E4 WIN Output'!$E$48 -> 213.66342 | N15: =IF(ISNUMBER('E4 WIN Output'!$E$50),'E4 WIN Output'!$E$50,"n/a") -> n/a | O15: =IF(ISNUMBER('E4 WIN Output'!$E$53),'E4 WIN Output'!$E$53,"n/a") -> n/a | P15: open | Q15: open | R15: open
B16: P01 Cigading Wharf 2 | C16: Committed project | D16: ='Global Inputs'!$E$93 -> 1 | E16: ='Global Inputs'!$F$93 -> 1 | F16: ='Global Inputs'!$G$93 -> 1 | G16: ='P01 CigWharf2 Input'!$E$25 -> 2025 | H16: ='P01 CigWharf2 Input'!$E$36 -> 12.8 | I16: ='P01 CigWharf2 Input'!$E$42 -> 0 | J16: ='P01 CigWharf2 Output'!$J$11 -> 127.70547 | K16: ='P01 CigWharf2 Output'!$M$11 -> 153.50193 | L16: ='P01 CigWharf2 Output'!$M$15 -> 110.37226 | M16: ='P01 CigWharf2 Output'!$E$47 -> 960.01466 | N16: =IF(ISNUMBER('P01 CigWharf2 Output'!$E$49),'P01 CigWharf2 Output'!$E$49,"n/a") -> 0.27587356 | O16: =IF(ISNUMBER('P01 CigWharf2 Output'!$E$52),'P01 CigWharf2 Output'!$E$52,"n/a") -> 2028 | P16: open | Q16: open | R16: open
B17: P02 Cigading Extended Conveyor | C17: Committed project | D17: ='Global Inputs'!$E$94 -> 1 | E17: ='Global Inputs'!$F$94 -> 1 | F17: ='Global Inputs'!$G$94 -> 1 | G17: ='P02 CigConveyor Input'!$E$25 -> 2025 | H17: ='P02 CigConveyor Input'!$E$36 -> 8 | I17: ='P02 CigConveyor Input'!$E$42 -> 0 | J17: ='P02 CigConveyor Output'!$J$11 -> 33.41835 | K17: ='P02 CigConveyor Output'!$M$11 -> 36.517133 | L17: ='P02 CigConveyor Output'!$M$15 -> 33.479033 | M17: ='P02 CigConveyor Output'!$E$47 -> 280.51826 | N17: =IF(ISNUMBER('P02 CigConveyor Output'!$E$49),'P02 CigConveyor Output'!$E$49,"n/a") -> 0.16210365 | O17: =IF(ISNUMBER('P02 CigConveyor Output'!$E$52),'P02 CigConveyor Output'!$E$52,"n/a") -> 2030 | P17: open | Q17: open | R17: open
B18: P03 KBS Warehouse Revitalisation (Cigading) | C18: Planned project | D18: ='Global Inputs'!$E$95 -> 1 | E18: ='Global Inputs'!$F$95 -> 1 | F18: ='Global Inputs'!$G$95 -> 1 | G18: ='P03 KBSWarehouse Input'!$E$25 -> 2027 | H18: ='P03 KBSWarehouse Input'!$E$40 -> 6.02459 | I18: ='P03 KBSWarehouse Input'!$E$46 -> 0 | J18: ='P03 KBSWarehouse Output'!$J$11 -> 53.023782 | K18: ='P03 KBSWarehouse Output'!$M$11 -> 57.940518 | L18: ='P03 KBSWarehouse Output'!$M$15 -> 23.176207 | M18: ='P03 KBSWarehouse Output'!$E$47 -> 189.57925 | N18: =IF(ISNUMBER('P03 KBSWarehouse Output'!$E$49),'P03 KBSWarehouse Output'!$E$49,"n/a") -> 0.13347383 | O18: =IF(ISNUMBER('P03 KBSWarehouse Output'!$E$52),'P03 KBSWarehouse Output'!$E$52,"n/a") -> 2032 | P18: open | Q18: open | R18: open
B19: P04 Teluk Lamong Silo | C19: Planned project | D19: ='Global Inputs'!$E$96 -> 1 | E19: ='Global Inputs'!$F$96 -> 1 | F19: ='Global Inputs'!$G$96 -> 1 | G19: ='P04 TTLSilo Input'!$E$25 -> 2027 | H19: ='P04 TTLSilo Input'!$E$39 -> 3.7623 | I19: ='P04 TTLSilo Input'!$E$45 -> 0 | J19: ='P04 TTLSilo Output'!$J$11 -> 13.26 | K19: ='P04 TTLSilo Output'!$M$11 -> 13.26 | L19: ='P04 TTLSilo Output'!$M$15 -> 13.1988 | M19: ='P04 TTLSilo Output'!$E$47 -> 104.74445 | N19: =IF(ISNUMBER('P04 TTLSilo Output'!$E$49),'P04 TTLSilo Output'!$E$49,"n/a") -> 0.12284866 | O19: =IF(ISNUMBER('P04 TTLSilo Output'!$E$52),'P04 TTLSilo Output'!$E$52,"n/a") -> 2032 | P19: open | Q19: open | R19: open
B20: P05 Dumai bagging & weighbridge | C20: Planned project | D20: ='Global Inputs'!$E$97 -> 1 | E20: ='Global Inputs'!$F$97 -> 1 | F20: ='Global Inputs'!$G$97 -> 1 | G20: ='P05 Dumai Input'!$E$25 -> 2026 | H20: ='P05 Dumai Input'!$E$39 -> 6.8095238 | I20: ='P05 Dumai Input'!$E$45 -> 0.325 | J20: ='P05 Dumai Output'!$J$11 -> 48.1 | K20: ='P05 Dumai Output'!$M$11 -> 51.4176 | L20: ='P05 Dumai Output'!$M$15 -> 26.051324 | M20: ='P05 Dumai Output'!$E$47 -> 197.60397 | N20: =IF(ISNUMBER('P05 Dumai Output'!$E$49),'P05 Dumai Output'!$E$49,"n/a") -> 0.1925954 | O20: =IF(ISNUMBER('P05 Dumai Output'!$E$52),'P05 Dumai Output'!$E$52,"n/a") -> 2031 | P20: open | Q20: open | R20: open
B21: P06 Ciwandan Expansion | C21: Planned project | D21: ='Global Inputs'!$E$98 -> 1 | E21: ='Global Inputs'!$F$98 -> 1 | F21: ='Global Inputs'!$G$98 -> 1 | G21: ='P06 Ciwandan Input'!$E$25 -> 2028 | H21: ='P06 Ciwandan Input'!$E$33 -> 5.0245927 | I21: ='P06 Ciwandan Input'!$E$39 -> 2.5122963 | J21: ='P06 Ciwandan Output'!$J$11 -> 0 | K21: ='P06 Ciwandan Output'!$M$11 -> 84.590383 | L21: ='P06 Ciwandan Output'!$M$15 -> 50.88063 | M21: ='P06 Ciwandan Output'!$E$47 -> 475.82384 | N21: =IF(ISNUMBER('P06 Ciwandan Output'!$E$49),'P06 Ciwandan Output'!$E$49,"n/a") -> 0.38580025 | O21: =IF(ISNUMBER('P06 Ciwandan Output'!$E$52),'P06 Ciwandan Output'!$E$52,"n/a") -> 2030 | P21: open | Q21: open | R21: open
B22: P08 DMS trucking fee (Teluk Lamong, Cigading, Ciwandan, Belawan) | C22: Planned project | D22: ='Global Inputs'!$E$99 -> 1 | E22: ='Global Inputs'!$F$99 -> 1 | F22: ='Global Inputs'!$G$99 -> 1 | G22: ='P08 DMSTrucking Input'!$E$25 -> 2027 | H22: =0 -> 0 | I22: =0 -> 0 | J22: ='P08 DMSTrucking Output'!$J$11 -> 2.7523996 | K22: ='P08 DMSTrucking Output'!$M$11 -> 3.5746249 | L22: ='P08 DMSTrucking Output'!$M$15 -> 2.8596999 | M22: ='P08 DMSTrucking Output'!$E$47 -> 23.736572 | N22: =IF(ISNUMBER('P08 DMSTrucking Output'!$E$49),'P08 DMSTrucking Output'!$E$49,"n/a") -> n/a | O22: =IF(ISNUMBER('P08 DMSTrucking Output'!$E$52),'P08 DMSTrucking Output'!$E$52,"n/a") -> n/a | P22: open | Q22: open | R22: open
B23: P12 BUMN operatorship schemes (Pelindo Teluk Lamong, KBS Cigading, Pelindo Belawan) | C23: BUMN synergy | D23: ='Global Inputs'!$E$100 -> 1 | E23: ='Global Inputs'!$F$100 -> 2 | F23: ='Global Inputs'!$G$100 -> 1 | G23: ='P12 BUMNOps Input'!$E$25 -> 2026 | H23: =0 -> 0 | I23: =0 -> 0 | J23: ='P12 BUMNOps Output'!$J$11 -> 134.53638 | K23: ='P12 BUMNOps Output'!$M$11 -> 149.12654 | L23: ='P12 BUMNOps Output'!$M$15 -> 68.059001 | M23: ='P12 BUMNOps Output'!$E$47 -> 532.3041 | N23: =IF(ISNUMBER('P12 BUMNOps Output'!$E$49),'P12 BUMNOps Output'!$E$49,"n/a") -> n/a | O23: =IF(ISNUMBER('P12 BUMNOps Output'!$E$52),'P12 BUMNOps Output'!$E$52,"n/a") -> n/a | P23: open | Q23: open | R23: open
B24: P15 TBM — Tanjung Batu / Pelindo land lease, warehousing and cargo handling | C24: Pipeline (excluded by default) | D24: ='Global Inputs'!$E$101 -> 0 | E24: ='Global Inputs'!$F$101 -> 1 | F24: ='Global Inputs'!$G$101 -> 1 | G24: ='P15 TBM Input'!$E$25 -> 2027 | H24: ='P15 TBM Input'!$E$53 -> 40.024593 | I24: ='P15 TBM Input'!$E$59 -> 0 | J24: ='P15 TBM Output'!$J$11 -> 0 | K24: ='P15 TBM Output'!$M$11 -> 374.7552 | L24: ='P15 TBM Output'!$M$15 -> 199.11267 | M24: ='P15 TBM Output'!$E$47 -> 1325.7316 | N24: =IF(ISNUMBER('P15 TBM Output'!$E$49),'P15 TBM Output'!$E$49,"n/a") -> 0.095422425 | O24: =IF(ISNUMBER('P15 TBM Output'!$E$52),'P15 TBM Output'!$E$52,"n/a") -> 2033 | P24: open | Q24: open | R24: open
B25: P19 Badas bulk terminal (FS pending — DUMMY data) | C25: Pipeline — FS pending (DUMMY inputs, excluded from headline valuation) | D25: ='Global Inputs'!$E$102 -> 0 | E25: ='Global Inputs'!$F$102 -> 1 | F25: ='Global Inputs'!$G$102 -> 1 | G25: ='P19 Badas FS Working Paper'!$E$25 -> 2029 | H25: ='P19 Badas FS Working Paper'!$E$57 -> 10 | I25: ='P19 Badas FS Working Paper'!$E$63 -> 10 | J25: ='P19 Badas Output'!$J$11 -> 0 | K25: ='P19 Badas Output'!$M$11 -> 37.96065 | L25: ='P19 Badas Output'!$M$15 -> 18.243868 | M25: ='P19 Badas Output'!$E$47 -> 35.230684 | N25: =IF(ISNUMBER('P19 Badas Output'!$E$49),'P19 Badas Output'!$E$49,"n/a") -> 0.0036863533 | O25: =IF(ISNUMBER('P19 Badas Output'!$E$52),'P19 Badas Output'!$E$52,"n/a") -> 2036 | P25: open | Q25: open | R25: open
B26: Total (all projects listed, before case flags) | H26: =SUM(H12:H25) -> 106.47019 | I26: =SUM(I12:I25) -> 19.837296 | J26: =SUM(J12:J25) -> 754.46249 | K26: =SUM(K12:K25) -> 1369.7323 | L26: =SUM(L12:L25) -> 792.72226 | M26: =SUM(M12:M25) -> 6228.2816
B28: B. Bridge: sum of project outputs -> company statements (both cases; IDR bn)
B29: Sum of project revenue x Without-BUMN flags | C29: IDR bn | F29: ='E1 TelukLamong Output'!F11*'Global Inputs'!$K$89+'E2 CigadingExist Output'!F11*'Global Inputs'!$K$90+'E3 Belawan Output'!F11*'Global Inputs'!$K$91+'E4 WIN Output'!F11*'Global Inputs'!$K$92+'P01 CigWharf2 Output'!F11*'Global Inputs'!$K$93+'P02 CigConveyor Output'!F11*'Global Inputs'!$K$94+'P03 KBSWarehouse Output'!F11*'Global Inputs'!$K$95+'P04 TTLSilo Output'!F11*'Global Inputs'!$K$96+'P05 Dumai Output'!F11*'Global Inputs'!$K$97+'P06 Ciwandan Output'!F11*'Global Inputs'!$K$98+'P08 DMSTrucking Output'!F11*'Global Inputs'!$K$99+'P12 BUMNOps Output'!F11*'Global Inputs'!$K$100+'P15 TBM Output'!F11*'Global Inputs'!$K$101+'P19 Badas Output'!F11*'Global Inputs'!$K$102 -> 0 | G29: ='E1 TelukLamong Output'!G11*'Global Inputs'!$K$89+'E2 CigadingExist Output'!G11*'Global Inputs'!$K$90+'E3 Belawan Output'!G11*'Global Inputs'!$K$91+'E4 WIN Output'!G11*'Global Inputs'!$K$92+'P01 CigWharf2 Output'!G11*'Global Inputs'!$K$93+'P02 CigConveyor Output'!G11*'Global Inputs'!$K$94+'P03 KBSWarehouse Output'!G11*'Global Inputs'!$K$95+'P04 TTLSilo Output'!G11*'Global Inputs'!$K$96+'P05 Dumai Output'!G11*'Global Inputs'!$K$97+'P06 Ciwandan Output'!G11*'Global Inputs'!$K$98+'P08 DMSTrucking Output'!G11*'Global Inputs'!$K$99+'P12 BUMNOps Output'!G11*'Global Inputs'!$K$100+'P15 TBM Output'!G11*'Global Inputs'!$K$101+'P19 Badas Output'!G11*'Global Inputs'!$K$102 -> 305.28841 | H29: ='E1 TelukLamong Output'!H11*'Global Inputs'!$K$89+'E2 CigadingExist Output'!H11*'Global Inputs'!$K$90+'E3 Belawan Output'!H11*'Global Inputs'!$K$91+'E4 WIN Output'!H11*'Global Inputs'!$K$92+'P01 CigWharf2 Output'!H11*'Global Inputs'!$K$93+'P02 CigConveyor Output'!H11*'Global Inputs'!$K$94+'P03 KBSWarehouse Output'!H11*'Global Inputs'!$K$95+'P04 TTLSilo Output'!H11*'Global Inputs'!$K$96+'P05 Dumai Output'!H11*'Global Inputs'!$K$97+'P06 Ciwandan Output'!H11*'Global Inputs'!$K$98+'P08 DMSTrucking Output'!H11*'Global Inputs'!$K$99+'P12 BUMNOps Output'!H11*'Global Inputs'!$K$100+'P15 TBM Output'!H11*'Global Inputs'!$K$101+'P19 Badas Output'!H11*'Global Inputs'!$K$102 -> 427.60264 | I29: ='E1 TelukLamong Output'!I11*'Global Inputs'!$K$89+'E2 CigadingExist Output'!I11*'Global Inputs'!$K$90+'E3 Belawan Output'!I11*'Global Inputs'!$K$91+'E4 WIN Output'!I11*'Global Inputs'!$K$92+'P01 CigWharf2 Output'!I11*'Global Inputs'!$K$93+'P02 CigConveyor Output'!I11*'Global Inputs'!$K$94+'P03 KBSWarehouse Output'!I11*'Global Inputs'!$K$95+'P04 TTLSilo Output'!I11*'Global Inputs'!$K$96+'P05 Dumai Output'!I11*'Global Inputs'!$K$97+'P06 Ciwandan Output'!I11*'Global Inputs'!$K$98+'P08 DMSTrucking Output'!I11*'Global Inputs'!$K$99+'P12 BUMNOps Output'!I11*'Global Inputs'!$K$100+'P15 TBM Output'!I11*'Global Inputs'!$K$101+'P19 Badas Output'!I11*'Global Inputs'!$K$102 -> 494.57084 | J29: ='E1 TelukLamong Output'!J11*'Global Inputs'!$K$89+'E2 CigadingExist Output'!J11*'Global Inputs'!$K$90+'E3 Belawan Output'!J11*'Global Inputs'!$K$91+'E4 WIN Output'!J11*'Global Inputs'!$K$92+'P01 CigWharf2 Output'!J11*'Global Inputs'!$K$93+'P02 CigConveyor Output'!J11*'Global Inputs'!$K$94+'P03 KBSWarehouse Output'!J11*'Global Inputs'!$K$95+'P04 TTLSilo Output'!J11*'Global Inputs'!$K$96+'P05 Dumai Output'!J11*'Global Inputs'!$K$97+'P06 Ciwandan Output'!J11*'Global Inputs'!$K$98+'P08 DMSTrucking Output'!J11*'Global Inputs'!$K$99+'P12 BUMNOps Output'!J11*'Global Inputs'!$K$100+'P15 TBM Output'!J11*'Global Inputs'!$K$101+'P19 Badas Output'!J11*'Global Inputs'!$K$102 -> 619.92611 | K29: ='E1 TelukLamong Output'!K11*'Global Inputs'!$K$89+'E2 CigadingExist Output'!K11*'Global Inputs'!$K$90+'E3 Belawan Output'!K11*'Global Inputs'!$K$91+'E4 WIN Output'!K11*'Global Inputs'!$K$92+'P01 CigWharf2 Output'!K11*'Global Inputs'!$K$93+'P02 CigConveyor Output'!K11*'Global Inputs'!$K$94+'P03 KBSWarehouse Output'!K11*'Global Inputs'!$K$95+'P04 TTLSilo Output'!K11*'Global Inputs'!$K$96+'P05 Dumai Output'!K11*'Global Inputs'!$K$97+'P06 Ciwandan Output'!K11*'Global Inputs'!$K$98+'P08 DMSTrucking Output'!K11*'Global Inputs'!$K$99+'P12 BUMNOps Output'!K11*'Global Inputs'!$K$100+'P15 TBM Output'!K11*'Global Inputs'!$K$101+'P19 Badas Output'!K11*'Global Inputs'!$K$102 -> 702.02883 | L29: ='E1 TelukLamong Output'!L11*'Global Inputs'!$K$89+'E2 CigadingExist Output'!L11*'Global Inputs'!$K$90+'E3 Belawan Output'!L11*'Global Inputs'!$K$91+'E4 WIN Output'!L11*'Global Inputs'!$K$92+'P01 CigWharf2 Output'!L11*'Global Inputs'!$K$93+'P02 CigConveyor Output'!L11*'Global Inputs'!$K$94+'P03 KBSWarehouse Output'!L11*'Global Inputs'!$K$95+'P04 TTLSilo Output'!L11*'Global Inputs'!$K$96+'P05 Dumai Output'!L11*'Global Inputs'!$K$97+'P06 Ciwandan Output'!L11*'Global Inputs'!$K$98+'P08 DMSTrucking Output'!L11*'Global Inputs'!$K$99+'P12 BUMNOps Output'!L11*'Global Inputs'!$K$100+'P15 TBM Output'!L11*'Global Inputs'!$K$101+'P19 Badas Output'!L11*'Global Inputs'!$K$102 -> 773.76406 | M29: ='E1 TelukLamong Output'!M11*'Global Inputs'!$K$89+'E2 CigadingExist Output'!M11*'Global Inputs'!$K$90+'E3 Belawan Output'!M11*'Global Inputs'!$K$91+'E4 WIN Output'!M11*'Global Inputs'!$K$92+'P01 CigWharf2 Output'!M11*'Global Inputs'!$K$93+'P02 CigConveyor Output'!M11*'Global Inputs'!$K$94+'P03 KBSWarehouse Output'!M11*'Global Inputs'!$K$95+'P04 TTLSilo Output'!M11*'Global Inputs'!$K$96+'P05 Dumai Output'!M11*'Global Inputs'!$K$97+'P06 Ciwandan Output'!M11*'Global Inputs'!$K$98+'P08 DMSTrucking Output'!M11*'Global Inputs'!$K$99+'P12 BUMNOps Output'!M11*'Global Inputs'!$K$100+'P15 TBM Output'!M11*'Global Inputs'!$K$101+'P19 Badas Output'!M11*'Global Inputs'!$K$102 -> 807.88996 | ... S29: ='E1 TelukLamong Output'!S11*'Global Inputs'!$K$89+'E2 CigadingExist Output'!S11*'Global Inputs'!$K$90+'E3 Belawan Output'!S11*'Global Inputs'!$K$91+'E4 WIN Output'!S11*'Global Inputs'!$K$92+'P01 CigWharf2 Output'!S11*'Global Inputs'!$K$93+'P02 CigConveyor Output'!S11*'Global Inputs'!$K$94+'P03 KBSWarehouse Output'!S11*'Global Inputs'!$K$95+'P04 TTLSilo Output'!S11*'Global Inputs'!$K$96+'P05 Dumai Output'!S11*'Global Inputs'!$K$97+'P06 Ciwandan Output'!S11*'Global Inputs'!$K$98+'P08 DMSTrucking Output'!S11*'Global Inputs'!$K$99+'P12 BUMNOps Output'!S11*'Global Inputs'!$K$100+'P15 TBM Output'!S11*'Global Inputs'!$K$101+'P19 Badas Output'!S11*'Global Inputs'!$K$102 -> 1040.9483
B30: FSL Financials — Without BUMN revenue | C30: IDR bn | F30: ='FSL Financials — Without BUMN'!F18 -> 0 | G30: ='FSL Financials — Without BUMN'!G18 -> 305.28841 | H30: ='FSL Financials — Without BUMN'!H18 -> 427.60264 | I30: ='FSL Financials — Without BUMN'!I18 -> 494.57084 | J30: ='FSL Financials — Without BUMN'!J18 -> 619.92611 | K30: ='FSL Financials — Without BUMN'!K18 -> 702.02883 | L30: ='FSL Financials — Without BUMN'!L18 -> 773.76406 | M30: ='FSL Financials — Without BUMN'!M18 -> 807.88996 | ... S30: ='FSL Financials — Without BUMN'!S18 -> 1040.9483
B31: Difference | C31: IDR bn | F31: =F29-F30 -> 0 | G31: =G29-G30 -> 0 | H31: =H29-H30 -> 0 | I31: =I29-I30 -> 0 | J31: =J29-J30 -> 0 | K31: =K29-K30 -> 0 | L31: =L29-L30 -> 0 | M31: =M29-M30 -> 0 | ... S31: =S29-S30 -> 0
B32: Sum of project revenue x With-BUMN flags | C32: IDR bn | F32: ='E1 TelukLamong Output'!F11*'Global Inputs'!$L$89+'E2 CigadingExist Output'!F11*'Global Inputs'!$L$90+'E3 Belawan Output'!F11*'Global Inputs'!$L$91+'E4 WIN Output'!F11*'Global Inputs'!$L$92+'P01 CigWharf2 Output'!F11*'Global Inputs'!$L$93+'P02 CigConveyor Output'!F11*'Global Inputs'!$L$94+'P03 KBSWarehouse Output'!F11*'Global Inputs'!$L$95+'P04 TTLSilo Output'!F11*'Global Inputs'!$L$96+'P05 Dumai Output'!F11*'Global Inputs'!$L$97+'P06 Ciwandan Output'!F11*'Global Inputs'!$L$98+'P08 DMSTrucking Output'!F11*'Global Inputs'!$L$99+'P12 BUMNOps Output'!F11*'Global Inputs'!$L$100+'P15 TBM Output'!F11*'Global Inputs'!$L$101+'P19 Badas Output'!F11*'Global Inputs'!$L$102 -> 0 | G32: ='E1 TelukLamong Output'!G11*'Global Inputs'!$L$89+'E2 CigadingExist Output'!G11*'Global Inputs'!$L$90+'E3 Belawan Output'!G11*'Global Inputs'!$L$91+'E4 WIN Output'!G11*'Global Inputs'!$L$92+'P01 CigWharf2 Output'!G11*'Global Inputs'!$L$93+'P02 CigConveyor Output'!G11*'Global Inputs'!$L$94+'P03 KBSWarehouse Output'!G11*'Global Inputs'!$L$95+'P04 TTLSilo Output'!G11*'Global Inputs'!$L$96+'P05 Dumai Output'!G11*'Global Inputs'!$L$97+'P06 Ciwandan Output'!G11*'Global Inputs'!$L$98+'P08 DMSTrucking Output'!G11*'Global Inputs'!$L$99+'P12 BUMNOps Output'!G11*'Global Inputs'!$L$100+'P15 TBM Output'!G11*'Global Inputs'!$L$101+'P19 Badas Output'!G11*'Global Inputs'!$L$102 -> 305.28841 | H32: ='E1 TelukLamong Output'!H11*'Global Inputs'!$L$89+'E2 CigadingExist Output'!H11*'Global Inputs'!$L$90+'E3 Belawan Output'!H11*'Global Inputs'!$L$91+'E4 WIN Output'!H11*'Global Inputs'!$L$92+'P01 CigWharf2 Output'!H11*'Global Inputs'!$L$93+'P02 CigConveyor Output'!H11*'Global Inputs'!$L$94+'P03 KBSWarehouse Output'!H11*'Global Inputs'!$L$95+'P04 TTLSilo Output'!H11*'Global Inputs'!$L$96+'P05 Dumai Output'!H11*'Global Inputs'!$L$97+'P06 Ciwandan Output'!H11*'Global Inputs'!$L$98+'P08 DMSTrucking Output'!H11*'Global Inputs'!$L$99+'P12 BUMNOps Output'!H11*'Global Inputs'!$L$100+'P15 TBM Output'!H11*'Global Inputs'!$L$101+'P19 Badas Output'!H11*'Global Inputs'!$L$102 -> 427.60264 | I32: ='E1 TelukLamong Output'!I11*'Global Inputs'!$L$89+'E2 CigadingExist Output'!I11*'Global Inputs'!$L$90+'E3 Belawan Output'!I11*'Global Inputs'!$L$91+'E4 WIN Output'!I11*'Global Inputs'!$L$92+'P01 CigWharf2 Output'!I11*'Global Inputs'!$L$93+'P02 CigConveyor Output'!I11*'Global Inputs'!$L$94+'P03 KBSWarehouse Output'!I11*'Global Inputs'!$L$95+'P04 TTLSilo Output'!I11*'Global Inputs'!$L$96+'P05 Dumai Output'!I11*'Global Inputs'!$L$97+'P06 Ciwandan Output'!I11*'Global Inputs'!$L$98+'P08 DMSTrucking Output'!I11*'Global Inputs'!$L$99+'P12 BUMNOps Output'!I11*'Global Inputs'!$L$100+'P15 TBM Output'!I11*'Global Inputs'!$L$101+'P19 Badas Output'!I11*'Global Inputs'!$L$102 -> 622.06456 | J32: ='E1 TelukLamong Output'!J11*'Global Inputs'!$L$89+'E2 CigadingExist Output'!J11*'Global Inputs'!$L$90+'E3 Belawan Output'!J11*'Global Inputs'!$L$91+'E4 WIN Output'!J11*'Global Inputs'!$L$92+'P01 CigWharf2 Output'!J11*'Global Inputs'!$L$93+'P02 CigConveyor Output'!J11*'Global Inputs'!$L$94+'P03 KBSWarehouse Output'!J11*'Global Inputs'!$L$95+'P04 TTLSilo Output'!J11*'Global Inputs'!$L$96+'P05 Dumai Output'!J11*'Global Inputs'!$L$97+'P06 Ciwandan Output'!J11*'Global Inputs'!$L$98+'P08 DMSTrucking Output'!J11*'Global Inputs'!$L$99+'P12 BUMNOps Output'!J11*'Global Inputs'!$L$100+'P15 TBM Output'!J11*'Global Inputs'!$L$101+'P19 Badas Output'!J11*'Global Inputs'!$L$102 -> 754.46249 | K32: ='E1 TelukLamong Output'!K11*'Global Inputs'!$L$89+'E2 CigadingExist Output'!K11*'Global Inputs'!$L$90+'E3 Belawan Output'!K11*'Global Inputs'!$L$91+'E4 WIN Output'!K11*'Global Inputs'!$L$92+'P01 CigWharf2 Output'!K11*'Global Inputs'!$L$93+'P02 CigConveyor Output'!K11*'Global Inputs'!$L$94+'P03 KBSWarehouse Output'!K11*'Global Inputs'!$L$95+'P04 TTLSilo Output'!K11*'Global Inputs'!$L$96+'P05 Dumai Output'!K11*'Global Inputs'!$L$97+'P06 Ciwandan Output'!K11*'Global Inputs'!$L$98+'P08 DMSTrucking Output'!K11*'Global Inputs'!$L$99+'P12 BUMNOps Output'!K11*'Global Inputs'!$L$100+'P15 TBM Output'!K11*'Global Inputs'!$L$101+'P19 Badas Output'!K11*'Global Inputs'!$L$102 -> 841.30923 | L32: ='E1 TelukLamong Output'!L11*'Global Inputs'!$L$89+'E2 CigadingExist Output'!L11*'Global Inputs'!$L$90+'E3 Belawan Output'!L11*'Global Inputs'!$L$91+'E4 WIN Output'!L11*'Global Inputs'!$L$92+'P01 CigWharf2 Output'!L11*'Global Inputs'!$L$93+'P02 CigConveyor Output'!L11*'Global Inputs'!$L$94+'P03 KBSWarehouse Output'!L11*'Global Inputs'!$L$95+'P04 TTLSilo Output'!L11*'Global Inputs'!$L$96+'P05 Dumai Output'!L11*'Global Inputs'!$L$97+'P06 Ciwandan Output'!L11*'Global Inputs'!$L$98+'P08 DMSTrucking Output'!L11*'Global Inputs'!$L$99+'P12 BUMNOps Output'!L11*'Global Inputs'!$L$100+'P15 TBM Output'!L11*'Global Inputs'!$L$101+'P19 Badas Output'!L11*'Global Inputs'!$L$102 -> 917.90667 | M32: ='E1 TelukLamong Output'!M11*'Global Inputs'!$L$89+'E2 CigadingExist Output'!M11*'Global Inputs'!$L$90+'E3 Belawan Output'!M11*'Global Inputs'!$L$91+'E4 WIN Output'!M11*'Global Inputs'!$L$92+'P01 CigWharf2 Output'!M11*'Global Inputs'!$L$93+'P02 CigConveyor Output'!M11*'Global Inputs'!$L$94+'P03 KBSWarehouse Output'!M11*'Global Inputs'!$L$95+'P04 TTLSilo Output'!M11*'Global Inputs'!$L$96+'P05 Dumai Output'!M11*'Global Inputs'!$L$97+'P06 Ciwandan Output'!M11*'Global Inputs'!$L$98+'P08 DMSTrucking Output'!M11*'Global Inputs'!$L$99+'P12 BUMNOps Output'!M11*'Global Inputs'!$L$100+'P15 TBM Output'!M11*'Global Inputs'!$L$101+'P19 Badas Output'!M11*'Global Inputs'!$L$102 -> 957.0165 | ... S32: ='E1 TelukLamong Output'!S11*'Global Inputs'!$L$89+'E2 CigadingExist Output'!S11*'Global Inputs'!$L$90+'E3 Belawan Output'!S11*'Global Inputs'!$L$91+'E4 WIN Output'!S11*'Global Inputs'!$L$92+'P01 CigWharf2 Output'!S11*'Global Inputs'!$L$93+'P02 CigConveyor Output'!S11*'Global Inputs'!$L$94+'P03 KBSWarehouse Output'!S11*'Global Inputs'!$L$95+'P04 TTLSilo Output'!S11*'Global Inputs'!$L$96+'P05 Dumai Output'!S11*'Global Inputs'!$L$97+'P06 Ciwandan Output'!S11*'Global Inputs'!$L$98+'P08 DMSTrucking Output'!S11*'Global Inputs'!$L$99+'P12 BUMNOps Output'!S11*'Global Inputs'!$L$100+'P15 TBM Output'!S11*'Global Inputs'!$L$101+'P19 Badas Output'!S11*'Global Inputs'!$L$102 -> 1212.2892
B33: FSL Financials — With BUMN revenue | C33: IDR bn | F33: ='FSL Financials — With BUMN'!F18 -> 0 | G33: ='FSL Financials — With BUMN'!G18 -> 305.28841 | H33: ='FSL Financials — With BUMN'!H18 -> 427.60264 | I33: ='FSL Financials — With BUMN'!I18 -> 622.06456 | J33: ='FSL Financials — With BUMN'!J18 -> 754.46249 | K33: ='FSL Financials — With BUMN'!K18 -> 841.30923 | L33: ='FSL Financials — With BUMN'!L18 -> 917.90667 | M33: ='FSL Financials — With BUMN'!M18 -> 957.0165 | ... S33: ='FSL Financials — With BUMN'!S18 -> 1212.2892
B34: Difference | C34: IDR bn | F34: =F32-F33 -> 0 | G34: =G32-G33 -> 0 | H34: =H32-H33 -> 0 | I34: =I32-I33 -> 0 | J34: =J32-J33 -> 0 | K34: =K32-K33 -> 0 | L34: =L32-L33 -> 0 | M34: =M32-M33 -> 0 | ... S34: =S32-S33 -> 0
B35: Sum of project FCFF x With-BUMN flags | C35: IDR bn | F35: ='E1 TelukLamong Output'!F28*'Global Inputs'!$L$89+'E2 CigadingExist Output'!F28*'Global Inputs'!$L$90+'E3 Belawan Output'!F28*'Global Inputs'!$L$91+'E4 WIN Output'!F28*'Global Inputs'!$L$92+'P01 CigWharf2 Output'!F28*'Global Inputs'!$L$93+'P02 CigConveyor Output'!F28*'Global Inputs'!$L$94+'P03 KBSWarehouse Output'!F28*'Global Inputs'!$L$95+'P04 TTLSilo Output'!F28*'Global Inputs'!$L$96+'P05 Dumai Output'!F28*'Global Inputs'!$L$97+'P06 Ciwandan Output'!F28*'Global Inputs'!$L$98+'P08 DMSTrucking Output'!F28*'Global Inputs'!$L$99+'P12 BUMNOps Output'!F28*'Global Inputs'!$L$100+'P15 TBM Output'!F28*'Global Inputs'!$L$101+'P19 Badas Output'!F28*'Global Inputs'!$L$102 -> -198.433 | G35: ='E1 TelukLamong Output'!G28*'Global Inputs'!$L$89+'E2 CigadingExist Output'!G28*'Global Inputs'!$L$90+'E3 Belawan Output'!G28*'Global Inputs'!$L$91+'E4 WIN Output'!G28*'Global Inputs'!$L$92+'P01 CigWharf2 Output'!G28*'Global Inputs'!$L$93+'P02 CigConveyor Output'!G28*'Global Inputs'!$L$94+'P03 KBSWarehouse Output'!G28*'Global Inputs'!$L$95+'P04 TTLSilo Output'!G28*'Global Inputs'!$L$96+'P05 Dumai Output'!G28*'Global Inputs'!$L$97+'P06 Ciwandan Output'!G28*'Global Inputs'!$L$98+'P08 DMSTrucking Output'!G28*'Global Inputs'!$L$99+'P12 BUMNOps Output'!G28*'Global Inputs'!$L$100+'P15 TBM Output'!G28*'Global Inputs'!$L$101+'P19 Badas Output'!G28*'Global Inputs'!$L$102 -> 11.8696 | H35: ='E1 TelukLamong Output'!H28*'Global Inputs'!$L$89+'E2 CigadingExist Output'!H28*'Global Inputs'!$L$90+'E3 Belawan Output'!H28*'Global Inputs'!$L$91+'E4 WIN Output'!H28*'Global Inputs'!$L$92+'P01 CigWharf2 Output'!H28*'Global Inputs'!$L$93+'P02 CigConveyor Output'!H28*'Global Inputs'!$L$94+'P03 KBSWarehouse Output'!H28*'Global Inputs'!$L$95+'P04 TTLSilo Output'!H28*'Global Inputs'!$L$96+'P05 Dumai Output'!H28*'Global Inputs'!$L$97+'P06 Ciwandan Output'!H28*'Global Inputs'!$L$98+'P08 DMSTrucking Output'!H28*'Global Inputs'!$L$99+'P12 BUMNOps Output'!H28*'Global Inputs'!$L$100+'P15 TBM Output'!H28*'Global Inputs'!$L$101+'P19 Badas Output'!H28*'Global Inputs'!$L$102 -> 196.17207 | I35: ='E1 TelukLamong Output'!I28*'Global Inputs'!$L$89+'E2 CigadingExist Output'!I28*'Global Inputs'!$L$90+'E3 Belawan Output'!I28*'Global Inputs'!$L$91+'E4 WIN Output'!I28*'Global Inputs'!$L$92+'P01 CigWharf2 Output'!I28*'Global Inputs'!$L$93+'P02 CigConveyor Output'!I28*'Global Inputs'!$L$94+'P03 KBSWarehouse Output'!I28*'Global Inputs'!$L$95+'P04 TTLSilo Output'!I28*'Global Inputs'!$L$96+'P05 Dumai Output'!I28*'Global Inputs'!$L$97+'P06 Ciwandan Output'!I28*'Global Inputs'!$L$98+'P08 DMSTrucking Output'!I28*'Global Inputs'!$L$99+'P12 BUMNOps Output'!I28*'Global Inputs'!$L$100+'P15 TBM Output'!I28*'Global Inputs'!$L$101+'P19 Badas Output'!I28*'Global Inputs'!$L$102 -> -133.2095 | J35: ='E1 TelukLamong Output'!J28*'Global Inputs'!$L$89+'E2 CigadingExist Output'!J28*'Global Inputs'!$L$90+'E3 Belawan Output'!J28*'Global Inputs'!$L$91+'E4 WIN Output'!J28*'Global Inputs'!$L$92+'P01 CigWharf2 Output'!J28*'Global Inputs'!$L$93+'P02 CigConveyor Output'!J28*'Global Inputs'!$L$94+'P03 KBSWarehouse Output'!J28*'Global Inputs'!$L$95+'P04 TTLSilo Output'!J28*'Global Inputs'!$L$96+'P05 Dumai Output'!J28*'Global Inputs'!$L$97+'P06 Ciwandan Output'!J28*'Global Inputs'!$L$98+'P08 DMSTrucking Output'!J28*'Global Inputs'!$L$99+'P12 BUMNOps Output'!J28*'Global Inputs'!$L$100+'P15 TBM Output'!J28*'Global Inputs'!$L$101+'P19 Badas Output'!J28*'Global Inputs'!$L$102 -> 205.30586 | K35: ='E1 TelukLamong Output'!K28*'Global Inputs'!$L$89+'E2 CigadingExist Output'!K28*'Global Inputs'!$L$90+'E3 Belawan Output'!K28*'Global Inputs'!$L$91+'E4 WIN Output'!K28*'Global Inputs'!$L$92+'P01 CigWharf2 Output'!K28*'Global Inputs'!$L$93+'P02 CigConveyor Output'!K28*'Global Inputs'!$L$94+'P03 KBSWarehouse Output'!K28*'Global Inputs'!$L$95+'P04 TTLSilo Output'!K28*'Global Inputs'!$L$96+'P05 Dumai Output'!K28*'Global Inputs'!$L$97+'P06 Ciwandan Output'!K28*'Global Inputs'!$L$98+'P08 DMSTrucking Output'!K28*'Global Inputs'!$L$99+'P12 BUMNOps Output'!K28*'Global Inputs'!$L$100+'P15 TBM Output'!K28*'Global Inputs'!$L$101+'P19 Badas Output'!K28*'Global Inputs'!$L$102 -> 411.92011 | L35: ='E1 TelukLamong Output'!L28*'Global Inputs'!$L$89+'E2 CigadingExist Output'!L28*'Global Inputs'!$L$90+'E3 Belawan Output'!L28*'Global Inputs'!$L$91+'E4 WIN Output'!L28*'Global Inputs'!$L$92+'P01 CigWharf2 Output'!L28*'Global Inputs'!$L$93+'P02 CigConveyor Output'!L28*'Global Inputs'!$L$94+'P03 KBSWarehouse Output'!L28*'Global Inputs'!$L$95+'P04 TTLSilo Output'!L28*'Global Inputs'!$L$96+'P05 Dumai Output'!L28*'Global Inputs'!$L$97+'P06 Ciwandan Output'!L28*'Global Inputs'!$L$98+'P08 DMSTrucking Output'!L28*'Global Inputs'!$L$99+'P12 BUMNOps Output'!L28*'Global Inputs'!$L$100+'P15 TBM Output'!L28*'Global Inputs'!$L$101+'P19 Badas Output'!L28*'Global Inputs'!$L$102 -> 456.29206 | M35: ='E1 TelukLamong Output'!M28*'Global Inputs'!$L$89+'E2 CigadingExist Output'!M28*'Global Inputs'!$L$90+'E3 Belawan Output'!M28*'Global Inputs'!$L$91+'E4 WIN Output'!M28*'Global Inputs'!$L$92+'P01 CigWharf2 Output'!M28*'Global Inputs'!$L$93+'P02 CigConveyor Output'!M28*'Global Inputs'!$L$94+'P03 KBSWarehouse Output'!M28*'Global Inputs'!$L$95+'P04 TTLSilo Output'!M28*'Global Inputs'!$L$96+'P05 Dumai Output'!M28*'Global Inputs'!$L$97+'P06 Ciwandan Output'!M28*'Global Inputs'!$L$98+'P08 DMSTrucking Output'!M28*'Global Inputs'!$L$99+'P12 BUMNOps Output'!M28*'Global Inputs'!$L$100+'P15 TBM Output'!M28*'Global Inputs'!$L$101+'P19 Badas Output'!M28*'Global Inputs'!$L$102 -> 478.00691 | ... S35: ='E1 TelukLamong Output'!S28*'Global Inputs'!$L$89+'E2 CigadingExist Output'!S28*'Global Inputs'!$L$90+'E3 Belawan Output'!S28*'Global Inputs'!$L$91+'E4 WIN Output'!S28*'Global Inputs'!$L$92+'P01 CigWharf2 Output'!S28*'Global Inputs'!$L$93+'P02 CigConveyor Output'!S28*'Global Inputs'!$L$94+'P03 KBSWarehouse Output'!S28*'Global Inputs'!$L$95+'P04 TTLSilo Output'!S28*'Global Inputs'!$L$96+'P05 Dumai Output'!S28*'Global Inputs'!$L$97+'P06 Ciwandan Output'!S28*'Global Inputs'!$L$98+'P08 DMSTrucking Output'!S28*'Global Inputs'!$L$99+'P12 BUMNOps Output'!S28*'Global Inputs'!$L$100+'P15 TBM Output'!S28*'Global Inputs'!$L$101+'P19 Badas Output'!S28*'Global Inputs'!$L$102 -> 596.57744
B36: Valuation — With BUMN FCFF | C36: IDR bn | F36: ='Valuation — With BUMN'!F31 -> -198.433 | G36: ='Valuation — With BUMN'!G31 -> 11.8696 | H36: ='Valuation — With BUMN'!H31 -> 196.17207 | I36: ='Valuation — With BUMN'!I31 -> -133.2095 | J36: ='Valuation — With BUMN'!J31 -> 205.30586 | K36: ='Valuation — With BUMN'!K31 -> 411.92011 | L36: ='Valuation — With BUMN'!L31 -> 456.29206 | M36: ='Valuation — With BUMN'!M31 -> 478.00691 | ... S36: ='Valuation — With BUMN'!S31 -> 596.57744
B37: Difference | C37: IDR bn | F37: =F35-F36 -> 0 | G37: =G35-G36 -> 0 | H37: =H35-H36 -> 0 | I37: =I35-I36 -> 0 | J37: =J35-J36 -> 0 | K37: =K35-K36 -> 0 | L37: =L35-L36 -> 0 | M37: =M35-M36 -> 0 | ... S37: =S35-S36 -> 0
B38: Company statements add corporate items (LT loan interest and its tax shield, dividends, injection, existing fixed assets, other balances) to the project sums; unlevered FCFF is identical by construction.
B40: E1 Teluk Lamong (NPLOG) cargodoring & delivery — Existing business — NPLOG Teluk Lamong
B41: Existing grain and meal terminal operations at Teluk Lamong (conveyor, warehouse, delivery): volume x tariff for meals and grains; variable costs per ton indexed from FY2023; fixed G&A lines; depreciation of existing assets. | C41: Input | D41: Calc | E41: Output | G41: ="In valuation: "&'Global Inputs'!$E$89&" | case: "&'Global Inputs'!$F$89&" | FSL interest: "&TEXT('Global Inputs'!$G$89,"0%") -> In valuation: 1 | case: 1 | FSL interest: 65%
B42: Revenue | C42: IDR bn | E42: =SUM(F42:S42) -> 2524.1108 | F42: ='E1 TelukLamong Output'!F11 -> 0 | G42: ='E1 TelukLamong Output'!G11 -> 156.43828 | H42: ='E1 TelukLamong Output'!H11 -> 161.13143 | I42: ='E1 TelukLamong Output'!I11 -> 165.96537 | J42: ='E1 TelukLamong Output'!J11 -> 170.94433 | K42: ='E1 TelukLamong Output'!K11 -> 176.07266 | L42: ='E1 TelukLamong Output'!L11 -> 186.79549 | M42: ='E1 TelukLamong Output'!M11 -> 192.39935 | ... S42: ='E1 TelukLamong Output'!S11 -> 236.62693
B43: EBITDA | C43: IDR bn | E43: =SUM(F43:S43) -> 1786.3683 | F43: ='E1 TelukLamong Output'!F15 -> 0 | G43: ='E1 TelukLamong Output'!G15 -> 112.5106 | H43: ='E1 TelukLamong Output'!H15 -> 115.41862 | I43: ='E1 TelukLamong Output'!I15 -> 118.36361 | J43: ='E1 TelukLamong Output'!J15 -> 121.38819 | K43: ='E1 TelukLamong Output'!K15 -> 124.47096 | L43: ='E1 TelukLamong Output'!L15 -> 133.03108 | M43: ='E1 TelukLamong Output'!M15 -> 136.39274 | ... S43: ='E1 TelukLamong Output'!S15 -> 164.71608
B44: EBIT | C44: IDR bn | E44: =SUM(F44:S44) -> 1219.2782 | F44: ='E1 TelukLamong Output'!F17 -> 0 | G44: ='E1 TelukLamong Output'!G17 -> 70.769814 | H44: ='E1 TelukLamong Output'!H17 -> 73.672367 | I44: ='E1 TelukLamong Output'!I17 -> 75.611774 | J44: ='E1 TelukLamong Output'!J17 -> 78.630654 | K44: ='E1 TelukLamong Output'!K17 -> 81.707618 | L44: ='E1 TelukLamong Output'!L17 -> 89.261806 | M44: ='E1 TelukLamong Output'!M17 -> 92.617426 | ... S44: ='E1 TelukLamong Output'!S17 -> 119.90188
B45: NOPAT (tax on project EBIT) | C45: IDR bn | E45: =SUM(F45:S45) -> 951.03699 | F45: ='E1 TelukLamong Output'!F19 -> 0 | G45: ='E1 TelukLamong Output'!G19 -> 55.200455 | H45: ='E1 TelukLamong Output'!H19 -> 57.464446 | I45: ='E1 TelukLamong Output'!I19 -> 58.977184 | J45: ='E1 TelukLamong Output'!J19 -> 61.33191 | K45: ='E1 TelukLamong Output'!K19 -> 63.731942 | L45: ='E1 TelukLamong Output'!L19 -> 69.624209 | M45: ='E1 TelukLamong Output'!M19 -> 72.241592 | ... S45: ='E1 TelukLamong Output'!S19 -> 93.523467
B46: Depreciation & amortisation | C46: IDR bn | E46: =SUM(F46:S46) -> -567.09009 | F46: ='E1 TelukLamong Output'!F16 -> 0 | G46: ='E1 TelukLamong Output'!G16 -> -41.740782 | H46: ='E1 TelukLamong Output'!H16 -> -41.746257 | I46: ='E1 TelukLamong Output'!I16 -> -42.75184 | J46: ='E1 TelukLamong Output'!J16 -> -42.757536 | K46: ='E1 TelukLamong Output'!K16 -> -42.763345 | L46: ='E1 TelukLamong Output'!L16 -> -43.76927 | M46: ='E1 TelukLamong Output'!M16 -> -43.775314 | ... S46: ='E1 TelukLamong Output'!S16 -> -44.814202
B47: Capex (USD m) | C47: USD m | E47: =SUM(F47:S47) -> 0 | F47: ='E1 TelukLamong Output'!F34 -> 0 | G47: ='E1 TelukLamong Output'!G34 -> 0 | H47: ='E1 TelukLamong Output'!H34 -> 0 | I47: ='E1 TelukLamong Output'!I34 -> 0 | J47: ='E1 TelukLamong Output'!J34 -> 0 | K47: ='E1 TelukLamong Output'!K34 -> 0 | L47: ='E1 TelukLamong Output'!L34 -> 0 | M47: ='E1 TelukLamong Output'!M34 -> 0 | ... S47: ='E1 TelukLamong Output'!S34 -> 0
B48: Capex (IDR bn) | C48: IDR bn | E48: =SUM(F48:S48) -> 0 | F48: ='E1 TelukLamong Output'!F35 -> 0 | G48: ='E1 TelukLamong Output'!G35 -> 0 | H48: ='E1 TelukLamong Output'!H35 -> 0 | I48: ='E1 TelukLamong Output'!I35 -> 0 | J48: ='E1 TelukLamong Output'!J35 -> 0 | K48: ='E1 TelukLamong Output'!K35 -> 0 | L48: ='E1 TelukLamong Output'!L35 -> 0 | M48: ='E1 TelukLamong Output'!M35 -> 0 | ... S48: ='E1 TelukLamong Output'!S35 -> 0
B49: Increase in net working capital | C49: IDR bn | E49: =SUM(F49:S49) -> -5.3422916 | F49: ='E1 TelukLamong Output'!F27 -> 0 | G49: ='E1 TelukLamong Output'!G27 -> 2.6946771 | H49: ='E1 TelukLamong Output'!H27 -> -0.51128558 | I49: ='E1 TelukLamong Output'!I27 -> -0.47511656 | J49: ='E1 TelukLamong Output'!J27 -> -0.48862769 | K49: ='E1 TelukLamong Output'!K27 -> -0.44934296 | L49: ='E1 TelukLamong Output'!L27 -> -1.2330101 | M49: ='E1 TelukLamong Output'!M27 -> -0.54522789 | ... S49: ='E1 TelukLamong Output'!S27 -> -0.58380184
B50: Free cash flow to firm | C50: IDR bn | E50: =SUM(F50:S50) -> 1512.7848 | F50: ='E1 TelukLamong Output'!F28 -> 0 | G50: ='E1 TelukLamong Output'!G28 -> 99.635914 | H50: ='E1 TelukLamong Output'!H28 -> 98.699417 | I50: ='E1 TelukLamong Output'!I28 -> 101.25391 | J50: ='E1 TelukLamong Output'!J28 -> 103.60082 | K50: ='E1 TelukLamong Output'!K28 -> 106.04594 | L50: ='E1 TelukLamong Output'!L28 -> 112.16047 | M50: ='E1 TelukLamong Output'!M28 -> 115.47168 | ... S50: ='E1 TelukLamong Output'!S28 -> 137.75387
B51: Cumulative FCFF | C51: IDR bn | F51: ='E1 TelukLamong Output'!F29 -> 0 | G51: ='E1 TelukLamong Output'!G29 -> 99.635914 | H51: ='E1 TelukLamong Output'!H29 -> 198.33533 | I51: ='E1 TelukLamong Output'!I29 -> 299.58924 | J51: ='E1 TelukLamong Output'!J29 -> 403.19006 | K51: ='E1 TelukLamong Output'!K29 -> 509.236 | L51: ='E1 TelukLamong Output'!L29 -> 621.39647 | M51: ='E1 TelukLamong Output'!M29 -> 736.86815 | ... S51: ='E1 TelukLamong Output'!S29 -> 1512.7848
B52: Net operating assets funded by FSL (PPE + receivables - payables) | C52: IDR bn | F52: ='E1 TelukLamong Output'!F39 -> 19.475303 | G52: ='E1 TelukLamong Output'!G39 -> 16.780626 | H52: ='E1 TelukLamong Output'!H39 -> 17.291911 | I52: ='E1 TelukLamong Output'!I39 -> 17.767028 | J52: ='E1 TelukLamong Output'!J39 -> 18.255656 | K52: ='E1 TelukLamong Output'!K39 -> 18.704999 | L52: ='E1 TelukLamong Output'!L39 -> 19.938009 | M52: ='E1 TelukLamong Output'!M39 -> 20.483236 | ... S52: ='E1 TelukLamong Output'!S39 -> 24.817594
B53: Funding need (cash shortfall to be funded by FSL) | C53: IDR bn | E53: =SUM(F53:S53) -> 0 | F53: ='E1 TelukLamong Output'!F31 -> 0 | G53: ='E1 TelukLamong Output'!G31 -> 0 | H53: ='E1 TelukLamong Output'!H31 -> 0 | I53: ='E1 TelukLamong Output'!I31 -> 0 | J53: ='E1 TelukLamong Output'!J31 -> 0 | K53: ='E1 TelukLamong Output'!K31 -> 0 | L53: ='E1 TelukLamong Output'!L31 -> 0 | M53: ='E1 TelukLamong Output'!M31 -> 0 | ... S53: ='E1 TelukLamong Output'!S31 -> 0
B54: PV at the valuation date of FCFF incl. terminal value (years after 31-Dec-2026) | C54: IDR bn | E54: =SUM(F54:S54) -> 1190.2163 | F54: ='E1 TelukLamong Output'!F47 -> 0 | G54: ='E1 TelukLamong Output'!G47 -> 0 | H54: ='E1 TelukLamong Output'!H47 -> 0 | I54: ='E1 TelukLamong Output'!I47 -> 0 | J54: ='E1 TelukLamong Output'!J47 -> 92.61111 | K54: ='E1 TelukLamong Output'!K47 -> 84.741055 | L54: ='E1 TelukLamong Output'!L47 -> 80.119739 | M54: ='E1 TelukLamong Output'!M47 -> 73.735239 | ... S54: ='E1 TelukLamong Output'!S47 -> 566.30464
B55: Returns: | C55: NPV @ 31-Dec-2026 (IDR bn) | D55: ='E1 TelukLamong Output'!$E$48 -> 1190.2163 | E55: Full-life project IRR | F55: =IF(ISNUMBER('E1 TelukLamong Output'!$E$50),'E1 TelukLamong Output'!$E$50,"n/a") -> n/a | G55: IRR incl. terminal value | H55: =IF(ISNUMBER('E1 TelukLamong Output'!$E$51),'E1 TelukLamong Output'!$E$51,"n/a") -> n/a | I55: Payback year | J55: =IF(ISNUMBER('E1 TelukLamong Output'!$E$53),'E1 TelukLamong Output'!$E$53,"n/a") -> n/a | K55: Total capex (USD m) | L55: ='E1 TelukLamong Output'!$E$55 -> 0 | M55: Capex after val. date (USD m) | N55: ='E1 TelukLamong Output'!$E$56 -> 0
B57: E2 Cigading Existing Terminal (SGT 2) — Existing business — SGT Cigading
B58: Existing grain terminal at Cigading: stevedoring / cargodoring volume at a per-ton tariff (Wharf 2 tariff from FY2025), variable costs per ton indexed from FY2023 actuals, fixed G&A lines, depreciation of existing assets. | C58: Input | D58: Calc | E58: Output | G58: ="In valuation: "&'Global Inputs'!$E$90&" | case: "&'Global Inputs'!$F$90&" | FSL interest: "&TEXT('Global Inputs'!$G$90,"0%") -> In valuation: 1 | case: 1 | FSL interest: 100%
B59: Revenue | C59: IDR bn | E59: =SUM(F59:S59) -> 914.58893 | F59: ='E2 CigadingExist Output'!F11 -> 0 | G59: ='E2 CigadingExist Output'!G11 -> 38.65796 | H59: ='E2 CigadingExist Output'!H11 -> 46.389552 | I59: ='E2 CigadingExist Output'!I11 -> 47.781239 | J59: ='E2 CigadingExist Output'!J11 -> 59.057611 | K59: ='E2 CigadingExist Output'!K11 -> 60.829339 | L59: ='E2 CigadingExist Output'!L11 -> 68.919641 | M59: ='E2 CigadingExist Output'!M11 -> 70.987231 | ... S59: ='E2 CigadingExist Output'!S11 -> 95.239106
B60: EBITDA | C60: IDR bn | E60: =SUM(F60:S60) -> 544.83645 | F60: ='E2 CigadingExist Output'!F15 -> 0 | G60: ='E2 CigadingExist Output'!G15 -> 16.08359 | H60: ='E2 CigadingExist Output'!H15 -> 22.990164 | I60: ='E2 CigadingExist Output'!I15 -> 23.489054 | J60: ='E2 CigadingExist Output'!J15 -> 33.869604 | K60: ='E2 CigadingExist Output'!K15 -> 34.707659 | L60: ='E2 CigadingExist Output'!L15 -> 41.791524 | M60: ='E2 CigadingExist Output'!M15 -> 42.844418 | ... S60: ='E2 CigadingExist Output'!S15 -> 59.990329
B61: EBIT | C61: IDR bn | E61: =SUM(F61:S61) -> -11.846441 | F61: ='E2 CigadingExist Output'!F17 -> 0 | G61: ='E2 CigadingExist Output'!G17 -> -24.875259 | H61: ='E2 CigadingExist Output'!H17 -> -17.971278 | I61: ='E2 CigadingExist Output'!I17 -> -18.475033 | J61: ='E2 CigadingExist Output'!J17 -> -8.0971803 | K61: ='E2 CigadingExist Output'!K17 -> -7.2618777 | L61: ='E2 CigadingExist Output'!L17 -> -1.1808192 | M61: ='E2 CigadingExist Output'!M17 -> -0.13078783 | ... S61: ='E2 CigadingExist Output'!S17 -> 15.996703
B62: NOPAT (tax on project EBIT) | C62: IDR bn | E62: =SUM(F62:S62) -> -26.398515 | F62: ='E2 CigadingExist Output'!F19 -> 0 | G62: ='E2 CigadingExist Output'!G19 -> -24.875259 | H62: ='E2 CigadingExist Output'!H19 -> -17.971278 | I62: ='E2 CigadingExist Output'!I19 -> -18.475033 | J62: ='E2 CigadingExist Output'!J19 -> -8.0971803 | K62: ='E2 CigadingExist Output'!K19 -> -7.2618777 | L62: ='E2 CigadingExist Output'!L19 -> -1.1808192 | M62: ='E2 CigadingExist Output'!M19 -> -0.13078783 | ... S62: ='E2 CigadingExist Output'!S19 -> 12.477428
B63: Depreciation & amortisation | C63: IDR bn | E63: =SUM(F63:S63) -> -556.68289 | F63: ='E2 CigadingExist Output'!F16 -> 0 | G63: ='E2 CigadingExist Output'!G16 -> -40.958849 | H63: ='E2 CigadingExist Output'!H16 -> -40.961442 | I63: ='E2 CigadingExist Output'!I16 -> -41.964087 | J63: ='E2 CigadingExist Output'!J16 -> -41.966785 | K63: ='E2 CigadingExist Output'!K16 -> -41.969536 | L63: ='E2 CigadingExist Output'!L16 -> -42.972343 | M63: ='E2 CigadingExist Output'!M16 -> -42.975206 | ... S63: ='E2 CigadingExist Output'!S16 -> -43.993626
B64: Capex (USD m) | C64: USD m | E64: =SUM(F64:S64) -> 0 | F64: ='E2 CigadingExist Output'!F34 -> 0 | G64: ='E2 CigadingExist Output'!G34 -> 0 | H64: ='E2 CigadingExist Output'!H34 -> 0 | I64: ='E2 CigadingExist Output'!I34 -> 0 | J64: ='E2 CigadingExist Output'!J34 -> 0 | K64: ='E2 CigadingExist Output'!K34 -> 0 | L64: ='E2 CigadingExist Output'!L34 -> 0 | M64: ='E2 CigadingExist Output'!M34 -> 0 | ... S64: ='E2 CigadingExist Output'!S34 -> 0
B65: Capex (IDR bn) | C65: IDR bn | E65: =SUM(F65:S65) -> 0 | F65: ='E2 CigadingExist Output'!F35 -> 0 | G65: ='E2 CigadingExist Output'!G35 -> 0 | H65: ='E2 CigadingExist Output'!H35 -> 0 | I65: ='E2 CigadingExist Output'!I35 -> 0 | J65: ='E2 CigadingExist Output'!J35 -> 0 | K65: ='E2 CigadingExist Output'!K35 -> 0 | L65: ='E2 CigadingExist Output'!L35 -> 0 | M65: ='E2 CigadingExist Output'!M35 -> 0 | ... S65: ='E2 CigadingExist Output'!S35 -> 0
B66: Increase in net working capital | C66: IDR bn | E66: =SUM(F66:S66) -> -5.8291012 | F66: ='E2 CigadingExist Output'!F27 -> 0 | G66: ='E2 CigadingExist Output'!G27 -> 0.43838631 | H66: ='E2 CigadingExist Output'!H27 -> -0.91975162 | I66: ='E2 CigadingExist Output'!I27 -> -0.1233338 | J66: ='E2 CigadingExist Output'!J27 -> -1.3425641 | K66: ='E2 CigadingExist Output'!K27 -> -0.15153439 | L66: ='E2 CigadingExist Output'!L27 -> -0.95934801 | M66: ='E2 CigadingExist Output'!M27 -> -0.20008626 | ... S66: ='E2 CigadingExist Output'!S27 -> -0.24202463
B67: Free cash flow to firm | C67: IDR bn | E67: =SUM(F67:S67) -> 524.45528 | F67: ='E2 CigadingExist Output'!F28 -> 0 | G67: ='E2 CigadingExist Output'!G28 -> 16.521977 | H67: ='E2 CigadingExist Output'!H28 -> 22.070412 | I67: ='E2 CigadingExist Output'!I28 -> 23.36572 | J67: ='E2 CigadingExist Output'!J28 -> 32.52704 | K67: ='E2 CigadingExist Output'!K28 -> 34.556124 | L67: ='E2 CigadingExist Output'!L28 -> 40.832176 | M67: ='E2 CigadingExist Output'!M28 -> 42.644332 | ... S67: ='E2 CigadingExist Output'!S28 -> 56.22903
B68: Cumulative FCFF | C68: IDR bn | F68: ='E2 CigadingExist Output'!F29 -> 0 | G68: ='E2 CigadingExist Output'!G29 -> 16.521977 | H68: ='E2 CigadingExist Output'!H29 -> 38.592389 | I68: ='E2 CigadingExist Output'!I29 -> 61.958109 | J68: ='E2 CigadingExist Output'!J29 -> 94.485149 | K68: ='E2 CigadingExist Output'!K29 -> 129.04127 | L68: ='E2 CigadingExist Output'!L29 -> 169.87345 | M68: ='E2 CigadingExist Output'!M29 -> 212.51778 | ... S68: ='E2 CigadingExist Output'!S29 -> 524.45528
B69: Net operating assets funded by FSL (PPE + receivables - payables) | C69: IDR bn | F69: ='E2 CigadingExist Output'!F39 -> 4.0912744 | G69: ='E2 CigadingExist Output'!G39 -> 3.6528881 | H69: ='E2 CigadingExist Output'!H39 -> 4.5726397 | I69: ='E2 CigadingExist Output'!I39 -> 4.6959735 | J69: ='E2 CigadingExist Output'!J39 -> 6.0385376 | K69: ='E2 CigadingExist Output'!K39 -> 6.190072 | L69: ='E2 CigadingExist Output'!L39 -> 7.14942 | M69: ='E2 CigadingExist Output'!M39 -> 7.3495063 | ... S69: ='E2 CigadingExist Output'!S39 -> 9.9203756
B70: Funding need (cash shortfall to be funded by FSL) | C70: IDR bn | E70: =SUM(F70:S70) -> 0 | F70: ='E2 CigadingExist Output'!F31 -> 0 | G70: ='E2 CigadingExist Output'!G31 -> 0 | H70: ='E2 CigadingExist Output'!H31 -> 0 | I70: ='E2 CigadingExist Output'!I31 -> 0 | J70: ='E2 CigadingExist Output'!J31 -> 0 | K70: ='E2 CigadingExist Output'!K31 -> 0 | L70: ='E2 CigadingExist Output'!L31 -> 0 | M70: ='E2 CigadingExist Output'!M31 -> 0 | ... S70: ='E2 CigadingExist Output'!S31 -> 0
B71: PV at the valuation date of FCFF incl. terminal value (years after 31-Dec-2026) | C71: IDR bn | E71: =SUM(F71:S71) -> 461.15059 | F71: ='E2 CigadingExist Output'!F47 -> 0 | G71: ='E2 CigadingExist Output'!G47 -> 0 | H71: ='E2 CigadingExist Output'!H47 -> 0 | I71: ='E2 CigadingExist Output'!I47 -> 0 | J71: ='E2 CigadingExist Output'!J47 -> 29.076655 | K71: ='E2 CigadingExist Output'!K47 -> 27.613715 | L71: ='E2 CigadingExist Output'!L47 -> 29.167703 | M71: ='E2 CigadingExist Output'!M47 -> 27.230833 | ... S71: ='E2 CigadingExist Output'!S47 -> 231.15693
B72: Returns: | C72: NPV @ 31-Dec-2026 (IDR bn) | D72: ='E2 CigadingExist Output'!$E$48 -> 461.15059 | E72: Full-life project IRR | F72: =IF(ISNUMBER('E2 CigadingExist Output'!$E$50),'E2 CigadingExist Output'!$E$50,"n/a") -> n/a | G72: IRR incl. terminal value | H72: =IF(ISNUMBER('E2 CigadingExist Output'!$E$51),'E2 CigadingExist Output'!$E$51,"n/a") -> n/a | I72: Payback year | J72: =IF(ISNUMBER('E2 CigadingExist Output'!$E$53),'E2 CigadingExist Output'!$E$53,"n/a") -> n/a | K72: Total capex (USD m) | L72: ='E2 CigadingExist Output'!$E$55 -> 0 | M72: Capex after val. date (USD m) | N72: ='E2 CigadingExist Output'!$E$56 -> 0
B74: E3 Belawan terminal (SGT3) incl. Belawan expansion — Existing business — SGT Belawan
B75: Existing grain terminal at Belawan plus its expansion: existing volume (3% growth) and typed additional expansion volume from FY2027 at a per-ton tariff; fixed and per-ton costs indexed from FY2023, concession fee 2.5% of revenue, insurance; nine fixed G&A lines; existing-asset depreciation plus 14.0 USD m of new assets depreciated from FY2026. | C75: Input | D75: Calc | E75: Output | G75: ="In valuation: "&'Global Inputs'!$E$91&" | case: "&'Global Inputs'!$F$91&" | FSL interest: "&TEXT('Global Inputs'!$G$91,"0%") -> In valuation: 1 | case: 1 | FSL interest: 100%
B76: Revenue | C76: IDR bn | E76: =SUM(F76:S76) -> 706.44399 | F76: ='E3 Belawan Output'!F11 -> 0 | G76: ='E3 Belawan Output'!G11 -> 22.2435 | H76: ='E3 Belawan Output'!H11 -> 22.910805 | I76: ='E3 Belawan Output'!I11 -> 34.967927 | J76: ='E3 Belawan Output'!J11 -> 44.806465 | K76: ='E3 Belawan Output'!K11 -> 49.526879 | L76: ='E3 Belawan Output'!L11 -> 54.524582 | M76: ='E3 Belawan Output'!M11 -> 59.814057 | ... S76: ='E3 Belawan Output'!S11 -> 61.316585
B77: EBITDA | C77: IDR bn | E77: =SUM(F77:S77) -> 500.64452 | F77: ='E3 Belawan Output'!F15 -> 0 | G77: ='E3 Belawan Output'!G15 -> 11.145605 | H77: ='E3 Belawan Output'!H15 -> 11.396081 | I77: ='E3 Belawan Output'!I15 -> 22.307214 | J77: ='E3 Belawan Output'!J15 -> 30.90414 | K77: ='E3 Belawan Output'!K15 -> 34.883762 | L77: ='E3 Belawan Output'!L15 -> 39.104689 | M77: ='E3 Belawan Output'!M15 -> 43.579698 | ... S77: ='E3 Belawan Output'!S15 -> 42.742255
B78: EBIT | C78: IDR bn | E78: =SUM(F78:S78) -> 356.95761 | F78: ='E3 Belawan Output'!F17 -> 0 | G78: ='E3 Belawan Output'!G17 -> 5.911631 | H78: ='E3 Belawan Output'!H17 -> 6.1621072 | I78: ='E3 Belawan Output'!I17 -> 13.120564 | J78: ='E3 Belawan Output'!J17 -> 17.787815 | K78: ='E3 Belawan Output'!K17 -> 21.767437 | L78: ='E3 Belawan Output'!L17 -> 25.988364 | M78: ='E3 Belawan Output'!M17 -> 30.463373 | ... S78: ='E3 Belawan Output'!S17 -> 32.477305
B79: NOPAT (tax on project EBIT) | C79: IDR bn | E79: =SUM(F79:S79) -> 278.42694 | F79: ='E3 Belawan Output'!F19 -> 0 | G79: ='E3 Belawan Output'!G19 -> 4.6110721 | H79: ='E3 Belawan Output'!H19 -> 4.8064437 | I79: ='E3 Belawan Output'!I19 -> 10.23404 | J79: ='E3 Belawan Output'!J19 -> 13.874495 | K79: ='E3 Belawan Output'!K19 -> 16.978601 | L79: ='E3 Belawan Output'!L19 -> 20.270924 | M79: ='E3 Belawan Output'!M19 -> 23.761431 | ... S79: ='E3 Belawan Output'!S19 -> 25.332298
B80: Depreciation & amortisation | C80: IDR bn | E80: =SUM(F80:S80) -> -143.68691 | F80: ='E3 Belawan Output'!F16 -> 0 | G80: ='E3 Belawan Output'!G16 -> -5.2339742 | H80: ='E3 Belawan Output'!H16 -> -5.2339742 | I80: ='E3 Belawan Output'!I16 -> -9.1866496 | J80: ='E3 Belawan Output'!J16 -> -13.116325 | K80: ='E3 Belawan Output'!K16 -> -13.116325 | L80: ='E3 Belawan Output'!L16 -> -13.116325 | M80: ='E3 Belawan Output'!M16 -> -13.116325 | ... S80: ='E3 Belawan Output'!S16 -> -10.26495
B81: Capex (USD m) | C81: USD m | E81: =SUM(F81:S81) -> 14.024593 | F81: ='E3 Belawan Output'!F34 -> 0 | G81: ='E3 Belawan Output'!G34 -> 0 | H81: ='E3 Belawan Output'!H34 -> 0 | I81: ='E3 Belawan Output'!I34 -> 7.0245927 | J81: ='E3 Belawan Output'!J34 -> 7 | K81: ='E3 Belawan Output'!K34 -> 0 | L81: ='E3 Belawan Output'!L34 -> 0 | M81: ='E3 Belawan Output'!M34 -> 0 | ... S81: ='E3 Belawan Output'!S34 -> 0
B82: Capex (IDR bn) | C82: IDR bn | E82: =SUM(F82:S82) -> 228.11 | F82: ='E3 Belawan Output'!F35 -> 0 | G82: ='E3 Belawan Output'!G35 -> 0 | H82: ='E3 Belawan Output'!H35 -> 0 | I82: ='E3 Belawan Output'!I35 -> 114.255 | J82: ='E3 Belawan Output'!J35 -> 113.855 | K82: ='E3 Belawan Output'!K35 -> 0 | L82: ='E3 Belawan Output'!L35 -> 0 | M82: ='E3 Belawan Output'!M35 -> 0 | ... S82: ='E3 Belawan Output'!S35 -> 0
B83: Increase in net working capital | C83: IDR bn | E83: =SUM(F83:S83) -> -4.0513969 | F83: ='E3 Belawan Output'!F27 -> 0 | G83: ='E3 Belawan Output'!G27 -> 0.24078747 | H83: ='E3 Belawan Output'!H27 -> -0.060871613 | I83: ='E3 Belawan Output'!I27 -> -1.3996822 | J83: ='E3 Belawan Output'!J27 -> -1.1185128 | K83: ='E3 Belawan Output'!K27 -> -0.51472847 | L83: ='E3 Belawan Output'!L27 -> -0.57451701 | M83: ='E3 Belawan Output'!M27 -> -0.59345819 | ... S83: ='E3 Belawan Output'!S27 -> -0.3669424
B84: Free cash flow to firm | C84: IDR bn | E84: =SUM(F84:S84) -> 189.95245 | F84: ='E3 Belawan Output'!F28 -> 0 | G84: ='E3 Belawan Output'!G28 -> 10.085834 | H84: ='E3 Belawan Output'!H28 -> 9.9795463 | I84: ='E3 Belawan Output'!I28 -> -96.233993 | J84: ='E3 Belawan Output'!J28 -> -87.982692 | K84: ='E3 Belawan Output'!K28 -> 29.580197 | L84: ='E3 Belawan Output'!L28 -> 32.812732 | M84: ='E3 Belawan Output'!M28 -> 36.284298 | ... S84: ='E3 Belawan Output'!S28 -> 35.230306
B85: Cumulative FCFF | C85: IDR bn | F85: ='E3 Belawan Output'!F29 -> 0 | G85: ='E3 Belawan Output'!G29 -> 10.085834 | H85: ='E3 Belawan Output'!H29 -> 20.06538 | I85: ='E3 Belawan Output'!I29 -> -76.168613 | J85: ='E3 Belawan Output'!J29 -> -164.15131 | K85: ='E3 Belawan Output'!K29 -> -134.57111 | L85: ='E3 Belawan Output'!L29 -> -101.75838 | M85: ='E3 Belawan Output'!M29 -> -65.474078 | ... S85: ='E3 Belawan Output'!S29 -> 189.95245
B86: Net operating assets funded by FSL (PPE + receivables - payables) | C86: IDR bn | F86: ='E3 Belawan Output'!F39 -> 2.3177636 | G86: ='E3 Belawan Output'!G39 -> 2.0769761 | H86: ='E3 Belawan Output'!H39 -> 2.1378478 | I86: ='E3 Belawan Output'!I39 -> 111.22287 | J86: ='E3 Belawan Output'!J39 -> 213.08006 | K86: ='E3 Belawan Output'!K39 -> 200.47846 | L86: ='E3 Belawan Output'!L39 -> 187.93665 | M86: ='E3 Belawan Output'!M39 -> 175.41378 | ... S86: ='E3 Belawan Output'!S39 -> 103.87719
B87: Funding need (cash shortfall to be funded by FSL) | C87: IDR bn | E87: =SUM(F87:S87) -> 184.21669 | F87: ='E3 Belawan Output'!F31 -> 0 | G87: ='E3 Belawan Output'!G31 -> 0 | H87: ='E3 Belawan Output'!H31 -> 0 | I87: ='E3 Belawan Output'!I31 -> 96.233993 | J87: ='E3 Belawan Output'!J31 -> 87.982692 | K87: ='E3 Belawan Output'!K31 -> 0 | L87: ='E3 Belawan Output'!L31 -> 0 | M87: ='E3 Belawan Output'!M31 -> 0 | ... S87: ='E3 Belawan Output'!S31 -> 0
B88: PV at the valuation date of FCFF incl. terminal value (years after 31-Dec-2026) | C88: IDR bn | E88: =SUM(F88:S88) -> 237.96397 | F88: ='E3 Belawan Output'!F47 -> 0 | G88: ='E3 Belawan Output'!G47 -> 0 | H88: ='E3 Belawan Output'!H47 -> 0 | I88: ='E3 Belawan Output'!I47 -> 0 | J88: ='E3 Belawan Output'!J47 -> -78.649715 | K88: ='E3 Belawan Output'!K47 -> 23.637464 | L88: ='E3 Belawan Output'!L47 -> 23.439163 | M88: ='E3 Belawan Output'!M47 -> 23.169589 | ... S88: ='E3 Belawan Output'!S47 -> 144.8314
B89: Returns: | C89: NPV @ 31-Dec-2026 (IDR bn) | D89: ='E3 Belawan Output'!$E$48 -> 237.96397 | E89: Full-life project IRR | F89: =IF(ISNUMBER('E3 Belawan Output'!$E$50),'E3 Belawan Output'!$E$50,"n/a") -> n/a | G89: IRR incl. terminal value | H89: =IF(ISNUMBER('E3 Belawan Output'!$E$51),'E3 Belawan Output'!$E$51,"n/a") -> n/a | I89: Payback year | J89: =IF(ISNUMBER('E3 Belawan Output'!$E$53),'E3 Belawan Output'!$E$53,"n/a") -> 2032 | K89: Total capex (USD m) | L89: ='E3 Belawan Output'!$E$55 -> 14.024593 | M89: Capex after val. date (USD m) | N89: ='E3 Belawan Output'!$E$56 -> 7
B91: E4 WIN stevedoring (Cilegon, Makassar, Surabaya, Medan) — Existing business — WIN
B92: Existing stevedoring business at four ports: per-commodity volume (FY2023 base x growth index) x stevedoring tariff; cost of sales = dock & port facilities fee (share of sales), employee cost, maintenance and insurance; fixed G&A lines; fixed depreciation of existing assets per site. | C92: Input | D92: Calc | E92: Output | G92: ="In valuation: "&'Global Inputs'!$E$92&" | case: "&'Global Inputs'!$F$92&" | FSL interest: "&TEXT('Global Inputs'!$G$92,"0%") -> In valuation: 1 | case: 1 | FSL interest: 100%
B93: Revenue | C93: IDR bn | E93: =SUM(F93:S93) -> 1102.6467 | F93: ='E4 WIN Output'!F11 -> 0 | G93: ='E4 WIN Output'!G11 -> 87.948672 | H93: ='E4 WIN Output'!H11 -> 65.358641 | I93: ='E4 WIN Output'!I11 -> 61.989729 | J93: ='E4 WIN Output'!J11 -> 66.857705 | K93: ='E4 WIN Output'!K11 -> 72.109308 | L93: ='E4 WIN Output'!L11 -> 77.774869 | M93: ='E4 WIN Output'!M11 -> 83.887124 | ... S93: ='E4 WIN Output'!S11 -> 102.46705
B94: EBITDA | C94: IDR bn | E94: =SUM(F94:S94) -> 317.94557 | F94: ='E4 WIN Output'!F15 -> 0 | G94: ='E4 WIN Output'!G15 -> 14.495482 | H94: ='E4 WIN Output'!H15 -> 13.945757 | I94: ='E4 WIN Output'!I15 -> 16.725265 | J94: ='E4 WIN Output'!J15 -> 18.431081 | K94: ='E4 WIN Output'!K15 -> 20.282634 | L94: ='E4 WIN Output'!L15 -> 22.29192 | M94: ='E4 WIN Output'!M15 -> 24.471909 | ... S94: ='E4 WIN Output'!S15 -> 34.748092
B95: EBIT | C95: IDR bn | E95: =SUM(F95:S95) -> 312.23232 | F95: ='E4 WIN Output'!F17 -> 0 | G95: ='E4 WIN Output'!G17 -> 14.056001 | H95: ='E4 WIN Output'!H17 -> 13.506276 | I95: ='E4 WIN Output'!I17 -> 16.285785 | J95: ='E4 WIN Output'!J17 -> 17.9916 | K95: ='E4 WIN Output'!K17 -> 19.843154 | L95: ='E4 WIN Output'!L17 -> 21.852439 | M95: ='E4 WIN Output'!M17 -> 24.032429 | ... S95: ='E4 WIN Output'!S17 -> 34.308612
B96: NOPAT (tax on project EBIT) | C96: IDR bn | E96: =SUM(F96:S96) -> 243.54121 | F96: ='E4 WIN Output'!F19 -> 0 | G96: ='E4 WIN Output'!G19 -> 10.963681 | H96: ='E4 WIN Output'!H19 -> 10.534895 | I96: ='E4 WIN Output'!I19 -> 12.702912 | J96: ='E4 WIN Output'!J19 -> 14.033448 | K96: ='E4 WIN Output'!K19 -> 15.47766 | L96: ='E4 WIN Output'!L19 -> 17.044903 | M96: ='E4 WIN Output'!M19 -> 18.745294 | ... S96: ='E4 WIN Output'!S19 -> 26.760717
B97: Depreciation & amortisation | C97: IDR bn | E97: =SUM(F97:S97) -> -5.7132454 | F97: ='E4 WIN Output'!F16 -> 0 | G97: ='E4 WIN Output'!G16 -> -0.43948042 | H97: ='E4 WIN Output'!H16 -> -0.43948042 | I97: ='E4 WIN Output'!I16 -> -0.43948042 | J97: ='E4 WIN Output'!J16 -> -0.43948042 | K97: ='E4 WIN Output'!K16 -> -0.43948042 | L97: ='E4 WIN Output'!L16 -> -0.43948042 | M97: ='E4 WIN Output'!M16 -> -0.43948042 | ... S97: ='E4 WIN Output'!S16 -> -0.43948042
B98: Capex (USD m) | C98: USD m | E98: =SUM(F98:S98) -> 0 | F98: ='E4 WIN Output'!F34 -> 0 | G98: ='E4 WIN Output'!G34 -> 0 | H98: ='E4 WIN Output'!H34 -> 0 | I98: ='E4 WIN Output'!I34 -> 0 | J98: ='E4 WIN Output'!J34 -> 0 | K98: ='E4 WIN Output'!K34 -> 0 | L98: ='E4 WIN Output'!L34 -> 0 | M98: ='E4 WIN Output'!M34 -> 0 | ... S98: ='E4 WIN Output'!S34 -> 0
B99: Capex (IDR bn) | C99: IDR bn | E99: =SUM(F99:S99) -> 0 | F99: ='E4 WIN Output'!F35 -> 0 | G99: ='E4 WIN Output'!G35 -> 0 | H99: ='E4 WIN Output'!H35 -> 0 | I99: ='E4 WIN Output'!I35 -> 0 | J99: ='E4 WIN Output'!J35 -> 0 | K99: ='E4 WIN Output'!K35 -> 0 | L99: ='E4 WIN Output'!L35 -> 0 | M99: ='E4 WIN Output'!M35 -> 0 | ... S99: ='E4 WIN Output'!S35 -> 0
B100: Increase in net working capital | C100: IDR bn | E100: =SUM(F100:S100) -> -2.8156756 | F100: ='E4 WIN Output'!F27 -> 0 | G100: ='E4 WIN Output'!G27 -> -0.53678605 | H100: ='E4 WIN Output'!H27 -> 0.95801157 | I100: ='E4 WIN Output'!I27 -> -0.091906821 | J100: ='E4 WIN Output'!J27 -> -0.34217935 | K100: ='E4 WIN Output'!K27 -> -0.35675539 | L100: ='E4 WIN Output'!L27 -> -0.41312528 | M100: ='E4 WIN Output'!M27 -> -0.43234553 | ... S100: ='E4 WIN Output'!S27 -> -0.32680758
B101: Free cash flow to firm | C101: IDR bn | E101: =SUM(F101:S101) -> 246.43878 | F101: ='E4 WIN Output'!F28 -> 0 | G101: ='E4 WIN Output'!G28 -> 10.866375 | H101: ='E4 WIN Output'!H28 -> 11.932387 | I101: ='E4 WIN Output'!I28 -> 13.050486 | J101: ='E4 WIN Output'!J28 -> 14.130749 | K101: ='E4 WIN Output'!K28 -> 15.560385 | L101: ='E4 WIN Output'!L28 -> 17.071258 | M101: ='E4 WIN Output'!M28 -> 18.752429 | ... S101: ='E4 WIN Output'!S28 -> 26.87339
B102: Cumulative FCFF | C102: IDR bn | F102: ='E4 WIN Output'!F29 -> 0 | G102: ='E4 WIN Output'!G29 -> 10.866375 | H102: ='E4 WIN Output'!H29 -> 22.798763 | I102: ='E4 WIN Output'!I29 -> 35.849249 | J102: ='E4 WIN Output'!J29 -> 49.979998 | K102: ='E4 WIN Output'!K29 -> 65.540383 | L102: ='E4 WIN Output'!L29 -> 82.611641 | M102: ='E4 WIN Output'!M29 -> 101.36407 | ... S102: ='E4 WIN Output'!S29 -> 246.43878
B103: Net operating assets funded by FSL (PPE + receivables - payables) | C103: IDR bn | F103: ='E4 WIN Output'!F39 -> 4.4436731 | G103: ='E4 WIN Output'!G39 -> 4.9804592 | H103: ='E4 WIN Output'!H39 -> 4.0224476 | I103: ='E4 WIN Output'!I39 -> 4.1143544 | J103: ='E4 WIN Output'!J39 -> 4.4565338 | K103: ='E4 WIN Output'!K39 -> 4.8132892 | L103: ='E4 WIN Output'!L39 -> 5.2264145 | M103: ='E4 WIN Output'!M39 -> 5.65876 | ... S103: ='E4 WIN Output'!S39 -> 7.2593487
B104: Funding need (cash shortfall to be funded by FSL) | C104: IDR bn | E104: =SUM(F104:S104) -> 0 | F104: ='E4 WIN Output'!F31 -> 0 | G104: ='E4 WIN Output'!G31 -> 0 | H104: ='E4 WIN Output'!H31 -> 0 | I104: ='E4 WIN Output'!I31 -> 0 | J104: ='E4 WIN Output'!J31 -> 0 | K104: ='E4 WIN Output'!K31 -> 0 | L104: ='E4 WIN Output'!L31 -> 0 | M104: ='E4 WIN Output'!M31 -> 0 | ... S104: ='E4 WIN Output'!S31 -> 0
B105: PV at the valuation date of FCFF incl. terminal value (years after 31-Dec-2026) | C105: IDR bn | E105: =SUM(F105:S105) -> 213.66342 | F105: ='E4 WIN Output'!F47 -> 0 | G105: ='E4 WIN Output'!G47 -> 0 | H105: ='E4 WIN Output'!H47 -> 0 | I105: ='E4 WIN Output'!I47 -> 0 | J105: ='E4 WIN Output'!J47 -> 12.631796 | K105: ='E4 WIN Output'!K47 -> 12.434266 | L105: ='E4 WIN Output'!L47 -> 12.194535 | M105: ='E4 WIN Output'!M47 -> 11.974493 | ... S105: ='E4 WIN Output'!S47 -> 110.47621
B106: Returns: | C106: NPV @ 31-Dec-2026 (IDR bn) | D106: ='E4 WIN Output'!$E$48 -> 213.66342 | E106: Full-life project IRR | F106: =IF(ISNUMBER('E4 WIN Output'!$E$50),'E4 WIN Output'!$E$50,"n/a") -> n/a | G106: IRR incl. terminal value | H106: =IF(ISNUMBER('E4 WIN Output'!$E$51),'E4 WIN Output'!$E$51,"n/a") -> n/a | I106: Payback year | J106: =IF(ISNUMBER('E4 WIN Output'!$E$53),'E4 WIN Output'!$E$53,"n/a") -> n/a | K106: Total capex (USD m) | L106: ='E4 WIN Output'!$E$55 -> 0 | M106: Capex after val. date (USD m) | N106: ='E4 WIN Output'!$E$56 -> 0
B108: P01 Cigading Wharf 2 — Committed project — SGT Cigading
...

Sheet FSL Financials — Without BUMN
B1: FSL FINANCIALS — WITHOUT BUMN (integrated income statement, balance sheet, cash flow)
B2: Sum of project outputs included in the Without-BUMN case + corporate items (LT loan, existing fixed assets, other balances). IDR bn. Green = link; black = formula.
B3: Go to: | C3: Navigation | D3: Global Inputs | E3: Project Summary | F3: Funding | G3: FSL w/o BUMN | H3: FSL w/ BUMN | I3: Val w/o BUMN | J3: Val w/ BUMN | K3: Checks | L3: Model Flow
B5: Year | C5: Unit | D5: Type | E5: Flag / total | F5: ='Global Inputs'!F$5 -> 2023 | G5: ='Global Inputs'!G$5 -> 2024 | H5: ='Global Inputs'!H$5 -> 2025 | I5: ='Global Inputs'!I$5 -> 2026 | J5: ='Global Inputs'!J$5 -> 2027 | K5: ='Global Inputs'!K$5 -> 2028 | L5: ='Global Inputs'!L$5 -> 2029 | M5: ='Global Inputs'!M$5 -> 2030 | ... S5: ='Global Inputs'!S$5 -> 2036 | T5: Source (v29 reference / basis) | U5: Note
B6: Period end | F6: ='Global Inputs'!F$6 -> 45291 | G6: ='Global Inputs'!G$6 -> 45657 | H6: ='Global Inputs'!H$6 -> 46022 | I6: ='Global Inputs'!I$6 -> 46387 | J6: ='Global Inputs'!J$6 -> 46752 | K6: ='Global Inputs'!K$6 -> 47118 | L6: ='Global Inputs'!L$6 -> 47483 | M6: ='Global Inputs'!M$6 -> 47848 | ... S6: ='Global Inputs'!S$6 -> 50040
B7: Days in year | F7: ='Global Inputs'!F$7 -> 365 | G7: ='Global Inputs'!G$7 -> 366 | H7: ='Global Inputs'!H$7 -> 365 | I7: ='Global Inputs'!I$7 -> 365 | J7: ='Global Inputs'!J$7 -> 365 | K7: ='Global Inputs'!K$7 -> 366 | L7: ='Global Inputs'!L$7 -> 365 | M7: ='Global Inputs'!M$7 -> 365 | ... S7: ='Global Inputs'!S$7 -> 366
B8: Forecast flag (1 = forecast year) | F8: ='Global Inputs'!F$8 -> 0 | G8: ='Global Inputs'!G$8 -> 1 | H8: ='Global Inputs'!H$8 -> 1 | I8: ='Global Inputs'!I$8 -> 1 | J8: ='Global Inputs'!J$8 -> 1 | K8: ='Global Inputs'!K$8 -> 1 | L8: ='Global Inputs'!L$8 -> 1 | M8: ='Global Inputs'!M$8 -> 1 | ... S8: ='Global Inputs'!S$8 -> 1
B10: Case: Without BUMN — scope and settings
B11: Company case | E11: Without BUMN
B12: Projects included in this case (count) | C12: count | E12: ='Global Inputs'!$K$89+'Global Inputs'!$K$90+'Global Inputs'!$K$91+'Global Inputs'!$K$92+'Global Inputs'!$K$93+'Global Inputs'!$K$94+'Global Inputs'!$K$95+'Global Inputs'!$K$96+'Global Inputs'!$K$97+'Global Inputs'!$K$98+'Global Inputs'!$K$99+'Global Inputs'!$K$100+'Global Inputs'!$K$101+'Global Inputs'!$K$102 -> 11
B13: Scope | E13: Existing businesses + committed and planned projects that are switched on in the Global Inputs register; excludes BUMN operatorship schemes (case 2 projects).
B14: This case drives the Funding Requirement (1 = yes) | C14: 0/1 | E14: =IF('Global Inputs'!$E$36=1,1,0) -> 1
B15: Sapphire is excluded (v29 Output_FSL!D2 = 0). Corporate items (LT loan, existing fixed assets, other assets / liabilities, inventory) are held centrally and not allocated to projects.
B17: A. Income statement (IDR bn)
B18: Revenue | C18: IDR bn | E18: =SUM(F18:S18) -> 9917.547 | F18: =F104 -> 0 | G18: =G104 -> 305.28841 | H18: =H104 -> 427.60264 | I18: =I104 -> 494.57084 | J18: =J104 -> 619.92611 | K18: =K104 -> 702.02883 | L18: =L104 -> 773.76406 | M18: =M104 -> 807.88996 | ... S18: =S104 -> 1040.9483
B19: Cost of sales | C19: IDR bn | E19: =SUM(F19:S19) -> -2137.7465 | F19: =F120 -> 0 | G19: =G120 -> -122.54304 | H19: =H120 -> -114.65874 | I19: =I120 -> -112.22494 | J19: =J120 -> -124.58111 | K19: =K120 -> -146.7349 | L19: =L120 -> -157.56432 | M19: =M120 -> -167.6231 | ... S19: =S120 -> -216.9311
B20: Gross profit | C20: IDR bn | E20: =SUM(F20:S20) -> 7779.8005 | F20: =F18+F19 -> 0 | G20: =G18+G19 -> 182.74537 | H20: =H18+H19 -> 312.94389 | I20: =I18+I19 -> 382.3459 | J20: =J18+J19 -> 495.345 | K20: =K18+K19 -> 555.29393 | L20: =L18+L19 -> 616.19974 | M20: =M18+M19 -> 640.26686 | ... S20: =S18+S19 -> 824.01717
B21: Operating expenses | C21: IDR bn | E21: =SUM(F21:S21) -> -1562.1657 | F21: =F136 -> 0 | G21: =G136 -> -28.510101 | H21: =H136 -> -49.385568 | I21: =I136 -> -73.173995 | J21: =J136 -> -106.54848 | K21: =K136 -> -119.72399 | L21: =L136 -> -128.01099 | M21: =M136 -> -132.96013 | ... S21: =S136 -> -168.11905
B22: EBITDA | C22: IDR bn | E22: =SUM(F22:S22) -> 6217.6349 | F22: =F20+F21 -> 0 | G22: =G20+G21 -> 154.23527 | H22: =H20+H21 -> 263.55833 | I22: =I20+I21 -> 309.1719 | J22: =J20+J21 -> 388.79652 | K22: =K20+K21 -> 435.56994 | L22: =L20+L21 -> 488.18875 | M22: =M20+M21 -> 507.30672 | ... S22: =S20+S21 -> 655.89811
B23: Depreciation & amortisation | C23: IDR bn | E23: =SUM(F23:S23) -> -1756.082 | F23: =F152 -> 0 | G23: =G152 -> -88.373086 | H23: =H152 -> -113.59971 | I23: =I152 -> -127.99828 | J23: =J152 -> -141.84087 | K23: =K152 -> -149.09796 | L23: =L152 -> -151.10669 | M23: =M152 -> -151.11559 | ... S23: =S152 -> -125.83761
B24: EBIT | C24: IDR bn | E24: =SUM(F24:S24) -> 4461.5529 | F24: =F22+F23 -> 0 | G24: =G22+G23 -> 65.862187 | H24: =H22+H23 -> 149.95862 | I24: =I22+I23 -> 181.17363 | J24: =J22+J23 -> 246.95565 | K24: =K22+K23 -> 286.47198 | L24: =L22+L23 -> 337.08206 | M24: =M22+M23 -> 356.19113 | ... S24: =S22+S23 -> 530.0605
B25: Corporate financing cost — existing / LT loan interest (Financing sheet) | C25: IDR bn | E25: =SUM(F25:S25) -> -43.591792 | F25: =-Financing!F22 -> 0 | G25: =-Financing!G22 -> -5.4709055 | H25: =-Financing!H22 -> -15.273462 | I25: =-Financing!I22 -> -15.273462 | J25: =-Financing!J22 -> -7.5739631 | K25: =-Financing!K22 -> 0 | L25: =-Financing!L22 -> 0 | M25: =-Financing!M22 -> 0 | ... S25: =-Financing!S22 -> 0
B26: Profit before tax | C26: IDR bn | E26: =SUM(F26:S26) -> 4417.9611 | F26: =F24+F25 -> 0 | G26: =G24+G25 -> 60.391281 | H26: =H24+H25 -> 134.68516 | I26: =I24+I25 -> 165.90016 | J26: =J24+J25 -> 239.38169 | K26: =K24+K25 -> 286.47198 | L26: =L24+L25 -> 337.08206 | M26: =M24+M25 -> 356.19113 | ... S26: =S24+S25 -> 530.0605
B27: Tax on project EBIT (sum of project lines, v29 method) | C27: IDR bn | E27: =SUM(F27:S27) -> -998.69992 | F27: =F168 -> 0 | G27: =G168 -> -19.962238 | H27: =H168 -> -36.944577 | I27: =I168 -> -43.922705 | J27: =J168 -> -56.111623 | K27: =K168 -> -64.621449 | L27: =L168 -> -74.417833 | M27: =M168 -> -78.390822 | ... S27: =S168 -> -116.61331
B28: Tax shield on corporate interest (Global switch) | C28: IDR bn | E28: =SUM(F28:S28) -> 9.5901942 | F28: =Financing!F23 -> 0 | G28: =Financing!G23 -> 1.2035992 | H28: =Financing!H23 -> 3.3601615 | I28: =Financing!I23 -> 3.3601615 | J28: =Financing!J23 -> 1.6662719 | K28: =Financing!K23 -> 0 | L28: =Financing!L23 -> 0 | M28: =Financing!M23 -> 0 | ... S28: =Financing!S23 -> 0
B29: Tax | C29: IDR bn | E29: =SUM(F29:S29) -> -989.10973 | F29: =F27+F28 -> 0 | G29: =G27+G28 -> -18.758639 | H29: =H27+H28 -> -33.584415 | I29: =I27+I28 -> -40.562544 | J29: =J27+J28 -> -54.445351 | K29: =K27+K28 -> -64.621449 | L29: =L27+L28 -> -74.417833 | M29: =M27+M28 -> -78.390822 | ... S29: =S27+S28 -> -116.61331
B30: Net profit | C30: IDR bn | E30: =SUM(F30:S30) -> 3428.8513 | F30: =F26+F29 -> 0 | G30: =G26+G29 -> 41.632643 | H30: =H26+H29 -> 101.10074 | I30: =I26+I29 -> 125.33762 | J30: =J26+J29 -> 184.93634 | K30: =K26+K29 -> 221.85053 | L30: =L26+L29 -> 262.66423 | M30: =M26+M29 -> 277.80031 | ... S30: =S26+S29 -> 413.44719
B31: Memo: non-controlling share of project NOPAT (NPLOG 35% etc.; v29 consolidates 100%) | C31: IDR bn | E31: =SUM(F31:S31) -> 332.86295 | F31: =F200 -> 0 | G31: =G200 -> 19.320159 | H31: =H200 -> 20.112556 | I31: =I200 -> 20.642014 | J31: =J200 -> 21.466169 | K31: =K200 -> 22.30618 | L31: =L200 -> 24.368473 | M31: =M200 -> 25.284557 | ... S31: =S200 -> 32.733213
B32: Memo: net profit attributable to FSL shareholders | C32: IDR bn | E32: =SUM(F32:S32) -> 3095.9884 | F32: =F30-F31 -> 0 | G32: =G30-G31 -> 22.312483 | H32: =H30-H31 -> 80.988184 | I32: =I30-I31 -> 104.69561 | J32: =J30-J31 -> 163.47017 | K32: =K30-K31 -> 199.54435 | L32: =L30-L31 -> 238.29575 | M32: =M30-M31 -> 252.51575 | ... S32: =S30-S31 -> 380.71398
B33: EBITDA margin | C33: % | F33: =IF(F18=0,0,F22/F18) -> 0 | G33: =IF(G18=0,0,G22/G18) -> 0.50521168 | H33: =IF(H18=0,0,H22/H18) -> 0.61636273 | I33: =IF(I18=0,0,I22/I18) -> 0.62513168 | J33: =IF(J18=0,0,J22/J18) -> 0.6271659 | K33: =IF(K18=0,0,K22/K18) -> 0.62044452 | L33: =IF(L18=0,0,L22/L18) -> 0.63092714 | M33: =IF(M18=0,0,M22/M18) -> 0.62794038 | ... S33: =IF(S18=0,0,S22/S18) -> 0.63009674
B34: Net margin | C34: % | F34: =IF(F18=0,0,F30/F18) -> 0 | G34: =IF(G18=0,0,G30/G18) -> 0.13637151 | H34: =IF(H18=0,0,H30/H18) -> 0.23643619 | I34: =IF(I18=0,0,I30/I18) -> 0.25342703 | J34: =IF(J18=0,0,J30/J18) -> 0.29831997 | K34: =IF(K18=0,0,K30/K18) -> 0.31601342 | L34: =IF(L18=0,0,L30/L18) -> 0.33946294 | M34: =IF(M18=0,0,M30/M18) -> 0.34385909 | ... S34: =IF(S18=0,0,S30/S18) -> 0.39718323
B36: B. Balance sheet (IDR bn) — 2023 column = opening balances (v29 Output_FSL column I)
B37: Cash and equivalents | C37: IDR bn | F37: =F66 -> 60.6389 | G37: =G66 -> 32.209449 | H37: =H66 -> 192.17176 | I37: =I66 -> 3 | J37: =J66 -> 155.3344 | K37: =K66 -> 458.32171 | L37: =L66 -> 792.44639 | M37: =M66 -> 1142.227 | ... S37: =S66 -> 3554.0774
B38: Inventory (held flat, centrally) | C38: IDR bn | F38: ='Global Inputs'!$E$30 -> 0.519811 | G38: ='Global Inputs'!$E$30 -> 0.519811 | H38: ='Global Inputs'!$E$30 -> 0.519811 | I38: ='Global Inputs'!$E$30 -> 0.519811 | J38: ='Global Inputs'!$E$30 -> 0.519811 | K38: ='Global Inputs'!$E$30 -> 0.519811 | L38: ='Global Inputs'!$E$30 -> 0.519811 | M38: ='Global Inputs'!$E$30 -> 0.519811 | ... S38: ='Global Inputs'!$E$30 -> 0.519811
B39: Trade receivables (sum of projects) | C39: IDR bn | F39: =F264 -> 45 | G39: =G264 -> 37.535461 | H39: =H264 -> 52.718133 | I39: =I264 -> 60.974487 | J39: =J264 -> 76.429247 | K39: =K264 -> 86.31502 | L39: =L264 -> 95.395569 | M39: =M264 -> 99.602871 | ... S39: =S264 -> 127.98544
B40: Fixed assets — existing businesses (unallocated; opening NBV less existing-asset depreciation) | C40: IDR bn | F40: ='Global Inputs'!$E$61 -> 826.022 | G40: =F40-G312 -> 737.64891 | H40: =G40-H312 -> 649.26776 | I40: =H40-I312 -> 561.49537 | J40: =I40-J312 -> 475.94121 | K40: =J40-K312 -> 390.28089 | L40: =K40-L312 -> 302.61185 | M40: =L40-M312 -> 214.9339 | N40: =M40-N312 -> 127.24686 | ... S40: =R40-S312 -> -321.33107
B41: Fixed assets — project capex (sum of project NBV) | C41: IDR bn | F41: =F296 -> 198.433 | G41: =G296 -> 323.6735 | H41: =H296 -> 313.09344 | I41: =I296 -> 692.63961 | J41: =J296 -> 796.35653 | K41: =K296 -> 732.91888 | L41: =L296 -> 669.48124 | M41: =M296 -> 606.04359 | ... S41: =S296 -> 309.35875
B42: Other assets (Dec-23 balance excl. reclassified assets under construction; held flat) | C42: IDR bn | F42: ='Global Inputs'!$E$109 -> 132.83 | G42: ='Global Inputs'!$E$109 -> 132.83 | H42: ='Global Inputs'!$E$109 -> 132.83 | I42: ='Global Inputs'!$E$109 -> 132.83 | J42: ='Global Inputs'!$E$109 -> 132.83 | K42: ='Global Inputs'!$E$109 -> 132.83 | L42: ='Global Inputs'!$E$109 -> 132.83 | M42: ='Global Inputs'!$E$109 -> 132.83 | ... S42: ='Global Inputs'!$E$109 -> 132.83
B43: Total assets | C43: IDR bn | F43: =F37+F38+F39+F40+F41+F42 -> 1263.4437 | G43: =G37+G38+G39+G40+G41+G42 -> 1264.4171 | H43: =H37+H38+H39+H40+H41+H42 -> 1340.6009 | I43: =I37+I38+I39+I40+I41+I42 -> 1451.4593 | J43: =J37+J38+J39+J40+J41+J42 -> 1637.4112 | K43: =K37+K38+K39+K40+K41+K42 -> 1801.1863 | L43: =L37+L38+L39+L40+L41+L42 -> 1993.2849 | M43: =M37+M38+M39+M40+M41+M42 -> 2196.1572 | ... S43: =S37+S38+S39+S40+S41+S42 -> 3803.4403
B44: Trade payables (sum of projects) | C44: IDR bn | F44: =-F280 -> 14.671986 | G44: =-G280 -> 10.044511 | H44: =-H280 -> 9.4240062 | I44: =-I280 -> 9.223968 | J44: =-J280 -> 10.239543 | K44: =-K280 -> 12.027451 | L44: =-L280 -> 12.950492 | M44: =-M280 -> 13.777241 | ... S44: =-S280 -> 17.781238
B45: Bank loans (Financing sheet) | C45: IDR bn | F45: =Financing!F24 -> 224.518 | G45: =Financing!G24 -> 195.18 | H45: =Financing!H24 -> 195.18 | I45: =Financing!I24 -> 195.18 | J45: =Financing!J24 -> 0 | K45: =Financing!K24 -> 0 | L45: =Financing!L24 -> 0 | M45: =Financing!M24 -> 0 | ... S45: =Financing!S24 -> 0
B46: Other liabilities (Dec-23 balance; held flat) | C46: IDR bn | F46: ='Global Inputs'!$E$65 -> 55.9245 | G46: ='Global Inputs'!$E$65 -> 55.9245 | H46: ='Global Inputs'!$E$65 -> 55.9245 | I46: ='Global Inputs'!$E$65 -> 55.9245 | J46: ='Global Inputs'!$E$65 -> 55.9245 | K46: ='Global Inputs'!$E$65 -> 55.9245 | L46: ='Global Inputs'!$E$65 -> 55.9245 | M46: ='Global Inputs'!$E$65 -> 55.9245 | ... S46: ='Global Inputs'!$E$65 -> 55.9245
B47: Total liabilities | C47: IDR bn | F47: =F44+F45+F46 -> 295.11449 | G47: =G44+G45+G46 -> 261.14901 | H47: =H44+H45+H46 -> 260.52851 | I47: =I44+I45+I46 -> 260.32847 | J47: =J44+J45+J46 -> 66.164043 | K47: =K44+K45+K46 -> 67.951951 | L47: =L44+L45+L46 -> 68.874992 | M47: =M44+M45+M46 -> 69.701741 | ... S47: =S44+S45+S46 -> 73.705738
B48: Paid-in capital (opening + capital injection) | C48: IDR bn | F48: =Financing!F36 -> 677.731 | G48: =Financing!G36 -> 677.731 | H48: =Financing!H36 -> 677.731 | I48: =Financing!I36 -> 677.731 | J48: =Financing!J36 -> 872.911 | K48: =Financing!K36 -> 872.911 | L48: =Financing!L36 -> 872.911 | M48: =Financing!M36 -> 872.911 | ... S48: =Financing!S36 -> 872.911
B49: Retained earnings | C49: IDR bn | F49: ='Global Inputs'!$E$67 -> 290.592 | G49: =F49+G30+G79 -> 325.5309 | H49: =G49+H30+H79 -> 402.33518 | I49: =H49+I30+I79 -> 513.39358 | J49: =I49+J30+J79 -> 698.32992 | K49: =J49+K30+K79 -> 860.31714 | L49: =K49+L30+L79 -> 1051.4926 | M49: =L49+M30+M79 -> 1253.5382 | N49: =M49+N30+N79 -> 1478.0965 | ... S49: =R49+S30+S79 -> 2856.8173
B50: Total equity | C50: IDR bn | F50: =F48+F49 -> 968.323 | G50: =G48+G49 -> 1003.2619 | H50: =H48+H49 -> 1080.0662 | I50: =I48+I49 -> 1191.1246 | J50: =J48+J49 -> 1571.2409 | K50: =K48+K49 -> 1733.2281 | L50: =L48+L49 -> 1924.4036 | M50: =M48+M49 -> 2126.4492 | ... S50: =S48+S49 -> 3729.7283
B51: Balance check: assets - liabilities - equity (2023 shows the v29 opening residual of 0.006) | C51: IDR bn | F51: =F43-F47-F50 -> 0.0062250171 | G51: =G43-G47-G50 -> 0.0062250171 | H51: =H43-H47-H50 -> 0.0062250171 | I51: =I43-I47-I50 -> 0.0062250171 | J51: =J43-J47-J50 -> 0.0062250171 | K51: =K43-K47-K50 -> 0.0062250171 | L51: =L43-L47-L50 -> 0.0062250171 | M51: =M43-M47-M50 -> 0.0062250171 | ... S51: =S43-S47-S50 -> 0.0062250171
B53: C. Cash flow statement (IDR bn)
B54: Net profit | C54: IDR bn | E54: =SUM(F54:S54) -> 3428.8513 | F54: =F30 -> 0 | G54: =G30 -> 41.632643 | H54: =H30 -> 101.10074 | I54: =I30 -> 125.33762 | J54: =J30 -> 184.93634 | K54: =K30 -> 221.85053 | L54: =L30 -> 262.66423 | M54: =M30 -> 277.80031 | ... S54: =S30 -> 413.44719
B55: Add back depreciation & amortisation | C55: IDR bn | E55: =SUM(F55:S55) -> 1756.082 | F55: =-F23 -> 0 | G55: =-G23 -> 88.373086 | H55: =-H23 -> 113.59971 | I55: =-I23 -> 127.99828 | J55: =-J23 -> 141.84087 | K55: =-K23 -> 149.09796 | L55: =-L23 -> 151.10669 | M55: =-M23 -> 151.11559 | ... S55: =-S23 -> 125.83761
B56: Increase in net working capital | C56: IDR bn | E56: =SUM(F56:S56) -> -79.876191 | F56: =-F248 -> 0 | G56: =-G248 -> 2.8370648 | H56: =-H248 -> -15.803178 | I56: =-I248 -> -8.4563923 | J56: =-J248 -> -14.439184 | K56: =-K248 -> -8.0978655 | L56: =-L248 -> -8.1575083 | M56: =-M248 -> -3.3805532 | ... S56: =-S248 -> -3.2820663
B57: Cash flow from operations | C57: IDR bn | E57: =SUM(F57:S57) -> 5105.0572 | F57: =F54+F55+F56 -> 0 | G57: =G54+G55+G56 -> 132.84279 | H57: =H54+H55+H56 -> 198.89727 | I57: =I54+I55+I56 -> 244.8795 | J57: =J54+J55+J56 -> 312.33802 | K57: =K54+K55+K56 -> 362.85062 | L57: =L54+L55+L56 -> 405.61341 | M57: =M54+M55+M56 -> 425.53535 | ... S57: =S54+S55+S56 -> 536.00274
B58: Capex (all projects in this case) | C58: IDR bn | E58: =SUM(F58:S58) -> -918.08767 | F58: =-F216 -> -198.433 | G58: =-G216 -> -125.2405 | H58: =-H216 -> -14.6385 | I58: =-I216 -> -419.77205 | J58: =-J216 -> -160.00362 | K58: =-K216 -> 0 | L58: =-L216 -> 0 | M58: =-M216 -> 0 | ... S58: =-S216 -> 0
B59: Cash flow from investing | C59: IDR bn | E59: =SUM(F59:S59) -> -918.08767 | F59: =F58 -> -198.433 | G59: =G58 -> -125.2405 | H59: =H58 -> -14.6385 | I59: =I58 -> -419.77205 | J59: =J58 -> -160.00362 | K59: =K58 -> 0 | L59: =L58 -> 0 | M59: =M58 -> 0 | ... S59: =S58 -> 0
B60: Capital injection received (Financing sheet) | C60: IDR bn | E60: =SUM(F60:S60) -> 195.18 | F60: =Financing!F33 -> 0 | G60: =Financing!G33 -> 0 | H60: =Financing!H33 -> 0 | I60: =Financing!I33 -> 0 | J60: =Financing!J33 -> 195.18 | K60: =Financing!K33 -> 0 | L60: =Financing!L33 -> 0 | M60: =Financing!M33 -> 0 | ... S60: =Financing!S33 -> 0
B61: Loan repayments — other loans FY2024 and LT loan at the injection date | C61: IDR bn | E61: =SUM(F61:S61) -> -224.518 | F61: =-Financing!F25 -> 0 | G61: =-Financing!G25 -> -29.338 | H61: =-Financing!H25 -> 0 | I61: =-Financing!I25 -> 0 | J61: =-Financing!J25 -> -195.18 | K61: =-Financing!K25 -> 0 | L61: =-Financing!L25 -> 0 | M61: =-Financing!M25 -> 0 | ... S61: =-Financing!S25 -> 0
B62: Dividends paid | C62: IDR bn | E62: =SUM(F62:S62) -> -862.62601 | F62: =F79 -> 0 | G62: =G79 -> -6.693745 | H62: =H79 -> -24.296455 | I62: =I79 -> -14.279223 | J62: =J79 -> 0 | K62: =K79 -> -59.863306 | L62: =L79 -> -71.488726 | M62: =M79 -> -75.754725 | ... S62: =S79 -> -114.21419
B63: Cash flow from financing | C63: IDR bn | E63: =SUM(F63:S63) -> -891.96401 | F63: =F60+F61+F62 -> 0 | G63: =G60+G61+G62 -> -36.031745 | H63: =H60+H61+H62 -> -24.296455 | I63: =I60+I61+I62 -> -14.279223 | J63: =J60+J61+J62 -> 0 | K63: =K60+K61+K62 -> -59.863306 | L63: =L60+L61+L62 -> -71.488726 | M63: =M60+M61+M62 -> -75.754725 | ... S63: =S60+S61+S62 -> -114.21419
B64: Net cash flow | C64: IDR bn | E64: =SUM(F64:S64) -> 3295.0055 | F64: =F57+F59+F63 -> -198.433 | G64: =G57+G59+G63 -> -28.429451 | H64: =H57+H59+H63 -> 159.96232 | I64: =I57+I59+I63 -> -189.17176 | J64: =J57+J59+J63 -> 152.3344 | K64: =K57+K59+K63 -> 302.98732 | L64: =L57+L59+L63 -> 334.12468 | M64: =M57+M59+M63 -> 349.78062 | ... S64: =S57+S59+S63 -> 421.78854
B65: Opening cash | C65: IDR bn | F65: =E66 -> 0 | G65: =F66 -> 60.6389 | H65: =G66 -> 32.209449 | I65: =H66 -> 192.17176 | J65: =I66 -> 3 | K65: =J66 -> 155.3344 | L65: =K66 -> 458.32171 | M65: =L66 -> 792.44639 | ... S65: =R66 -> 3132.2888
B66: Closing cash | C66: IDR bn | F66: ='Global Inputs'!$E$58 -> 60.6389 | G66: =G65+G64 -> 32.209449 | H66: =H65+H64 -> 192.17176 | I66: =I65+I64 -> 3 | J66: =J65+J64 -> 155.3344 | K66: =K65+K64 -> 458.32171 | L66: =L65+L64 -> 792.44639 | M66: =M65+M64 -> 1142.227 | N66: =N65+N64 -> 1511.555 | ... S66: =S65+S64 -> 3554.0774
B67: Check: closing cash = pre-equity cash path + cumulative injection | C67: IDR bn | F67: =F66-(F80+Financing!F35) -> 0 | G67: =G66-(G80+Financing!G35) -> 0 | H67: =H66-(H80+Financing!H35) -> 0 | I67: =I66-(I80+Financing!I35) -> 0 | J67: =J66-(J80+Financing!J35) -> 0 | K67: =K66-(K80+Financing!K35) -> 0 | L67: =L66-(L80+Financing!L35) -> 0 | M67: =M66-(M80+Financing!M35) -> 0 | ... S67: =S66-(S80+Financing!S35) -> 0
B69: D. Funding roll-forward and dividends (this case) — cash BEFORE new equity; dividends are never paid out of the injection
B70: Opening cash — pre-equity path | C70: IDR bn | F70: =E80 -> 0 | G70: =F80 -> 60.6389 | H70: =G80 -> 32.209449 | I70: =H80 -> 192.17176 | J70: =I80 -> 3 | K70: =J80 -> -39.845605 | L70: =K80 -> 263.14171 | M70: =L80 -> 597.26639 | ... S70: =R80 -> 2937.1088
B71: Cash flow from operations | C71: IDR bn | F71: =F57 -> 0 | G71: =G57 -> 132.84279 | H71: =H57 -> 198.89727 | I71: =I57 -> 244.8795 | J71: =J57 -> 312.33802 | K71: =K57 -> 362.85062 | L71: =L57 -> 405.61341 | M71: =M57 -> 425.53535 | ... S71: =S57 -> 536.00274
B72: Capex | C72: IDR bn | F72: =F58 -> -198.433 | G72: =G58 -> -125.2405 | H72: =H58 -> -14.6385 | I72: =I58 -> -419.77205 | J72: =J58 -> -160.00362 | K72: =K58 -> 0 | L72: =L58 -> 0 | M72: =M58 -> 0 | ... S72: =S58 -> 0
B73: Debt service (principal): other loans FY2024, LT loan at the injection date | C73: IDR bn | F73: =F61 -> 0 | G73: =G61 -> -29.338 | H73: =H61 -> 0 | I73: =I61 -> 0 | J73: =J61 -> -195.18 | K73: =K61 -> 0 | L73: =L61 -> 0 | M73: =M61 -> 0 | ... S73: =S61 -> 0
B74: Cash before dividends and new equity | C74: IDR bn | F74: =F70+F71+F72+F73 -> -198.433 | G74: =G70+G71+G72+G73 -> 38.903194 | H74: =H70+H71+H72+H73 -> 216.46822 | I74: =I70+I71+I72+I73 -> 17.279223 | J74: =J70+J71+J72+J73 -> -39.845605 | K74: =K70+K71+K72+K73 -> 323.00502 | L74: =L70+L71+L72+L73 -> 668.75512 | M74: =M70+M71+M72+M73 -> 1022.8017 | ... S74: =S70+S71+S72+S73 -> 3473.1116
B75: Dividend cap 1: cash available above the minimum cash (pre-equity) | C75: IDR bn | F75: =MAX(0,F74-'Global Inputs'!$E$82) -> 0 | G75: =MAX(0,G74-'Global Inputs'!$E$82) -> 35.903194 | H75: =MAX(0,H74-'Global Inputs'!$E$82) -> 213.46822 | I75: =MAX(0,I74-'Global Inputs'!$E$82) -> 14.279223 | J75: =MAX(0,J74-'Global Inputs'!$E$82) -> 0 | K75: =MAX(0,K74-'Global Inputs'!$E$82) -> 320.00502 | L75: =MAX(0,L74-'Global Inputs'!$E$82) -> 665.75512 | M75: =MAX(0,M74-'Global Inputs'!$E$82) -> 1019.8017 | ... S75: =MAX(0,S74-'Global Inputs'!$E$82) -> 3470.1116
B76: Profit attributable to FSL shareholders (net profit less non-controlling share) | C76: IDR bn | F76: =F30-F31 -> 0 | G76: =G30-G31 -> 22.312483 | H76: =H30-H31 -> 80.988184 | I76: =I30-I31 -> 104.69561 | J76: =J30-J31 -> 163.47017 | K76: =K30-K31 -> 199.54435 | L76: =L30-L31 -> 238.29575 | M76: =M30-M31 -> 252.51575 | ... S76: =S30-S31 -> 380.71398
B77: Dividend cap 2: payout ratio x attributable profit | C77: IDR bn | F77: =MAX(0,'Global Inputs'!$E$83*F76) -> 0 | G77: =MAX(0,'Global Inputs'!$E$83*G76) -> 6.693745 | H77: =MAX(0,'Global Inputs'!$E$83*H76) -> 24.296455 | I77: =MAX(0,'Global Inputs'!$E$83*I76) -> 31.408682 | J77: =MAX(0,'Global Inputs'!$E$83*J76) -> 49.04105 | K77: =MAX(0,'Global Inputs'!$E$83*K76) -> 59.863306 | L77: =MAX(0,'Global Inputs'!$E$83*L76) -> 71.488726 | M77: =MAX(0,'Global Inputs'!$E$83*M76) -> 75.754725 | ... S77: =MAX(0,'Global Inputs'!$E$83*S76) -> 114.21419
B78: Dividend cap 3: net profit + opening retained earnings - statutory reserve | C78: IDR bn | F78: =MAX(0,F30+E49-'Global Inputs'!$E$84*'Global Inputs'!$E$24/1000*'Global Inputs'!$E$85) -> 0 | G78: =MAX(0,G30+F49-'Global Inputs'!$E$84*'Global Inputs'!$E$24/1000*'Global Inputs'!$E$85) -> 273.67064 | H78: =MAX(0,H30+G49-'Global Inputs'!$E$84*'Global Inputs'!$E$24/1000*'Global Inputs'!$E$85) -> 368.07764 | I78: =MAX(0,I30+H49-'Global Inputs'!$E$84*'Global Inputs'!$E$24/1000*'Global Inputs'!$E$85) -> 469.1188 | J78: =MAX(0,J30+I49-'Global Inputs'!$E$84*'Global Inputs'!$E$24/1000*'Global Inputs'!$E$85) -> 639.77592 | K78: =MAX(0,K30+J49-'Global Inputs'!$E$84*'Global Inputs'!$E$24/1000*'Global Inputs'!$E$85) -> 861.62645 | L78: =MAX(0,L30+K49-'Global Inputs'!$E$84*'Global Inputs'!$E$24/1000*'Global Inputs'!$E$85) -> 1064.4274 | M78: =MAX(0,M30+L49-'Global Inputs'!$E$84*'Global Inputs'!$E$24/1000*'Global Inputs'!$E$85) -> 1270.739 | ... S78: =MAX(0,S30+R49-'Global Inputs'!$E$84*'Global Inputs'!$E$24/1000*'Global Inputs'!$E$85) -> 2912.4775
B79: Dividends paid = -MIN(caps) x policy switch | C79: IDR bn | E79: =SUM(F79:S79) -> -862.62601 | F79: =0 -> 0 | G79: =-MIN(G77,G78,G75)*'Global Inputs'!$E$35*G$8 -> -6.693745 | H79: =-MIN(H77,H78,H75)*'Global Inputs'!$E$35*H$8 -> -24.296455 | I79: =-MIN(I77,I78,I75)*'Global Inputs'!$E$35*I$8 -> -14.279223 | J79: =-MIN(J77,J78,J75)*'Global Inputs'!$E$35*J$8 -> 0 | K79: =-MIN(K77,K78,K75)*'Global Inputs'!$E$35*K$8 -> -59.863306 | L79: =-MIN(L77,L78,L75)*'Global Inputs'!$E$35*L$8 -> -71.488726 | M79: =-MIN(M77,M78,M75)*'Global Inputs'!$E$35*M$8 -> -75.754725 | N79: =-MIN(N77,N78,N75)*'Global Inputs'!$E$35*N$8 -> -85.003169 | ... S79: =-MIN(S77,S78,S75)*'Global Inputs'!$E$35*S$8 -> -114.21419
B80: Cash before new equity (pre-equity path) | C80: IDR bn | F80: ='Global Inputs'!$E$58 -> 60.6389 | G80: =G74+G79 -> 32.209449 | H80: =H74+H79 -> 192.17176 | I80: =I74+I79 -> 3 | J80: =J74+J79 -> -39.845605 | K80: =K74+K79 -> 263.14171 | L80: =L74+L79 -> 597.26639 | M80: =M74+M79 -> 947.04702 | N80: =N74+N79 -> 1316.375 | ... S80: =S74+S79 -> 3358.8974
B81: Minimum operating cash | C81: IDR bn | F81: ='Global Inputs'!$E$82*F$8 -> 0 | G81: ='Global Inputs'!$E$82*G$8 -> 3 | H81: ='Global Inputs'!$E$82*H$8 -> 3 | I81: ='Global Inputs'!$E$82*I$8 -> 3 | J81: ='Global Inputs'!$E$82*J$8 -> 3 | K81: ='Global Inputs'!$E$82*K$8 -> 3 | L81: ='Global Inputs'!$E$82*L$8 -> 3 | M81: ='Global Inputs'!$E$82*M$8 -> 3 | ... S81: ='Global Inputs'!$E$82*S$8 -> 3
B82: Shortfall against minimum cash before new equity | C82: IDR bn | F82: =MAX(0,F81-F80) -> 0 | G82: =MAX(0,G81-G80) -> 0 | H82: =MAX(0,H81-H80) -> 0 | I82: =MAX(0,I81-I80) -> 0 | J82: =MAX(0,J81-J80) -> 42.845605 | K82: =MAX(0,K81-K80) -> 0 | L82: =MAX(0,L81-L80) -> 0 | M82: =MAX(0,M81-M80) -> 0 | ... S82: =MAX(0,S81-S80) -> 0
B83: of which before the injection year (bridge need — not covered by the injection assumption until received) | C83: IDR bn | F83: =IF(F$5<'Global Inputs'!$E$77,F82,0) -> 0 | G83: =IF(G$5<'Global Inputs'!$E$77,G82,0) -> 0 | H83: =IF(H$5<'Global Inputs'!$E$77,H82,0) -> 0 | I83: =IF(I$5<'Global Inputs'!$E$77,I82,0) -> 0 | J83: =IF(J$5<'Global Inputs'!$E$77,J82,0) -> 0 | K83: =IF(K$5<'Global Inputs'!$E$77,K82,0) -> 0 | L83: =IF(L$5<'Global Inputs'!$E$77,L82,0) -> 0 | M83: =IF(M$5<'Global Inputs'!$E$77,M82,0) -> 0 | ... S83: =IF(S$5<'Global Inputs'!$E$77,S82,0) -> 0
B84: of which from the injection year onward | C84: IDR bn | F84: =IF(F$5>='Global Inputs'!$E$77,F82,0) -> 0 | G84: =IF(G$5>='Global Inputs'!$E$77,G82,0) -> 0 | H84: =IF(H$5>='Global Inputs'!$E$77,H82,0) -> 0 | I84: =IF(I$5>='Global Inputs'!$E$77,I82,0) -> 0 | J84: =IF(J$5>='Global Inputs'!$E$77,J82,0) -> 42.845605 | K84: =IF(K$5>='Global Inputs'!$E$77,K82,0) -> 0 | L84: =IF(L$5>='Global Inputs'!$E$77,L82,0) -> 0 | M84: =IF(M$5>='Global Inputs'!$E$77,M82,0) -> 0 | ... S84: =IF(S$5>='Global Inputs'!$E$77,S82,0) -> 0
B85: Equity requirement at the injection date = MAX(largest shortfall from the injection year onward, planned LT loan repayment) — this case | C85: IDR bn | E85: =SUM(F85:S85) -> 195.18 | F85: =IF(F$5='Global Inputs'!$E$77,MAX(MAX($F$84:$S$84),Financing!F16),0) -> 0 | G85: =IF(G$5='Global Inputs'!$E$77,MAX(MAX($F$84:$S$84),Financing!G16),0) -> 0 | H85: =IF(H$5='Global Inputs'!$E$77,MAX(MAX($F$84:$S$84),Financing!H16),0) -> 0 | I85: =IF(I$5='Global Inputs'!$E$77,MAX(MAX($F$84:$S$84),Financing!I16),0) -> 0 | J85: =IF(J$5='Global Inputs'!$E$77,MAX(MAX($F$84:$S$84),Financing!J16),0) -> 195.18 | K85: =IF(K$5='Global Inputs'!$E$77,MAX(MAX($F$84:$S$84),Financing!K16),0) -> 0 | L85: =IF(L$5='Global Inputs'!$E$77,MAX(MAX($F$84:$S$84),Financing!L16),0) -> 0 | M85: =IF(M$5='Global Inputs'!$E$77,MAX(MAX($F$84:$S$84),Financing!M16),0) -> 0 | ... S85: =IF(S$5='Global Inputs'!$E$77,MAX(MAX($F$84:$S$84),Financing!S16),0) -> 0 | U85: The injection always covers at least the planned loan repayment (board-deck use of proceeds); the shortfall already counts the repayment as a use of cash.
B86: Residual gap after the actual injection (should be nil; non-nil if the injection is fixed too low or sized on the other case) | C86: IDR bn | E86: =SUM(F86:S86) -> 0 | F86: =MAX(0,F81-F66)*F$8 -> 0 | G86: =MAX(0,G81-G66)*G$8 -> 0 | H86: =MAX(0,H81-H66)*H$8 -> 0 | I86: =MAX(0,I81-I66)*I$8 -> 0 | J86: =MAX(0,J81-J66)*J$8 -> 0 | K86: =MAX(0,K81-K66)*K$8 -> 0 | L86: =MAX(0,L81-L66)*L$8 -> 0 | M86: =MAX(0,M81-M66)*M$8 -> 0 | ... S86: =MAX(0,S81-S66)*S$8 -> 0
B88: E. Consolidation workings — project outputs x case inclusion flag (column E). Sums feed the statements above.
B89: Revenue
B90: E1 Teluk Lamong (NPLOG) cargodoring & delivery | C90: IDR bn | E90: ='Global Inputs'!$K$89 -> 1 | F90: ='E1 TelukLamong Output'!F11*$E$90 -> 0 | G90: ='E1 TelukLamong Output'!G11*$E$90 -> 156.43828 | H90: ='E1 TelukLamong Output'!H11*$E$90 -> 161.13143 | I90: ='E1 TelukLamong Output'!I11*$E$90 -> 165.96537 | J90: ='E1 TelukLamong Output'!J11*$E$90 -> 170.94433 | K90: ='E1 TelukLamong Output'!K11*$E$90 -> 176.07266 | L90: ='E1 TelukLamong Output'!L11*$E$90 -> 186.79549 | M90: ='E1 TelukLamong Output'!M11*$E$90 -> 192.39935 | ... S90: ='E1 TelukLamong Output'!S11*$E$90 -> 236.62693
B91: E2 Cigading Existing Terminal (SGT 2) | C91: IDR bn | E91: ='Global Inputs'!$K$90 -> 1 | F91: ='E2 CigadingExist Output'!F11*$E$91 -> 0 | G91: ='E2 CigadingExist Output'!G11*$E$91 -> 38.65796 | H91: ='E2 CigadingExist Output'!H11*$E$91 -> 46.389552 | I91: ='E2 CigadingExist Output'!I11*$E$91 -> 47.781239 | J91: ='E2 CigadingExist Output'!J11*$E$91 -> 59.057611 | K91: ='E2 CigadingExist Output'!K11*$E$91 -> 60.829339 | L91: ='E2 CigadingExist Output'!L11*$E$91 -> 68.919641 | M91: ='E2 CigadingExist Output'!M11*$E$91 -> 70.987231 | ... S91: ='E2 CigadingExist Output'!S11*$E$91 -> 95.239106
B92: E3 Belawan terminal (SGT3) incl. Belawan expansion | C92: IDR bn | E92: ='Global Inputs'!$K$91 -> 1 | F92: ='E3 Belawan Output'!F11*$E$92 -> 0 | G92: ='E3 Belawan Output'!G11*$E$92 -> 22.2435 | H92: ='E3 Belawan Output'!H11*$E$92 -> 22.910805 | I92: ='E3 Belawan Output'!I11*$E$92 -> 34.967927 | J92: ='E3 Belawan Output'!J11*$E$92 -> 44.806465 | K92: ='E3 Belawan Output'!K11*$E$92 -> 49.526879 | L92: ='E3 Belawan Output'!L11*$E$92 -> 54.524582 | M92: ='E3 Belawan Output'!M11*$E$92 -> 59.814057 | ... S92: ='E3 Belawan Output'!S11*$E$92 -> 61.316585
B93: E4 WIN stevedoring (Cilegon, Makassar, Surabaya, Medan) | C93: IDR bn | E93: ='Global Inputs'!$K$92 -> 1 | F93: ='E4 WIN Output'!F11*$E$93 -> 0 | G93: ='E4 WIN Output'!G11*$E$93 -> 87.948672 | H93: ='E4 WIN Output'!H11*$E$93 -> 65.358641 | I93: ='E4 WIN Output'!I11*$E$93 -> 61.989729 | J93: ='E4 WIN Output'!J11*$E$93 -> 66.857705 | K93: ='E4 WIN Output'!K11*$E$93 -> 72.109308 | L93: ='E4 WIN Output'!L11*$E$93 -> 77.774869 | M93: ='E4 WIN Output'!M11*$E$93 -> 83.887124 | ... S93: ='E4 WIN Output'!S11*$E$93 -> 102.46705
B94: P01 Cigading Wharf 2 | C94: IDR bn | E94: ='Global Inputs'!$K$93 -> 1 | F94: ='P01 CigWharf2 Output'!F11*$E$94 -> 0 | G94: ='P01 CigWharf2 Output'!G11*$E$94 -> 0 | H94: ='P01 CigWharf2 Output'!H11*$E$94 -> 100.31221 | I94: ='P01 CigWharf2 Output'!I11*$E$94 -> 103.32158 | J94: ='P01 CigWharf2 Output'!J11*$E$94 -> 127.70547 | K94: ='P01 CigWharf2 Output'!K11*$E$94 -> 131.53663 | L94: ='P01 CigWharf2 Output'!L11*$E$94 -> 149.031 | M94: ='P01 CigWharf2 Output'!M11*$E$94 -> 153.50193 | ... S94: ='P01 CigWharf2 Output'!S11*$E$94 -> 205.9439
B95: P02 Cigading Extended Conveyor | C95: IDR bn | E95: ='Global Inputs'!$K$94 -> 1 | F95: ='P02 CigConveyor Output'!F11*$E$95 -> 0 | G95: ='P02 CigConveyor Output'!G11*$E$95 -> 0 | H95: ='P02 CigConveyor Output'!H11*$E$95 -> 31.5 | I95: ='P02 CigConveyor Output'!I11*$E$95 -> 32.445 | J95: ='P02 CigConveyor Output'!J11*$E$95 -> 33.41835 | K95: ='P02 CigConveyor Output'!K11*$E$95 -> 34.420901 | L95: ='P02 CigConveyor Output'!L11*$E$95 -> 35.453528 | M95: ='P02 CigConveyor Output'!M11*$E$95 -> 36.517133 | ... S95: ='P02 CigConveyor Output'!S11*$E$95 -> 43.603367
B96: P03 KBS Warehouse Revitalisation (Cigading) | C96: IDR bn | E96: ='Global Inputs'!$K$95 -> 1 | F96: ='P03 KBSWarehouse Output'!F11*$E$96 -> 0 | G96: ='P03 KBSWarehouse Output'!G11*$E$96 -> 0 | H96: ='P03 KBSWarehouse Output'!H11*$E$96 -> 0 | I96: ='P03 KBSWarehouse Output'!I11*$E$96 -> 0 | J96: ='P03 KBSWarehouse Output'!J11*$E$96 -> 53.023782 | K96: ='P03 KBSWarehouse Output'!K11*$E$96 -> 54.614495 | L96: ='P03 KBSWarehouse Output'!L11*$E$96 -> 56.25293 | M96: ='P03 KBSWarehouse Output'!M11*$E$96 -> 57.940518 | ... S96: ='P03 KBSWarehouse Output'!S11*$E$96 -> 69.184009
B97: P04 Teluk Lamong Silo | C97: IDR bn | E97: ='Global Inputs'!$K$96 -> 1 | F97: ='P04 TTLSilo Output'!F11*$E$97 -> 0 | G97: ='P04 TTLSilo Output'!G11*$E$97 -> 0 | H97: ='P04 TTLSilo Output'!H11*$E$97 -> 0 | I97: ='P04 TTLSilo Output'!I11*$E$97 -> 0 | J97: ='P04 TTLSilo Output'!J11*$E$97 -> 13.26 | K97: ='P04 TTLSilo Output'!K11*$E$97 -> 13.26 | L97: ='P04 TTLSilo Output'!L11*$E$97 -> 13.26 | M97: ='P04 TTLSilo Output'!M11*$E$97 -> 13.26 | ... S97: ='P04 TTLSilo Output'!S11*$E$97 -> 13.26
B98: P05 Dumai bagging & weighbridge | C98: IDR bn | E98: ='Global Inputs'!$K$97 -> 1 | F98: ='P05 Dumai Output'!F11*$E$98 -> 0 | G98: ='P05 Dumai Output'!G11*$E$98 -> 0 | H98: ='P05 Dumai Output'!H11*$E$98 -> 0 | I98: ='P05 Dumai Output'!I11*$E$98 -> 48.1 | J98: ='P05 Dumai Output'!J11*$E$98 -> 48.1 | K98: ='P05 Dumai Output'!K11*$E$98 -> 48.1 | L98: ='P05 Dumai Output'!L11*$E$98 -> 51.4176 | M98: ='P05 Dumai Output'!M11*$E$98 -> 51.4176 | ... S98: ='P05 Dumai Output'!S11*$E$98 -> 54.9682
B99: P06 Ciwandan Expansion | C99: IDR bn | E99: ='Global Inputs'!$K$98 -> 1 | F99: ='P06 Ciwandan Output'!F11*$E$99 -> 0 | G99: ='P06 Ciwandan Output'!G11*$E$99 -> 0 | H99: ='P06 Ciwandan Output'!H11*$E$99 -> 0 | I99: ='P06 Ciwandan Output'!I11*$E$99 -> 0 | J99: ='P06 Ciwandan Output'!J11*$E$99 -> 0 | K99: ='P06 Ciwandan Output'!K11*$E$99 -> 58.25784 | L99: ='P06 Ciwandan Output'!L11*$E$99 -> 76.900348 | M99: ='P06 Ciwandan Output'!M11*$E$99 -> 84.590383 | ... S99: ='P06 Ciwandan Output'!S11*$E$99 -> 153.90312
B100: P08 DMS trucking fee (Teluk Lamong, Cigading, Ciwandan, Belawan) | C100: IDR bn | E100: ='Global Inputs'!$K$99 -> 1 | F100: ='P08 DMSTrucking Output'!F11*$E$100 -> 0 | G100: ='P08 DMSTrucking Output'!G11*$E$100 -> 0 | H100: ='P08 DMSTrucking Output'!H11*$E$100 -> 0 | I100: ='P08 DMSTrucking Output'!I11*$E$100 -> 0 | J100: ='P08 DMSTrucking Output'!J11*$E$100 -> 2.7523996 | K100: ='P08 DMSTrucking Output'!K11*$E$100 -> 3.3007715 | L100: ='P08 DMSTrucking Output'!L11*$E$100 -> 3.4340747 | M100: ='P08 DMSTrucking Output'!M11*$E$100 -> 3.5746249 | ... S100: ='P08 DMSTrucking Output'!S11*$E$100 -> 4.4360102
B101: P12 BUMN operatorship schemes (Pelindo Teluk Lamong, KBS Cigading, Pelindo Belawan) | C101: IDR bn | E101: ='Global Inputs'!$K$100 -> 0 | F101: ='P12 BUMNOps Output'!F11*$E$101 -> 0 | G101: ='P12 BUMNOps Output'!G11*$E$101 -> 0 | H101: ='P12 BUMNOps Output'!H11*$E$101 -> 0 | I101: ='P12 BUMNOps Output'!I11*$E$101 -> 0 | J101: ='P12 BUMNOps Output'!J11*$E$101 -> 0 | K101: ='P12 BUMNOps Output'!K11*$E$101 -> 0 | L101: ='P12 BUMNOps Output'!L11*$E$101 -> 0 | M101: ='P12 BUMNOps Output'!M11*$E$101 -> 0 | ... S101: ='P12 BUMNOps Output'!S11*$E$101 -> 0
B102: P15 TBM — Tanjung Batu / Pelindo land lease, warehousing and cargo handling | C102: IDR bn | E102: ='Global Inputs'!$K$101 -> 0 | F102: ='P15 TBM Output'!F11*$E$102 -> 0 | G102: ='P15 TBM Output'!G11*$E$102 -> 0 | H102: ='P15 TBM Output'!H11*$E$102 -> 0 | I102: ='P15 TBM Output'!I11*$E$102 -> 0 | J102: ='P15 TBM Output'!J11*$E$102 -> 0 | K102: ='P15 TBM Output'!K11*$E$102 -> 0 | L102: ='P15 TBM Output'!L11*$E$102 -> 0 | M102: ='P15 TBM Output'!M11*$E$102 -> 0 | ... S102: ='P15 TBM Output'!S11*$E$102 -> 0
B103: P19 Badas bulk terminal (FS pending — DUMMY data) | C103: IDR bn | E103: ='Global Inputs'!$K$102 -> 0 | F103: ='P19 Badas Output'!F11*$E$103 -> 0 | G103: ='P19 Badas Output'!G11*$E$103 -> 0 | H103: ='P19 Badas Output'!H11*$E$103 -> 0 | I103: ='P19 Badas Output'!I11*$E$103 -> 0 | J103: ='P19 Badas Output'!J11*$E$103 -> 0 | K103: ='P19 Badas Output'!K11*$E$103 -> 0 | L103: ='P19 Badas Output'!L11*$E$103 -> 0 | M103: ='P19 Badas Output'!M11*$E$103 -> 0 | ... S103: ='P19 Badas Output'!S11*$E$103 -> 0
B104: Total — Revenue | C104: IDR bn | E104: =SUM(F104:S104) -> 9917.547 | F104: =F90+F91+F92+F93+F94+F95+F96+F97+F98+F99+F100+F101+F102+F103 -> 0 | G104: =G90+G91+G92+G93+G94+G95+G96+G97+G98+G99+G100+G101+G102+G103 -> 305.28841 | H104: =H90+H91+H92+H93+H94+H95+H96+H97+H98+H99+H100+H101+H102+H103 -> 427.60264 | I104: =I90+I91+I92+I93+I94+I95+I96+I97+I98+I99+I100+I101+I102+I103 -> 494.57084 | J104: =J90+J91+J92+J93+J94+J95+J96+J97+J98+J99+J100+J101+J102+J103 -> 619.92611 | K104: =K90+K91+K92+K93+K94+K95+K96+K97+K98+K99+K100+K101+K102+K103 -> 702.02883 | L104: =L90+L91+L92+L93+L94+L95+L96+L97+L98+L99+L100+L101+L102+L103 -> 773.76406 | M104: =M90+M91+M92+M93+M94+M95+M96+M97+M98+M99+M100+M101+M102+M103 -> 807.88996 | ... S104: =S90+S91+S92+S93+S94+S95+S96+S97+S98+S99+S100+S101+S102+S103 -> 1040.9483
B105: Cost of sales
B106: E1 Teluk Lamong (NPLOG) cargodoring & delivery | C106: IDR bn | E106: ='Global Inputs'!$K$89 -> 1 | F106: ='E1 TelukLamong Output'!F12*$E$106 -> 0 | G106: ='E1 TelukLamong Output'!G12*$E$106 -> -29.933786 | H106: ='E1 TelukLamong Output'!H12*$E$106 -> -31.312221 | I106: ='E1 TelukLamong Output'!I12*$E$106 -> -32.782551 | J106: ='E1 TelukLamong Output'!J12*$E$106 -> -34.306022 | K106: ='E1 TelukLamong Output'!K12*$E$106 -> -35.908011 | L106: ='E1 TelukLamong Output'!L12*$E$106 -> -37.614126 | M106: ='E1 TelukLamong Output'!M12*$E$106 -> -39.386317 | ... S106: ='E1 TelukLamong Output'!S12*$E$106 -> -52.165749
B107: E2 Cigading Existing Terminal (SGT 2) | C107: IDR bn | E107: ='Global Inputs'!$K$90 -> 1 | F107: ='E2 CigadingExist Output'!F12*$E$107 -> 0 | G107: ='E2 CigadingExist Output'!G12*$E$107 -> -13.421705 | H107: ='E2 CigadingExist Output'!H12*$E$107 -> -13.950545 | I107: ='E2 CigadingExist Output'!I12*$E$107 -> -14.537514 | J107: ='E2 CigadingExist Output'!J12*$E$107 -> -15.117542 | K107: ='E2 CigadingExist Output'!K12*$E$107 -> -15.72513 | L107: ='E2 CigadingExist Output'!L12*$E$107 -> -16.394852 | M107: ='E2 CigadingExist Output'!M12*$E$107 -> -17.061853 | ... S107: ='E2 CigadingExist Output'!S12*$E$107 -> -21.830077
...

Sheet FSL Financials — With BUMN
B1: FSL FINANCIALS — WITH BUMN (integrated income statement, balance sheet, cash flow)
B2: Sum of project outputs included in the With-BUMN case (incl. BUMN operatorship schemes) + corporate items. IDR bn.
B3: Go to: | C3: Navigation | D3: Global Inputs | E3: Project Summary | F3: Funding | G3: FSL w/o BUMN | H3: FSL w/ BUMN | I3: Val w/o BUMN | J3: Val w/ BUMN | K3: Checks | L3: Model Flow
B5: Year | C5: Unit | D5: Type | E5: Flag / total | F5: ='Global Inputs'!F$5 -> 2023 | G5: ='Global Inputs'!G$5 -> 2024 | H5: ='Global Inputs'!H$5 -> 2025 | I5: ='Global Inputs'!I$5 -> 2026 | J5: ='Global Inputs'!J$5 -> 2027 | K5: ='Global Inputs'!K$5 -> 2028 | L5: ='Global Inputs'!L$5 -> 2029 | M5: ='Global Inputs'!M$5 -> 2030 | ... S5: ='Global Inputs'!S$5 -> 2036 | T5: Source (v29 reference / basis) | U5: Note
B6: Period end | F6: ='Global Inputs'!F$6 -> 45291 | G6: ='Global Inputs'!G$6 -> 45657 | H6: ='Global Inputs'!H$6 -> 46022 | I6: ='Global Inputs'!I$6 -> 46387 | J6: ='Global Inputs'!J$6 -> 46752 | K6: ='Global Inputs'!K$6 -> 47118 | L6: ='Global Inputs'!L$6 -> 47483 | M6: ='Global Inputs'!M$6 -> 47848 | ... S6: ='Global Inputs'!S$6 -> 50040
B7: Days in year | F7: ='Global Inputs'!F$7 -> 365 | G7: ='Global Inputs'!G$7 -> 366 | H7: ='Global Inputs'!H$7 -> 365 | I7: ='Global Inputs'!I$7 -> 365 | J7: ='Global Inputs'!J$7 -> 365 | K7: ='Global Inputs'!K$7 -> 366 | L7: ='Global Inputs'!L$7 -> 365 | M7: ='Global Inputs'!M$7 -> 365 | ... S7: ='Global Inputs'!S$7 -> 366
B8: Forecast flag (1 = forecast year) | F8: ='Global Inputs'!F$8 -> 0 | G8: ='Global Inputs'!G$8 -> 1 | H8: ='Global Inputs'!H$8 -> 1 | I8: ='Global Inputs'!I$8 -> 1 | J8: ='Global Inputs'!J$8 -> 1 | K8: ='Global Inputs'!K$8 -> 1 | L8: ='Global Inputs'!L$8 -> 1 | M8: ='Global Inputs'!M$8 -> 1 | ... S8: ='Global Inputs'!S$8 -> 1
B10: Case: With BUMN — scope and settings
B11: Company case | E11: With BUMN
B12: Projects included in this case (count) | C12: count | E12: ='Global Inputs'!$L$89+'Global Inputs'!$L$90+'Global Inputs'!$L$91+'Global Inputs'!$L$92+'Global Inputs'!$L$93+'Global Inputs'!$L$94+'Global Inputs'!$L$95+'Global Inputs'!$L$96+'Global Inputs'!$L$97+'Global Inputs'!$L$98+'Global Inputs'!$L$99+'Global Inputs'!$L$100+'Global Inputs'!$L$101+'Global Inputs'!$L$102 -> 12
B13: Scope | E13: Existing businesses + committed and planned projects switched on + BUMN operatorship schemes (case 2 projects).
B14: This case drives the Funding Requirement (1 = yes) | C14: 0/1 | E14: =IF('Global Inputs'!$E$36=2,1,0) -> 0
B15: Sapphire is excluded (v29 Output_FSL!D2 = 0). Corporate items (LT loan, existing fixed assets, other assets / liabilities, inventory) are held centrally and not allocated to projects.
B17: A. Income statement (IDR bn)
B18: Revenue | C18: IDR bn | E18: =SUM(F18:S18) -> 11598.728 | F18: =F104 -> 0 | G18: =G104 -> 305.28841 | H18: =H104 -> 427.60264 | I18: =I104 -> 622.06456 | J18: =J104 -> 754.46249 | K18: =K104 -> 841.30923 | L18: =L104 -> 917.90667 | M18: =M104 -> 957.0165 | ... S18: =S104 -> 1212.2892
B19: Cost of sales | C19: IDR bn | E19: =SUM(F19:S19) -> -2137.7465 | F19: =F120 -> 0 | G19: =G120 -> -122.54304 | H19: =H120 -> -114.65874 | I19: =I120 -> -112.22494 | J19: =J120 -> -124.58111 | K19: =K120 -> -146.7349 | L19: =L120 -> -157.56432 | M19: =M120 -> -167.6231 | ... S19: =S120 -> -216.9311
B20: Gross profit | C20: IDR bn | E20: =SUM(F20:S20) -> 9460.9818 | F20: =F18+F19 -> 0 | G20: =G18+G19 -> 182.74537 | H20: =H18+H19 -> 312.94389 | I20: =I18+I19 -> 509.83961 | J20: =J18+J19 -> 629.88138 | K20: =K18+K19 -> 694.57432 | L20: =L18+L19 -> 760.34234 | M20: =M18+M19 -> 789.3934 | ... S20: =S18+S19 -> 995.35806
B21: Operating expenses | C21: IDR bn | E21: =SUM(F21:S21) -> -2475.6651 | F21: =F136 -> 0 | G21: =G136 -> -28.510101 | H21: =H136 -> -49.385568 | I21: =I136 -> -142.34958 | J21: =J136 -> -179.63351 | K21: =K136 -> -195.40509 | L21: =L136 -> -206.35229 | M21: =M136 -> -214.02768 | ... S21: =S136 -> -261.08526
B22: EBITDA | C22: IDR bn | E22: =SUM(F22:S22) -> 6985.3167 | F22: =F20+F21 -> 0 | G22: =G20+G21 -> 154.23527 | H22: =H20+H21 -> 263.55833 | I22: =I20+I21 -> 367.49003 | J22: =J20+J21 -> 450.24787 | K22: =K20+K21 -> 499.16924 | L22: =L20+L21 -> 553.99006 | M22: =M20+M21 -> 575.36572 | ... S22: =S20+S21 -> 734.2728
B23: Depreciation & amortisation | C23: IDR bn | E23: =SUM(F23:S23) -> -1756.082 | F23: =F152 -> 0 | G23: =G152 -> -88.373086 | H23: =H152 -> -113.59971 | I23: =I152 -> -127.99828 | J23: =J152 -> -141.84087 | K23: =K152 -> -149.09796 | L23: =L152 -> -151.10669 | M23: =M152 -> -151.11559 | ... S23: =S152 -> -125.83761
B24: EBIT | C24: IDR bn | E24: =SUM(F24:S24) -> 5229.2347 | F24: =F22+F23 -> 0 | G24: =G22+G23 -> 65.862187 | H24: =H22+H23 -> 149.95862 | I24: =I22+I23 -> 239.49175 | J24: =J22+J23 -> 308.407 | K24: =K22+K23 -> 350.07128 | L24: =L22+L23 -> 402.88337 | M24: =M22+M23 -> 424.25013 | ... S24: =S22+S23 -> 608.43519
B25: Corporate financing cost — existing / LT loan interest (Financing sheet) | C25: IDR bn | E25: =SUM(F25:S25) -> -43.591792 | F25: =-Financing!F22 -> 0 | G25: =-Financing!G22 -> -5.4709055 | H25: =-Financing!H22 -> -15.273462 | I25: =-Financing!I22 -> -15.273462 | J25: =-Financing!J22 -> -7.5739631 | K25: =-Financing!K22 -> 0 | L25: =-Financing!L22 -> 0 | M25: =-Financing!M22 -> 0 | ... S25: =-Financing!S22 -> 0
B26: Profit before tax | C26: IDR bn | E26: =SUM(F26:S26) -> 5185.6429 | F26: =F24+F25 -> 0 | G26: =G24+G25 -> 60.391281 | H26: =H24+H25 -> 134.68516 | I26: =I24+I25 -> 224.21829 | J26: =J24+J25 -> 300.83304 | K26: =K24+K25 -> 350.07128 | L26: =L24+L25 -> 402.88337 | M26: =M24+M25 -> 424.25013 | ... S26: =S24+S25 -> 608.43519
B27: Tax on project EBIT (sum of project lines, v29 method) | C27: IDR bn | E27: =SUM(F27:S27) -> -1167.5899 | F27: =F168 -> 0 | G27: =G168 -> -19.962238 | H27: =H168 -> -36.944577 | I27: =I168 -> -56.752693 | J27: =J168 -> -69.63092 | K27: =K168 -> -78.613295 | L27: =L168 -> -88.894121 | M27: =M168 -> -93.363802 | ... S27: =S168 -> -133.85574
B28: Tax shield on corporate interest (Global switch) | C28: IDR bn | E28: =SUM(F28:S28) -> 9.5901942 | F28: =Financing!F23 -> 0 | G28: =Financing!G23 -> 1.2035992 | H28: =Financing!H23 -> 3.3601615 | I28: =Financing!I23 -> 3.3601615 | J28: =Financing!J23 -> 1.6662719 | K28: =Financing!K23 -> 0 | L28: =Financing!L23 -> 0 | M28: =Financing!M23 -> 0 | ... S28: =Financing!S23 -> 0
B29: Tax | C29: IDR bn | E29: =SUM(F29:S29) -> -1157.9997 | F29: =F27+F28 -> 0 | G29: =G27+G28 -> -18.758639 | H29: =H27+H28 -> -33.584415 | I29: =I27+I28 -> -53.392532 | J29: =J27+J28 -> -67.964648 | K29: =K27+K28 -> -78.613295 | L29: =L27+L28 -> -88.894121 | M29: =M27+M28 -> -93.363802 | ... S29: =S27+S28 -> -133.85574
B30: Net profit | C30: IDR bn | E30: =SUM(F30:S30) -> 4027.6432 | F30: =F26+F29 -> 0 | G30: =G26+G29 -> 41.632643 | H30: =H26+H29 -> 101.10074 | I30: =I26+I29 -> 170.82576 | J30: =J26+J29 -> 232.86839 | K30: =K26+K29 -> 271.45799 | L30: =L26+L29 -> 313.98925 | M30: =M26+M29 -> 330.88633 | ... S30: =S26+S29 -> 474.57945
B31: Memo: non-controlling share of project NOPAT (NPLOG 35% etc.; v29 consolidates 100%) | C31: IDR bn | E31: =SUM(F31:S31) -> 332.86295 | F31: =F200 -> 0 | G31: =G200 -> 19.320159 | H31: =H200 -> 20.112556 | I31: =I200 -> 20.642014 | J31: =J200 -> 21.466169 | K31: =K200 -> 22.30618 | L31: =L200 -> 24.368473 | M31: =M200 -> 25.284557 | ... S31: =S200 -> 32.733213
B32: Memo: net profit attributable to FSL shareholders | C32: IDR bn | E32: =SUM(F32:S32) -> 3694.7802 | F32: =F30-F31 -> 0 | G32: =G30-G31 -> 22.312483 | H32: =H30-H31 -> 80.988184 | I32: =I30-I31 -> 150.18375 | J32: =J30-J31 -> 211.40222 | K32: =K30-K31 -> 249.15181 | L32: =L30-L31 -> 289.62077 | M32: =M30-M31 -> 305.60177 | ... S32: =S30-S31 -> 441.84624
B33: EBITDA margin | C33: % | F33: =IF(F18=0,0,F22/F18) -> 0 | G33: =IF(G18=0,0,G22/G18) -> 0.50521168 | H33: =IF(H18=0,0,H22/H18) -> 0.61636273 | I33: =IF(I18=0,0,I22/I18) -> 0.59075867 | J33: =IF(J18=0,0,J22/J18) -> 0.59677966 | K33: =IF(K18=0,0,K22/K18) -> 0.59332433 | L33: =IF(L18=0,0,L22/L18) -> 0.60353637 | M33: =IF(M18=0,0,M22/M18) -> 0.60120774 | ... S33: =IF(S18=0,0,S22/S18) -> 0.60569114
B34: Net margin | C34: % | F34: =IF(F18=0,0,F30/F18) -> 0 | G34: =IF(G18=0,0,G30/G18) -> 0.13637151 | H34: =IF(H18=0,0,H30/H18) -> 0.23643619 | I34: =IF(I18=0,0,I30/I18) -> 0.27461099 | J34: =IF(J18=0,0,J30/J18) -> 0.30865469 | K34: =IF(K18=0,0,K30/K18) -> 0.32266137 | L34: =IF(L18=0,0,L30/L18) -> 0.34207099 | M34: =IF(M18=0,0,M30/M18) -> 0.34574778 | ... S34: =IF(S18=0,0,S30/S18) -> 0.3914738
B36: B. Balance sheet (IDR bn) — 2023 column = opening balances (v29 Output_FSL column I)
B37: Cash and equivalents | C37: IDR bn | F37: =F66 -> 60.6389 | G37: =G66 -> 32.209449 | H37: =H66 -> 192.17176 | I37: =I66 -> 3 | J37: =J66 -> 198.18 | K37: =K66 -> 535.35457 | L37: =L66 -> 904.7604 | M37: =M66 -> 1291.0868 | ... S37: =S66 -> 3946.2033
B38: Inventory (held flat, centrally) | C38: IDR bn | F38: ='Global Inputs'!$E$30 -> 0.519811 | G38: ='Global Inputs'!$E$30 -> 0.519811 | H38: ='Global Inputs'!$E$30 -> 0.519811 | I38: ='Global Inputs'!$E$30 -> 0.519811 | J38: ='Global Inputs'!$E$30 -> 0.519811 | K38: ='Global Inputs'!$E$30 -> 0.519811 | L38: ='Global Inputs'!$E$30 -> 0.519811 | M38: ='Global Inputs'!$E$30 -> 0.519811 | ... S38: ='Global Inputs'!$E$30 -> 0.519811
B39: Trade receivables (sum of projects) | C39: IDR bn | F39: =F264 -> 45 | G39: =G264 -> 37.535461 | H39: =H264 -> 52.718133 | I39: =I264 -> 76.692891 | J39: =J264 -> 93.015924 | K39: =K264 -> 103.43966 | L39: =L264 -> 113.16658 | M39: =M264 -> 117.98834 | ... S39: =S264 -> 149.05195
B40: Fixed assets — existing businesses (unallocated; opening NBV less existing-asset depreciation) | C40: IDR bn | F40: ='Global Inputs'!$E$61 -> 826.022 | G40: =F40-G312 -> 737.64891 | H40: =G40-H312 -> 649.26776 | I40: =H40-I312 -> 561.49537 | J40: =I40-J312 -> 475.94121 | K40: =J40-K312 -> 390.28089 | L40: =K40-L312 -> 302.61185 | M40: =L40-M312 -> 214.9339 | N40: =M40-N312 -> 127.24686 | ... S40: =R40-S312 -> -321.33107
B41: Fixed assets — project capex (sum of project NBV) | C41: IDR bn | F41: =F296 -> 198.433 | G41: =G296 -> 323.6735 | H41: =H296 -> 313.09344 | I41: =I296 -> 692.63961 | J41: =J296 -> 796.35653 | K41: =K296 -> 732.91888 | L41: =L296 -> 669.48124 | M41: =M296 -> 606.04359 | ... S41: =S296 -> 309.35875
B42: Other assets (Dec-23 balance excl. reclassified assets under construction; held flat) | C42: IDR bn | F42: ='Global Inputs'!$E$109 -> 132.83 | G42: ='Global Inputs'!$E$109 -> 132.83 | H42: ='Global Inputs'!$E$109 -> 132.83 | I42: ='Global Inputs'!$E$109 -> 132.83 | J42: ='Global Inputs'!$E$109 -> 132.83 | K42: ='Global Inputs'!$E$109 -> 132.83 | L42: ='Global Inputs'!$E$109 -> 132.83 | M42: ='Global Inputs'!$E$109 -> 132.83 | ... S42: ='Global Inputs'!$E$109 -> 132.83
B43: Total assets | C43: IDR bn | F43: =F37+F38+F39+F40+F41+F42 -> 1263.4437 | G43: =G37+G38+G39+G40+G41+G42 -> 1264.4171 | H43: =H37+H38+H39+H40+H41+H42 -> 1340.6009 | I43: =I37+I38+I39+I40+I41+I42 -> 1467.1777 | J43: =J37+J38+J39+J40+J41+J42 -> 1696.8435 | K43: =K37+K38+K39+K40+K41+K42 -> 1895.3438 | L43: =L37+L38+L39+L40+L41+L42 -> 2123.3699 | M43: =M37+M38+M39+M40+M41+M42 -> 2363.4024 | ... S43: =S37+S38+S39+S40+S41+S42 -> 4216.6327
B44: Trade payables (sum of projects) | C44: IDR bn | F44: =-F280 -> 14.671986 | G44: =-G280 -> 10.044511 | H44: =-H280 -> 9.4240062 | I44: =-I280 -> 9.223968 | J44: =-J280 -> 10.239543 | K44: =-K280 -> 12.027451 | L44: =-L280 -> 12.950492 | M44: =-M280 -> 13.777241 | ... S44: =-S280 -> 17.781238
B45: Bank loans (Financing sheet) | C45: IDR bn | F45: =Financing!F24 -> 224.518 | G45: =Financing!G24 -> 195.18 | H45: =Financing!H24 -> 195.18 | I45: =Financing!I24 -> 195.18 | J45: =Financing!J24 -> 0 | K45: =Financing!K24 -> 0 | L45: =Financing!L24 -> 0 | M45: =Financing!M24 -> 0 | ... S45: =Financing!S24 -> 0
B46: Other liabilities (Dec-23 balance; held flat) | C46: IDR bn | F46: ='Global Inputs'!$E$65 -> 55.9245 | G46: ='Global Inputs'!$E$65 -> 55.9245 | H46: ='Global Inputs'!$E$65 -> 55.9245 | I46: ='Global Inputs'!$E$65 -> 55.9245 | J46: ='Global Inputs'!$E$65 -> 55.9245 | K46: ='Global Inputs'!$E$65 -> 55.9245 | L46: ='Global Inputs'!$E$65 -> 55.9245 | M46: ='Global Inputs'!$E$65 -> 55.9245 | ... S46: ='Global Inputs'!$E$65 -> 55.9245
B47: Total liabilities | C47: IDR bn | F47: =F44+F45+F46 -> 295.11449 | G47: =G44+G45+G46 -> 261.14901 | H47: =H44+H45+H46 -> 260.52851 | I47: =I44+I45+I46 -> 260.32847 | J47: =J44+J45+J46 -> 66.164043 | K47: =K44+K45+K46 -> 67.951951 | L47: =L44+L45+L46 -> 68.874992 | M47: =M44+M45+M46 -> 69.701741 | ... S47: =S44+S45+S46 -> 73.705738
B48: Paid-in capital (opening + capital injection) | C48: IDR bn | F48: =Financing!F36 -> 677.731 | G48: =Financing!G36 -> 677.731 | H48: =Financing!H36 -> 677.731 | I48: =Financing!I36 -> 677.731 | J48: =Financing!J36 -> 872.911 | K48: =Financing!K36 -> 872.911 | L48: =Financing!L36 -> 872.911 | M48: =Financing!M36 -> 872.911 | ... S48: =Financing!S36 -> 872.911
B49: Retained earnings | C49: IDR bn | F49: ='Global Inputs'!$E$67 -> 290.592 | G49: =F49+G30+G79 -> 325.5309 | H49: =G49+H30+H79 -> 402.33518 | I49: =H49+I30+I79 -> 529.11198 | J49: =I49+J30+J79 -> 757.7622 | K49: =J49+K30+K79 -> 954.47464 | L49: =K49+L30+L79 -> 1181.5777 | M49: =L49+M30+M79 -> 1420.7835 | N49: =M49+N30+N79 -> 1683.766 | ... S49: =R49+S30+S79 -> 3270.0098
B50: Total equity | C50: IDR bn | F50: =F48+F49 -> 968.323 | G50: =G48+G49 -> 1003.2619 | H50: =H48+H49 -> 1080.0662 | I50: =I48+I49 -> 1206.843 | J50: =J48+J49 -> 1630.6732 | K50: =K48+K49 -> 1827.3856 | L50: =L48+L49 -> 2054.4887 | M50: =M48+M49 -> 2293.6945 | ... S50: =S48+S49 -> 4142.9208
B51: Balance check: assets - liabilities - equity (2023 shows the v29 opening residual of 0.006) | C51: IDR bn | F51: =F43-F47-F50 -> 0.0062250171 | G51: =G43-G47-G50 -> 0.0062250171 | H51: =H43-H47-H50 -> 0.0062250171 | I51: =I43-I47-I50 -> 0.0062250171 | J51: =J43-J47-J50 -> 0.0062250171 | K51: =K43-K47-K50 -> 0.0062250171 | L51: =L43-L47-L50 -> 0.0062250171 | M51: =M43-M47-M50 -> 0.0062250171 | ... S51: =S43-S47-S50 -> 0.0062250171
B53: C. Cash flow statement (IDR bn)
B54: Net profit | C54: IDR bn | E54: =SUM(F54:S54) -> 4027.6432 | F54: =F30 -> 0 | G54: =G30 -> 41.632643 | H54: =H30 -> 101.10074 | I54: =I30 -> 170.82576 | J54: =J30 -> 232.86839 | K54: =K30 -> 271.45799 | L54: =L30 -> 313.98925 | M54: =M30 -> 330.88633 | ... S54: =S30 -> 474.57945
B55: Add back depreciation & amortisation | C55: IDR bn | E55: =SUM(F55:S55) -> 1756.082 | F55: =-F23 -> 0 | G55: =-G23 -> 88.373086 | H55: =-H23 -> 113.59971 | I55: =-I23 -> 127.99828 | J55: =-J23 -> 141.84087 | K55: =-K23 -> 149.09796 | L55: =-L23 -> 151.10669 | M55: =-M23 -> 151.11559 | ... S55: =-S23 -> 125.83761
B56: Increase in net working capital | C56: IDR bn | E56: =SUM(F56:S56) -> -100.94269 | F56: =-F248 -> 0 | G56: =-G248 -> 2.8370648 | H56: =-H248 -> -15.803178 | I56: =-I248 -> -24.174796 | J56: =-J248 -> -15.307458 | K56: =-K248 -> -8.6358277 | L56: =-L248 -> -8.8038752 | M56: =-M248 -> -3.9950113 | ... S56: =-S248 -> -3.8396184
B57: Cash flow from operations | C57: IDR bn | E57: =SUM(F57:S57) -> 5682.7825 | F57: =F54+F55+F56 -> 0 | G57: =G54+G55+G56 -> 132.84279 | H57: =H54+H55+H56 -> 198.89727 | I57: =I54+I55+I56 -> 274.64924 | J57: =J54+J55+J56 -> 359.4018 | K57: =K54+K55+K56 -> 411.92011 | L57: =L54+L55+L56 -> 456.29206 | M57: =M54+M55+M56 -> 478.00691 | ... S57: =S54+S55+S56 -> 596.57744
B58: Capex (all projects in this case) | C58: IDR bn | E58: =SUM(F58:S58) -> -918.08767 | F58: =-F216 -> -198.433 | G58: =-G216 -> -125.2405 | H58: =-H216 -> -14.6385 | I58: =-I216 -> -419.77205 | J58: =-J216 -> -160.00362 | K58: =-K216 -> 0 | L58: =-L216 -> 0 | M58: =-M216 -> 0 | ... S58: =-S216 -> 0
B59: Cash flow from investing | C59: IDR bn | E59: =SUM(F59:S59) -> -918.08767 | F59: =F58 -> -198.433 | G59: =G58 -> -125.2405 | H59: =H58 -> -14.6385 | I59: =I58 -> -419.77205 | J59: =J58 -> -160.00362 | K59: =K58 -> 0 | L59: =L58 -> 0 | M59: =M58 -> 0 | ... S59: =S58 -> 0
B60: Capital injection received (Financing sheet) | C60: IDR bn | E60: =SUM(F60:S60) -> 195.18 | F60: =Financing!F33 -> 0 | G60: =Financing!G33 -> 0 | H60: =Financing!H33 -> 0 | I60: =Financing!I33 -> 0 | J60: =Financing!J33 -> 195.18 | K60: =Financing!K33 -> 0 | L60: =Financing!L33 -> 0 | M60: =Financing!M33 -> 0 | ... S60: =Financing!S33 -> 0
B61: Loan repayments — other loans FY2024 and LT loan at the injection date | C61: IDR bn | E61: =SUM(F61:S61) -> -224.518 | F61: =-Financing!F25 -> 0 | G61: =-Financing!G25 -> -29.338 | H61: =-Financing!H25 -> 0 | I61: =-Financing!I25 -> 0 | J61: =-Financing!J25 -> -195.18 | K61: =-Financing!K25 -> 0 | L61: =-Financing!L25 -> 0 | M61: =-Financing!M25 -> 0 | ... S61: =-Financing!S25 -> 0
B62: Dividends paid | C62: IDR bn | E62: =SUM(F62:S62) -> -1048.2254 | F62: =F79 -> 0 | G62: =G79 -> -6.693745 | H62: =H79 -> -24.296455 | I62: =I79 -> -44.04896 | J62: =J79 -> -4.2181735 | K62: =K79 -> -74.745542 | L62: =L79 -> -86.886232 | M62: =M79 -> -91.680531 | ... S62: =S79 -> -132.55387
B63: Cash flow from financing | C63: IDR bn | E63: =SUM(F63:S63) -> -1077.5634 | F63: =F60+F61+F62 -> 0 | G63: =G60+G61+G62 -> -36.031745 | H63: =H60+H61+H62 -> -24.296455 | I63: =I60+I61+I62 -> -44.04896 | J63: =J60+J61+J62 -> -4.2181735 | K63: =K60+K61+K62 -> -74.745542 | L63: =L60+L61+L62 -> -86.886232 | M63: =M60+M61+M62 -> -91.680531 | ... S63: =S60+S61+S62 -> -132.55387
B64: Net cash flow | C64: IDR bn | E64: =SUM(F64:S64) -> 3687.1314 | F64: =F57+F59+F63 -> -198.433 | G64: =G57+G59+G63 -> -28.429451 | H64: =H57+H59+H63 -> 159.96232 | I64: =I57+I59+I63 -> -189.17176 | J64: =J57+J59+J63 -> 195.18 | K64: =K57+K59+K63 -> 337.17457 | L64: =L57+L59+L63 -> 369.40583 | M64: =M57+M59+M63 -> 386.32638 | ... S64: =S57+S59+S63 -> 464.02357
B65: Opening cash | C65: IDR bn | F65: =E66 -> 0 | G65: =F66 -> 60.6389 | H65: =G66 -> 32.209449 | I65: =H66 -> 192.17176 | J65: =I66 -> 3 | K65: =J66 -> 198.18 | L65: =K66 -> 535.35457 | M65: =L66 -> 904.7604 | ... S65: =R66 -> 3482.1797
B66: Closing cash | C66: IDR bn | F66: ='Global Inputs'!$E$58 -> 60.6389 | G66: =G65+G64 -> 32.209449 | H66: =H65+H64 -> 192.17176 | I66: =I65+I64 -> 3 | J66: =J65+J64 -> 198.18 | K66: =K65+K64 -> 535.35457 | L66: =L65+L64 -> 904.7604 | M66: =M65+M64 -> 1291.0868 | N66: =N65+N64 -> 1698.209 | ... S66: =S65+S64 -> 3946.2033
B67: Check: closing cash = pre-equity cash path + cumulative injection | C67: IDR bn | F67: =F66-(F80+Financing!F35) -> 0 | G67: =G66-(G80+Financing!G35) -> 0 | H67: =H66-(H80+Financing!H35) -> 0 | I67: =I66-(I80+Financing!I35) -> 2.8421709e-14 | J67: =J66-(J80+Financing!J35) -> 0 | K67: =K66-(K80+Financing!K35) -> 0 | L67: =L66-(L80+Financing!L35) -> 0 | M67: =M66-(M80+Financing!M35) -> 0 | ... S67: =S66-(S80+Financing!S35) -> 0
B69: D. Funding roll-forward and dividends (this case) — cash BEFORE new equity; dividends are never paid out of the injection
B70: Opening cash — pre-equity path | C70: IDR bn | F70: =E80 -> 0 | G70: =F80 -> 60.6389 | H70: =G80 -> 32.209449 | I70: =H80 -> 192.17176 | J70: =I80 -> 3 | K70: =J80 -> 3 | L70: =K80 -> 340.17457 | M70: =L80 -> 709.5804 | ... S70: =R80 -> 3286.9997
B71: Cash flow from operations | C71: IDR bn | F71: =F57 -> 0 | G71: =G57 -> 132.84279 | H71: =H57 -> 198.89727 | I71: =I57 -> 274.64924 | J71: =J57 -> 359.4018 | K71: =K57 -> 411.92011 | L71: =L57 -> 456.29206 | M71: =M57 -> 478.00691 | ... S71: =S57 -> 596.57744
B72: Capex | C72: IDR bn | F72: =F58 -> -198.433 | G72: =G58 -> -125.2405 | H72: =H58 -> -14.6385 | I72: =I58 -> -419.77205 | J72: =J58 -> -160.00362 | K72: =K58 -> 0 | L72: =L58 -> 0 | M72: =M58 -> 0 | ... S72: =S58 -> 0
B73: Debt service (principal): other loans FY2024, LT loan at the injection date | C73: IDR bn | F73: =F61 -> 0 | G73: =G61 -> -29.338 | H73: =H61 -> 0 | I73: =I61 -> 0 | J73: =J61 -> -195.18 | K73: =K61 -> 0 | L73: =L61 -> 0 | M73: =M61 -> 0 | ... S73: =S61 -> 0
B74: Cash before dividends and new equity | C74: IDR bn | F74: =F70+F71+F72+F73 -> -198.433 | G74: =G70+G71+G72+G73 -> 38.903194 | H74: =H70+H71+H72+H73 -> 216.46822 | I74: =I70+I71+I72+I73 -> 47.04896 | J74: =J70+J71+J72+J73 -> 7.2181735 | K74: =K70+K71+K72+K73 -> 414.92011 | L74: =L70+L71+L72+L73 -> 796.46663 | M74: =M70+M71+M72+M73 -> 1187.5873 | ... S74: =S70+S71+S72+S73 -> 3883.5772
B75: Dividend cap 1: cash available above the minimum cash (pre-equity) | C75: IDR bn | F75: =MAX(0,F74-'Global Inputs'!$E$82) -> 0 | G75: =MAX(0,G74-'Global Inputs'!$E$82) -> 35.903194 | H75: =MAX(0,H74-'Global Inputs'!$E$82) -> 213.46822 | I75: =MAX(0,I74-'Global Inputs'!$E$82) -> 44.04896 | J75: =MAX(0,J74-'Global Inputs'!$E$82) -> 4.2181735 | K75: =MAX(0,K74-'Global Inputs'!$E$82) -> 411.92011 | L75: =MAX(0,L74-'Global Inputs'!$E$82) -> 793.46663 | M75: =MAX(0,M74-'Global Inputs'!$E$82) -> 1184.5873 | ... S75: =MAX(0,S74-'Global Inputs'!$E$82) -> 3880.5772
B76: Profit attributable to FSL shareholders (net profit less non-controlling share) | C76: IDR bn | F76: =F30-F31 -> 0 | G76: =G30-G31 -> 22.312483 | H76: =H30-H31 -> 80.988184 | I76: =I30-I31 -> 150.18375 | J76: =J30-J31 -> 211.40222 | K76: =K30-K31 -> 249.15181 | L76: =L30-L31 -> 289.62077 | M76: =M30-M31 -> 305.60177 | ... S76: =S30-S31 -> 441.84624
B77: Dividend cap 2: payout ratio x attributable profit | C77: IDR bn | F77: =MAX(0,'Global Inputs'!$E$83*F76) -> 0 | G77: =MAX(0,'Global Inputs'!$E$83*G76) -> 6.693745 | H77: =MAX(0,'Global Inputs'!$E$83*H76) -> 24.296455 | I77: =MAX(0,'Global Inputs'!$E$83*I76) -> 45.055124 | J77: =MAX(0,'Global Inputs'!$E$83*J76) -> 63.420666 | K77: =MAX(0,'Global Inputs'!$E$83*K76) -> 74.745542 | L77: =MAX(0,'Global Inputs'!$E$83*L76) -> 86.886232 | M77: =MAX(0,'Global Inputs'!$E$83*M76) -> 91.680531 | ... S77: =MAX(0,'Global Inputs'!$E$83*S76) -> 132.55387
B78: Dividend cap 3: net profit + opening retained earnings - statutory reserve | C78: IDR bn | F78: =MAX(0,F30+E49-'Global Inputs'!$E$84*'Global Inputs'!$E$24/1000*'Global Inputs'!$E$85) -> 0 | G78: =MAX(0,G30+F49-'Global Inputs'!$E$84*'Global Inputs'!$E$24/1000*'Global Inputs'!$E$85) -> 273.67064 | H78: =MAX(0,H30+G49-'Global Inputs'!$E$84*'Global Inputs'!$E$24/1000*'Global Inputs'!$E$85) -> 368.07764 | I78: =MAX(0,I30+H49-'Global Inputs'!$E$84*'Global Inputs'!$E$24/1000*'Global Inputs'!$E$85) -> 514.60694 | J78: =MAX(0,J30+I49-'Global Inputs'!$E$84*'Global Inputs'!$E$24/1000*'Global Inputs'!$E$85) -> 703.42637 | K78: =MAX(0,K30+J49-'Global Inputs'!$E$84*'Global Inputs'!$E$24/1000*'Global Inputs'!$E$85) -> 970.66618 | L78: =MAX(0,L30+K49-'Global Inputs'!$E$84*'Global Inputs'!$E$24/1000*'Global Inputs'!$E$85) -> 1209.9099 | M78: =MAX(0,M30+L49-'Global Inputs'!$E$84*'Global Inputs'!$E$24/1000*'Global Inputs'!$E$85) -> 1453.91 | ... S78: =MAX(0,S30+R49-'Global Inputs'!$E$84*'Global Inputs'!$E$24/1000*'Global Inputs'!$E$85) -> 3344.0096
B79: Dividends paid = -MIN(caps) x policy switch | C79: IDR bn | E79: =SUM(F79:S79) -> -1048.2254 | F79: =0 -> 0 | G79: =-MIN(G77,G78,G75)*'Global Inputs'!$E$35*G$8 -> -6.693745 | H79: =-MIN(H77,H78,H75)*'Global Inputs'!$E$35*H$8 -> -24.296455 | I79: =-MIN(I77,I78,I75)*'Global Inputs'!$E$35*I$8 -> -44.04896 | J79: =-MIN(J77,J78,J75)*'Global Inputs'!$E$35*J$8 -> -4.2181735 | K79: =-MIN(K77,K78,K75)*'Global Inputs'!$E$35*K$8 -> -74.745542 | L79: =-MIN(L77,L78,L75)*'Global Inputs'!$E$35*L$8 -> -86.886232 | M79: =-MIN(M77,M78,M75)*'Global Inputs'!$E$35*M$8 -> -91.680531 | N79: =-MIN(N77,N78,N75)*'Global Inputs'!$E$35*N$8 -> -101.4707 | ... S79: =-MIN(S77,S78,S75)*'Global Inputs'!$E$35*S$8 -> -132.55387
B80: Cash before new equity (pre-equity path) | C80: IDR bn | F80: ='Global Inputs'!$E$58 -> 60.6389 | G80: =G74+G79 -> 32.209449 | H80: =H74+H79 -> 192.17176 | I80: =I74+I79 -> 3 | J80: =J74+J79 -> 3 | K80: =K74+K79 -> 340.17457 | L80: =L74+L79 -> 709.5804 | M80: =M74+M79 -> 1095.9068 | N80: =N74+N79 -> 1503.029 | ... S80: =S74+S79 -> 3751.0233
B81: Minimum operating cash | C81: IDR bn | F81: ='Global Inputs'!$E$82*F$8 -> 0 | G81: ='Global Inputs'!$E$82*G$8 -> 3 | H81: ='Global Inputs'!$E$82*H$8 -> 3 | I81: ='Global Inputs'!$E$82*I$8 -> 3 | J81: ='Global Inputs'!$E$82*J$8 -> 3 | K81: ='Global Inputs'!$E$82*K$8 -> 3 | L81: ='Global Inputs'!$E$82*L$8 -> 3 | M81: ='Global Inputs'!$E$82*M$8 -> 3 | ... S81: ='Global Inputs'!$E$82*S$8 -> 3
B82: Shortfall against minimum cash before new equity | C82: IDR bn | F82: =MAX(0,F81-F80) -> 0 | G82: =MAX(0,G81-G80) -> 0 | H82: =MAX(0,H81-H80) -> 0 | I82: =MAX(0,I81-I80) -> 0 | J82: =MAX(0,J81-J80) -> 0 | K82: =MAX(0,K81-K80) -> 0 | L82: =MAX(0,L81-L80) -> 0 | M82: =MAX(0,M81-M80) -> 0 | ... S82: =MAX(0,S81-S80) -> 0
B83: of which before the injection year (bridge need — not covered by the injection assumption until received) | C83: IDR bn | F83: =IF(F$5<'Global Inputs'!$E$77,F82,0) -> 0 | G83: =IF(G$5<'Global Inputs'!$E$77,G82,0) -> 0 | H83: =IF(H$5<'Global Inputs'!$E$77,H82,0) -> 0 | I83: =IF(I$5<'Global Inputs'!$E$77,I82,0) -> 0 | J83: =IF(J$5<'Global Inputs'!$E$77,J82,0) -> 0 | K83: =IF(K$5<'Global Inputs'!$E$77,K82,0) -> 0 | L83: =IF(L$5<'Global Inputs'!$E$77,L82,0) -> 0 | M83: =IF(M$5<'Global Inputs'!$E$77,M82,0) -> 0 | ... S83: =IF(S$5<'Global Inputs'!$E$77,S82,0) -> 0
B84: of which from the injection year onward | C84: IDR bn | F84: =IF(F$5>='Global Inputs'!$E$77,F82,0) -> 0 | G84: =IF(G$5>='Global Inputs'!$E$77,G82,0) -> 0 | H84: =IF(H$5>='Global Inputs'!$E$77,H82,0) -> 0 | I84: =IF(I$5>='Global Inputs'!$E$77,I82,0) -> 0 | J84: =IF(J$5>='Global Inputs'!$E$77,J82,0) -> 0 | K84: =IF(K$5>='Global Inputs'!$E$77,K82,0) -> 0 | L84: =IF(L$5>='Global Inputs'!$E$77,L82,0) -> 0 | M84: =IF(M$5>='Global Inputs'!$E$77,M82,0) -> 0 | ... S84: =IF(S$5>='Global Inputs'!$E$77,S82,0) -> 0
B85: Equity requirement at the injection date = MAX(largest shortfall from the injection year onward, planned LT loan repayment) — this case | C85: IDR bn | E85: =SUM(F85:S85) -> 195.18 | F85: =IF(F$5='Global Inputs'!$E$77,MAX(MAX($F$84:$S$84),Financing!F16),0) -> 0 | G85: =IF(G$5='Global Inputs'!$E$77,MAX(MAX($F$84:$S$84),Financing!G16),0) -> 0 | H85: =IF(H$5='Global Inputs'!$E$77,MAX(MAX($F$84:$S$84),Financing!H16),0) -> 0 | I85: =IF(I$5='Global Inputs'!$E$77,MAX(MAX($F$84:$S$84),Financing!I16),0) -> 0 | J85: =IF(J$5='Global Inputs'!$E$77,MAX(MAX($F$84:$S$84),Financing!J16),0) -> 195.18 | K85: =IF(K$5='Global Inputs'!$E$77,MAX(MAX($F$84:$S$84),Financing!K16),0) -> 0 | L85: =IF(L$5='Global Inputs'!$E$77,MAX(MAX($F$84:$S$84),Financing!L16),0) -> 0 | M85: =IF(M$5='Global Inputs'!$E$77,MAX(MAX($F$84:$S$84),Financing!M16),0) -> 0 | ... S85: =IF(S$5='Global Inputs'!$E$77,MAX(MAX($F$84:$S$84),Financing!S16),0) -> 0 | U85: The injection always covers at least the planned loan repayment (board-deck use of proceeds); the shortfall already counts the repayment as a use of cash.
B86: Residual gap after the actual injection (should be nil; non-nil if the injection is fixed too low or sized on the other case) | C86: IDR bn | E86: =SUM(F86:S86) -> 0 | F86: =MAX(0,F81-F66)*F$8 -> 0 | G86: =MAX(0,G81-G66)*G$8 -> 0 | H86: =MAX(0,H81-H66)*H$8 -> 0 | I86: =MAX(0,I81-I66)*I$8 -> 0 | J86: =MAX(0,J81-J66)*J$8 -> 0 | K86: =MAX(0,K81-K66)*K$8 -> 0 | L86: =MAX(0,L81-L66)*L$8 -> 0 | M86: =MAX(0,M81-M66)*M$8 -> 0 | ... S86: =MAX(0,S81-S66)*S$8 -> 0
B88: E. Consolidation workings — project outputs x case inclusion flag (column E). Sums feed the statements above.
B89: Revenue
B90: E1 Teluk Lamong (NPLOG) cargodoring & delivery | C90: IDR bn | E90: ='Global Inputs'!$L$89 -> 1 | F90: ='E1 TelukLamong Output'!F11*$E$90 -> 0 | G90: ='E1 TelukLamong Output'!G11*$E$90 -> 156.43828 | H90: ='E1 TelukLamong Output'!H11*$E$90 -> 161.13143 | I90: ='E1 TelukLamong Output'!I11*$E$90 -> 165.96537 | J90: ='E1 TelukLamong Output'!J11*$E$90 -> 170.94433 | K90: ='E1 TelukLamong Output'!K11*$E$90 -> 176.07266 | L90: ='E1 TelukLamong Output'!L11*$E$90 -> 186.79549 | M90: ='E1 TelukLamong Output'!M11*$E$90 -> 192.39935 | ... S90: ='E1 TelukLamong Output'!S11*$E$90 -> 236.62693
B91: E2 Cigading Existing Terminal (SGT 2) | C91: IDR bn | E91: ='Global Inputs'!$L$90 -> 1 | F91: ='E2 CigadingExist Output'!F11*$E$91 -> 0 | G91: ='E2 CigadingExist Output'!G11*$E$91 -> 38.65796 | H91: ='E2 CigadingExist Output'!H11*$E$91 -> 46.389552 | I91: ='E2 CigadingExist Output'!I11*$E$91 -> 47.781239 | J91: ='E2 CigadingExist Output'!J11*$E$91 -> 59.057611 | K91: ='E2 CigadingExist Output'!K11*$E$91 -> 60.829339 | L91: ='E2 CigadingExist Output'!L11*$E$91 -> 68.919641 | M91: ='E2 CigadingExist Output'!M11*$E$91 -> 70.987231 | ... S91: ='E2 CigadingExist Output'!S11*$E$91 -> 95.239106
B92: E3 Belawan terminal (SGT3) incl. Belawan expansion | C92: IDR bn | E92: ='Global Inputs'!$L$91 -> 1 | F92: ='E3 Belawan Output'!F11*$E$92 -> 0 | G92: ='E3 Belawan Output'!G11*$E$92 -> 22.2435 | H92: ='E3 Belawan Output'!H11*$E$92 -> 22.910805 | I92: ='E3 Belawan Output'!I11*$E$92 -> 34.967927 | J92: ='E3 Belawan Output'!J11*$E$92 -> 44.806465 | K92: ='E3 Belawan Output'!K11*$E$92 -> 49.526879 | L92: ='E3 Belawan Output'!L11*$E$92 -> 54.524582 | M92: ='E3 Belawan Output'!M11*$E$92 -> 59.814057 | ... S92: ='E3 Belawan Output'!S11*$E$92 -> 61.316585
B93: E4 WIN stevedoring (Cilegon, Makassar, Surabaya, Medan) | C93: IDR bn | E93: ='Global Inputs'!$L$92 -> 1 | F93: ='E4 WIN Output'!F11*$E$93 -> 0 | G93: ='E4 WIN Output'!G11*$E$93 -> 87.948672 | H93: ='E4 WIN Output'!H11*$E$93 -> 65.358641 | I93: ='E4 WIN Output'!I11*$E$93 -> 61.989729 | J93: ='E4 WIN Output'!J11*$E$93 -> 66.857705 | K93: ='E4 WIN Output'!K11*$E$93 -> 72.109308 | L93: ='E4 WIN Output'!L11*$E$93 -> 77.774869 | M93: ='E4 WIN Output'!M11*$E$93 -> 83.887124 | ... S93: ='E4 WIN Output'!S11*$E$93 -> 102.46705
B94: P01 Cigading Wharf 2 | C94: IDR bn | E94: ='Global Inputs'!$L$93 -> 1 | F94: ='P01 CigWharf2 Output'!F11*$E$94 -> 0 | G94: ='P01 CigWharf2 Output'!G11*$E$94 -> 0 | H94: ='P01 CigWharf2 Output'!H11*$E$94 -> 100.31221 | I94: ='P01 CigWharf2 Output'!I11*$E$94 -> 103.32158 | J94: ='P01 CigWharf2 Output'!J11*$E$94 -> 127.70547 | K94: ='P01 CigWharf2 Output'!K11*$E$94 -> 131.53663 | L94: ='P01 CigWharf2 Output'!L11*$E$94 -> 149.031 | M94: ='P01 CigWharf2 Output'!M11*$E$94 -> 153.50193 | ... S94: ='P01 CigWharf2 Output'!S11*$E$94 -> 205.9439
B95: P02 Cigading Extended Conveyor | C95: IDR bn | E95: ='Global Inputs'!$L$94 -> 1 | F95: ='P02 CigConveyor Output'!F11*$E$95 -> 0 | G95: ='P02 CigConveyor Output'!G11*$E$95 -> 0 | H95: ='P02 CigConveyor Output'!H11*$E$95 -> 31.5 | I95: ='P02 CigConveyor Output'!I11*$E$95 -> 32.445 | J95: ='P02 CigConveyor Output'!J11*$E$95 -> 33.41835 | K95: ='P02 CigConveyor Output'!K11*$E$95 -> 34.420901 | L95: ='P02 CigConveyor Output'!L11*$E$95 -> 35.453528 | M95: ='P02 CigConveyor Output'!M11*$E$95 -> 36.517133 | ... S95: ='P02 CigConveyor Output'!S11*$E$95 -> 43.603367
B96: P03 KBS Warehouse Revitalisation (Cigading) | C96: IDR bn | E96: ='Global Inputs'!$L$95 -> 1 | F96: ='P03 KBSWarehouse Output'!F11*$E$96 -> 0 | G96: ='P03 KBSWarehouse Output'!G11*$E$96 -> 0 | H96: ='P03 KBSWarehouse Output'!H11*$E$96 -> 0 | I96: ='P03 KBSWarehouse Output'!I11*$E$96 -> 0 | J96: ='P03 KBSWarehouse Output'!J11*$E$96 -> 53.023782 | K96: ='P03 KBSWarehouse Output'!K11*$E$96 -> 54.614495 | L96: ='P03 KBSWarehouse Output'!L11*$E$96 -> 56.25293 | M96: ='P03 KBSWarehouse Output'!M11*$E$96 -> 57.940518 | ... S96: ='P03 KBSWarehouse Output'!S11*$E$96 -> 69.184009
B97: P04 Teluk Lamong Silo | C97: IDR bn | E97: ='Global Inputs'!$L$96 -> 1 | F97: ='P04 TTLSilo Output'!F11*$E$97 -> 0 | G97: ='P04 TTLSilo Output'!G11*$E$97 -> 0 | H97: ='P04 TTLSilo Output'!H11*$E$97 -> 0 | I97: ='P04 TTLSilo Output'!I11*$E$97 -> 0 | J97: ='P04 TTLSilo Output'!J11*$E$97 -> 13.26 | K97: ='P04 TTLSilo Output'!K11*$E$97 -> 13.26 | L97: ='P04 TTLSilo Output'!L11*$E$97 -> 13.26 | M97: ='P04 TTLSilo Output'!M11*$E$97 -> 13.26 | ... S97: ='P04 TTLSilo Output'!S11*$E$97 -> 13.26
B98: P05 Dumai bagging & weighbridge | C98: IDR bn | E98: ='Global Inputs'!$L$97 -> 1 | F98: ='P05 Dumai Output'!F11*$E$98 -> 0 | G98: ='P05 Dumai Output'!G11*$E$98 -> 0 | H98: ='P05 Dumai Output'!H11*$E$98 -> 0 | I98: ='P05 Dumai Output'!I11*$E$98 -> 48.1 | J98: ='P05 Dumai Output'!J11*$E$98 -> 48.1 | K98: ='P05 Dumai Output'!K11*$E$98 -> 48.1 | L98: ='P05 Dumai Output'!L11*$E$98 -> 51.4176 | M98: ='P05 Dumai Output'!M11*$E$98 -> 51.4176 | ... S98: ='P05 Dumai Output'!S11*$E$98 -> 54.9682
B99: P06 Ciwandan Expansion | C99: IDR bn | E99: ='Global Inputs'!$L$98 -> 1 | F99: ='P06 Ciwandan Output'!F11*$E$99 -> 0 | G99: ='P06 Ciwandan Output'!G11*$E$99 -> 0 | H99: ='P06 Ciwandan Output'!H11*$E$99 -> 0 | I99: ='P06 Ciwandan Output'!I11*$E$99 -> 0 | J99: ='P06 Ciwandan Output'!J11*$E$99 -> 0 | K99: ='P06 Ciwandan Output'!K11*$E$99 -> 58.25784 | L99: ='P06 Ciwandan Output'!L11*$E$99 -> 76.900348 | M99: ='P06 Ciwandan Output'!M11*$E$99 -> 84.590383 | ... S99: ='P06 Ciwandan Output'!S11*$E$99 -> 153.90312
B100: P08 DMS trucking fee (Teluk Lamong, Cigading, Ciwandan, Belawan) | C100: IDR bn | E100: ='Global Inputs'!$L$99 -> 1 | F100: ='P08 DMSTrucking Output'!F11*$E$100 -> 0 | G100: ='P08 DMSTrucking Output'!G11*$E$100 -> 0 | H100: ='P08 DMSTrucking Output'!H11*$E$100 -> 0 | I100: ='P08 DMSTrucking Output'!I11*$E$100 -> 0 | J100: ='P08 DMSTrucking Output'!J11*$E$100 -> 2.7523996 | K100: ='P08 DMSTrucking Output'!K11*$E$100 -> 3.3007715 | L100: ='P08 DMSTrucking Output'!L11*$E$100 -> 3.4340747 | M100: ='P08 DMSTrucking Output'!M11*$E$100 -> 3.5746249 | ... S100: ='P08 DMSTrucking Output'!S11*$E$100 -> 4.4360102
B101: P12 BUMN operatorship schemes (Pelindo Teluk Lamong, KBS Cigading, Pelindo Belawan) | C101: IDR bn | E101: ='Global Inputs'!$L$100 -> 1 | F101: ='P12 BUMNOps Output'!F11*$E$101 -> 0 | G101: ='P12 BUMNOps Output'!G11*$E$101 -> 0 | H101: ='P12 BUMNOps Output'!H11*$E$101 -> 0 | I101: ='P12 BUMNOps Output'!I11*$E$101 -> 127.49372 | J101: ='P12 BUMNOps Output'!J11*$E$101 -> 134.53638 | K101: ='P12 BUMNOps Output'!K11*$E$101 -> 139.2804 | L101: ='P12 BUMNOps Output'!L11*$E$101 -> 144.1426 | M101: ='P12 BUMNOps Output'!M11*$E$101 -> 149.12654 | ... S101: ='P12 BUMNOps Output'!S11*$E$101 -> 171.34089
B102: P15 TBM — Tanjung Batu / Pelindo land lease, warehousing and cargo handling | C102: IDR bn | E102: ='Global Inputs'!$L$101 -> 0 | F102: ='P15 TBM Output'!F11*$E$102 -> 0 | G102: ='P15 TBM Output'!G11*$E$102 -> 0 | H102: ='P15 TBM Output'!H11*$E$102 -> 0 | I102: ='P15 TBM Output'!I11*$E$102 -> 0 | J102: ='P15 TBM Output'!J11*$E$102 -> 0 | K102: ='P15 TBM Output'!K11*$E$102 -> 0 | L102: ='P15 TBM Output'!L11*$E$102 -> 0 | M102: ='P15 TBM Output'!M11*$E$102 -> 0 | ... S102: ='P15 TBM Output'!S11*$E$102 -> 0
B103: P19 Badas bulk terminal (FS pending — DUMMY data) | C103: IDR bn | E103: ='Global Inputs'!$L$102 -> 0 | F103: ='P19 Badas Output'!F11*$E$103 -> 0 | G103: ='P19 Badas Output'!G11*$E$103 -> 0 | H103: ='P19 Badas Output'!H11*$E$103 -> 0 | I103: ='P19 Badas Output'!I11*$E$103 -> 0 | J103: ='P19 Badas Output'!J11*$E$103 -> 0 | K103: ='P19 Badas Output'!K11*$E$103 -> 0 | L103: ='P19 Badas Output'!L11*$E$103 -> 0 | M103: ='P19 Badas Output'!M11*$E$103 -> 0 | ... S103: ='P19 Badas Output'!S11*$E$103 -> 0
B104: Total — Revenue | C104: IDR bn | E104: =SUM(F104:S104) -> 11598.728 | F104: =F90+F91+F92+F93+F94+F95+F96+F97+F98+F99+F100+F101+F102+F103 -> 0 | G104: =G90+G91+G92+G93+G94+G95+G96+G97+G98+G99+G100+G101+G102+G103 -> 305.28841 | H104: =H90+H91+H92+H93+H94+H95+H96+H97+H98+H99+H100+H101+H102+H103 -> 427.60264 | I104: =I90+I91+I92+I93+I94+I95+I96+I97+I98+I99+I100+I101+I102+I103 -> 622.06456 | J104: =J90+J91+J92+J93+J94+J95+J96+J97+J98+J99+J100+J101+J102+J103 -> 754.46249 | K104: =K90+K91+K92+K93+K94+K95+K96+K97+K98+K99+K100+K101+K102+K103 -> 841.30923 | L104: =L90+L91+L92+L93+L94+L95+L96+L97+L98+L99+L100+L101+L102+L103 -> 917.90667 | M104: =M90+M91+M92+M93+M94+M95+M96+M97+M98+M99+M100+M101+M102+M103 -> 957.0165 | ... S104: =S90+S91+S92+S93+S94+S95+S96+S97+S98+S99+S100+S101+S102+S103 -> 1212.2892
B105: Cost of sales
B106: E1 Teluk Lamong (NPLOG) cargodoring & delivery | C106: IDR bn | E106: ='Global Inputs'!$L$89 -> 1 | F106: ='E1 TelukLamong Output'!F12*$E$106 -> 0 | G106: ='E1 TelukLamong Output'!G12*$E$106 -> -29.933786 | H106: ='E1 TelukLamong Output'!H12*$E$106 -> -31.312221 | I106: ='E1 TelukLamong Output'!I12*$E$106 -> -32.782551 | J106: ='E1 TelukLamong Output'!J12*$E$106 -> -34.306022 | K106: ='E1 TelukLamong Output'!K12*$E$106 -> -35.908011 | L106: ='E1 TelukLamong Output'!L12*$E$106 -> -37.614126 | M106: ='E1 TelukLamong Output'!M12*$E$106 -> -39.386317 | ... S106: ='E1 TelukLamong Output'!S12*$E$106 -> -52.165749
B107: E2 Cigading Existing Terminal (SGT 2) | C107: IDR bn | E107: ='Global Inputs'!$L$90 -> 1 | F107: ='E2 CigadingExist Output'!F12*$E$107 -> 0 | G107: ='E2 CigadingExist Output'!G12*$E$107 -> -13.421705 | H107: ='E2 CigadingExist Output'!H12*$E$107 -> -13.950545 | I107: ='E2 CigadingExist Output'!I12*$E$107 -> -14.537514 | J107: ='E2 CigadingExist Output'!J12*$E$107 -> -15.117542 | K107: ='E2 CigadingExist Output'!K12*$E$107 -> -15.72513 | L107: ='E2 CigadingExist Output'!L12*$E$107 -> -16.394852 | M107: ='E2 CigadingExist Output'!M12*$E$107 -> -17.061853 | ... S107: ='E2 CigadingExist Output'!S12*$E$107 -> -21.830077
...

Sheet Funding Requirement
B1: FUNDING REQUIREMENT — how much equity do we need, and when?
B2: Cash roll-forward of the selected operating case: investment, internally generated cash, minimum cash, debt service incl. the LT loan repayment at the injection, remaining equity gap; capex-only projects added separately. IDR bn.
B3: Go to: | C3: Navigation | D3: Global Inputs | E3: Project Summary | F3: Funding | G3: FSL w/o BUMN | H3: FSL w/ BUMN | I3: Val w/o BUMN | J3: Val w/ BUMN | K3: Checks | L3: Model Flow
B5: Year | C5: Unit | D5: Type | E5: Value / total | F5: ='Global Inputs'!F$5 -> 2023 | G5: ='Global Inputs'!G$5 -> 2024 | H5: ='Global Inputs'!H$5 -> 2025 | I5: ='Global Inputs'!I$5 -> 2026 | J5: ='Global Inputs'!J$5 -> 2027 | K5: ='Global Inputs'!K$5 -> 2028 | L5: ='Global Inputs'!L$5 -> 2029 | M5: ='Global Inputs'!M$5 -> 2030 | ... S5: ='Global Inputs'!S$5 -> 2036 | T5: Source (v29 reference / basis) | U5: Note
B6: Period end | F6: ='Global Inputs'!F$6 -> 45291 | G6: ='Global Inputs'!G$6 -> 45657 | H6: ='Global Inputs'!H$6 -> 46022 | I6: ='Global Inputs'!I$6 -> 46387 | J6: ='Global Inputs'!J$6 -> 46752 | K6: ='Global Inputs'!K$6 -> 47118 | L6: ='Global Inputs'!L$6 -> 47483 | M6: ='Global Inputs'!M$6 -> 47848 | ... S6: ='Global Inputs'!S$6 -> 50040
B7: Days in year | F7: ='Global Inputs'!F$7 -> 365 | G7: ='Global Inputs'!G$7 -> 366 | H7: ='Global Inputs'!H$7 -> 365 | I7: ='Global Inputs'!I$7 -> 365 | J7: ='Global Inputs'!J$7 -> 365 | K7: ='Global Inputs'!K$7 -> 366 | L7: ='Global Inputs'!L$7 -> 365 | M7: ='Global Inputs'!M$7 -> 365 | ... S7: ='Global Inputs'!S$7 -> 366
B8: Forecast flag (1 = forecast year) | F8: ='Global Inputs'!F$8 -> 0 | G8: ='Global Inputs'!G$8 -> 1 | H8: ='Global Inputs'!H$8 -> 1 | I8: ='Global Inputs'!I$8 -> 1 | J8: ='Global Inputs'!J$8 -> 1 | K8: ='Global Inputs'!K$8 -> 1 | L8: ='Global Inputs'!L$8 -> 1 | M8: ='Global Inputs'!M$8 -> 1 | ... S8: ='Global Inputs'!S$8 -> 1
B10: A. How much equity do we need? (headline answers)
B11: Operating case underlying the funding calculation (Global Inputs switch) | E11: =IF('Global Inputs'!$E$36=1,"Without BUMN (conservative)","With BUMN") -> Without BUMN (conservative)
B12: Capital injection date (provisional — Global Inputs) | C12: date | E12: ='Global Inputs'!$E$76 -> 46568
B13: Injection amount mode (1 = computed requirement, 2 = fixed amount) | C13: 1/2 | E13: ='Global Inputs'!$E$79 -> 1
B14: Equity requirement — valuation-scope operations incl. LT loan repayment (funding case), IDR bn | C14: IDR bn | E14: =SUM($F$39:$S$39) -> 195.18
B15: same in USD m (injection-year exchange rate) | C15: USD m | E15: =$E$14/INDEX('Global Inputs'!$F$22:$S$22,MATCH('Global Inputs'!$E$77,'Global Inputs'!$F$15:$S$15,0))*1000 -> 12
B16: Additional capex-only request — Badas (when outside the valuation) and funding-only placeholders F01-F05, IDR bn | C16: IDR bn | E16: =SUM($F$112:$S$112) -> 162.65
B17: TOTAL EQUITY FUNDING REQUEST (IDR bn) | C17: IDR bn | E17: =$E$14+$E$16 -> 357.83
B18: TOTAL EQUITY FUNDING REQUEST (USD m) | C18: USD m | E18: =$E$17/INDEX('Global Inputs'!$F$22:$S$22,MATCH('Global Inputs'!$E$77,'Global Inputs'!$F$15:$S$15,0))*1000 -> 22
B19: of which depends on provisional / DUMMY assumptions (Badas dummy capex, blank placeholders, unconfirmed pre-valuation spend timing) | C19: IDR bn | E19: =$E$16+$E$20 -> 357.83
B20: unconfirmed pre-valuation capex (v29 timing, not actuals) within the valuation-scope requirement, IDR bn | C20: IDR bn | E20: =MIN($E$14,-SUMPRODUCT($F$31:$S$31,--('Global Inputs'!$F$15:$S$15<='Global Inputs'!$E$12),--('Global Inputs'!$F$15:$S$15>=2024))) -> 195.18
B21: of which planned LT loan repayment funded from the proceeds | C21: IDR bn | E21: =SUM(Financing!$F$16:$S$16) -> 195.18
B22: Bridge need before the injection (largest pre-injection shortfall against minimum cash) — to be covered by shareholder / bank bridge | C22: IDR bn | E22: =MAX($F$37:$S$37) -> 0
B23: Comparison: requirement Without BUMN | C23: IDR bn | E23: =SUM('FSL Financials — Without BUMN'!$F$85:$S$85) -> 195.18
B24: Comparison: requirement With BUMN | C24: IDR bn | E24: =SUM('FSL Financials — With BUMN'!$F$85:$S$85) -> 195.18
B25: Residual gap after the actual injection (funding case) — nil in mode 1 | C25: IDR bn | E25: =SUM($F$42:$S$42) -> 0
B26: Equity requirement (cash to be contributed) is NOT the equity value of FSL — see the Valuation sheets.
B28: B. Cash roll-forward — funding case (linked from the selected FSL Financials sheet; IDR bn)
B29: Opening cash (pre-equity path) | C29: IDR bn | F29: =IF('Global Inputs'!$E$36=1,'FSL Financials — Without BUMN'!F70,'FSL Financials — With BUMN'!F70) -> 0 | G29: =IF('Global Inputs'!$E$36=1,'FSL Financials — Without BUMN'!G70,'FSL Financials — With BUMN'!G70) -> 60.6389 | H29: =IF('Global Inputs'!$E$36=1,'FSL Financials — Without BUMN'!H70,'FSL Financials — With BUMN'!H70) -> 32.209449 | I29: =IF('Global Inputs'!$E$36=1,'FSL Financials — Without BUMN'!I70,'FSL Financials — With BUMN'!I70) -> 192.17176 | J29: =IF('Global Inputs'!$E$36=1,'FSL Financials — Without BUMN'!J70,'FSL Financials — With BUMN'!J70) -> 3 | K29: =IF('Global Inputs'!$E$36=1,'FSL Financials — Without BUMN'!K70,'FSL Financials — With BUMN'!K70) -> -39.845605 | L29: =IF('Global Inputs'!$E$36=1,'FSL Financials — Without BUMN'!L70,'FSL Financials — With BUMN'!L70) -> 263.14171 | M29: =IF('Global Inputs'!$E$36=1,'FSL Financials — Without BUMN'!M70,'FSL Financials — With BUMN'!M70) -> 597.26639 | ... S29: =IF('Global Inputs'!$E$36=1,'FSL Financials — Without BUMN'!S70,'FSL Financials — With BUMN'!S70) -> 2937.1088
B30: + Cash flow from operations (net profit + D&A - working capital increase; interest and tax inside net profit) | C30: IDR bn | F30: =IF('Global Inputs'!$E$36=1,'FSL Financials — Without BUMN'!F71,'FSL Financials — With BUMN'!F71) -> 0 | G30: =IF('Global Inputs'!$E$36=1,'FSL Financials — Without BUMN'!G71,'FSL Financials — With BUMN'!G71) -> 132.84279 | H30: =IF('Global Inputs'!$E$36=1,'FSL Financials — Without BUMN'!H71,'FSL Financials — With BUMN'!H71) -> 198.89727 | I30: =IF('Global Inputs'!$E$36=1,'FSL Financials — Without BUMN'!I71,'FSL Financials — With BUMN'!I71) -> 244.8795 | J30: =IF('Global Inputs'!$E$36=1,'FSL Financials — Without BUMN'!J71,'FSL Financials — With BUMN'!J71) -> 312.33802 | K30: =IF('Global Inputs'!$E$36=1,'FSL Financials — Without BUMN'!K71,'FSL Financials — With BUMN'!K71) -> 362.85062 | L30: =IF('Global Inputs'!$E$36=1,'FSL Financials — Without BUMN'!L71,'FSL Financials — With BUMN'!L71) -> 405.61341 | M30: =IF('Global Inputs'!$E$36=1,'FSL Financials — Without BUMN'!M71,'FSL Financials — With BUMN'!M71) -> 425.53535 | ... S30: =IF('Global Inputs'!$E$36=1,'FSL Financials — Without BUMN'!S71,'FSL Financials — With BUMN'!S71) -> 536.00274
B31: - Project investment (capex, projects in the case) | C31: IDR bn | E31: =SUM(F31:S31) -> -918.08767 | F31: =IF('Global Inputs'!$E$36=1,'FSL Financials — Without BUMN'!F72,'FSL Financials — With BUMN'!F72) -> -198.433 | G31: =IF('Global Inputs'!$E$36=1,'FSL Financials — Without BUMN'!G72,'FSL Financials — With BUMN'!G72) -> -125.2405 | H31: =IF('Global Inputs'!$E$36=1,'FSL Financials — Without BUMN'!H72,'FSL Financials — With BUMN'!H72) -> -14.6385 | I31: =IF('Global Inputs'!$E$36=1,'FSL Financials — Without BUMN'!I72,'FSL Financials — With BUMN'!I72) -> -419.77205 | J31: =IF('Global Inputs'!$E$36=1,'FSL Financials — Without BUMN'!J72,'FSL Financials — With BUMN'!J72) -> -160.00362 | K31: =IF('Global Inputs'!$E$36=1,'FSL Financials — Without BUMN'!K72,'FSL Financials — With BUMN'!K72) -> 0 | L31: =IF('Global Inputs'!$E$36=1,'FSL Financials — Without BUMN'!L72,'FSL Financials — With BUMN'!L72) -> 0 | M31: =IF('Global Inputs'!$E$36=1,'FSL Financials — Without BUMN'!M72,'FSL Financials — With BUMN'!M72) -> 0 | ... S31: =IF('Global Inputs'!$E$36=1,'FSL Financials — Without BUMN'!S72,'FSL Financials — With BUMN'!S72) -> 0
B32: - Debt service: other loans FY2024, LT loan repayment at the injection | C32: IDR bn | E32: =SUM(F32:S32) -> -224.518 | F32: =IF('Global Inputs'!$E$36=1,'FSL Financials — Without BUMN'!F73,'FSL Financials — With BUMN'!F73) -> 0 | G32: =IF('Global Inputs'!$E$36=1,'FSL Financials — Without BUMN'!G73,'FSL Financials — With BUMN'!G73) -> -29.338 | H32: =IF('Global Inputs'!$E$36=1,'FSL Financials — Without BUMN'!H73,'FSL Financials — With BUMN'!H73) -> 0 | I32: =IF('Global Inputs'!$E$36=1,'FSL Financials — Without BUMN'!I73,'FSL Financials — With BUMN'!I73) -> 0 | J32: =IF('Global Inputs'!$E$36=1,'FSL Financials — Without BUMN'!J73,'FSL Financials — With BUMN'!J73) -> -195.18 | K32: =IF('Global Inputs'!$E$36=1,'FSL Financials — Without BUMN'!K73,'FSL Financials — With BUMN'!K73) -> 0 | L32: =IF('Global Inputs'!$E$36=1,'FSL Financials — Without BUMN'!L73,'FSL Financials — With BUMN'!L73) -> 0 | M32: =IF('Global Inputs'!$E$36=1,'FSL Financials — Without BUMN'!M73,'FSL Financials — With BUMN'!M73) -> 0 | ... S32: =IF('Global Inputs'!$E$36=1,'FSL Financials — Without BUMN'!S73,'FSL Financials — With BUMN'!S73) -> 0
B33: - Dividends (policy; capped by pre-equity cash) | C33: IDR bn | E33: =SUM(F33:S33) -> -862.62601 | F33: =IF('Global Inputs'!$E$36=1,'FSL Financials — Without BUMN'!F79,'FSL Financials — With BUMN'!F79) -> 0 | G33: =IF('Global Inputs'!$E$36=1,'FSL Financials — Without BUMN'!G79,'FSL Financials — With BUMN'!G79) -> -6.693745 | H33: =IF('Global Inputs'!$E$36=1,'FSL Financials — Without BUMN'!H79,'FSL Financials — With BUMN'!H79) -> -24.296455 | I33: =IF('Global Inputs'!$E$36=1,'FSL Financials — Without BUMN'!I79,'FSL Financials — With BUMN'!I79) -> -14.279223 | J33: =IF('Global Inputs'!$E$36=1,'FSL Financials — Without BUMN'!J79,'FSL Financials — With BUMN'!J79) -> 0 | K33: =IF('Global Inputs'!$E$36=1,'FSL Financials — Without BUMN'!K79,'FSL Financials — With BUMN'!K79) -> -59.863306 | L33: =IF('Global Inputs'!$E$36=1,'FSL Financials — Without BUMN'!L79,'FSL Financials — With BUMN'!L79) -> -71.488726 | M33: =IF('Global Inputs'!$E$36=1,'FSL Financials — Without BUMN'!M79,'FSL Financials — With BUMN'!M79) -> -75.754725 | ... S33: =IF('Global Inputs'!$E$36=1,'FSL Financials — Without BUMN'!S79,'FSL Financials — With BUMN'!S79) -> -114.21419
B34: Cash before new equity | C34: IDR bn | F34: =IF('Global Inputs'!$E$36=1,'FSL Financials — Without BUMN'!F80,'FSL Financials — With BUMN'!F80) -> 60.6389 | G34: =IF('Global Inputs'!$E$36=1,'FSL Financials — Without BUMN'!G80,'FSL Financials — With BUMN'!G80) -> 32.209449 | H34: =IF('Global Inputs'!$E$36=1,'FSL Financials — Without BUMN'!H80,'FSL Financials — With BUMN'!H80) -> 192.17176 | I34: =IF('Global Inputs'!$E$36=1,'FSL Financials — Without BUMN'!I80,'FSL Financials — With BUMN'!I80) -> 3 | J34: =IF('Global Inputs'!$E$36=1,'FSL Financials — Without BUMN'!J80,'FSL Financials — With BUMN'!J80) -> -39.845605 | K34: =IF('Global Inputs'!$E$36=1,'FSL Financials — Without BUMN'!K80,'FSL Financials — With BUMN'!K80) -> 263.14171 | L34: =IF('Global Inputs'!$E$36=1,'FSL Financials — Without BUMN'!L80,'FSL Financials — With BUMN'!L80) -> 597.26639 | M34: =IF('Global Inputs'!$E$36=1,'FSL Financials — Without BUMN'!M80,'FSL Financials — With BUMN'!M80) -> 947.04702 | ... S34: =IF('Global Inputs'!$E$36=1,'FSL Financials — Without BUMN'!S80,'FSL Financials — With BUMN'!S80) -> 3358.8974
B35: Minimum operating cash | C35: IDR bn | F35: =IF('Global Inputs'!$E$36=1,'FSL Financials — Without BUMN'!F81,'FSL Financials — With BUMN'!F81) -> 0 | G35: =IF('Global Inputs'!$E$36=1,'FSL Financials — Without BUMN'!G81,'FSL Financials — With BUMN'!G81) -> 3 | H35: =IF('Global Inputs'!$E$36=1,'FSL Financials — Without BUMN'!H81,'FSL Financials — With BUMN'!H81) -> 3 | I35: =IF('Global Inputs'!$E$36=1,'FSL Financials — Without BUMN'!I81,'FSL Financials — With BUMN'!I81) -> 3 | J35: =IF('Global Inputs'!$E$36=1,'FSL Financials — Without BUMN'!J81,'FSL Financials — With BUMN'!J81) -> 3 | K35: =IF('Global Inputs'!$E$36=1,'FSL Financials — Without BUMN'!K81,'FSL Financials — With BUMN'!K81) -> 3 | L35: =IF('Global Inputs'!$E$36=1,'FSL Financials — Without BUMN'!L81,'FSL Financials — With BUMN'!L81) -> 3 | M35: =IF('Global Inputs'!$E$36=1,'FSL Financials — Without BUMN'!M81,'FSL Financials — With BUMN'!M81) -> 3 | ... S35: =IF('Global Inputs'!$E$36=1,'FSL Financials — Without BUMN'!S81,'FSL Financials — With BUMN'!S81) -> 3
B36: Shortfall against minimum cash (before new equity) | C36: IDR bn | F36: =IF('Global Inputs'!$E$36=1,'FSL Financials — Without BUMN'!F82,'FSL Financials — With BUMN'!F82) -> 0 | G36: =IF('Global Inputs'!$E$36=1,'FSL Financials — Without BUMN'!G82,'FSL Financials — With BUMN'!G82) -> 0 | H36: =IF('Global Inputs'!$E$36=1,'FSL Financials — Without BUMN'!H82,'FSL Financials — With BUMN'!H82) -> 0 | I36: =IF('Global Inputs'!$E$36=1,'FSL Financials — Without BUMN'!I82,'FSL Financials — With BUMN'!I82) -> 0 | J36: =IF('Global Inputs'!$E$36=1,'FSL Financials — Without BUMN'!J82,'FSL Financials — With BUMN'!J82) -> 42.845605 | K36: =IF('Global Inputs'!$E$36=1,'FSL Financials — Without BUMN'!K82,'FSL Financials — With BUMN'!K82) -> 0 | L36: =IF('Global Inputs'!$E$36=1,'FSL Financials — Without BUMN'!L82,'FSL Financials — With BUMN'!L82) -> 0 | M36: =IF('Global Inputs'!$E$36=1,'FSL Financials — Without BUMN'!M82,'FSL Financials — With BUMN'!M82) -> 0 | ... S36: =IF('Global Inputs'!$E$36=1,'FSL Financials — Without BUMN'!S82,'FSL Financials — With BUMN'!S82) -> 0
B37: before the injection year (bridge need) | C37: IDR bn | F37: =IF('Global Inputs'!$E$36=1,'FSL Financials — Without BUMN'!F83,'FSL Financials — With BUMN'!F83) -> 0 | G37: =IF('Global Inputs'!$E$36=1,'FSL Financials — Without BUMN'!G83,'FSL Financials — With BUMN'!G83) -> 0 | H37: =IF('Global Inputs'!$E$36=1,'FSL Financials — Without BUMN'!H83,'FSL Financials — With BUMN'!H83) -> 0 | I37: =IF('Global Inputs'!$E$36=1,'FSL Financials — Without BUMN'!I83,'FSL Financials — With BUMN'!I83) -> 0 | J37: =IF('Global Inputs'!$E$36=1,'FSL Financials — Without BUMN'!J83,'FSL Financials — With BUMN'!J83) -> 0 | K37: =IF('Global Inputs'!$E$36=1,'FSL Financials — Without BUMN'!K83,'FSL Financials — With BUMN'!K83) -> 0 | L37: =IF('Global Inputs'!$E$36=1,'FSL Financials — Without BUMN'!L83,'FSL Financials — With BUMN'!L83) -> 0 | M37: =IF('Global Inputs'!$E$36=1,'FSL Financials — Without BUMN'!M83,'FSL Financials — With BUMN'!M83) -> 0 | ... S37: =IF('Global Inputs'!$E$36=1,'FSL Financials — Without BUMN'!S83,'FSL Financials — With BUMN'!S83) -> 0
B38: from the injection year onward | C38: IDR bn | F38: =IF('Global Inputs'!$E$36=1,'FSL Financials — Without BUMN'!F84,'FSL Financials — With BUMN'!F84) -> 0 | G38: =IF('Global Inputs'!$E$36=1,'FSL Financials — Without BUMN'!G84,'FSL Financials — With BUMN'!G84) -> 0 | H38: =IF('Global Inputs'!$E$36=1,'FSL Financials — Without BUMN'!H84,'FSL Financials — With BUMN'!H84) -> 0 | I38: =IF('Global Inputs'!$E$36=1,'FSL Financials — Without BUMN'!I84,'FSL Financials — With BUMN'!I84) -> 0 | J38: =IF('Global Inputs'!$E$36=1,'FSL Financials — Without BUMN'!J84,'FSL Financials — With BUMN'!J84) -> 42.845605 | K38: =IF('Global Inputs'!$E$36=1,'FSL Financials — Without BUMN'!K84,'FSL Financials — With BUMN'!K84) -> 0 | L38: =IF('Global Inputs'!$E$36=1,'FSL Financials — Without BUMN'!L84,'FSL Financials — With BUMN'!L84) -> 0 | M38: =IF('Global Inputs'!$E$36=1,'FSL Financials — Without BUMN'!M84,'FSL Financials — With BUMN'!M84) -> 0 | ... S38: =IF('Global Inputs'!$E$36=1,'FSL Financials — Without BUMN'!S84,'FSL Financials — With BUMN'!S84) -> 0
B39: EQUITY REQUIREMENT at the injection date = largest shortfall from the injection year onward | C39: IDR bn | E39: =SUM(F39:S39) -> 195.18 | F39: =IF('Global Inputs'!$E$36=1,'FSL Financials — Without BUMN'!F85,'FSL Financials — With BUMN'!F85) -> 0 | G39: =IF('Global Inputs'!$E$36=1,'FSL Financials — Without BUMN'!G85,'FSL Financials — With BUMN'!G85) -> 0 | H39: =IF('Global Inputs'!$E$36=1,'FSL Financials — Without BUMN'!H85,'FSL Financials — With BUMN'!H85) -> 0 | I39: =IF('Global Inputs'!$E$36=1,'FSL Financials — Without BUMN'!I85,'FSL Financials — With BUMN'!I85) -> 0 | J39: =IF('Global Inputs'!$E$36=1,'FSL Financials — Without BUMN'!J85,'FSL Financials — With BUMN'!J85) -> 195.18 | K39: =IF('Global Inputs'!$E$36=1,'FSL Financials — Without BUMN'!K85,'FSL Financials — With BUMN'!K85) -> 0 | L39: =IF('Global Inputs'!$E$36=1,'FSL Financials — Without BUMN'!L85,'FSL Financials — With BUMN'!L85) -> 0 | M39: =IF('Global Inputs'!$E$36=1,'FSL Financials — Without BUMN'!M85,'FSL Financials — With BUMN'!M85) -> 0 | ... S39: =IF('Global Inputs'!$E$36=1,'FSL Financials — Without BUMN'!S85,'FSL Financials — With BUMN'!S85) -> 0
B40: Capital injection received (Financing sheet) | C40: IDR bn | E40: =SUM(F40:S40) -> 195.18 | F40: =IF('Global Inputs'!$E$36=1,'FSL Financials — Without BUMN'!F60,'FSL Financials — With BUMN'!F60) -> 0 | G40: =IF('Global Inputs'!$E$36=1,'FSL Financials — Without BUMN'!G60,'FSL Financials — With BUMN'!G60) -> 0 | H40: =IF('Global Inputs'!$E$36=1,'FSL Financials — Without BUMN'!H60,'FSL Financials — With BUMN'!H60) -> 0 | I40: =IF('Global Inputs'!$E$36=1,'FSL Financials — Without BUMN'!I60,'FSL Financials — With BUMN'!I60) -> 0 | J40: =IF('Global Inputs'!$E$36=1,'FSL Financials — Without BUMN'!J60,'FSL Financials — With BUMN'!J60) -> 195.18 | K40: =IF('Global Inputs'!$E$36=1,'FSL Financials — Without BUMN'!K60,'FSL Financials — With BUMN'!K60) -> 0 | L40: =IF('Global Inputs'!$E$36=1,'FSL Financials — Without BUMN'!L60,'FSL Financials — With BUMN'!L60) -> 0 | M40: =IF('Global Inputs'!$E$36=1,'FSL Financials — Without BUMN'!M60,'FSL Financials — With BUMN'!M60) -> 0 | ... S40: =IF('Global Inputs'!$E$36=1,'FSL Financials — Without BUMN'!S60,'FSL Financials — With BUMN'!S60) -> 0
B41: Closing cash after the injection | C41: IDR bn | F41: =IF('Global Inputs'!$E$36=1,'FSL Financials — Without BUMN'!F66,'FSL Financials — With BUMN'!F66) -> 60.6389 | G41: =IF('Global Inputs'!$E$36=1,'FSL Financials — Without BUMN'!G66,'FSL Financials — With BUMN'!G66) -> 32.209449 | H41: =IF('Global Inputs'!$E$36=1,'FSL Financials — Without BUMN'!H66,'FSL Financials — With BUMN'!H66) -> 192.17176 | I41: =IF('Global Inputs'!$E$36=1,'FSL Financials — Without BUMN'!I66,'FSL Financials — With BUMN'!I66) -> 3 | J41: =IF('Global Inputs'!$E$36=1,'FSL Financials — Without BUMN'!J66,'FSL Financials — With BUMN'!J66) -> 155.3344 | K41: =IF('Global Inputs'!$E$36=1,'FSL Financials — Without BUMN'!K66,'FSL Financials — With BUMN'!K66) -> 458.32171 | L41: =IF('Global Inputs'!$E$36=1,'FSL Financials — Without BUMN'!L66,'FSL Financials — With BUMN'!L66) -> 792.44639 | M41: =IF('Global Inputs'!$E$36=1,'FSL Financials — Without BUMN'!M66,'FSL Financials — With BUMN'!M66) -> 1142.227 | ... S41: =IF('Global Inputs'!$E$36=1,'FSL Financials — Without BUMN'!S66,'FSL Financials — With BUMN'!S66) -> 3554.0774
B42: Residual gap after the injection | C42: IDR bn | E42: =SUM(F42:S42) -> 0 | F42: =IF('Global Inputs'!$E$36=1,'FSL Financials — Without BUMN'!F86,'FSL Financials — With BUMN'!F86) -> 0 | G42: =IF('Global Inputs'!$E$36=1,'FSL Financials — Without BUMN'!G86,'FSL Financials — With BUMN'!G86) -> 0 | H42: =IF('Global Inputs'!$E$36=1,'FSL Financials — Without BUMN'!H86,'FSL Financials — With BUMN'!H86) -> 0 | I42: =IF('Global Inputs'!$E$36=1,'FSL Financials — Without BUMN'!I86,'FSL Financials — With BUMN'!I86) -> 0 | J42: =IF('Global Inputs'!$E$36=1,'FSL Financials — Without BUMN'!J86,'FSL Financials — With BUMN'!J86) -> 0 | K42: =IF('Global Inputs'!$E$36=1,'FSL Financials — Without BUMN'!K86,'FSL Financials — With BUMN'!K86) -> 0 | L42: =IF('Global Inputs'!$E$36=1,'FSL Financials — Without BUMN'!L86,'FSL Financials — With BUMN'!L86) -> 0 | M42: =IF('Global Inputs'!$E$36=1,'FSL Financials — Without BUMN'!M86,'FSL Financials — With BUMN'!M86) -> 0 | ... S42: =IF('Global Inputs'!$E$36=1,'FSL Financials — Without BUMN'!S86,'FSL Financials — With BUMN'!S86) -> 0
B43: No double counting: interest and tax are inside net profit (CFO); working-capital movements are inside CFO; the LT loan repayment appears once, as debt service.
B45: C. Funding needs by project and year — projects in the funding case (cash shortfall = MAX(0, -FCFF); IDR bn)
B46: E1 Teluk Lamong (NPLOG) cargodoring & delivery | C46: IDR bn | E46: =SUM(F46:S46) -> 0 | F46: ='E1 TelukLamong Output'!F31*IF('Global Inputs'!$E$36=1,'Global Inputs'!$K$89,'Global Inputs'!$L$89) -> 0 | G46: ='E1 TelukLamong Output'!G31*IF('Global Inputs'!$E$36=1,'Global Inputs'!$K$89,'Global Inputs'!$L$89) -> 0 | H46: ='E1 TelukLamong Output'!H31*IF('Global Inputs'!$E$36=1,'Global Inputs'!$K$89,'Global Inputs'!$L$89) -> 0 | I46: ='E1 TelukLamong Output'!I31*IF('Global Inputs'!$E$36=1,'Global Inputs'!$K$89,'Global Inputs'!$L$89) -> 0 | J46: ='E1 TelukLamong Output'!J31*IF('Global Inputs'!$E$36=1,'Global Inputs'!$K$89,'Global Inputs'!$L$89) -> 0 | K46: ='E1 TelukLamong Output'!K31*IF('Global Inputs'!$E$36=1,'Global Inputs'!$K$89,'Global Inputs'!$L$89) -> 0 | L46: ='E1 TelukLamong Output'!L31*IF('Global Inputs'!$E$36=1,'Global Inputs'!$K$89,'Global Inputs'!$L$89) -> 0 | M46: ='E1 TelukLamong Output'!M31*IF('Global Inputs'!$E$36=1,'Global Inputs'!$K$89,'Global Inputs'!$L$89) -> 0 | ... S46: ='E1 TelukLamong Output'!S31*IF('Global Inputs'!$E$36=1,'Global Inputs'!$K$89,'Global Inputs'!$L$89) -> 0
B47: E2 Cigading Existing Terminal (SGT 2) | C47: IDR bn | E47: =SUM(F47:S47) -> 0 | F47: ='E2 CigadingExist Output'!F31*IF('Global Inputs'!$E$36=1,'Global Inputs'!$K$90,'Global Inputs'!$L$90) -> 0 | G47: ='E2 CigadingExist Output'!G31*IF('Global Inputs'!$E$36=1,'Global Inputs'!$K$90,'Global Inputs'!$L$90) -> 0 | H47: ='E2 CigadingExist Output'!H31*IF('Global Inputs'!$E$36=1,'Global Inputs'!$K$90,'Global Inputs'!$L$90) -> 0 | I47: ='E2 CigadingExist Output'!I31*IF('Global Inputs'!$E$36=1,'Global Inputs'!$K$90,'Global Inputs'!$L$90) -> 0 | J47: ='E2 CigadingExist Output'!J31*IF('Global Inputs'!$E$36=1,'Global Inputs'!$K$90,'Global Inputs'!$L$90) -> 0 | K47: ='E2 CigadingExist Output'!K31*IF('Global Inputs'!$E$36=1,'Global Inputs'!$K$90,'Global Inputs'!$L$90) -> 0 | L47: ='E2 CigadingExist Output'!L31*IF('Global Inputs'!$E$36=1,'Global Inputs'!$K$90,'Global Inputs'!$L$90) -> 0 | M47: ='E2 CigadingExist Output'!M31*IF('Global Inputs'!$E$36=1,'Global Inputs'!$K$90,'Global Inputs'!$L$90) -> 0 | ... S47: ='E2 CigadingExist Output'!S31*IF('Global Inputs'!$E$36=1,'Global Inputs'!$K$90,'Global Inputs'!$L$90) -> 0
B48: E3 Belawan terminal (SGT3) incl. Belawan expansion | C48: IDR bn | E48: =SUM(F48:S48) -> 184.21669 | F48: ='E3 Belawan Output'!F31*IF('Global Inputs'!$E$36=1,'Global Inputs'!$K$91,'Global Inputs'!$L$91) -> 0 | G48: ='E3 Belawan Output'!G31*IF('Global Inputs'!$E$36=1,'Global Inputs'!$K$91,'Global Inputs'!$L$91) -> 0 | H48: ='E3 Belawan Output'!H31*IF('Global Inputs'!$E$36=1,'Global Inputs'!$K$91,'Global Inputs'!$L$91) -> 0 | I48: ='E3 Belawan Output'!I31*IF('Global Inputs'!$E$36=1,'Global Inputs'!$K$91,'Global Inputs'!$L$91) -> 96.233993 | J48: ='E3 Belawan Output'!J31*IF('Global Inputs'!$E$36=1,'Global Inputs'!$K$91,'Global Inputs'!$L$91) -> 87.982692 | K48: ='E3 Belawan Output'!K31*IF('Global Inputs'!$E$36=1,'Global Inputs'!$K$91,'Global Inputs'!$L$91) -> 0 | L48: ='E3 Belawan Output'!L31*IF('Global Inputs'!$E$36=1,'Global Inputs'!$K$91,'Global Inputs'!$L$91) -> 0 | M48: ='E3 Belawan Output'!M31*IF('Global Inputs'!$E$36=1,'Global Inputs'!$K$91,'Global Inputs'!$L$91) -> 0 | ... S48: ='E3 Belawan Output'!S31*IF('Global Inputs'!$E$36=1,'Global Inputs'!$K$91,'Global Inputs'!$L$91) -> 0
B49: E4 WIN stevedoring (Cilegon, Makassar, Surabaya, Medan) | C49: IDR bn | E49: =SUM(F49:S49) -> 0 | F49: ='E4 WIN Output'!F31*IF('Global Inputs'!$E$36=1,'Global Inputs'!$K$92,'Global Inputs'!$L$92) -> 0 | G49: ='E4 WIN Output'!G31*IF('Global Inputs'!$E$36=1,'Global Inputs'!$K$92,'Global Inputs'!$L$92) -> 0 | H49: ='E4 WIN Output'!H31*IF('Global Inputs'!$E$36=1,'Global Inputs'!$K$92,'Global Inputs'!$L$92) -> 0 | I49: ='E4 WIN Output'!I31*IF('Global Inputs'!$E$36=1,'Global Inputs'!$K$92,'Global Inputs'!$L$92) -> 0 | J49: ='E4 WIN Output'!J31*IF('Global Inputs'!$E$36=1,'Global Inputs'!$K$92,'Global Inputs'!$L$92) -> 0 | K49: ='E4 WIN Output'!K31*IF('Global Inputs'!$E$36=1,'Global Inputs'!$K$92,'Global Inputs'!$L$92) -> 0 | L49: ='E4 WIN Output'!L31*IF('Global Inputs'!$E$36=1,'Global Inputs'!$K$92,'Global Inputs'!$L$92) -> 0 | M49: ='E4 WIN Output'!M31*IF('Global Inputs'!$E$36=1,'Global Inputs'!$K$92,'Global Inputs'!$L$92) -> 0 | ... S49: ='E4 WIN Output'!S31*IF('Global Inputs'!$E$36=1,'Global Inputs'!$K$92,'Global Inputs'!$L$92) -> 0
B50: P01 Cigading Wharf 2 | C50: IDR bn | E50: =SUM(F50:S50) -> 200.0595 | F50: ='P01 CigWharf2 Output'!F31*IF('Global Inputs'!$E$36=1,'Global Inputs'!$K$93,'Global Inputs'!$L$93) -> 162.65 | G50: ='P01 CigWharf2 Output'!G31*IF('Global Inputs'!$E$36=1,'Global Inputs'!$K$93,'Global Inputs'!$L$93) -> 37.4095 | H50: ='P01 CigWharf2 Output'!H31*IF('Global Inputs'!$E$36=1,'Global Inputs'!$K$93,'Global Inputs'!$L$93) -> 0 | I50: ='P01 CigWharf2 Output'!I31*IF('Global Inputs'!$E$36=1,'Global Inputs'!$K$93,'Global Inputs'!$L$93) -> 0 | J50: ='P01 CigWharf2 Output'!J31*IF('Global Inputs'!$E$36=1,'Global Inputs'!$K$93,'Global Inputs'!$L$93) -> 0 | K50: ='P01 CigWharf2 Output'!K31*IF('Global Inputs'!$E$36=1,'Global Inputs'!$K$93,'Global Inputs'!$L$93) -> 0 | L50: ='P01 CigWharf2 Output'!L31*IF('Global Inputs'!$E$36=1,'Global Inputs'!$K$93,'Global Inputs'!$L$93) -> 0 | M50: ='P01 CigWharf2 Output'!M31*IF('Global Inputs'!$E$36=1,'Global Inputs'!$K$93,'Global Inputs'!$L$93) -> 0 | ... S50: ='P01 CigWharf2 Output'!S31*IF('Global Inputs'!$E$36=1,'Global Inputs'!$K$93,'Global Inputs'!$L$93) -> 0
